{
  "type": "Feature",
  "properties": {
    "gn:admin1_code":"08",
    "gn:admin2_code":"42",
    "gn:asciiname":"Natoumpe",
    "gn:country_code":"BF",
    "gn:dem":271,
    "gn:feature_class":"P",
    "gn:feature_code":"PPL",
    "gn:name":"Natoump\u00e9",
    "gn:population":0,
    "gn:timezone":"Africa/Ouagadougou",
    "iso:country":"BF",
    "wof:name":"Natoumpe",
    "wof:placetype":"locality"
},
  "geometry": {"coordinates":[1.2591,12.20991],"type":"Point"}
}