{
  "type": "Feature",
  "properties": {
    "gn:admin1_code":"01",
    "gn:asciiname":"Boune",
    "gn:country_code":"BF",
    "gn:dem":265,
    "gn:feature_class":"P",
    "gn:feature_code":"PPL",
    "gn:name":"Boun\u00e9",
    "gn:population":0,
    "gn:timezone":"Africa/Ouagadougou",
    "iso:country":"BF",
    "name:ceb_x_preferred":[
        "Boune"
    ],
    "name:swe_x_preferred":[
        "Boune"
    ],
    "wof:name":"Boune",
    "wof:placetype":"locality"
},
  "geometry": {"coordinates":[-3.58333,12.66667],"type":"Point"}
}