{
  "type": "Feature",
  "properties": {
    "gn:admin1_code":"08",
    "gn:admin2_code":"42",
    "gn:asciiname":"Seneguele",
    "gn:country_code":"BF",
    "gn:dem":224,
    "gn:feature_class":"P",
    "gn:feature_code":"PPL",
    "gn:name":"S\u00e9n\u00e9gu\u00e9l\u00e9",
    "gn:population":0,
    "gn:timezone":"Africa/Ouagadougou",
    "iso:country":"BF",
    "wof:name":"Seneguele",
    "wof:placetype":"locality"
},
  "geometry": {"coordinates":[1.9943,12.65717],"type":"Point"}
}