{
  "type": "Feature",
  "properties": {
    "gn:admin1_code":"04",
    "gn:asciiname":"Pelaga",
    "gn:country_code":"BF",
    "gn:dem":304,
    "gn:feature_class":"P",
    "gn:feature_code":"PPL",
    "gn:name":"P\u00e9laga",
    "gn:population":0,
    "gn:timezone":"Africa/Ouagadougou",
    "iso:country":"BF",
    "wof:name":"Pelaga",
    "wof:placetype":"locality"
},
  "geometry": {"coordinates":[-0.41667,12.31667],"type":"Point"}
}