{
  "type": "Feature",
  "properties": {
    "gn:admin1_code":"07",
    "gn:asciiname":"Yakala",
    "gn:country_code":"BF",
    "gn:dem":233,
    "gn:feature_class":"P",
    "gn:feature_code":"PPL",
    "gn:name":"Yakala",
    "gn:population":0,
    "gn:timezone":"Africa/Ouagadougou",
    "iso:country":"BF",
    "name:und_x_variant":[
        "Yakata",
        "Yakala"
    ],
    "wof:name":"Yakala",
    "wof:placetype":"locality"
},
  "geometry": {"coordinates":[-0.71667,11.51667],"type":"Point"}
}