{
  "type": "Feature",
  "properties": {
    "gn:admin1_code":"13",
    "gn:asciiname":"Kokolibou",
    "gn:country_code":"BF",
    "gn:dem":309,
    "gn:feature_class":"P",
    "gn:feature_code":"PPL",
    "gn:name":"Kokolibou",
    "gn:population":0,
    "gn:timezone":"Africa/Ouagadougou",
    "iso:country":"BF",
    "name:und_x_variant":[
        "Kokolioou",
        "Kokolibou"
    ],
    "wof:name":"Kokolibou",
    "wof:placetype":"locality"
},
  "geometry": {"coordinates":[-2.98333,10.91667],"type":"Point"}
}