{
  "type": "Feature",
  "properties": {
    "gn:admin1_code":"06",
    "gn:asciiname":"Bylyonvalse",
    "gn:country_code":"BF",
    "gn:dem":266,
    "gn:feature_class":"P",
    "gn:feature_code":"PPL",
    "gn:name":"Bylyonvals\u00e8",
    "gn:population":0,
    "gn:timezone":"Africa/Ouagadougou",
    "iso:country":"BF",
    "wof:name":"Bylyonvalse",
    "wof:placetype":"locality"
},
  "geometry": {"coordinates":[-2.63333,12.25],"type":"Point"}
}