{
  "type": "Feature",
  "properties": {
    "gn:admin1_code":"06",
    "gn:asciiname":"Ramibouli",
    "gn:country_code":"BF",
    "gn:dem":304,
    "gn:feature_class":"P",
    "gn:feature_code":"PPL",
    "gn:name":"Ramibouli",
    "gn:population":0,
    "gn:timezone":"Africa/Ouagadougou",
    "iso:country":"BF",
    "wof:name":"Ramibouli",
    "wof:placetype":"locality"
},
  "geometry": {"coordinates":[-2.26667,12.23333],"type":"Point"}
}