{
  "type": "Feature",
  "properties": {
    "gn:admin1_code":"08",
    "gn:admin2_code":"42",
    "gn:asciiname":"Gounda",
    "gn:country_code":"BF",
    "gn:dem":268,
    "gn:feature_class":"P",
    "gn:feature_code":"PPL",
    "gn:name":"Gounda",
    "gn:population":0,
    "gn:timezone":"Africa/Ouagadougou",
    "iso:country":"BF",
    "wof:name":"Gounda",
    "wof:placetype":"locality"
},
  "geometry": {"coordinates":[1.82909,12.10595],"type":"Point"}
}