{
  "type": "Feature",
  "properties": {
    "gn:admin1_code":"12",
    "gn:admin2_code":"40",
    "gn:asciiname":"Hamdallay",
    "gn:country_code":"BF",
    "gn:dem":308,
    "gn:feature_class":"P",
    "gn:feature_code":"PPL",
    "gn:name":"Hamdallay",
    "gn:population":0,
    "gn:timezone":"Africa/Ouagadougou",
    "iso:country":"BF",
    "name:und_x_variant":[
        "Amdalay",
        "Hamdallay"
    ],
    "wof:name":"Hamdallay",
    "wof:placetype":"locality"
},
  "geometry": {"coordinates":[-1.95294,14.23741],"type":"Point"}
}