{
  "type": "Feature",
  "properties": {
    "gn:admin1_code":"05",
    "gn:admin2_code":"64",
    "gn:asciiname":"Jitoera",
    "gn:country_code":"BF",
    "gn:dem":302,
    "gn:feature_class":"P",
    "gn:feature_code":"PPL",
    "gn:name":"Jitoera",
    "gn:population":0,
    "gn:timezone":"Africa/Ouagadougou",
    "iso:country":"BF",
    "wof:name":"Jitoera",
    "wof:placetype":"locality"
},
  "geometry": {"coordinates":[-0.55676,13.46832],"type":"Point"}
}