{
  "type": "Feature",
  "properties": {
    "gn:admin1_code":"04",
    "gn:asciiname":"Oueenga",
    "gn:country_code":"BF",
    "gn:dem":289,
    "gn:feature_class":"P",
    "gn:feature_code":"PPL",
    "gn:name":"Ou\u00e9enga",
    "gn:population":0,
    "gn:timezone":"Africa/Ouagadougou",
    "iso:country":"BF",
    "name:und_x_variant":[
        "Winga",
        "Ou\u00e9enga"
    ],
    "wof:name":"Oueenga",
    "wof:placetype":"locality"
},
  "geometry": {"coordinates":[-0.31667,12.48333],"type":"Point"}
}