{
  "type": "Feature",
  "properties": {
    "gn:admin1_code":"01",
    "gn:admin2_code":"73",
    "gn:asciiname":"Danouin",
    "gn:country_code":"BF",
    "gn:dem":307,
    "gn:feature_class":"P",
    "gn:feature_code":"PPL",
    "gn:name":"Danouin",
    "gn:population":0,
    "gn:timezone":"Africa/Ouagadougou",
    "iso:country":"BF",
    "wof:name":"Danouin",
    "wof:placetype":"locality"
},
  "geometry": {"coordinates":[-2.7021,13.141],"type":"Point"}
}