{
  "type": "Feature",
  "properties": {
    "gn:admin1_code":"10",
    "gn:admin2_code":"76",
    "gn:asciiname":"Kouossey",
    "gn:country_code":"BF",
    "gn:dem":319,
    "gn:feature_class":"P",
    "gn:feature_code":"PPL",
    "gn:name":"Kouossey",
    "gn:population":0,
    "gn:timezone":"Africa/Ouagadougou",
    "iso:country":"BF",
    "name:und_x_variant":[
        "Kouosseye",
        "Kouossey"
    ],
    "wof:name":"Kouossey",
    "wof:placetype":"locality"
},
  "geometry": {"coordinates":[-2.41351,13.04635],"type":"Point"}
}