{
  "type": "Feature",
  "properties": {
    "gn:admin1_code":"12",
    "gn:admin2_code":"75",
    "gn:asciiname":"Boulani",
    "gn:country_code":"BF",
    "gn:dem":273,
    "gn:feature_class":"P",
    "gn:feature_code":"PPL",
    "gn:name":"Boulani",
    "gn:population":0,
    "gn:timezone":"Africa/Ouagadougou",
    "iso:country":"BF",
    "wof:name":"Boulani",
    "wof:placetype":"locality"
},
  "geometry": {"coordinates":[0.55607,13.61815],"type":"Point"}
}