{
  "type": "Feature",
  "properties": {
    "gn:admin1_code":"10",
    "gn:admin2_code":"76",
    "gn:asciiname":"Nomo",
    "gn:country_code":"BF",
    "gn:dem":294,
    "gn:feature_class":"P",
    "gn:feature_code":"PPL",
    "gn:name":"Nomo",
    "gn:population":0,
    "gn:timezone":"Africa/Ouagadougou",
    "iso:country":"BF",
    "name:ceb_x_preferred":[
        "Nomo"
    ],
    "name:deu_x_preferred":[
        "Nomo"
    ],
    "name:glg_x_preferred":[
        "Nomo"
    ],
    "name:ita_x_preferred":[
        "Nomo"
    ],
    "name:por_x_preferred":[
        "Nomo"
    ],
    "name:slk_x_preferred":[
        "Nomo"
    ],
    "name:swe_x_preferred":[
        "Nomo"
    ],
    "wof:name":"Nomo",
    "wof:placetype":"locality"
},
  "geometry": {"coordinates":[-2.71438,13.82515],"type":"Point"}
}