{
  "type": "Feature",
  "properties": {
    "gn:admin1_code":"01",
    "gn:asciiname":"Ba Yangasso",
    "gn:country_code":"BF",
    "gn:dem":340,
    "gn:feature_class":"P",
    "gn:feature_code":"PPL",
    "gn:name":"Ba Yangasso",
    "gn:population":0,
    "gn:timezone":"Africa/Ouagadougou",
    "iso:country":"BF",
    "wof:name":"Ba Yangasso",
    "wof:placetype":"locality"
},
  "geometry": {"coordinates":[-3.28333,12.03333],"type":"Point"}
}