{
  "type": "Feature",
  "properties": {
    "gn:admin1_code":"12",
    "gn:admin2_code":"40",
    "gn:asciiname":"Tahati",
    "gn:country_code":"BF",
    "gn:dem":293,
    "gn:feature_class":"P",
    "gn:feature_code":"PPL",
    "gn:name":"Tahati",
    "gn:population":0,
    "gn:timezone":"Africa/Ouagadougou",
    "iso:country":"BF",
    "name:fas_x_preferred":[
        "\u062a\u062d\u062a\u06cc"
    ],
    "wof:name":"Tahati",
    "wof:placetype":"locality"
},
  "geometry": {"coordinates":[-1.07945,13.86502],"type":"Point"}
}