{
  "type": "Feature",
  "properties": {
    "gn:admin1_code":"10",
    "gn:admin2_code":"34",
    "gn:asciiname":"Koupela",
    "gn:country_code":"BF",
    "gn:dem":340,
    "gn:feature_class":"P",
    "gn:feature_code":"PPL",
    "gn:name":"Koup\u00e9la",
    "gn:population":0,
    "gn:timezone":"Africa/Ouagadougou",
    "iso:country":"BF",
    "wof:name":"Koupela",
    "wof:placetype":"locality"
},
  "geometry": {"coordinates":[-1.78819,13.0139],"type":"Point"}
}