{
  "type": "Feature",
  "properties": {
    "gn:admin1_code":"02",
    "gn:asciiname":"Tourny",
    "gn:country_code":"BF",
    "gn:dem":477,
    "gn:feature_class":"P",
    "gn:feature_code":"PPL",
    "gn:name":"Tourny",
    "gn:population":0,
    "gn:timezone":"Africa/Ouagadougou",
    "iso:country":"BF",
    "name:und_x_variant":[
        "Tourni",
        "Tourny"
    ],
    "wof:name":"Tourny",
    "wof:placetype":"locality"
},
  "geometry": {"coordinates":[-5.15,10.76667],"type":"Point"}
}