{
  "type": "Feature",
  "properties": {
    "gn:admin1_code":"02",
    "gn:asciiname":"Tourny",
    "gn:country_code":"BF",
    "gn:dem":477,
    "gn:feature_class":"P",
    "gn:feature_code":"PPL",
    "gn:name":"Tourny",
    "gn:population":0,
    "gn:timezone":"Africa/Ouagadougou",
    "iso:country":"BF",
    "name:bug_x_preferred":[
        "Tourny"
    ],
    "name:cat_x_preferred":[
        "Tourny"
    ],
    "name:ceb_x_preferred":[
        "Tourny"
    ],
    "name:ces_x_preferred":[
        "Tourny"
    ],
    "name:deu_x_preferred":[
        "Tourny"
    ],
    "name:eus_x_preferred":[
        "Tourny"
    ],
    "name:fra_x_preferred":[
        "Tourny"
    ],
    "name:hun_x_preferred":[
        "Tourny"
    ],
    "name:ind_x_preferred":[
        "Tourny"
    ],
    "name:ita_x_preferred":[
        "Tourny"
    ],
    "name:kaz_x_preferred":[
        "\u0422\u0443\u0440\u043d\u0438"
    ],
    "name:lat_x_preferred":[
        "Tourny"
    ],
    "name:mlg_x_preferred":[
        "Tourny"
    ],
    "name:msa_x_preferred":[
        "Tourny"
    ],
    "name:nld_x_preferred":[
        "Tourny"
    ],
    "name:oci_x_preferred":[
        "Tourny"
    ],
    "name:pms_x_preferred":[
        "Tourny"
    ],
    "name:pol_x_preferred":[
        "Tourny"
    ],
    "name:por_x_preferred":[
        "Tourny"
    ],
    "name:ron_x_preferred":[
        "Tourny"
    ],
    "name:slk_x_preferred":[
        "Tourny"
    ],
    "name:spa_x_preferred":[
        "Tourny"
    ],
    "name:swe_x_preferred":[
        "Tourny"
    ],
    "name:ukr_x_preferred":[
        "\u0422\u0443\u0440\u043d\u0456"
    ],
    "name:und_x_variant":[
        "Tourni",
        "Tourny"
    ],
    "name:vie_x_preferred":[
        "Tourny"
    ],
    "name:vol_x_preferred":[
        "Tourny"
    ],
    "name:war_x_preferred":[
        "Tourny"
    ],
    "name:zho_x_preferred":[
        "\u56fe\u5c14\u5c3c"
    ],
    "wof:name":"Tourny",
    "wof:placetype":"locality"
},
  "geometry": {"coordinates":[-5.15,10.76667],"type":"Point"}
}