{
  "type": "Feature",
  "properties": {
    "gn:admin1_code":"11",
    "gn:admin2_code":"68",
    "gn:asciiname":"Ziga",
    "gn:country_code":"BF",
    "gn:dem":280,
    "gn:feature_class":"P",
    "gn:feature_code":"PPL",
    "gn:name":"Ziga",
    "gn:population":0,
    "gn:timezone":"Africa/Ouagadougou",
    "iso:country":"BF",
    "name:bar_x_preferred":[
        "Ziga"
    ],
    "name:fra_x_preferred":[
        "Ziga"
    ],
    "wof:name":"Ziga",
    "wof:placetype":"locality"
},
  "geometry": {"coordinates":[-1.10917,12.56056],"type":"Point"}
}