{
  "type": "Feature",
  "properties": {
    "gn:admin1_code":"12",
    "gn:admin2_code":"71",
    "gn:asciiname":"Baougou Pore",
    "gn:country_code":"BF",
    "gn:dem":287,
    "gn:feature_class":"P",
    "gn:feature_code":"PPL",
    "gn:name":"Baougou Por\u00e9",
    "gn:population":0,
    "gn:timezone":"Africa/Ouagadougou",
    "iso:country":"BF",
    "wof:name":"Baougou Pore",
    "wof:placetype":"locality"
},
  "geometry": {"coordinates":[-0.44204,13.97162],"type":"Point"}
}