{
  "type": "Feature",
  "properties": {
    "gn:admin1_code":"11",
    "gn:asciiname":"Weotenga",
    "gn:country_code":"BF",
    "gn:dem":302,
    "gn:feature_class":"P",
    "gn:feature_code":"PPL",
    "gn:name":"W\u00e9otenga",
    "gn:population":0,
    "gn:timezone":"Africa/Ouagadougou",
    "iso:country":"BF",
    "name:und_x_variant":[
        "Ou\u00e9otenga",
        "W\u00e9otenga"
    ],
    "wof:name":"Weotenga",
    "wof:placetype":"locality"
},
  "geometry": {"coordinates":[-0.93333,12.36667],"type":"Point"}
}