{
  "type": "Feature",
  "properties": {
    "gn:admin1_code":"05",
    "gn:admin2_code":"15",
    "gn:asciiname":"Togoma",
    "gn:country_code":"BF",
    "gn:dem":334,
    "gn:feature_class":"P",
    "gn:feature_code":"PPL",
    "gn:name":"Togoma",
    "gn:population":0,
    "gn:timezone":"Africa/Ouagadougou",
    "iso:country":"BF",
    "wof:name":"Togoma",
    "wof:placetype":"locality"
},
  "geometry": {"coordinates":[-1.53032,13.12319],"type":"Point"}
}