{
  "type": "Feature",
  "properties": {
    "gn:admin1_code":"10",
    "gn:admin2_code":"76",
    "gn:asciiname":"Baskorma",
    "gn:country_code":"BF",
    "gn:dem":318,
    "gn:feature_class":"P",
    "gn:feature_code":"PPL",
    "gn:name":"Baskorma",
    "gn:population":0,
    "gn:timezone":"Africa/Ouagadougou",
    "iso:country":"BF",
    "wof:name":"Baskorma",
    "wof:placetype":"locality"
},
  "geometry": {"coordinates":[-2.21204,13.1674],"type":"Point"}
}