{
  "type": "Feature",
  "properties": {
    "gn:admin1_code":"08",
    "gn:admin2_code":"42",
    "gn:asciiname":"Koudyantyagou",
    "gn:country_code":"BF",
    "gn:dem":241,
    "gn:feature_class":"P",
    "gn:feature_code":"PPL",
    "gn:name":"Koudyantyagou",
    "gn:population":0,
    "gn:timezone":"Africa/Ouagadougou",
    "iso:country":"BF",
    "wof:name":"Koudyantyagou",
    "wof:placetype":"locality"
},
  "geometry": {"coordinates":[1.53039,12.27385],"type":"Point"}
}