{
  "type": "Feature",
  "properties": {
    "gn:admin1_code":"05",
    "gn:admin2_code":"64",
    "gn:asciiname":"Tisseme",
    "gn:country_code":"BF",
    "gn:dem":286,
    "gn:feature_class":"P",
    "gn:feature_code":"PPL",
    "gn:name":"Tiss\u00e9m\u00e9",
    "gn:population":0,
    "gn:timezone":"Africa/Ouagadougou",
    "iso:country":"BF",
    "name:und_x_variant":[
        "Tissimi",
        "Tiss\u00e9m\u00e9"
    ],
    "wof:name":"Tisseme",
    "wof:placetype":"locality"
},
  "geometry": {"coordinates":[-0.42765,13.01657],"type":"Point"}
}