{
  "type": "Feature",
  "properties": {
    "gn:admin1_code":"12",
    "gn:admin2_code":"71",
    "gn:asciiname":"Goumodyo",
    "gn:country_code":"BF",
    "gn:dem":293,
    "gn:feature_class":"P",
    "gn:feature_code":"PPL",
    "gn:name":"Goumodyo",
    "gn:population":0,
    "gn:timezone":"Africa/Ouagadougou",
    "iso:country":"BF",
    "wof:name":"Goumodyo",
    "wof:placetype":"locality"
},
  "geometry": {"coordinates":[0.02804,13.58743],"type":"Point"}
}