{
  "type": "Feature",
  "properties": {
    "gn:admin1_code":"13",
    "gn:asciiname":"Bamena",
    "gn:country_code":"BF",
    "gn:dem":279,
    "gn:feature_class":"P",
    "gn:feature_code":"PPL",
    "gn:name":"Bamena",
    "gn:population":0,
    "gn:timezone":"Africa/Ouagadougou",
    "iso:country":"BF",
    "name:fra_x_preferred":[
        "Bamena"
    ],
    "name:nld_x_preferred":[
        "Bamena"
    ],
    "wof:name":"Bamena",
    "wof:placetype":"locality"
},
  "geometry": {"coordinates":[-2.95,9.81667],"type":"Point"}
}