{
  "type": "Feature",
  "properties": {
    "gn:admin1_code":"07",
    "gn:asciiname":"Koulpelle",
    "gn:country_code":"BF",
    "gn:dem":306,
    "gn:feature_class":"P",
    "gn:feature_code":"PPL",
    "gn:name":"Koulpell\u00e9",
    "gn:population":0,
    "gn:timezone":"Africa/Ouagadougou",
    "iso:country":"BF",
    "name:azb_x_preferred":[
        "\u06a9\u0648\u0644\u067e\u0644\u0647"
    ],
    "name:ceb_x_preferred":[
        "Koulpell\u00e9"
    ],
    "name:fas_x_preferred":[
        "\u06a9\u0648\u0644\u067e\u0644\u0647"
    ],
    "name:swe_x_preferred":[
        "Koulpell\u00e9"
    ],
    "name:und_x_variant":[
        "Koulpell\u00e9"
    ],
    "wof:name":"Koulpelle",
    "wof:placetype":"locality"
},
  "geometry": {"coordinates":[-1.26667,11.91667],"type":"Point"}
}