{
  "type": "Feature",
  "properties": {
    "gn:admin1_code":"01",
    "gn:asciiname":"Nanou",
    "gn:country_code":"BF",
    "gn:dem":276,
    "gn:feature_class":"P",
    "gn:feature_code":"PPL",
    "gn:name":"Nanou",
    "gn:population":0,
    "gn:timezone":"Africa/Ouagadougou",
    "iso:country":"BF",
    "name:und_x_variant":[
        "Na",
        "Nanou"
    ],
    "wof:name":"Nanou",
    "wof:placetype":"locality"
},
  "geometry": {"coordinates":[-3.08333,11.76667],"type":"Point"}
}