{
  "type": "Feature",
  "properties": {
    "gn:admin1_code":"01",
    "gn:asciiname":"Fie",
    "gn:country_code":"BF",
    "gn:dem":310,
    "gn:feature_class":"P",
    "gn:feature_code":"PPL",
    "gn:name":"Fi\u00e9",
    "gn:population":0,
    "gn:timezone":"Africa/Ouagadougou",
    "iso:country":"BF",
    "name:ceb_x_preferred":[
        "Fie"
    ],
    "name:jav_x_preferred":[
        "Fie"
    ],
    "name:msa_x_preferred":[
        "Fie"
    ],
    "name:und_x_variant":[
        "Pi\u00e9",
        "Fi\u00e9"
    ],
    "wof:name":"Fie",
    "wof:placetype":"locality"
},
  "geometry": {"coordinates":[-3.41667,12.18333],"type":"Point"}
}