{
  "type": "Feature",
  "properties": {
    "gn:admin1_code":"13",
    "gn:asciiname":"Tabouale",
    "gn:country_code":"BF",
    "gn:dem":256,
    "gn:feature_class":"P",
    "gn:feature_code":"PPL",
    "gn:name":"Taboual\u00e9",
    "gn:population":0,
    "gn:timezone":"Africa/Ouagadougou",
    "iso:country":"BF",
    "wof:name":"Tabouale",
    "wof:placetype":"locality"
},
  "geometry": {"coordinates":[-2.95,10.58333],"type":"Point"}
}