{
  "type": "Feature",
  "properties": {
    "gn:admin1_code":"02",
    "gn:asciiname":"Balegogo",
    "gn:country_code":"BF",
    "gn:dem":365,
    "gn:feature_class":"P",
    "gn:feature_code":"PPL",
    "gn:name":"Bal\u00e9gogo",
    "gn:population":0,
    "gn:timezone":"Africa/Ouagadougou",
    "iso:country":"BF",
    "wof:name":"Balegogo",
    "wof:placetype":"locality"
},
  "geometry": {"coordinates":[-4.03333,10.18333],"type":"Point"}
}