{
  "type": "Feature",
  "properties": {
    "gn:admin1_code":"05",
    "gn:admin2_code":"70",
    "gn:asciiname":"Dimkilga",
    "gn:country_code":"BF",
    "gn:dem":306,
    "gn:feature_class":"P",
    "gn:feature_code":"PPL",
    "gn:name":"Dimkilga",
    "gn:population":0,
    "gn:timezone":"Africa/Ouagadougou",
    "iso:country":"BF",
    "wof:name":"Dimkilga",
    "wof:placetype":"locality"
},
  "geometry": {"coordinates":[-0.86579,13.01075],"type":"Point"}
}