{
  "type": "Feature",
  "properties": {
    "gn:admin1_code":"04",
    "gn:asciiname":"Gouli",
    "gn:country_code":"BF",
    "gn:dem":248,
    "gn:feature_class":"P",
    "gn:feature_code":"PPL",
    "gn:name":"Gouli",
    "gn:population":0,
    "gn:timezone":"Africa/Ouagadougou",
    "iso:country":"BF",
    "wof:name":"Gouli",
    "wof:placetype":"locality"
},
  "geometry": {"coordinates":[-0.08333,11.65],"type":"Point"}
}