{
  "type": "Feature",
  "properties": {
    "gn:admin1_code":"03",
    "gn:admin2_code":"53",
    "gn:asciiname":"Konguen",
    "gn:country_code":"BF",
    "gn:dem":317,
    "gn:feature_class":"P",
    "gn:feature_code":"PPL",
    "gn:name":"Konguen",
    "gn:population":0,
    "gn:timezone":"Africa/Ouagadougou",
    "iso:country":"BF",
    "name:und_x_variant":[
        "Konghin",
        "Konguen"
    ],
    "wof:name":"Konguen",
    "wof:placetype":"locality"
},
  "geometry": {"coordinates":[-1.60306,12.24417],"type":"Point"}
}