{
  "type": "Feature",
  "properties": {
    "gn:admin1_code":"05",
    "gn:admin2_code":"15",
    "gn:asciiname":"Baribsi",
    "gn:country_code":"BF",
    "gn:dem":369,
    "gn:feature_class":"P",
    "gn:feature_code":"PPL",
    "gn:name":"Baribsi",
    "gn:population":0,
    "gn:timezone":"Africa/Ouagadougou",
    "iso:country":"BF",
    "name:azb_x_preferred":[
        "\u0628\u0627\u0631\u06cc\u0628\u0633\u06cc"
    ],
    "name:fas_x_preferred":[
        "\u0628\u0627\u0631\u06cc\u0628\u0633\u06cc"
    ],
    "wof:name":"Baribsi",
    "wof:placetype":"locality"
},
  "geometry": {"coordinates":[-1.71798,13.33411],"type":"Point"}
}