{
  "type": "Feature",
  "properties": {
    "gn:admin1_code":"10",
    "gn:admin2_code":"76",
    "gn:asciiname":"Saadogo",
    "gn:country_code":"BF",
    "gn:dem":336,
    "gn:feature_class":"P",
    "gn:feature_code":"PPL",
    "gn:name":"Saadogo",
    "gn:population":0,
    "gn:timezone":"Africa/Ouagadougou",
    "iso:country":"BF",
    "wof:name":"Saadogo",
    "wof:placetype":"locality"
},
  "geometry": {"coordinates":[-2.53567,13.35334],"type":"Point"}
}