{
  "type": "Feature",
  "properties": {
    "gn:admin1_code":"10",
    "gn:admin2_code":"76",
    "gn:asciiname":"Zogore",
    "gn:country_code":"BF",
    "gn:dem":345,
    "gn:feature_class":"P",
    "gn:feature_code":"PPL",
    "gn:name":"Zogor\u00e9",
    "gn:population":0,
    "gn:timezone":"Africa/Ouagadougou",
    "iso:country":"BF",
    "name:deu_x_preferred":[
        "Zogor\u00e9"
    ],
    "name:fra_x_preferred":[
        "Zogor\u00e9"
    ],
    "name:ita_x_preferred":[
        "Zogor\u00e9"
    ],
    "name:spa_x_preferred":[
        "Zogor\u00e9"
    ],
    "name:und_x_variant":[
        "Diogor\u00e9",
        "Zogor\u00e9"
    ],
    "wof:name":"Zogore",
    "wof:placetype":"locality"
},
  "geometry": {"coordinates":[-2.59244,13.40169],"type":"Point"}
}