{
  "type": "Feature",
  "properties": {
    "gn:admin1_code":"13",
    "gn:asciiname":"Dielindiala",
    "gn:country_code":"BF",
    "gn:dem":286,
    "gn:feature_class":"P",
    "gn:feature_code":"PPL",
    "gn:name":"Di\u00e9lindiala",
    "gn:population":0,
    "gn:timezone":"Africa/Ouagadougou",
    "iso:country":"BF",
    "wof:name":"Dielindiala",
    "wof:placetype":"locality"
},
  "geometry": {"coordinates":[-3.11667,10.46667],"type":"Point"}
}