{
  "type": "Feature",
  "properties": {
    "gn:admin1_code":"07",
    "gn:asciiname":"Souli",
    "gn:country_code":"BF",
    "gn:dem":334,
    "gn:feature_class":"P",
    "gn:feature_code":"PPL",
    "gn:name":"Souli",
    "gn:population":0,
    "gn:timezone":"Africa/Ouagadougou",
    "iso:country":"BF",
    "wof:name":"Souli",
    "wof:placetype":"locality"
},
  "geometry": {"coordinates":[-1.51667,11.91667],"type":"Point"}
}