{
  "type": "Feature",
  "properties": {
    "gn:admin1_code":"04",
    "gn:asciiname":"Zargo",
    "gn:country_code":"BF",
    "gn:dem":255,
    "gn:feature_class":"P",
    "gn:feature_code":"PPL",
    "gn:name":"Zargo",
    "gn:population":0,
    "gn:timezone":"Africa/Ouagadougou",
    "iso:country":"BF",
    "wof:name":"Zargo",
    "wof:placetype":"locality"
},
  "geometry": {"coordinates":[-0.61667,11.68333],"type":"Point"}
}