{
  "type": "Feature",
  "properties": {
    "gn:admin1_code":"12",
    "gn:admin2_code":"75",
    "gn:asciiname":"Desse",
    "gn:country_code":"BF",
    "gn:dem":272,
    "gn:feature_class":"P",
    "gn:feature_code":"PPL",
    "gn:name":"D\u00e9ss\u00e9",
    "gn:population":0,
    "gn:timezone":"Africa/Ouagadougou",
    "iso:country":"BF",
    "name:azb_x_preferred":[
        "\u062f\u0633\u0647"
    ],
    "name:ceb_x_preferred":[
        "D\u00e9ss\u00e9"
    ],
    "name:fas_x_preferred":[
        "\u062f\u0633\u0647"
    ],
    "name:fra_x_preferred":[
        "D\u00e8ss\u00e8"
    ],
    "name:swe_x_preferred":[
        "D\u00e9ss\u00e9"
    ],
    "name:und_x_variant":[
        "D\u00e9ss\u00e9"
    ],
    "wof:name":"Desse",
    "wof:placetype":"locality"
},
  "geometry": {"coordinates":[0.62479,13.50685],"type":"Point"}
}