{
  "type": "Feature",
  "properties": {
    "gn:admin1_code":"05",
    "gn:admin2_code":"15",
    "gn:asciiname":"Norde",
    "gn:country_code":"BF",
    "gn:dem":334,
    "gn:feature_class":"P",
    "gn:feature_code":"PPL",
    "gn:name":"Nord\u00e9",
    "gn:population":0,
    "gn:timezone":"Africa/Ouagadougou",
    "iso:country":"BF",
    "name:azb_x_preferred":[
        "\u0646\u0648\u0631\u062f\u0647"
    ],
    "name:ceb_x_preferred":[
        "Nord\u00e9"
    ],
    "name:fas_x_preferred":[
        "\u0646\u0648\u0631\u062f\u0647"
    ],
    "name:fra_x_preferred":[
        "Nord\u00e9"
    ],
    "name:swe_x_preferred":[
        "Nord\u00e9"
    ],
    "wof:name":"Norde",
    "wof:placetype":"locality"
},
  "geometry": {"coordinates":[-1.37838,13.54024],"type":"Point"}
}