{
  "type": "Feature",
  "properties": {
    "gn:admin1_code":"01",
    "gn:asciiname":"Diouroum",
    "gn:country_code":"BF",
    "gn:dem":282,
    "gn:feature_class":"P",
    "gn:feature_code":"PPL",
    "gn:name":"Diouroum",
    "gn:population":0,
    "gn:timezone":"Africa/Ouagadougou",
    "iso:country":"BF",
    "name:und_x_variant":[
        "Diurum",
        "Diouroum"
    ],
    "wof:name":"Diouroum",
    "wof:placetype":"locality"
},
  "geometry": {"coordinates":[-3.11239,12.99057],"type":"Point"}
}