{
  "type": "Feature",
  "properties": {
    "gn:admin1_code":"04",
    "gn:asciiname":"Sane",
    "gn:country_code":"BF",
    "gn:dem":258,
    "gn:feature_class":"P",
    "gn:feature_code":"PPL",
    "gn:name":"San\u00e9",
    "gn:population":0,
    "gn:timezone":"Africa/Ouagadougou",
    "iso:country":"BF",
    "name:cat_x_preferred":[
        "Sane"
    ],
    "name:ceb_x_preferred":[
        "Sane"
    ],
    "name:fin_x_preferred":[
        "Sane"
    ],
    "name:heb_x_preferred":[
        "\u05e1\u05d0\u05e0\u05d4"
    ],
    "name:kaz_x_preferred":[
        "\u0421\u0430\u043d\u043a"
    ],
    "name:spa_x_preferred":[
        "Sane"
    ],
    "name:swe_x_preferred":[
        "Sane"
    ],
    "wof:name":"Sane",
    "wof:placetype":"locality"
},
  "geometry": {"coordinates":[-0.46667,11.65],"type":"Point"}
}