{
  "type": "Feature",
  "properties": {
    "gn:admin1_code":"09",
    "gn:admin2_code":"51",
    "gn:asciiname":"Panamasso",
    "gn:country_code":"BF",
    "gn:dem":332,
    "gn:feature_class":"P",
    "gn:feature_code":"PPL",
    "gn:name":"Panamasso",
    "gn:population":0,
    "gn:timezone":"Africa/Ouagadougou",
    "iso:country":"BF",
    "name:und_x_variant":[
        "Fandamasso",
        "Panamanso",
        "Pandamasso",
        "Panamasso"
    ],
    "wof:name":"Panamasso",
    "wof:placetype":"locality"
},
  "geometry": {"coordinates":[-4.20379,11.386],"type":"Point"}
}