{
  "type": "Feature",
  "properties": {
    "gn:admin1_code":"05",
    "gn:admin2_code":"70",
    "gn:asciiname":"Soubsi",
    "gn:country_code":"BF",
    "gn:dem":327,
    "gn:feature_class":"P",
    "gn:feature_code":"PPL",
    "gn:name":"Soubsi",
    "gn:population":0,
    "gn:timezone":"Africa/Ouagadougou",
    "iso:country":"BF",
    "wof:name":"Soubsi",
    "wof:placetype":"locality"
},
  "geometry": {"coordinates":[-1.35624,13.11982],"type":"Point"}
}