{
  "type": "Feature",
  "properties": {
    "gn:admin1_code":"11",
    "gn:asciiname":"Kosoden",
    "gn:country_code":"BF",
    "gn:dem":287,
    "gn:feature_class":"P",
    "gn:feature_code":"PPL",
    "gn:name":"Kosoden",
    "gn:population":0,
    "gn:timezone":"Africa/Ouagadougou",
    "iso:country":"BF",
    "name:und_x_variant":[
        "Kossodin",
        "Kosoden"
    ],
    "wof:name":"Kosoden",
    "wof:placetype":"locality"
},
  "geometry": {"coordinates":[-1.38333,12.53333],"type":"Point"}
}