{
  "type": "Feature",
  "properties": {
    "gn:admin1_code":"13",
    "gn:asciiname":"Noukouala",
    "gn:country_code":"BF",
    "gn:dem":368,
    "gn:feature_class":"P",
    "gn:feature_code":"PPL",
    "gn:name":"Noukouala",
    "gn:population":0,
    "gn:timezone":"Africa/Ouagadougou",
    "iso:country":"BF",
    "wof:name":"Noukouala",
    "wof:placetype":"locality"
},
  "geometry": {"coordinates":[-3.55,9.98333],"type":"Point"}
}