{
  "type": "Feature",
  "properties": {
    "gn:admin1_code":"08",
    "gn:asciiname":"Kouare",
    "gn:country_code":"BF",
    "gn:dem":292,
    "gn:feature_class":"P",
    "gn:feature_code":"PPL",
    "gn:name":"Kouar\u00e9",
    "gn:population":0,
    "gn:timezone":"Africa/Ouagadougou",
    "iso:country":"BF",
    "wof:name":"Kouare",
    "wof:placetype":"locality"
},
  "geometry": {"coordinates":[0.30065,11.94053],"type":"Point"}
}