{
  "type": "Feature",
  "properties": {
    "gn:admin1_code":"10",
    "gn:admin2_code":"76",
    "gn:asciiname":"Rambi",
    "gn:country_code":"BF",
    "gn:dem":311,
    "gn:feature_class":"P",
    "gn:feature_code":"PPL",
    "gn:name":"Rambi",
    "gn:population":0,
    "gn:timezone":"Africa/Ouagadougou",
    "iso:country":"BF",
    "name:und_x_variant":[
        "Rammbi",
        "Rambi"
    ],
    "wof:name":"Rambi",
    "wof:placetype":"locality"
},
  "geometry": {"coordinates":[-2.23446,13.52565],"type":"Point"}
}