{
  "type": "Feature",
  "properties": {
    "gn:admin1_code":"09",
    "gn:admin2_code":"54",
    "gn:asciiname":"Blari",
    "gn:country_code":"BF",
    "gn:dem":396,
    "gn:feature_class":"P",
    "gn:feature_code":"PPL",
    "gn:name":"Blari",
    "gn:population":0,
    "gn:timezone":"Africa/Ouagadougou",
    "iso:country":"BF",
    "wof:name":"Blari",
    "wof:placetype":"locality"
},
  "geometry": {"coordinates":[-5.11564,11.28739],"type":"Point"}
}