{
  "type": "Feature",
  "properties": {
    "gn:admin1_code":"11",
    "gn:admin2_code":"60",
    "gn:asciiname":"Mouni",
    "gn:country_code":"BF",
    "gn:dem":337,
    "gn:feature_class":"P",
    "gn:feature_code":"PPL",
    "gn:name":"Mouni",
    "gn:population":0,
    "gn:timezone":"Africa/Ouagadougou",
    "iso:country":"BF",
    "name:ceb_x_preferred":[
        "Mouni"
    ],
    "name:fas_x_preferred":[
        "\u0645\u0648\u0646\u06cc"
    ],
    "name:fra_x_preferred":[
        "Mouni"
    ],
    "name:swe_x_preferred":[
        "Mouni"
    ],
    "name:und_x_variant":[
        "Moni",
        "Mouni"
    ],
    "wof:name":"Mouni",
    "wof:placetype":"locality"
},
  "geometry": {"coordinates":[-1.84944,12.805],"type":"Point"}
}