{
  "type": "Feature",
  "properties": {
    "gn:admin1_code":"11",
    "gn:admin2_code":"20",
    "gn:asciiname":"Zam",
    "gn:country_code":"BF",
    "gn:dem":289,
    "gn:feature_class":"P",
    "gn:feature_code":"PPL",
    "gn:name":"Zam",
    "gn:population":0,
    "gn:timezone":"Africa/Ouagadougou",
    "iso:country":"BF",
    "name:deu_x_preferred":[
        "Zam"
    ],
    "name:fra_x_preferred":[
        "Zam"
    ],
    "name:ita_x_preferred":[
        "Zam"
    ],
    "name:por_x_preferred":[
        "Zam"
    ],
    "name:spa_x_preferred":[
        "Zam"
    ],
    "name:vie_x_preferred":[
        "Zam"
    ],
    "wof:name":"Zam",
    "wof:placetype":"locality"
},
  "geometry": {"coordinates":[-0.83189,12.33959],"type":"Point"}
}