{
  "type": "Feature",
  "properties": {
    "gn:admin1_code":"06",
    "gn:asciiname":"Poa",
    "gn:country_code":"BF",
    "gn:dem":329,
    "gn:feature_class":"P",
    "gn:feature_code":"PPL",
    "gn:name":"Poa",
    "gn:population":0,
    "gn:timezone":"Africa/Ouagadougou",
    "iso:country":"BF",
    "wof:name":"Poa",
    "wof:placetype":"locality"
},
  "geometry": {"coordinates":[-1.83333,11.68333],"type":"Point"}
}