{
  "type": "Feature",
  "properties": {
    "gn:admin1_code":"10",
    "gn:admin2_code":"76",
    "gn:asciiname":"Ouokinga Ouobilo",
    "gn:country_code":"BF",
    "gn:dem":292,
    "gn:feature_class":"P",
    "gn:feature_code":"PPL",
    "gn:name":"Ouokinga Ouobilo",
    "gn:population":0,
    "gn:timezone":"Africa/Ouagadougou",
    "iso:country":"BF",
    "name:und_x_variant":[
        "Wotienga Wobila",
        "Ouokinga Ouobilo"
    ],
    "wof:name":"Ouokinga Ouobilo",
    "wof:placetype":"locality"
},
  "geometry": {"coordinates":[-2.67,13.6427],"type":"Point"}
}