{
  "type": "Feature",
  "properties": {
    "gn:admin1_code":"05",
    "gn:asciiname":"Tore",
    "gn:country_code":"BF",
    "gn:dem":282,
    "gn:feature_class":"P",
    "gn:feature_code":"PPL",
    "gn:name":"Tor\u00e9",
    "gn:population":0,
    "gn:timezone":"Africa/Ouagadougou",
    "iso:country":"BF",
    "name:dan_x_preferred":[
        "Tore"
    ],
    "name:deu_x_preferred":[
        "Tore"
    ],
    "name:fin_x_preferred":[
        "Tore"
    ],
    "name:ita_x_preferred":[
        "Tore"
    ],
    "name:nno_x_preferred":[
        "Tore"
    ],
    "name:nor_x_preferred":[
        "Tore"
    ],
    "name:por_x_preferred":[
        "Tore"
    ],
    "name:swe_x_preferred":[
        "Tore"
    ],
    "name:und_x_variant":[
        "Toguen",
        "Tor\u00e9"
    ],
    "wof:name":"Tore",
    "wof:placetype":"locality"
},
  "geometry": {"coordinates":[-1.08333,12.81667],"type":"Point"}
}