{
  "type": "Feature",
  "properties": {
    "gn:admin1_code":"04",
    "gn:asciiname":"Lenga",
    "gn:country_code":"BF",
    "gn:dem":337,
    "gn:feature_class":"P",
    "gn:feature_code":"PPL",
    "gn:name":"Lenga",
    "gn:population":0,
    "gn:timezone":"Africa/Ouagadougou",
    "iso:country":"BF",
    "name:ceb_x_preferred":[
        "Lenga"
    ],
    "name:deu_x_preferred":[
        "Lenga"
    ],
    "name:oci_x_preferred":[
        "Lenga"
    ],
    "name:swe_x_preferred":[
        "Lenga"
    ],
    "wof:name":"Lenga",
    "wof:placetype":"locality"
},
  "geometry": {"coordinates":[-0.73333,11.58333],"type":"Point"}
}