{
  "type": "Feature",
  "properties": {
    "gn:admin1_code":"03",
    "gn:admin2_code":"53",
    "gn:asciiname":"Ouidi",
    "gn:country_code":"BF",
    "gn:dem":315,
    "gn:feature_class":"P",
    "gn:feature_code":"PPL",
    "gn:name":"Ouidi",
    "gn:population":0,
    "gn:timezone":"Africa/Ouagadougou",
    "iso:country":"BF",
    "wof:name":"Ouidi",
    "wof:placetype":"locality"
},
  "geometry": {"coordinates":[-1.68111,12.39556],"type":"Point"}
}