{
  "type": "Feature",
  "properties": {
    "gn:admin1_code":"02",
    "gn:asciiname":"Nonfesso",
    "gn:country_code":"BF",
    "gn:dem":329,
    "gn:feature_class":"P",
    "gn:feature_code":"PPL",
    "gn:name":"Nonfesso",
    "gn:population":0,
    "gn:timezone":"Africa/Ouagadougou",
    "iso:country":"BF",
    "wof:name":"Nonfesso",
    "wof:placetype":"locality"
},
  "geometry": {"coordinates":[-4.78333,10.13333],"type":"Point"}
}