{
  "type": "Feature",
  "properties": {
    "gn:admin1_code":"10",
    "gn:admin2_code":"76",
    "gn:asciiname":"Kalehena",
    "gn:country_code":"BF",
    "gn:dem":317,
    "gn:feature_class":"P",
    "gn:feature_code":"PPL",
    "gn:name":"Kal\u00e9h\u00e9na",
    "gn:population":0,
    "gn:timezone":"Africa/Ouagadougou",
    "iso:country":"BF",
    "wof:name":"Kalehena",
    "wof:placetype":"locality"
},
  "geometry": {"coordinates":[-2.25022,13.71898],"type":"Point"}
}