{
  "type": "Feature",
  "properties": {
    "gn:admin1_code":"09",
    "gn:admin2_code":"51",
    "gn:asciiname":"Dinngasso",
    "gn:country_code":"BF",
    "gn:dem":348,
    "gn:feature_class":"P",
    "gn:feature_code":"PPL",
    "gn:name":"Dinngasso",
    "gn:population":0,
    "gn:timezone":"Africa/Ouagadougou",
    "iso:country":"BF",
    "wof:name":"Dinngasso",
    "wof:placetype":"locality"
},
  "geometry": {"coordinates":[-4.29435,11.05948],"type":"Point"}
}