{
  "type": "Feature",
  "properties": {
    "gn:admin1_code":"12",
    "gn:admin2_code":"75",
    "gn:asciiname":"Ouro Dyanigangore",
    "gn:country_code":"BF",
    "gn:dem":283,
    "gn:feature_class":"P",
    "gn:feature_code":"PPL",
    "gn:name":"Ouro Dyanigangor\u00e9",
    "gn:population":0,
    "gn:timezone":"Africa/Ouagadougou",
    "iso:country":"BF",
    "wof:name":"Ouro Dyanigangore",
    "wof:placetype":"locality"
},
  "geometry": {"coordinates":[0.16144,13.53757],"type":"Point"}
}