{
  "type": "Feature",
  "properties": {
    "gn:admin1_code":"13",
    "gn:asciiname":"Zolo",
    "gn:country_code":"BF",
    "gn:dem":266,
    "gn:feature_class":"P",
    "gn:feature_code":"PPL",
    "gn:name":"Zolo",
    "gn:population":0,
    "gn:timezone":"Africa/Ouagadougou",
    "iso:country":"BF",
    "name:ceb_x_preferred":[
        "Zolo"
    ],
    "name:swe_x_preferred":[
        "Zolo"
    ],
    "wof:name":"Zolo",
    "wof:placetype":"locality"
},
  "geometry": {"coordinates":[-3.05,10.81667],"type":"Point"}
}