{
  "type": "Feature",
  "properties": {
    "gn:admin1_code":"08",
    "gn:admin2_code":"21",
    "gn:asciiname":"Sankala",
    "gn:country_code":"BF",
    "gn:dem":276,
    "gn:feature_class":"P",
    "gn:feature_code":"PPL",
    "gn:name":"Sankala",
    "gn:population":0,
    "gn:timezone":"Africa/Ouagadougou",
    "iso:country":"BF",
    "wof:name":"Sankala",
    "wof:placetype":"locality"
},
  "geometry": {"coordinates":[-0.39146,13.06487],"type":"Point"}
}