{
  "type": "Feature",
  "properties": {
    "gn:admin1_code":"12",
    "gn:admin2_code":"75",
    "gn:asciiname":"Soulountou",
    "gn:country_code":"BF",
    "gn:dem":256,
    "gn:feature_class":"P",
    "gn:feature_code":"PPL",
    "gn:name":"Soulountou",
    "gn:population":0,
    "gn:timezone":"Africa/Ouagadougou",
    "iso:country":"BF",
    "wof:name":"Soulountou",
    "wof:placetype":"locality"
},
  "geometry": {"coordinates":[0.93658,13.49569],"type":"Point"}
}