{
  "type": "Feature",
  "properties": {
    "gn:admin1_code":"11",
    "gn:admin2_code":"68",
    "gn:asciiname":"Sawana",
    "gn:country_code":"BF",
    "gn:dem":292,
    "gn:feature_class":"P",
    "gn:feature_code":"PPL",
    "gn:name":"Sawana",
    "gn:population":0,
    "gn:timezone":"Africa/Ouagadougou",
    "iso:country":"BF",
    "wof:name":"Sawana",
    "wof:placetype":"locality"
},
  "geometry": {"coordinates":[-1.14056,12.60639],"type":"Point"}
}