{
  "type": "Feature",
  "properties": {
    "gn:admin1_code":"06",
    "gn:asciiname":"Bandeo-Napone",
    "gn:country_code":"BF",
    "gn:dem":268,
    "gn:feature_class":"P",
    "gn:feature_code":"PPL",
    "gn:name":"Band\u00e9o-Napon\u00e9",
    "gn:population":0,
    "gn:timezone":"Africa/Ouagadougou",
    "iso:country":"BF",
    "name:und_x_variant":[
        "Banda Napoli",
        "Band\u00e9o-Napon\u00e9",
        "Bandeo Napor\u00e9"
    ],
    "wof:name":"Bandeo-Napone",
    "wof:placetype":"locality"
},
  "geometry": {"coordinates":[-2.52094,12.04605],"type":"Point"}
}