{
  "type": "Feature",
  "properties": {
    "gn:admin1_code":"05",
    "gn:admin2_code":"64",
    "gn:asciiname":"Taparko",
    "gn:country_code":"BF",
    "gn:dem":277,
    "gn:feature_class":"P",
    "gn:feature_code":"PPL",
    "gn:name":"Taparko",
    "gn:population":0,
    "gn:timezone":"Africa/Ouagadougou",
    "iso:country":"BF",
    "name:und_x_variant":[
        "Taparko Bagar\u00e9",
        "Tatarko",
        "Taparko"
    ],
    "wof:name":"Taparko",
    "wof:placetype":"locality"
},
  "geometry": {"coordinates":[-0.32444,13.46536],"type":"Point"}
}