{
  "type": "Feature",
  "properties": {
    "gn:admin1_code":"12",
    "gn:admin2_code":"71",
    "gn:asciiname":"Fairdi Syenou",
    "gn:country_code":"BF",
    "gn:dem":277,
    "gn:feature_class":"P",
    "gn:feature_code":"PPL",
    "gn:name":"Fairdi Sy\u00e9nou",
    "gn:population":0,
    "gn:timezone":"Africa/Ouagadougou",
    "iso:country":"BF",
    "wof:name":"Fairdi Syenou",
    "wof:placetype":"locality"
},
  "geometry": {"coordinates":[-0.28872,14.02377],"type":"Point"}
}