{
  "type": "Feature",
  "properties": {
    "gn:admin1_code":"12",
    "gn:admin2_code":"33",
    "gn:asciiname":"Lao",
    "gn:country_code":"BF",
    "gn:dem":255,
    "gn:feature_class":"P",
    "gn:feature_code":"PPL",
    "gn:name":"Lao",
    "gn:population":0,
    "gn:timezone":"Africa/Ouagadougou",
    "iso:country":"BF",
    "name:cat_x_preferred":[
        "Lao"
    ],
    "name:ceb_x_preferred":[
        "Lao"
    ],
    "name:cym_x_preferred":[
        "Lao"
    ],
    "name:fin_x_preferred":[
        "Lao"
    ],
    "name:fra_x_preferred":[
        "Lao"
    ],
    "name:hrv_x_preferred":[
        "Lao"
    ],
    "name:nld_x_preferred":[
        "Lao"
    ],
    "name:pol_x_preferred":[
        "Lao"
    ],
    "name:por_x_preferred":[
        "Lao"
    ],
    "name:spa_x_preferred":[
        "Lao"
    ],
    "name:swe_x_preferred":[
        "Lao"
    ],
    "name:und_x_variant":[
        "Gountour\u00e9"
    ],
    "name:uzb_x_preferred":[
        "Lao"
    ],
    "name:vie_x_preferred":[
        "Lao"
    ],
    "wof:name":"Lao",
    "wof:placetype":"locality"
},
  "geometry": {"coordinates":[0.07758,14.40378],"type":"Point"}
}