{
  "type": "Feature",
  "properties": {
    "gn:admin1_code":"01",
    "gn:admin2_code":"58",
    "gn:asciiname":"Balave",
    "gn:country_code":"BF",
    "gn:dem":333,
    "gn:feature_class":"P",
    "gn:feature_code":"PPL",
    "gn:name":"Balav\u00e9",
    "gn:population":0,
    "gn:timezone":"Africa/Ouagadougou",
    "iso:country":"BF",
    "name:und_x_variant":[
        "Balay\u00e9",
        "Balav\u00e9"
    ],
    "wof:name":"Balave",
    "wof:placetype":"locality"
},
  "geometry": {"coordinates":[-4.15681,12.37588],"type":"Point"}
}