{
  "type": "Feature",
  "properties": {
    "gn:admin1_code":"07",
    "gn:admin2_code":"44",
    "gn:asciiname":"Zourma",
    "gn:country_code":"BF",
    "gn:dem":281,
    "gn:feature_class":"P",
    "gn:feature_code":"PPL",
    "gn:name":"Zourma",
    "gn:population":0,
    "gn:timezone":"Africa/Ouagadougou",
    "iso:country":"BF",
    "name:fra_x_preferred":[
        "Zourma"
    ],
    "wof:name":"Zourma",
    "wof:placetype":"locality"
},
  "geometry": {"coordinates":[-0.79556,11.39083],"type":"Point"}
}