{
  "type": "Feature",
  "properties": {
    "gn:admin1_code":"13",
    "gn:asciiname":"Gbingue",
    "gn:country_code":"BF",
    "gn:dem":323,
    "gn:feature_class":"P",
    "gn:feature_code":"PPL",
    "gn:name":"Gbingu\u00e9",
    "gn:population":0,
    "gn:timezone":"Africa/Ouagadougou",
    "iso:country":"BF",
    "name:und_x_variant":[
        "Gbingu\u00e9"
    ],
    "wof:name":"Gbingue",
    "wof:placetype":"locality"
},
  "geometry": {"coordinates":[-3.71667,10.71667],"type":"Point"}
}