{
  "type": "Feature",
  "properties": {
    "gn:admin1_code":"10",
    "gn:admin2_code":"76",
    "gn:asciiname":"Samba",
    "gn:country_code":"BF",
    "gn:dem":323,
    "gn:feature_class":"P",
    "gn:feature_code":"PPL",
    "gn:name":"Samba",
    "gn:population":0,
    "gn:timezone":"Africa/Ouagadougou",
    "iso:country":"BF",
    "name:und_x_variant":[
        "Sammba",
        "Samba"
    ],
    "wof:name":"Samba",
    "wof:placetype":"locality"
},
  "geometry": {"coordinates":[-2.28174,13.02512],"type":"Point"}
}