{
  "type": "Feature",
  "properties": {
    "gn:admin1_code":"05",
    "gn:asciiname":"Tokoumi",
    "gn:country_code":"BF",
    "gn:dem":288,
    "gn:feature_class":"P",
    "gn:feature_code":"PPL",
    "gn:name":"Tokoumi",
    "gn:population":0,
    "gn:timezone":"Africa/Ouagadougou",
    "iso:country":"BF",
    "wof:name":"Tokoumi",
    "wof:placetype":"locality"
},
  "geometry": {"coordinates":[-0.48333,12.95],"type":"Point"}
}