{
  "type": "Feature",
  "properties": {
    "gn:admin1_code":"13",
    "gn:asciiname":"Paoun",
    "gn:country_code":"BF",
    "gn:dem":322,
    "gn:feature_class":"P",
    "gn:feature_code":"PPL",
    "gn:name":"Paoun",
    "gn:population":0,
    "gn:timezone":"Africa/Ouagadougou",
    "iso:country":"BF",
    "wof:name":"Paoun",
    "wof:placetype":"locality"
},
  "geometry": {"coordinates":[-2.98333,10.23333],"type":"Point"}
}