{
  "type": "Feature",
  "properties": {
    "gn:admin1_code":"00",
    "gn:asciiname":"Sambiri",
    "gn:country_code":"BF",
    "gn:dem":311,
    "gn:feature_class":"P",
    "gn:feature_code":"PPL",
    "gn:name":"Sambiri",
    "gn:population":0,
    "gn:timezone":"Africa/Ouagadougou",
    "iso:country":"BF",
    "name:und_x_variant":[
        "sambiri",
        "Sambiri"
    ],
    "wof:name":"Sambiri",
    "wof:placetype":"locality"
},
  "geometry": {"coordinates":[-1.21667,12.41667],"type":"Point"}
}