{
  "type": "Feature",
  "properties": {
    "gn:admin1_code":"01",
    "gn:admin2_code":"58",
    "gn:asciiname":"Doubale",
    "gn:country_code":"BF",
    "gn:dem":300,
    "gn:feature_class":"P",
    "gn:feature_code":"PPL",
    "gn:name":"Doubal\u00e9",
    "gn:population":0,
    "gn:timezone":"Africa/Ouagadougou",
    "iso:country":"BF",
    "wof:name":"Doubale",
    "wof:placetype":"locality"
},
  "geometry": {"coordinates":[-4.0469,12.4142],"type":"Point"}
}