{
  "type": "Feature",
  "properties": {
    "gn:admin1_code":"01",
    "gn:asciiname":"Bitiako",
    "gn:country_code":"BF",
    "gn:dem":292,
    "gn:feature_class":"P",
    "gn:feature_code":"PPL",
    "gn:name":"Bitiako",
    "gn:population":0,
    "gn:timezone":"Africa/Ouagadougou",
    "iso:country":"BF",
    "name:und_x_variant":[
        "Bitia",
        "Bitiako"
    ],
    "wof:name":"Bitiako",
    "wof:placetype":"locality"
},
  "geometry": {"coordinates":[-3.01667,11.81667],"type":"Point"}
}