{
  "type": "Feature",
  "properties": {
    "gn:admin1_code":"01",
    "gn:asciiname":"Bitiako",
    "gn:country_code":"BF",
    "gn:dem":292,
    "gn:feature_class":"P",
    "gn:feature_code":"PPL",
    "gn:name":"Bitiako",
    "gn:population":0,
    "gn:timezone":"Africa/Ouagadougou",
    "iso:country":"BF",
    "name:azb_x_preferred":[
        "\u0628\u06cc\u062a\u06cc\u0627\u06a9\u0648"
    ],
    "name:ceb_x_preferred":[
        "Bitiako"
    ],
    "name:fas_x_preferred":[
        "\u0628\u06cc\u062a\u06cc\u0627\u06a9\u0648"
    ],
    "name:fra_x_preferred":[
        "Bitiako"
    ],
    "name:swe_x_preferred":[
        "Bitiako"
    ],
    "name:und_x_variant":[
        "Bitia"
    ],
    "wof:name":"Bitiako",
    "wof:placetype":"locality"
},
  "geometry": {"coordinates":[-3.01667,11.81667],"type":"Point"}
}