{
  "type": "Feature",
  "properties": {
    "gn:admin1_code":"01",
    "gn:asciiname":"Zoum",
    "gn:country_code":"BF",
    "gn:dem":276,
    "gn:feature_class":"P",
    "gn:feature_code":"PPL",
    "gn:name":"Zoum",
    "gn:population":0,
    "gn:timezone":"Africa/Ouagadougou",
    "iso:country":"BF",
    "wof:name":"Zoum",
    "wof:placetype":"locality"
},
  "geometry": {"coordinates":[-3.98333,12.76667],"type":"Point"}
}