{
  "type": "Feature",
  "properties": {
    "gn:admin1_code":"01",
    "gn:asciiname":"Pahin",
    "gn:country_code":"BF",
    "gn:dem":271,
    "gn:feature_class":"P",
    "gn:feature_code":"PPL",
    "gn:name":"Pahin",
    "gn:population":0,
    "gn:timezone":"Africa/Ouagadougou",
    "iso:country":"BF",
    "wof:name":"Pahin",
    "wof:placetype":"locality"
},
  "geometry": {"coordinates":[-3.23333,11.71667],"type":"Point"}
}