{
  "type": "Feature",
  "properties": {
    "gn:admin1_code":"01",
    "gn:asciiname":"Pahin",
    "gn:country_code":"BF",
    "gn:dem":271,
    "gn:feature_class":"P",
    "gn:feature_code":"PPL",
    "gn:name":"Pahin",
    "gn:population":0,
    "gn:timezone":"Africa/Ouagadougou",
    "iso:country":"BF",
    "name:azb_x_preferred":[
        "\u067e\u0627\u0647\u06cc\u0646"
    ],
    "name:ceb_x_preferred":[
        "Pahin"
    ],
    "name:fas_x_preferred":[
        "\u067e\u0627\u0647\u06cc\u0646"
    ],
    "name:fra_x_preferred":[
        "Pahin"
    ],
    "name:swe_x_preferred":[
        "Pahin"
    ],
    "wof:name":"Pahin",
    "wof:placetype":"locality"
},
  "geometry": {"coordinates":[-3.23333,11.71667],"type":"Point"}
}