{
  "type": "Feature",
  "properties": {
    "gn:admin1_code":"13",
    "gn:asciiname":"Yelintara",
    "gn:country_code":"BF",
    "gn:dem":329,
    "gn:feature_class":"P",
    "gn:feature_code":"PPL",
    "gn:name":"Y\u00e9lintara",
    "gn:population":0,
    "gn:timezone":"Africa/Ouagadougou",
    "iso:country":"BF",
    "wof:name":"Yelintara",
    "wof:placetype":"locality"
},
  "geometry": {"coordinates":[-3.41667,9.98333],"type":"Point"}
}