{
  "type": "Feature",
  "properties": {
    "gn:admin1_code":"01",
    "gn:admin2_code":"58",
    "gn:asciiname":"Zehui",
    "gn:country_code":"BF",
    "gn:dem":316,
    "gn:feature_class":"P",
    "gn:feature_code":"PPL",
    "gn:name":"Z\u00e9hui",
    "gn:population":0,
    "gn:timezone":"Africa/Ouagadougou",
    "iso:country":"BF",
    "wof:name":"Zehui",
    "wof:placetype":"locality"
},
  "geometry": {"coordinates":[-4.159,12.9067],"type":"Point"}
}