{
  "type": "Feature",
  "properties": {
    "gn:admin1_code":"01",
    "gn:asciiname":"Bankoumani",
    "gn:country_code":"BF",
    "gn:dem":269,
    "gn:feature_class":"P",
    "gn:feature_code":"PPL",
    "gn:name":"Bankoumani",
    "gn:population":0,
    "gn:timezone":"Africa/Ouagadougou",
    "iso:country":"BF",
    "wof:name":"Bankoumani",
    "wof:placetype":"locality"
},
  "geometry": {"coordinates":[-3.91667,12.61667],"type":"Point"}
}