{
  "type": "Feature",
  "properties": {
    "gn:admin1_code":"07",
    "gn:admin2_code":"47",
    "gn:asciiname":"Seloguen",
    "gn:country_code":"BF",
    "gn:dem":295,
    "gn:feature_class":"P",
    "gn:feature_code":"PPL",
    "gn:name":"S\u00e9loguen",
    "gn:population":0,
    "gn:timezone":"Africa/Ouagadougou",
    "iso:country":"BF",
    "name:und_x_variant":[
        "S\u00e9logen",
        "S\u00e9loguen"
    ],
    "wof:name":"Seloguen",
    "wof:placetype":"locality"
},
  "geometry": {"coordinates":[-1.30639,12.03417],"type":"Point"}
}