{
  "type": "Feature",
  "properties": {
    "gn:admin1_code":"10",
    "gn:admin2_code":"76",
    "gn:asciiname":"Keleguem",
    "gn:country_code":"BF",
    "gn:dem":316,
    "gn:feature_class":"P",
    "gn:feature_code":"PPL",
    "gn:name":"K\u00e9l\u00e9guem",
    "gn:population":0,
    "gn:timezone":"Africa/Ouagadougou",
    "iso:country":"BF",
    "name:und_x_variant":[
        "K\u00e9l\u00e9gom",
        "Ki\u00e9l\u00e9guem",
        "K\u00e9l\u00e9kom",
        "Kelgueme",
        "K\u00e9l\u00e9guem"
    ],
    "wof:name":"Keleguem",
    "wof:placetype":"locality"
},
  "geometry": {"coordinates":[-2.17075,13.16807],"type":"Point"}
}