{
  "type": "Feature",
  "properties": {
    "gn:admin1_code":"13",
    "gn:asciiname":"Tanloule",
    "gn:country_code":"BF",
    "gn:dem":335,
    "gn:feature_class":"P",
    "gn:feature_code":"PPL",
    "gn:name":"Tanloul\u00e9",
    "gn:population":0,
    "gn:timezone":"Africa/Ouagadougou",
    "iso:country":"BF",
    "wof:name":"Tanloule",
    "wof:placetype":"locality"
},
  "geometry": {"coordinates":[-3.15,11.15],"type":"Point"}
}