{
  "type": "Feature",
  "properties": {
    "gn:admin1_code":"09",
    "gn:admin2_code":"51",
    "gn:asciiname":"Yegueresso",
    "gn:country_code":"BF",
    "gn:dem":345,
    "gn:feature_class":"P",
    "gn:feature_code":"PPL",
    "gn:name":"Y\u00e9gu\u00e9resso",
    "gn:population":0,
    "gn:timezone":"Africa/Ouagadougou",
    "iso:country":"BF",
    "wof:name":"Yegueresso",
    "wof:placetype":"locality"
},
  "geometry": {"coordinates":[-4.15622,11.155],"type":"Point"}
}