{
  "type": "Feature",
  "properties": {
    "gn:admin1_code":"12",
    "gn:admin2_code":"40",
    "gn:asciiname":"Ouapassi",
    "gn:country_code":"BF",
    "gn:dem":286,
    "gn:feature_class":"P",
    "gn:feature_code":"PPL",
    "gn:name":"Ouapassi",
    "gn:population":0,
    "gn:timezone":"Africa/Ouagadougou",
    "iso:country":"BF",
    "name:fra_x_preferred":[
        "Ouapassi"
    ],
    "name:und_x_variant":[
        "Ouapass\u00e9",
        "Ouapassi"
    ],
    "wof:name":"Ouapassi",
    "wof:placetype":"locality"
},
  "geometry": {"coordinates":[-0.74704,13.93964],"type":"Point"}
}