{
  "type": "Feature",
  "properties": {
    "gn:admin1_code":"06",
    "gn:asciiname":"Loro",
    "gn:country_code":"BF",
    "gn:dem":260,
    "gn:feature_class":"P",
    "gn:feature_code":"PPL",
    "gn:name":"Loro",
    "gn:population":0,
    "gn:timezone":"Africa/Ouagadougou",
    "iso:country":"BF",
    "name:ceb_x_preferred":[
        "Loro"
    ],
    "name:deu_x_preferred":[
        "Loro"
    ],
    "name:fra_x_preferred":[
        "Loro"
    ],
    "name:ita_x_preferred":[
        "Loro"
    ],
    "name:rus_x_preferred":[
        "\u041b\u043e\u0440\u043e"
    ],
    "name:spa_x_preferred":[
        "Loro"
    ],
    "name:swe_x_preferred":[
        "Loro"
    ],
    "name:tgl_x_preferred":[
        "Loro"
    ],
    "name:ukr_x_preferred":[
        "\u041b\u043e\u0440\u043e"
    ],
    "wof:name":"Loro",
    "wof:placetype":"locality"
},
  "geometry": {"coordinates":[-2.73333,11.85],"type":"Point"}
}