{
  "type": "Feature",
  "properties": {
    "gn:admin1_code":"10",
    "gn:admin2_code":"76",
    "gn:asciiname":"Sim",
    "gn:country_code":"BF",
    "gn:dem":310,
    "gn:feature_class":"P",
    "gn:feature_code":"PPL",
    "gn:name":"Sim",
    "gn:population":0,
    "gn:timezone":"Africa/Ouagadougou",
    "iso:country":"BF",
    "name:bre_x_preferred":[
        "Sim"
    ],
    "name:cat_x_preferred":[
        "Sim"
    ],
    "name:ceb_x_preferred":[
        "Sim"
    ],
    "name:kat_x_preferred":[
        "\u10e1\u10d8\u10db\u10d8"
    ],
    "name:nld_x_preferred":[
        "Sim"
    ],
    "name:nor_x_preferred":[
        "Sim"
    ],
    "name:por_x_preferred":[
        "Sim"
    ],
    "name:spa_x_preferred":[
        "Sim"
    ],
    "name:swe_x_preferred":[
        "SIM"
    ],
    "name:vie_x_preferred":[
        "Sim"
    ],
    "wof:name":"Sim",
    "wof:placetype":"locality"
},
  "geometry": {"coordinates":[-2.57991,13.79438],"type":"Point"}
}