{
  "type": "Feature",
  "properties": {
    "gn:admin1_code":"00",
    "gn:asciiname":"Salaren",
    "gn:country_code":"BF",
    "gn:dem":301,
    "gn:feature_class":"P",
    "gn:feature_code":"PPL",
    "gn:name":"Salaren",
    "gn:population":0,
    "gn:timezone":"Africa/Ouagadougou",
    "iso:country":"BF",
    "wof:name":"Salaren",
    "wof:placetype":"locality"
},
  "geometry": {"coordinates":[-0.51667,12.31667],"type":"Point"}
}