{
  "type": "Feature",
  "properties": {
    "gn:admin1_code":"08",
    "gn:asciiname":"Madiagoune",
    "gn:country_code":"BF",
    "gn:dem":213,
    "gn:feature_class":"P",
    "gn:feature_code":"PPL",
    "gn:name":"Madiagoun\u00e9",
    "gn:population":0,
    "gn:timezone":"Africa/Ouagadougou",
    "iso:country":"BF",
    "name:und_x_variant":[
        "Madiagdune",
        "Nadiagoun",
        "Madiagune",
        "Madiagoun\u00e9"
    ],
    "wof:name":"Madiagoune",
    "wof:placetype":"locality"
},
  "geometry": {"coordinates":[0.83333,11.16667],"type":"Point"}
}