{
  "type": "Feature",
  "properties": {
    "gn:admin1_code":"01",
    "gn:admin2_code":"58",
    "gn:asciiname":"Sikogo",
    "gn:country_code":"BF",
    "gn:dem":275,
    "gn:feature_class":"P",
    "gn:feature_code":"PPL",
    "gn:name":"Sikogo",
    "gn:population":0,
    "gn:timezone":"Africa/Ouagadougou",
    "iso:country":"BF",
    "wof:name":"Sikogo",
    "wof:placetype":"locality"
},
  "geometry": {"coordinates":[-3.8838,13.1737],"type":"Point"}
}