{
  "type": "Feature",
  "properties": {
    "gn:admin1_code":"06",
    "gn:asciiname":"Basziri",
    "gn:country_code":"BF",
    "gn:dem":289,
    "gn:feature_class":"P",
    "gn:feature_code":"PPL",
    "gn:name":"Basziri",
    "gn:population":0,
    "gn:timezone":"Africa/Ouagadougou",
    "iso:country":"BF",
    "name:azb_x_preferred":[
        "\u0628\u0627\u0633\u0632\u06cc\u0631\u06cc"
    ],
    "name:fas_x_preferred":[
        "\u0628\u0627\u0633\u0632\u06cc\u0631\u06cc"
    ],
    "name:fra_x_preferred":[
        "Basziri"
    ],
    "wof:name":"Basziri",
    "wof:placetype":"locality"
},
  "geometry": {"coordinates":[-2.21667,12.65],"type":"Point"}
}