{
  "type": "Feature",
  "properties": {
    "gn:admin1_code":"12",
    "gn:admin2_code":"40",
    "gn:asciiname":"Oulool Dyouam",
    "gn:country_code":"BF",
    "gn:dem":293,
    "gn:feature_class":"P",
    "gn:feature_code":"PPL",
    "gn:name":"Oulool Dyouam",
    "gn:population":0,
    "gn:timezone":"Africa/Ouagadougou",
    "iso:country":"BF",
    "wof:name":"Oulool Dyouam",
    "wof:placetype":"locality"
},
  "geometry": {"coordinates":[-1.76761,14.14201],"type":"Point"}
}