{
  "type": "Feature",
  "properties": {
    "gn:admin1_code":"11",
    "gn:asciiname":"Kandatenga",
    "gn:country_code":"BF",
    "gn:dem":306,
    "gn:feature_class":"P",
    "gn:feature_code":"PPL",
    "gn:name":"Kandatenga",
    "gn:population":0,
    "gn:timezone":"Africa/Ouagadougou",
    "iso:country":"BF",
    "wof:name":"Kandatenga",
    "wof:placetype":"locality"
},
  "geometry": {"coordinates":[-0.56667,12.15],"type":"Point"}
}