{
  "type": "Feature",
  "properties": {
    "gn:admin1_code":"11",
    "gn:asciiname":"Koumisi",
    "gn:country_code":"BF",
    "gn:dem":309,
    "gn:feature_class":"P",
    "gn:feature_code":"PPL",
    "gn:name":"Koumisi",
    "gn:population":0,
    "gn:timezone":"Africa/Ouagadougou",
    "iso:country":"BF",
    "name:und_x_variant":[
        "Koumissi",
        "Koumisi"
    ],
    "wof:name":"Koumisi",
    "wof:placetype":"locality"
},
  "geometry": {"coordinates":[-1.46667,12.86667],"type":"Point"}
}