{
  "type": "Feature",
  "properties": {
    "gn:admin1_code":"08",
    "gn:admin2_code":"42",
    "gn:asciiname":"Kanlayenou",
    "gn:country_code":"BF",
    "gn:dem":234,
    "gn:feature_class":"P",
    "gn:feature_code":"PPL",
    "gn:name":"Kanlay\u00e9nou",
    "gn:population":0,
    "gn:timezone":"Africa/Ouagadougou",
    "iso:country":"BF",
    "wof:name":"Kanlayenou",
    "wof:placetype":"locality"
},
  "geometry": {"coordinates":[2.15985,12.63057],"type":"Point"}
}