{
  "type": "Feature",
  "properties": {
    "gn:admin1_code":"10",
    "gn:asciiname":"Toesse",
    "gn:country_code":"BF",
    "gn:dem":299,
    "gn:feature_class":"P",
    "gn:feature_code":"PPL",
    "gn:name":"To\u00e8ss\u00e9",
    "gn:population":0,
    "gn:timezone":"Africa/Ouagadougou",
    "iso:country":"BF",
    "name:und_x_variant":[
        "Tw\u00e9s\u00e9",
        "To\u00e8ss\u00e9"
    ],
    "wof:name":"Toesse",
    "wof:placetype":"locality"
},
  "geometry": {"coordinates":[-2.38333,12.73333],"type":"Point"}
}