{
  "type": "Feature",
  "properties": {
    "gn:admin1_code":"12",
    "gn:admin2_code":"75",
    "gn:asciiname":"Gongongou",
    "gn:country_code":"BF",
    "gn:dem":253,
    "gn:feature_class":"P",
    "gn:feature_code":"PPL",
    "gn:name":"Gongongou",
    "gn:population":0,
    "gn:timezone":"Africa/Ouagadougou",
    "iso:country":"BF",
    "wof:name":"Gongongou",
    "wof:placetype":"locality"
},
  "geometry": {"coordinates":[0.63821,13.43503],"type":"Point"}
}