{
  "type": "Feature",
  "properties": {
    "gn:admin1_code":"13",
    "gn:asciiname":"Kolibie",
    "gn:country_code":"BF",
    "gn:dem":263,
    "gn:feature_class":"P",
    "gn:feature_code":"PPL",
    "gn:name":"Kolibi\u00e9",
    "gn:population":0,
    "gn:timezone":"Africa/Ouagadougou",
    "iso:country":"BF",
    "wof:name":"Kolibie",
    "wof:placetype":"locality"
},
  "geometry": {"coordinates":[-2.85,10.08333],"type":"Point"}
}