{
  "type": "Feature",
  "properties": {
    "gn:admin1_code":"12",
    "gn:admin2_code":"75",
    "gn:asciiname":"Dina Lahi",
    "gn:country_code":"BF",
    "gn:dem":268,
    "gn:feature_class":"P",
    "gn:feature_code":"PPL",
    "gn:name":"Dina Lahi",
    "gn:population":0,
    "gn:timezone":"Africa/Ouagadougou",
    "iso:country":"BF",
    "wof:name":"Dina Lahi",
    "wof:placetype":"locality"
},
  "geometry": {"coordinates":[0.40925,13.63347],"type":"Point"}
}