{
  "type": "Feature",
  "properties": {
    "gn:admin1_code":"05",
    "gn:admin2_code":"70",
    "gn:asciiname":"Lonnti",
    "gn:country_code":"BF",
    "gn:dem":349,
    "gn:feature_class":"P",
    "gn:feature_code":"PPL",
    "gn:name":"Lonnti",
    "gn:population":0,
    "gn:timezone":"Africa/Ouagadougou",
    "iso:country":"BF",
    "wof:name":"Lonnti",
    "wof:placetype":"locality"
},
  "geometry": {"coordinates":[-1.35553,13.07031],"type":"Point"}
}