{
  "type": "Feature",
  "properties": {
    "gn:admin1_code":"11",
    "gn:asciiname":"Ouidi",
    "gn:country_code":"BF",
    "gn:dem":290,
    "gn:feature_class":"P",
    "gn:feature_code":"PPL",
    "gn:name":"Ouidi",
    "gn:population":0,
    "gn:timezone":"Africa/Ouagadougou",
    "iso:country":"BF",
    "wof:name":"Ouidi",
    "wof:placetype":"locality"
},
  "geometry": {"coordinates":[-0.73333,12.33333],"type":"Point"}
}