{
  "type": "Feature",
  "properties": {
    "gn:admin1_code":"01",
    "gn:asciiname":"Souanko",
    "gn:country_code":"BF",
    "gn:dem":354,
    "gn:feature_class":"P",
    "gn:feature_code":"PPL",
    "gn:name":"Souanko",
    "gn:population":0,
    "gn:timezone":"Africa/Ouagadougou",
    "iso:country":"BF",
    "wof:name":"Souanko",
    "wof:placetype":"locality"
},
  "geometry": {"coordinates":[-3.56667,12.11667],"type":"Point"}
}