{
  "type": "Feature",
  "properties": {
    "gn:admin1_code":"05",
    "gn:admin2_code":"70",
    "gn:asciiname":"Rabele",
    "gn:country_code":"BF",
    "gn:dem":326,
    "gn:feature_class":"P",
    "gn:feature_code":"PPL",
    "gn:name":"Rab\u00e9l\u00e9",
    "gn:population":0,
    "gn:timezone":"Africa/Ouagadougou",
    "iso:country":"BF",
    "wof:name":"Rabele",
    "wof:placetype":"locality"
},
  "geometry": {"coordinates":[-1.32807,13.05186],"type":"Point"}
}