{
  "type": "Feature",
  "properties": {
    "gn:admin1_code":"06",
    "gn:asciiname":"Bouyase",
    "gn:country_code":"BF",
    "gn:dem":283,
    "gn:feature_class":"P",
    "gn:feature_code":"PPL",
    "gn:name":"Bouyas\u00e9",
    "gn:population":0,
    "gn:timezone":"Africa/Ouagadougou",
    "iso:country":"BF",
    "wof:name":"Bouyase",
    "wof:placetype":"locality"
},
  "geometry": {"coordinates":[-2.38333,12.05],"type":"Point"}
}