{
  "type": "Feature",
  "properties": {
    "gn:admin1_code":"16",
    "gn:asciiname":"Kankaguen",
    "gn:country_code":"BF",
    "gn:dem":289,
    "gn:feature_class":"P",
    "gn:feature_code":"PPL",
    "gn:name":"Kankaguen",
    "gn:population":0,
    "gn:timezone":"Africa/Ouagadougou",
    "iso:country":"BF",
    "wof:name":"Kankaguen",
    "wof:placetype":"locality"
},
  "geometry": {"coordinates":[-1.2125,12.15667],"type":"Point"}
}