{
  "type": "Feature",
  "properties": {
    "gn:admin1_code":"03",
    "gn:admin2_code":"53",
    "gn:asciiname":"Goguen",
    "gn:country_code":"BF",
    "gn:dem":329,
    "gn:feature_class":"P",
    "gn:feature_code":"PPL",
    "gn:name":"Goguen",
    "gn:population":0,
    "gn:timezone":"Africa/Ouagadougou",
    "iso:country":"BF",
    "name:und_x_variant":[
        "Gogen",
        "Goguen",
        "Goghin",
        "Goguin"
    ],
    "wof:name":"Goguen",
    "wof:placetype":"locality"
},
  "geometry": {"coordinates":[-1.71917,12.335],"type":"Point"}
}