{
  "type": "Feature",
  "properties": {
    "gn:admin1_code":"05",
    "gn:admin2_code":"70",
    "gn:asciiname":"Bendogo",
    "gn:country_code":"BF",
    "gn:dem":312,
    "gn:feature_class":"P",
    "gn:feature_code":"PPL",
    "gn:name":"B\u00e8ndogo",
    "gn:population":0,
    "gn:timezone":"Africa/Ouagadougou",
    "iso:country":"BF",
    "wof:name":"Bendogo",
    "wof:placetype":"locality"
},
  "geometry": {"coordinates":[-1.30262,13.16662],"type":"Point"}
}