{
  "type": "Feature",
  "properties": {
    "gn:admin1_code":"08",
    "gn:asciiname":"Bartibougou",
    "gn:country_code":"BF",
    "gn:dem":263,
    "gn:feature_class":"P",
    "gn:feature_code":"PPL",
    "gn:name":"Bartibougou",
    "gn:population":0,
    "gn:timezone":"Africa/Ouagadougou",
    "iso:country":"BF",
    "wof:name":"Bartibougou",
    "wof:placetype":"locality"
},
  "geometry": {"coordinates":[0.79375,12.87292],"type":"Point"}
}