{
  "type": "Feature",
  "properties": {
    "gn:admin1_code":"08",
    "gn:admin2_code":"21",
    "gn:asciiname":"Tanbwanga",
    "gn:country_code":"BF",
    "gn:dem":285,
    "gn:feature_class":"P",
    "gn:feature_code":"PPL",
    "gn:name":"Tanbwanga",
    "gn:population":0,
    "gn:timezone":"Africa/Ouagadougou",
    "iso:country":"BF",
    "wof:name":"Tanbwanga",
    "wof:placetype":"locality"
},
  "geometry": {"coordinates":[-0.16642,13.00641],"type":"Point"}
}