{
  "type": "Feature",
  "properties": {
    "gn:admin1_code":"08",
    "gn:admin2_code":"42",
    "gn:asciiname":"Nabaga",
    "gn:country_code":"BF",
    "gn:dem":243,
    "gn:feature_class":"P",
    "gn:feature_code":"PPL",
    "gn:name":"Nabaga",
    "gn:population":0,
    "gn:timezone":"Africa/Ouagadougou",
    "iso:country":"BF",
    "wof:name":"Nabaga",
    "wof:placetype":"locality"
},
  "geometry": {"coordinates":[2.0374,12.34435],"type":"Point"}
}