{
  "type": "Feature",
  "properties": {
    "gn:admin1_code":"09",
    "gn:admin2_code":"51",
    "gn:asciiname":"Toussiemasso",
    "gn:country_code":"BF",
    "gn:dem":511,
    "gn:feature_class":"P",
    "gn:feature_code":"PPL",
    "gn:name":"Toussi\u00e9masso",
    "gn:population":0,
    "gn:timezone":"Africa/Ouagadougou",
    "iso:country":"BF",
    "wof:name":"Toussiemasso",
    "wof:placetype":"locality"
},
  "geometry": {"coordinates":[-4.84483,10.9772],"type":"Point"}
}