{
  "type": "Feature",
  "properties": {
    "gn:admin1_code":"08",
    "gn:admin2_code":"21",
    "gn:asciiname":"Ouro Tongogo",
    "gn:country_code":"BF",
    "gn:dem":296,
    "gn:feature_class":"P",
    "gn:feature_code":"PPL",
    "gn:name":"Ouro Tongogo",
    "gn:population":0,
    "gn:timezone":"Africa/Ouagadougou",
    "iso:country":"BF",
    "wof:name":"Ouro Tongogo",
    "wof:placetype":"locality"
},
  "geometry": {"coordinates":[0.0245,13.5584],"type":"Point"}
}