{
  "type": "Feature",
  "properties": {
    "gn:admin1_code":"08",
    "gn:asciiname":"Pamdyega",
    "gn:country_code":"BF",
    "gn:dem":275,
    "gn:feature_class":"P",
    "gn:feature_code":"PPL",
    "gn:name":"Pamdyega",
    "gn:population":0,
    "gn:timezone":"Africa/Ouagadougou",
    "iso:country":"BF",
    "wof:name":"Pamdyega",
    "wof:placetype":"locality"
},
  "geometry": {"coordinates":[0.36667,12.75],"type":"Point"}
}