{
  "type": "Feature",
  "properties": {
    "gn:admin1_code":"13",
    "gn:asciiname":"Bohira",
    "gn:country_code":"BF",
    "gn:dem":303,
    "gn:feature_class":"P",
    "gn:feature_code":"PPL",
    "gn:name":"Bohira",
    "gn:population":0,
    "gn:timezone":"Africa/Ouagadougou",
    "iso:country":"BF",
    "wof:name":"Bohira",
    "wof:placetype":"locality"
},
  "geometry": {"coordinates":[-3.28333,10.45],"type":"Point"}
}