{
  "type": "Feature",
  "properties": {
    "gn:admin1_code":"07",
    "gn:admin2_code":"47",
    "gn:asciiname":"Ouavousse",
    "gn:country_code":"BF",
    "gn:dem":326,
    "gn:feature_class":"P",
    "gn:feature_code":"PPL",
    "gn:name":"Ouavouss\u00e9",
    "gn:population":0,
    "gn:timezone":"Africa/Ouagadougou",
    "iso:country":"BF",
    "wof:name":"Ouavousse",
    "wof:placetype":"locality"
},
  "geometry": {"coordinates":[-1.36833,12.04667],"type":"Point"}
}