{
  "type": "Feature",
  "properties": {
    "gn:admin1_code":"09",
    "gn:admin2_code":"54",
    "gn:asciiname":"Samorogouan",
    "gn:country_code":"BF",
    "gn:dem":375,
    "gn:feature_class":"P",
    "gn:feature_code":"PPL",
    "gn:name":"Samorogouan",
    "gn:population":0,
    "gn:timezone":"Africa/Ouagadougou",
    "iso:country":"BF",
    "name:und_x_variant":[
        "Samorogan",
        "Samorogwan",
        "Samorokogan",
        "Samorogouan"
    ],
    "wof:name":"Samorogouan",
    "wof:placetype":"locality"
},
  "geometry": {"coordinates":[-4.93882,11.39249],"type":"Point"}
}