{
  "type": "Feature",
  "properties": {
    "gn:admin1_code":"08",
    "gn:admin2_code":"56",
    "gn:asciiname":"Bongori",
    "gn:country_code":"BF",
    "gn:dem":261,
    "gn:feature_class":"P",
    "gn:feature_code":"PPL",
    "gn:name":"Bongori",
    "gn:population":0,
    "gn:timezone":"Africa/Ouagadougou",
    "iso:country":"BF",
    "wof:name":"Bongori",
    "wof:placetype":"locality"
},
  "geometry": {"coordinates":[1.00205,12.73023],"type":"Point"}
}