{
  "type": "Feature",
  "properties": {
    "gn:admin1_code":"10",
    "gn:admin2_code":"76",
    "gn:asciiname":"Benie Tanga",
    "gn:country_code":"BF",
    "gn:dem":320,
    "gn:feature_class":"P",
    "gn:feature_code":"PPL",
    "gn:name":"B\u00e9ni\u00e9 Tanga",
    "gn:population":0,
    "gn:timezone":"Africa/Ouagadougou",
    "iso:country":"BF",
    "wof:name":"Benie Tanga",
    "wof:placetype":"locality"
},
  "geometry": {"coordinates":[-2.68547,13.74602],"type":"Point"}
}