{
  "type": "Feature",
  "properties": {
    "gn:admin1_code":"01",
    "gn:admin2_code":"73",
    "gn:asciiname":"Gourmassa",
    "gn:country_code":"BF",
    "gn:dem":308,
    "gn:feature_class":"P",
    "gn:feature_code":"PPL",
    "gn:name":"Gourmassa",
    "gn:population":0,
    "gn:timezone":"Africa/Ouagadougou",
    "iso:country":"BF",
    "wof:name":"Gourmassa",
    "wof:placetype":"locality"
},
  "geometry": {"coordinates":[-2.53586,13.18205],"type":"Point"}
}