{
  "type": "Feature",
  "properties": {
    "gn:admin1_code":"10",
    "gn:admin2_code":"76",
    "gn:asciiname":"Leleguere",
    "gn:country_code":"BF",
    "gn:dem":321,
    "gn:feature_class":"P",
    "gn:feature_code":"PPL",
    "gn:name":"L\u00e9l\u00e9gu\u00e9r\u00e9",
    "gn:population":0,
    "gn:timezone":"Africa/Ouagadougou",
    "iso:country":"BF",
    "name:und_x_variant":[
        "L\u00e9l\u00e9gu\u00e9n\u00e9",
        "L\u00e9l\u00e9gu\u00e9r\u00e9"
    ],
    "wof:name":"Leleguere",
    "wof:placetype":"locality"
},
  "geometry": {"coordinates":[-2.40784,13.27185],"type":"Point"}
}