{
  "type": "Feature",
  "properties": {
    "gn:admin1_code":"07",
    "gn:admin2_code":"47",
    "gn:asciiname":"Goumsa",
    "gn:country_code":"BF",
    "gn:dem":313,
    "gn:feature_class":"P",
    "gn:feature_code":"PPL",
    "gn:name":"Goumsa",
    "gn:population":0,
    "gn:timezone":"Africa/Ouagadougou",
    "iso:country":"BF",
    "name:azb_x_preferred":[
        "\u0642\u0648\u0645\u0633\u0627"
    ],
    "name:ceb_x_preferred":[
        "Goumsa"
    ],
    "name:fas_x_preferred":[
        "\u06af\u0648\u0645\u0633\u0627"
    ],
    "name:swe_x_preferred":[
        "Goumsa"
    ],
    "wof:name":"Goumsa",
    "wof:placetype":"locality"
},
  "geometry": {"coordinates":[-1.86306,12.05611],"type":"Point"}
}