{
  "type": "Feature",
  "properties": {
    "gn:admin1_code":"04",
    "gn:asciiname":"Naftenga",
    "gn:country_code":"BF",
    "gn:dem":291,
    "gn:feature_class":"P",
    "gn:feature_code":"PPL",
    "gn:name":"Naftenga",
    "gn:population":0,
    "gn:timezone":"Africa/Ouagadougou",
    "iso:country":"BF",
    "wof:name":"Naftenga",
    "wof:placetype":"locality"
},
  "geometry": {"coordinates":[-0.38333,12.11667],"type":"Point"}
}