{
  "type": "Feature",
  "properties": {
    "gn:admin1_code":"10",
    "gn:admin2_code":"76",
    "gn:asciiname":"Bene",
    "gn:country_code":"BF",
    "gn:dem":341,
    "gn:feature_class":"P",
    "gn:feature_code":"PPL",
    "gn:name":"B\u00e8n\u00e9",
    "gn:population":0,
    "gn:timezone":"Africa/Ouagadougou",
    "iso:country":"BF",
    "name:ceb_x_preferred":[
        "Bene"
    ],
    "name:deu_x_preferred":[
        "Bene"
    ],
    "name:fra_x_preferred":[
        "Bene"
    ],
    "name:ita_x_preferred":[
        "Bene"
    ],
    "name:rus_x_preferred":[
        "\u0411\u0435\u043d\u0435"
    ],
    "name:srp_x_preferred":[
        "\u0411\u0435\u043d\u0435"
    ],
    "name:swe_x_preferred":[
        "Bene"
    ],
    "name:ukr_x_preferred":[
        "\u0411\u0435\u043d\u0435"
    ],
    "wof:name":"Bene",
    "wof:placetype":"locality"
},
  "geometry": {"coordinates":[-2.32323,13.71609],"type":"Point"}
}