{
  "type": "Feature",
  "properties": {
    "gn:admin1_code":"10",
    "gn:asciiname":"Bargo",
    "gn:country_code":"BF",
    "gn:dem":313,
    "gn:feature_class":"P",
    "gn:feature_code":"PPL",
    "gn:name":"Bargo",
    "gn:population":0,
    "gn:timezone":"Africa/Ouagadougou",
    "iso:country":"BF",
    "wof:name":"Bargo",
    "wof:placetype":"locality"
},
  "geometry": {"coordinates":[-2.05,12.73333],"type":"Point"}
}