{
  "type": "Feature",
  "properties": {
    "gn:admin1_code":"11",
    "gn:asciiname":"Lalle",
    "gn:country_code":"BF",
    "gn:dem":304,
    "gn:feature_class":"P",
    "gn:feature_code":"PPL",
    "gn:name":"Lall\u00e9",
    "gn:population":0,
    "gn:timezone":"Africa/Ouagadougou",
    "iso:country":"BF",
    "wof:name":"Lalle",
    "wof:placetype":"locality"
},
  "geometry": {"coordinates":[-0.86667,12.43333],"type":"Point"}
}