{
  "type": "Feature",
  "properties": {
    "gn:admin1_code":"08",
    "gn:admin2_code":"42",
    "gn:asciiname":"Kerta",
    "gn:country_code":"BF",
    "gn:dem":261,
    "gn:feature_class":"P",
    "gn:feature_code":"PPL",
    "gn:name":"K\u00e8rta",
    "gn:population":0,
    "gn:timezone":"Africa/Ouagadougou",
    "iso:country":"BF",
    "name:ces_x_preferred":[
        "Kerta"
    ],
    "name:epo_x_preferred":[
        "Kerta"
    ],
    "name:fas_x_preferred":[
        "\u06a9\u0631\u062a\u0627"
    ],
    "name:fra_x_preferred":[
        "Kerta"
    ],
    "name:hun_x_preferred":[
        "Kerta"
    ],
    "name:ita_x_preferred":[
        "Kerta"
    ],
    "name:msa_x_preferred":[
        "Kerta"
    ],
    "name:nld_x_preferred":[
        "Kerta"
    ],
    "name:ron_x_preferred":[
        "Kerta"
    ],
    "name:slk_x_preferred":[
        "Kerta"
    ],
    "name:slv_x_preferred":[
        "Kerta"
    ],
    "name:swe_x_preferred":[
        "Kerta"
    ],
    "name:vie_x_preferred":[
        "Kerta"
    ],
    "name:zho_x_preferred":[
        "\u51ef\u5c14\u9676"
    ],
    "wof:name":"Kerta",
    "wof:placetype":"locality"
},
  "geometry": {"coordinates":[1.50525,12.66243],"type":"Point"}
}