{
  "type": "Feature",
  "properties": {
    "gn:admin1_code":"09",
    "gn:admin2_code":"54",
    "gn:asciiname":"Niene",
    "gn:country_code":"BF",
    "gn:dem":325,
    "gn:feature_class":"P",
    "gn:feature_code":"PPL",
    "gn:name":"Ni\u00e9n\u00e9",
    "gn:population":0,
    "gn:timezone":"Africa/Ouagadougou",
    "iso:country":"BF",
    "wof:name":"Niene",
    "wof:placetype":"locality"
},
  "geometry": {"coordinates":[-4.86215,11.95867],"type":"Point"}
}