{
  "type": "Feature",
  "properties": {
    "gn:admin1_code":"03",
    "gn:admin2_code":"53",
    "gn:asciiname":"Wamtenga",
    "gn:country_code":"BF",
    "gn:dem":313,
    "gn:feature_class":"P",
    "gn:feature_code":"PPL",
    "gn:name":"Wamtenga",
    "gn:population":0,
    "gn:timezone":"Africa/Ouagadougou",
    "iso:country":"BF",
    "name:und_x_variant":[
        "Ouamtenga"
    ],
    "wof:name":"Wamtenga",
    "wof:placetype":"locality"
},
  "geometry": {"coordinates":[-1.41472,12.38016],"type":"Point"}
}