{
  "type": "Feature",
  "properties": {
    "gn:admin1_code":"08",
    "gn:admin2_code":"21",
    "gn:asciiname":"Dakiri",
    "gn:country_code":"BF",
    "gn:dem":263,
    "gn:feature_class":"P",
    "gn:feature_code":"PPL",
    "gn:name":"Dakiri",
    "gn:population":0,
    "gn:timezone":"Africa/Ouagadougou",
    "iso:country":"BF",
    "name:ceb_x_preferred":[
        "Dakiri"
    ],
    "name:fra_x_preferred":[
        "Dakiri"
    ],
    "name:swe_x_preferred":[
        "Dakiri"
    ],
    "wof:name":"Dakiri",
    "wof:placetype":"locality"
},
  "geometry": {"coordinates":[-0.24471,13.29558],"type":"Point"}
}