{
  "type": "Feature",
  "properties": {
    "gn:admin1_code":"05",
    "gn:admin2_code":"70",
    "gn:asciiname":"Nongo",
    "gn:country_code":"BF",
    "gn:dem":318,
    "gn:feature_class":"P",
    "gn:feature_code":"PPL",
    "gn:name":"Nongo",
    "gn:population":0,
    "gn:timezone":"Africa/Ouagadougou",
    "iso:country":"BF",
    "name:und_x_variant":[
        "Diongo",
        "Nongo"
    ],
    "wof:name":"Nongo",
    "wof:placetype":"locality"
},
  "geometry": {"coordinates":[-1.09061,13.33804],"type":"Point"}
}