{
  "type": "Feature",
  "properties": {
    "gn:admin1_code":"10",
    "gn:admin2_code":"76",
    "gn:asciiname":"Banh",
    "gn:country_code":"BF",
    "gn:dem":304,
    "gn:feature_class":"P",
    "gn:feature_code":"PPL",
    "gn:name":"Banh",
    "gn:population":0,
    "gn:timezone":"Africa/Ouagadougou",
    "iso:country":"BF",
    "name:und_x_variant":[
        "B\u00e8nh",
        "Banh"
    ],
    "wof:name":"Banh",
    "wof:placetype":"locality"
},
  "geometry": {"coordinates":[-2.70945,13.79265],"type":"Point"}
}