{
  "type": "Feature",
  "properties": {
    "gn:admin1_code":"10",
    "gn:admin2_code":"76",
    "gn:asciiname":"Zay",
    "gn:country_code":"BF",
    "gn:dem":298,
    "gn:feature_class":"P",
    "gn:feature_code":"PPL",
    "gn:name":"Zay",
    "gn:population":0,
    "gn:timezone":"Africa/Ouagadougou",
    "iso:country":"BF",
    "name:ceb_x_preferred":[
        "Zay"
    ],
    "name:deu_x_preferred":[
        "Zay"
    ],
    "name:fra_x_preferred":[
        "Zay"
    ],
    "name:nds_x_preferred":[
        "Zay"
    ],
    "name:swe_x_preferred":[
        "Zay"
    ],
    "name:und_x_variant":[
        "Zay\u00e9",
        "Zay"
    ],
    "wof:name":"Zay",
    "wof:placetype":"locality"
},
  "geometry": {"coordinates":[-2.35809,13.99],"type":"Point"}
}