{
  "type": "Feature",
  "properties": {
    "iso:country":"BF",
    "name:bul_x_preferred":[
        "\u0411\u043e\u0440\u043e\u043c\u043e"
    ],
    "name:chi_x_preferred":[
        "\u535a\u7f85\u83ab"
    ],
    "name:dut_x_preferred":[
        "Boromo"
    ],
    "name:eng_x_preferred":[
        "Boromo"
    ],
    "name:fin_x_preferred":[
        "Boromo"
    ],
    "name:fre_x_preferred":[
        "Boromo"
    ],
    "name:ger_x_preferred":[
        "Boromo"
    ],
    "name:hun_x_preferred":[
        "Boromo"
    ],
    "name:ita_x_preferred":[
        "Boromo"
    ],
    "name:jpn_x_preferred":[
        "\u30dc\u30ed\u30e2"
    ],
    "name:nan_x_preferred":[
        "Boromo"
    ],
    "name:nob_x_preferred":[
        "Boromo"
    ],
    "name:per_x_preferred":[
        "\u0628\u0648\u0631\u0648\u0645\u0648"
    ],
    "name:pol_x_preferred":[
        "Boromo"
    ],
    "name:por_x_preferred":[
        "Boromo"
    ],
    "name:rum_x_preferred":[
        "Boromo"
    ],
    "name:rus_x_preferred":[
        "\u0411\u043e\u0440\u043e\u043c\u043e"
    ],
    "name:swe_x_preferred":[
        "Boromo"
    ],
    "name:ukr_x_preferred":[
        "\u0411\u043e\u0440\u043e\u043c\u043e"
    ],
    "name:urd_x_preferred":[
        "\u0628\u0648\u0631\u0648\u0645\u0648"
    ],
    "name:vie_x_preferred":[
        "Boromo"
    ],
    "name:war_x_preferred":[
        "Boromo"
    ],
    "qs:gn_pop":0,
    "qs:name":"Boromo",
    "qs:name_adm0":"Burkina Faso",
    "qs:name_adm1":"Bal\u00e9",
    "qs:photos":5,
    "qs:photos_1k":1,
    "qs:photos_9k":1,
    "qs:photos_9r":1,
    "qs:photos_all":5,
    "qs:photos_sr":1,
    "qs:placetype":"Town",
    "qs:pop_sr":"0",
    "qs:woe_adm0":23424978,
    "wof:name":"Boromo",
    "wof:placetype":"locality"
},
  "geometry": {"coordinates":[-2.927169,11.750151],"type":"Point"}
}