{
  "type": "Feature",
  "properties": {
    "gn:admin1_code":"13",
    "gn:asciiname":"Kpo",
    "gn:country_code":"BF",
    "gn:dem":316,
    "gn:feature_class":"P",
    "gn:feature_code":"PPL",
    "gn:name":"Kpo",
    "gn:population":0,
    "gn:timezone":"Africa/Ouagadougou",
    "iso:country":"BF",
    "wof:name":"Kpo",
    "wof:placetype":"locality"
},
  "geometry": {"coordinates":[-2.96667,10.36667],"type":"Point"}
}