{
  "type": "Feature",
  "properties": {
    "gn:admin1_code":"08",
    "gn:asciiname":"Damali",
    "gn:country_code":"BF",
    "gn:dem":270,
    "gn:feature_class":"P",
    "gn:feature_code":"PPL",
    "gn:name":"Damali",
    "gn:population":0,
    "gn:timezone":"Africa/Ouagadougou",
    "iso:country":"BF",
    "wof:name":"Damali",
    "wof:placetype":"locality"
},
  "geometry": {"coordinates":[0.11667,12.98333],"type":"Point"}
}