{
  "type": "Feature",
  "properties": {
    "gn:admin1_code":"09",
    "gn:asciiname":"Kotoura",
    "gn:country_code":"BF",
    "gn:dem":540,
    "gn:feature_class":"P",
    "gn:feature_code":"PPL",
    "gn:name":"Kotoura",
    "gn:population":0,
    "gn:timezone":"Africa/Ouagadougou",
    "iso:country":"BF",
    "name:und_x_variant":[
        "Kotoula",
        "Koutoura",
        "Kotoura"
    ],
    "wof:name":"Kotoura",
    "wof:placetype":"locality"
},
  "geometry": {"coordinates":[-5.28333,10.96667],"type":"Point"}
}