{
  "type": "Feature",
  "properties": {
    "gn:admin1_code":"13",
    "gn:asciiname":"Sankolonpo",
    "gn:country_code":"BF",
    "gn:dem":347,
    "gn:feature_class":"P",
    "gn:feature_code":"PPL",
    "gn:name":"Sankolonpo",
    "gn:population":0,
    "gn:timezone":"Africa/Ouagadougou",
    "iso:country":"BF",
    "wof:name":"Sankolonpo",
    "wof:placetype":"locality"
},
  "geometry": {"coordinates":[-3.43333,10.31667],"type":"Point"}
}