{
  "type": "Feature",
  "properties": {
    "gn:admin1_code":"07",
    "gn:asciiname":"Silinba",
    "gn:country_code":"BF",
    "gn:dem":307,
    "gn:feature_class":"P",
    "gn:feature_code":"PPL",
    "gn:name":"Silinba",
    "gn:population":0,
    "gn:timezone":"Africa/Ouagadougou",
    "iso:country":"BF",
    "wof:name":"Silinba",
    "wof:placetype":"locality"
},
  "geometry": {"coordinates":[-1.56667,11.83333],"type":"Point"}
}