{
  "type": "Feature",
  "properties": {
    "gn:admin1_code":"10",
    "gn:asciiname":"Koualtanguen",
    "gn:country_code":"BF",
    "gn:dem":303,
    "gn:feature_class":"P",
    "gn:feature_code":"PPL",
    "gn:name":"Koualtanguen",
    "gn:population":0,
    "gn:timezone":"Africa/Ouagadougou",
    "iso:country":"BF",
    "name:und_x_variant":[
        "Koualtangen",
        "Koaltinquin",
        "Koualtanguen"
    ],
    "wof:name":"Koualtanguen",
    "wof:placetype":"locality"
},
  "geometry": {"coordinates":[-2.33333,12.85],"type":"Point"}
}