{
  "type": "Feature",
  "properties": {
    "gn:admin1_code":"12",
    "gn:admin2_code":"71",
    "gn:asciiname":"Gountoudie",
    "gn:country_code":"BF",
    "gn:dem":282,
    "gn:feature_class":"P",
    "gn:feature_code":"PPL",
    "gn:name":"Gountoudi\u00e9",
    "gn:population":0,
    "gn:timezone":"Africa/Ouagadougou",
    "iso:country":"BF",
    "wof:name":"Gountoudie",
    "wof:placetype":"locality"
},
  "geometry": {"coordinates":[-0.45126,14.10366],"type":"Point"}
}