{
  "type": "Feature",
  "properties": {
    "gn:admin1_code":"03",
    "gn:admin2_code":"53",
    "gn:asciiname":"Dayoubsi",
    "gn:country_code":"BF",
    "gn:dem":329,
    "gn:feature_class":"P",
    "gn:feature_code":"PPL",
    "gn:name":"Dayoubsi",
    "gn:population":0,
    "gn:timezone":"Africa/Ouagadougou",
    "iso:country":"BF",
    "wof:name":"Dayoubsi",
    "wof:placetype":"locality"
},
  "geometry": {"coordinates":[-1.61028,12.23694],"type":"Point"}
}