{
  "type": "Feature",
  "properties": {
    "gn:admin1_code":"02",
    "gn:asciiname":"Sirakoro",
    "gn:country_code":"BF",
    "gn:dem":310,
    "gn:feature_class":"P",
    "gn:feature_code":"PPL",
    "gn:name":"Sirakoro",
    "gn:population":0,
    "gn:timezone":"Africa/Ouagadougou",
    "iso:country":"BF",
    "name:ceb_x_preferred":[
        "Sirakoro"
    ],
    "name:fra_x_preferred":[
        "Sirakoro"
    ],
    "name:spa_x_preferred":[
        "Sirakoro"
    ],
    "name:swe_x_preferred":[
        "Sirakoro"
    ],
    "wof:name":"Sirakoro",
    "wof:placetype":"locality"
},
  "geometry": {"coordinates":[-4.15,10.11667],"type":"Point"}
}