{
  "type": "Feature",
  "properties": {
    "gn:admin1_code":"12",
    "gn:admin2_code":"40",
    "gn:asciiname":"Gargaboulli",
    "gn:country_code":"BF",
    "gn:dem":351,
    "gn:feature_class":"P",
    "gn:feature_code":"PPL",
    "gn:name":"Gargaboulli",
    "gn:population":0,
    "gn:timezone":"Africa/Ouagadougou",
    "iso:country":"BF",
    "wof:name":"Gargaboulli",
    "wof:placetype":"locality"
},
  "geometry": {"coordinates":[-1.77488,13.80724],"type":"Point"}
}