{
  "type": "Feature",
  "properties": {
    "gn:admin1_code":"08",
    "gn:admin2_code":"42",
    "gn:asciiname":"Namobonga",
    "gn:country_code":"BF",
    "gn:dem":260,
    "gn:feature_class":"P",
    "gn:feature_code":"PPL",
    "gn:name":"Namobonga",
    "gn:population":0,
    "gn:timezone":"Africa/Ouagadougou",
    "iso:country":"BF",
    "wof:name":"Namobonga",
    "wof:placetype":"locality"
},
  "geometry": {"coordinates":[1.59939,12.47171],"type":"Point"}
}