{
  "type": "Feature",
  "properties": {
    "gn:admin1_code":"10",
    "gn:admin2_code":"76",
    "gn:asciiname":"Rambo",
    "gn:country_code":"BF",
    "gn:dem":336,
    "gn:feature_class":"P",
    "gn:feature_code":"PPL",
    "gn:name":"Rambo",
    "gn:population":0,
    "gn:timezone":"Africa/Ouagadougou",
    "iso:country":"BF",
    "name:und_x_variant":[
        "Ranbo",
        "Rambo"
    ],
    "wof:name":"Rambo",
    "wof:placetype":"locality"
},
  "geometry": {"coordinates":[-1.82611,13.24028],"type":"Point"}
}