{
  "type": "Feature",
  "properties": {
    "gn:admin1_code":"11",
    "gn:admin2_code":"68",
    "gn:asciiname":"Nakoalba",
    "gn:country_code":"BF",
    "gn:dem":312,
    "gn:feature_class":"P",
    "gn:feature_code":"PPL",
    "gn:name":"Nakoalba",
    "gn:population":0,
    "gn:timezone":"Africa/Ouagadougou",
    "iso:country":"BF",
    "wof:name":"Nakoalba",
    "wof:placetype":"locality"
},
  "geometry": {"coordinates":[-1.38361,12.84444],"type":"Point"}
}