{
  "type": "Feature",
  "properties": {
    "gn:admin1_code":"10",
    "gn:admin2_code":"76",
    "gn:asciiname":"Ouagaya",
    "gn:country_code":"BF",
    "gn:dem":327,
    "gn:feature_class":"P",
    "gn:feature_code":"PPL",
    "gn:name":"Ouagaya",
    "gn:population":0,
    "gn:timezone":"Africa/Ouagadougou",
    "iso:country":"BF",
    "name:und_x_variant":[
        "Wagaya",
        "Ouagaya"
    ],
    "wof:name":"Ouagaya",
    "wof:placetype":"locality"
},
  "geometry": {"coordinates":[-2.2116,13.6626],"type":"Point"}
}