{
  "type": "Feature",
  "properties": {
    "gn:admin1_code":"01",
    "gn:admin2_code":"58",
    "gn:asciiname":"Manikui",
    "gn:country_code":"BF",
    "gn:dem":310,
    "gn:feature_class":"P",
    "gn:feature_code":"PPL",
    "gn:name":"Manikui",
    "gn:population":0,
    "gn:timezone":"Africa/Ouagadougou",
    "iso:country":"BF",
    "wof:name":"Manikui",
    "wof:placetype":"locality"
},
  "geometry": {"coordinates":[-4.0517,13.1465],"type":"Point"}
}