{
  "type": "Feature",
  "properties": {
    "gn:admin1_code":"10",
    "gn:admin2_code":"76",
    "gn:asciiname":"Poura",
    "gn:country_code":"BF",
    "gn:dem":312,
    "gn:feature_class":"P",
    "gn:feature_code":"PPL",
    "gn:name":"Poura",
    "gn:population":0,
    "gn:timezone":"Africa/Ouagadougou",
    "iso:country":"BF",
    "name:und_x_variant":[
        "Pourra",
        "Poura"
    ],
    "wof:name":"Poura",
    "wof:placetype":"locality"
},
  "geometry": {"coordinates":[-1.81612,13.1311],"type":"Point"}
}