{
  "type": "Feature",
  "properties": {
    "gn:admin1_code":"12",
    "gn:admin2_code":"33",
    "gn:asciiname":"Oulo",
    "gn:country_code":"BF",
    "gn:dem":278,
    "gn:feature_class":"P",
    "gn:feature_code":"PPL",
    "gn:name":"Oulo",
    "gn:population":0,
    "gn:timezone":"Africa/Ouagadougou",
    "iso:country":"BF",
    "name:und_x_variant":[
        "Ulo",
        "Ouolo",
        "Oulo"
    ],
    "wof:name":"Oulo",
    "wof:placetype":"locality"
},
  "geometry": {"coordinates":[-0.2353,14.0448],"type":"Point"}
}