{
  "type": "Feature",
  "properties": {
    "gn:admin1_code":"05",
    "gn:admin2_code":"70",
    "gn:asciiname":"Tansera",
    "gn:country_code":"BF",
    "gn:dem":315,
    "gn:feature_class":"P",
    "gn:feature_code":"PPL",
    "gn:name":"Tans\u00e8ra",
    "gn:population":0,
    "gn:timezone":"Africa/Ouagadougou",
    "iso:country":"BF",
    "wof:name":"Tansera",
    "wof:placetype":"locality"
},
  "geometry": {"coordinates":[-1.10646,13.42756],"type":"Point"}
}