{
  "type": "Feature",
  "properties": {
    "gn:admin1_code":"03",
    "gn:admin2_code":"53",
    "gn:asciiname":"Gogo",
    "gn:country_code":"BF",
    "gn:dem":331,
    "gn:feature_class":"P",
    "gn:feature_code":"PPL",
    "gn:name":"Gogo",
    "gn:population":0,
    "gn:timezone":"Africa/Ouagadougou",
    "iso:country":"BF",
    "name:und_x_variant":[
        "Googho",
        "Gogo"
    ],
    "wof:name":"Gogo",
    "wof:placetype":"locality"
},
  "geometry": {"coordinates":[-1.63889,12.23806],"type":"Point"}
}