{
  "type": "Feature",
  "properties": {
    "gn:admin1_code":"11",
    "gn:asciiname":"Sagwem",
    "gn:country_code":"BF",
    "gn:dem":314,
    "gn:feature_class":"P",
    "gn:feature_code":"PPL",
    "gn:name":"Sagw\u00e8m",
    "gn:population":0,
    "gn:timezone":"Africa/Ouagadougou",
    "iso:country":"BF",
    "wof:name":"Sagwem",
    "wof:placetype":"locality"
},
  "geometry": {"coordinates":[-0.55,12.25],"type":"Point"}
}