{
  "type": "Feature",
  "properties": {
    "gn:admin1_code":"13",
    "gn:asciiname":"Dissini",
    "gn:country_code":"BF",
    "gn:dem":278,
    "gn:feature_class":"P",
    "gn:feature_code":"PPL",
    "gn:name":"Dissini",
    "gn:population":0,
    "gn:timezone":"Africa/Ouagadougou",
    "iso:country":"BF",
    "name:fra_x_preferred":[
        "Dissin"
    ],
    "name:und_x_variant":[
        "Disini",
        "Dissin",
        "Dissini"
    ],
    "wof:name":"Dissini",
    "wof:placetype":"locality"
},
  "geometry": {"coordinates":[-2.93333,10.93333],"type":"Point"}
}