{
  "type": "Feature",
  "properties": {
    "gn:admin1_code":"09",
    "gn:asciiname":"Ouakuy",
    "gn:country_code":"BF",
    "gn:dem":302,
    "gn:feature_class":"P",
    "gn:feature_code":"PPL",
    "gn:name":"Ouakuy",
    "gn:population":0,
    "gn:timezone":"Africa/Ouagadougou",
    "iso:country":"BF",
    "name:und_x_variant":[
        "Wakui",
        "Ouakuy"
    ],
    "wof:name":"Ouakuy",
    "wof:placetype":"locality"
},
  "geometry": {"coordinates":[-3.63333,11.68333],"type":"Point"}
}