{
  "type": "Feature",
  "properties": {
    "gn:admin1_code":"01",
    "gn:admin2_code":"73",
    "gn:asciiname":"Gosson",
    "gn:country_code":"BF",
    "gn:dem":273,
    "gn:feature_class":"P",
    "gn:feature_code":"PPL",
    "gn:name":"Gosson",
    "gn:population":0,
    "gn:timezone":"Africa/Ouagadougou",
    "iso:country":"BF",
    "name:und_x_variant":[
        "Gosso",
        "Gosson"
    ],
    "wof:name":"Gosson",
    "wof:placetype":"locality"
},
  "geometry": {"coordinates":[-3.0871,13.159],"type":"Point"}
}