{
  "type": "Feature",
  "properties": {
    "gn:admin1_code":"03",
    "gn:admin2_code":"53",
    "gn:asciiname":"Ouidtoghin",
    "gn:country_code":"BF",
    "gn:dem":289,
    "gn:feature_class":"P",
    "gn:feature_code":"PPL",
    "gn:name":"Ouidtoghin",
    "gn:population":0,
    "gn:timezone":"Africa/Ouagadougou",
    "iso:country":"BF",
    "name:und_x_variant":[
        "Ouidtogen",
        "Ouidtoguen",
        "Ouidtoghin",
        "Ouidtoguin"
    ],
    "wof:name":"Ouidtoghin",
    "wof:placetype":"locality"
},
  "geometry": {"coordinates":[-1.44927,12.40935],"type":"Point"}
}