{
  "type": "Feature",
  "properties": {
    "gn:admin1_code":"08",
    "gn:admin2_code":"42",
    "gn:asciiname":"Tourbou",
    "gn:country_code":"BF",
    "gn:dem":239,
    "gn:feature_class":"P",
    "gn:feature_code":"PPL",
    "gn:name":"Tourbou",
    "gn:population":0,
    "gn:timezone":"Africa/Ouagadougou",
    "iso:country":"BF",
    "wof:name":"Tourbou",
    "wof:placetype":"locality"
},
  "geometry": {"coordinates":[1.79788,12.41647],"type":"Point"}
}