{
  "type": "Feature",
  "properties": {
    "gn:admin1_code":"11",
    "gn:admin2_code":"68",
    "gn:asciiname":"Absouya",
    "gn:country_code":"BF",
    "gn:dem":281,
    "gn:feature_class":"P",
    "gn:feature_code":"PPL",
    "gn:name":"Absouya",
    "gn:population":0,
    "gn:timezone":"Africa/Ouagadougou",
    "iso:country":"BF",
    "wof:name":"Absouya",
    "wof:placetype":"locality"
},
  "geometry": {"coordinates":[-1.05556,12.64],"type":"Point"}
}