{
  "type": "Feature",
  "properties": {
    "gn:admin1_code":"11",
    "gn:admin2_code":"68",
    "gn:asciiname":"Absouya",
    "gn:country_code":"BF",
    "gn:dem":281,
    "gn:feature_class":"P",
    "gn:feature_code":"PPL",
    "gn:name":"Absouya",
    "gn:population":0,
    "gn:timezone":"Africa/Ouagadougou",
    "iso:country":"BF",
    "name:deu_x_preferred":[
        "Absouya"
    ],
    "name:fas_x_preferred":[
        "\u0634\u0647\u0631\u0633\u062a\u0627\u0646 \u0627\u0628\u0633\u0648\u06cc"
    ],
    "name:fra_x_preferred":[
        "Absouya"
    ],
    "name:ita_x_preferred":[
        "Absouya"
    ],
    "name:spa_x_preferred":[
        "Absouya"
    ],
    "name:vie_x_preferred":[
        "Absouya"
    ],
    "wof:name":"Absouya",
    "wof:placetype":"locality"
},
  "geometry": {"coordinates":[-1.05556,12.64],"type":"Point"}
}