{
  "type": "Feature",
  "properties": {
    "gn:admin1_code":"05",
    "gn:admin2_code":"15",
    "gn:asciiname":"Kougsabla",
    "gn:country_code":"BF",
    "gn:dem":327,
    "gn:feature_class":"P",
    "gn:feature_code":"PPL",
    "gn:name":"Kougsabla",
    "gn:population":0,
    "gn:timezone":"Africa/Ouagadougou",
    "iso:country":"BF",
    "name:azb_x_preferred":[
        "\u06a9\u0648\u0642\u0633\u0627\u0628\u0644\u0627"
    ],
    "name:ceb_x_preferred":[
        "Kougsabla"
    ],
    "name:fas_x_preferred":[
        "\u06a9\u0648\u06af\u0633\u0627\u0628\u0644\u0627"
    ],
    "name:swe_x_preferred":[
        "Kougsabla"
    ],
    "wof:name":"Kougsabla",
    "wof:placetype":"locality"
},
  "geometry": {"coordinates":[-1.55657,13.2722],"type":"Point"}
}