{
  "type": "Feature",
  "properties": {
    "gn:admin1_code":"07",
    "gn:asciiname":"Kalinga",
    "gn:country_code":"BF",
    "gn:dem":287,
    "gn:feature_class":"P",
    "gn:feature_code":"PPL",
    "gn:name":"Kalinga",
    "gn:population":0,
    "gn:timezone":"Africa/Ouagadougou",
    "iso:country":"BF",
    "name:cat_x_preferred":[
        "Kalinga"
    ],
    "name:ceb_x_preferred":[
        "Kalinga"
    ],
    "name:deu_x_preferred":[
        "Kalinga"
    ],
    "name:fra_x_preferred":[
        "Kalinga"
    ],
    "name:ita_x_preferred":[
        "Kalinga"
    ],
    "name:nld_x_preferred":[
        "Kalinga"
    ],
    "name:ori_x_preferred":[
        "\u0b15\u0b33\u0b3f\u0b19\u0b4d\u0b17"
    ],
    "name:por_x_preferred":[
        "Kalinga"
    ],
    "name:rus_x_preferred":[
        "\u041a\u0430\u043b\u0438\u043d\u0433\u0430"
    ],
    "name:tgl_x_preferred":[
        "Kalinga"
    ],
    "wof:name":"Kalinga",
    "wof:placetype":"locality"
},
  "geometry": {"coordinates":[-1.06667,11.53333],"type":"Point"}
}