{
  "type": "Feature",
  "properties": {
    "gn:admin1_code":"09",
    "gn:admin2_code":"51",
    "gn:asciiname":"Banfoulague",
    "gn:country_code":"BF",
    "gn:dem":401,
    "gn:feature_class":"P",
    "gn:feature_code":"PPL",
    "gn:name":"Banfoulagu\u00e9",
    "gn:population":0,
    "gn:timezone":"Africa/Ouagadougou",
    "iso:country":"BF",
    "name:und_x_variant":[
        "Banfoutagu\u00e9",
        "Banfoulagu\u00e9"
    ],
    "wof:name":"Banfoulague",
    "wof:placetype":"locality"
},
  "geometry": {"coordinates":[-4.73656,11.14056],"type":"Point"}
}