{
  "type": "Feature",
  "properties": {
    "gn:admin1_code":"08",
    "gn:admin2_code":"56",
    "gn:asciiname":"Foadyendyengou",
    "gn:country_code":"BF",
    "gn:dem":254,
    "gn:feature_class":"P",
    "gn:feature_code":"PPL",
    "gn:name":"Foadyendyengou",
    "gn:population":0,
    "gn:timezone":"Africa/Ouagadougou",
    "iso:country":"BF",
    "wof:name":"Foadyendyengou",
    "wof:placetype":"locality"
},
  "geometry": {"coordinates":[1.00297,12.68877],"type":"Point"}
}