{
  "type": "Feature",
  "properties": {
    "gn:admin1_code":"01",
    "gn:admin2_code":"58",
    "gn:asciiname":"Kinsere",
    "gn:country_code":"BF",
    "gn:dem":262,
    "gn:feature_class":"P",
    "gn:feature_code":"PPL",
    "gn:name":"Kins\u00e9r\u00e9",
    "gn:population":0,
    "gn:timezone":"Africa/Ouagadougou",
    "iso:country":"BF",
    "name:und_x_variant":[
        "Kinsik\u00e9",
        "Kinsir\u00e9",
        "Kins\u00e9r\u00e9"
    ],
    "wof:name":"Kinsere",
    "wof:placetype":"locality"
},
  "geometry": {"coordinates":[-3.7001,13.0903],"type":"Point"}
}