{
  "type": "Feature",
  "properties": {
    "gn:admin1_code":"02",
    "gn:asciiname":"Kassande",
    "gn:country_code":"BF",
    "gn:dem":337,
    "gn:feature_class":"P",
    "gn:feature_code":"PPL",
    "gn:name":"Kassand\u00e9",
    "gn:population":0,
    "gn:timezone":"Africa/Ouagadougou",
    "iso:country":"BF",
    "name:ceb_x_preferred":[
        "Kassand\u00e9"
    ],
    "name:fra_x_preferred":[
        "Kassande"
    ],
    "name:swe_x_preferred":[
        "Kassand\u00e9"
    ],
    "name:und_x_variant":[
        "Kasand\u00e9",
        "Kassand\u00e9"
    ],
    "wof:name":"Kassande",
    "wof:placetype":"locality"
},
  "geometry": {"coordinates":[-4.28739,10.53064],"type":"Point"}
}