{
  "type": "Feature",
  "properties": {
    "gn:admin1_code":"08",
    "gn:admin2_code":"21",
    "gn:asciiname":"Diankougou",
    "gn:country_code":"BF",
    "gn:dem":262,
    "gn:feature_class":"P",
    "gn:feature_code":"PPL",
    "gn:name":"Diankougou",
    "gn:population":0,
    "gn:timezone":"Africa/Ouagadougou",
    "iso:country":"BF",
    "wof:name":"Diankougou",
    "wof:placetype":"locality"
},
  "geometry": {"coordinates":[-0.14168,13.32712],"type":"Point"}
}