{
  "type": "Feature",
  "properties": {
    "gn:admin1_code":"07",
    "gn:admin2_code":"47",
    "gn:asciiname":"Yougoupele",
    "gn:country_code":"BF",
    "gn:dem":342,
    "gn:feature_class":"P",
    "gn:feature_code":"PPL",
    "gn:name":"Yougoup\u00e9l\u00e9",
    "gn:population":0,
    "gn:timezone":"Africa/Ouagadougou",
    "iso:country":"BF",
    "name:und_x_variant":[
        "Yougpels\u00e9",
        "Yougoup\u00e9l\u00e9"
    ],
    "wof:name":"Yougoupele",
    "wof:placetype":"locality"
},
  "geometry": {"coordinates":[-1.56028,12.04861],"type":"Point"}
}