{
  "type": "Feature",
  "properties": {
    "gn:admin1_code":"07",
    "gn:asciiname":"Konkosse",
    "gn:country_code":"BF",
    "gn:dem":334,
    "gn:feature_class":"P",
    "gn:feature_code":"PPL",
    "gn:name":"Konkoss\u00e9",
    "gn:population":0,
    "gn:timezone":"Africa/Ouagadougou",
    "iso:country":"BF",
    "name:azb_x_preferred":[
        "\u06a9\u0648\u0646\u06a9\u0648\u0633\u0647"
    ],
    "name:ceb_x_preferred":[
        "Konkoss\u00e9"
    ],
    "name:fas_x_preferred":[
        "\u06a9\u0648\u0646\u06a9\u0648\u0633\u0647"
    ],
    "name:swe_x_preferred":[
        "Konkoss\u00e9"
    ],
    "name:und_x_variant":[
        "Konkoss\u00e9"
    ],
    "wof:name":"Konkosse",
    "wof:placetype":"locality"
},
  "geometry": {"coordinates":[-1.38333,11.88333],"type":"Point"}
}