{
  "type": "Feature",
  "properties": {
    "gn:admin1_code":"09",
    "gn:admin2_code":"51",
    "gn:asciiname":"Bindowe",
    "gn:country_code":"BF",
    "gn:dem":337,
    "gn:feature_class":"P",
    "gn:feature_code":"PPL",
    "gn:name":"Bindow\u00e9",
    "gn:population":0,
    "gn:timezone":"Africa/Ouagadougou",
    "iso:country":"BF",
    "wof:name":"Bindowe",
    "wof:placetype":"locality"
},
  "geometry": {"coordinates":[-4.09265,11.15738],"type":"Point"}
}