{
  "type": "Feature",
  "properties": {
    "gn:admin1_code":"12",
    "gn:admin2_code":"71",
    "gn:asciiname":"Demnouo",
    "gn:country_code":"BF",
    "gn:dem":302,
    "gn:feature_class":"P",
    "gn:feature_code":"PPL",
    "gn:name":"Demnouo",
    "gn:population":0,
    "gn:timezone":"Africa/Ouagadougou",
    "iso:country":"BF",
    "name:und_x_variant":[
        "Demounoudor\u00e9",
        "D\u00e8mnoua",
        "Demnouo"
    ],
    "wof:name":"Demnouo",
    "wof:placetype":"locality"
},
  "geometry": {"coordinates":[-0.48843,13.87081],"type":"Point"}
}