{
  "type": "Feature",
  "properties": {
    "gn:admin1_code":"07",
    "gn:asciiname":"Widi",
    "gn:country_code":"BF",
    "gn:dem":331,
    "gn:feature_class":"P",
    "gn:feature_code":"PPL",
    "gn:name":"Widi",
    "gn:population":0,
    "gn:timezone":"Africa/Ouagadougou",
    "iso:country":"BF",
    "name:azb_x_preferred":[
        "\u0648\u06cc\u062f\u06cc"
    ],
    "name:ceb_x_preferred":[
        "Widi"
    ],
    "name:fas_x_preferred":[
        "\u0648\u06cc\u062f\u06cc"
    ],
    "name:fra_x_preferred":[
        "Widi"
    ],
    "wof:name":"Widi",
    "wof:placetype":"locality"
},
  "geometry": {"coordinates":[-1.58333,11.93333],"type":"Point"}
}