{
  "type": "Feature",
  "properties": {
    "gn:admin1_code":"08",
    "gn:admin2_code":"42",
    "gn:asciiname":"Padyanga",
    "gn:country_code":"BF",
    "gn:dem":245,
    "gn:feature_class":"P",
    "gn:feature_code":"PPL",
    "gn:name":"Padyanga",
    "gn:population":0,
    "gn:timezone":"Africa/Ouagadougou",
    "iso:country":"BF",
    "wof:name":"Padyanga",
    "wof:placetype":"locality"
},
  "geometry": {"coordinates":[2.11267,12.4357],"type":"Point"}
}