{
  "type": "Feature",
  "properties": {
    "gn:admin1_code":"03",
    "gn:admin2_code":"53",
    "gn:asciiname":"Kobogo",
    "gn:country_code":"BF",
    "gn:dem":325,
    "gn:feature_class":"P",
    "gn:feature_code":"PPL",
    "gn:name":"Kobogo",
    "gn:population":0,
    "gn:timezone":"Africa/Ouagadougou",
    "iso:country":"BF",
    "name:ceb_x_preferred":[
        "Kobogo"
    ],
    "name:swe_x_preferred":[
        "Kobogo"
    ],
    "name:und_x_variant":[
        "Kossodo"
    ],
    "wof:name":"Kobogo",
    "wof:placetype":"locality"
},
  "geometry": {"coordinates":[-1.675,12.16194],"type":"Point"}
}