{
  "type": "Feature",
  "properties": {
    "gn:admin1_code":"09",
    "gn:asciiname":"Kongolikan",
    "gn:country_code":"BF",
    "gn:dem":348,
    "gn:feature_class":"P",
    "gn:feature_code":"PPL",
    "gn:name":"Kongolikan",
    "gn:population":0,
    "gn:timezone":"Africa/Ouagadougou",
    "iso:country":"BF",
    "name:und_x_variant":[
        "Kongolika",
        "Kongolikan"
    ],
    "wof:name":"Kongolikan",
    "wof:placetype":"locality"
},
  "geometry": {"coordinates":[-3.75229,11.21242],"type":"Point"}
}