{
  "type": "Feature",
  "properties": {
    "gn:admin1_code":"12",
    "gn:admin2_code":"71",
    "gn:asciiname":"Pimpindiangou",
    "gn:country_code":"BF",
    "gn:dem":293,
    "gn:feature_class":"P",
    "gn:feature_code":"PPL",
    "gn:name":"Pimpindiangou",
    "gn:population":0,
    "gn:timezone":"Africa/Ouagadougou",
    "iso:country":"BF",
    "name:und_x_variant":[
        "Penpemdiadou",
        "Pimpindiangou"
    ],
    "wof:name":"Pimpindiangou",
    "wof:placetype":"locality"
},
  "geometry": {"coordinates":[-0.05934,13.93052],"type":"Point"}
}