{
  "type": "Feature",
  "properties": {
    "gn:admin1_code":"10",
    "gn:admin2_code":"76",
    "gn:asciiname":"Bouna",
    "gn:country_code":"BF",
    "gn:dem":317,
    "gn:feature_class":"P",
    "gn:feature_code":"PPL",
    "gn:name":"Bouna",
    "gn:population":0,
    "gn:timezone":"Africa/Ouagadougou",
    "iso:country":"BF",
    "name:ceb_x_preferred":[
        "Bouna"
    ],
    "name:fra_x_preferred":[
        "Bouna"
    ],
    "name:ita_x_preferred":[
        "Bouna"
    ],
    "name:swa_x_preferred":[
        "Bouna"
    ],
    "name:swe_x_preferred":[
        "Bouna"
    ],
    "wof:name":"Bouna",
    "wof:placetype":"locality"
},
  "geometry": {"coordinates":[-1.97119,13.77017],"type":"Point"}
}