{
  "type": "Feature",
  "properties": {
    "gn:admin1_code":"10",
    "gn:admin2_code":"76",
    "gn:asciiname":"Kanday",
    "gn:country_code":"BF",
    "gn:dem":306,
    "gn:feature_class":"P",
    "gn:feature_code":"PPL",
    "gn:name":"Kanday",
    "gn:population":0,
    "gn:timezone":"Africa/Ouagadougou",
    "iso:country":"BF",
    "name:und_x_variant":[
        "Kandaye",
        "Kanday"
    ],
    "wof:name":"Kanday",
    "wof:placetype":"locality"
},
  "geometry": {"coordinates":[-2.73324,13.73444],"type":"Point"}
}