{
  "type": "Feature",
  "properties": {
    "gn:admin1_code":"12",
    "gn:admin2_code":"71",
    "gn:asciiname":"Ouro Mossibe",
    "gn:country_code":"BF",
    "gn:dem":297,
    "gn:feature_class":"P",
    "gn:feature_code":"PPL",
    "gn:name":"Ouro Mossib\u00e9",
    "gn:population":0,
    "gn:timezone":"Africa/Ouagadougou",
    "iso:country":"BF",
    "wof:name":"Ouro Mossibe",
    "wof:placetype":"locality"
},
  "geometry": {"coordinates":[0.37938,13.78326],"type":"Point"}
}