{
  "type": "Feature",
  "properties": {
    "gn:admin1_code":"12",
    "gn:admin2_code":"71",
    "gn:asciiname":"Gwanda",
    "gn:country_code":"BF",
    "gn:dem":272,
    "gn:feature_class":"P",
    "gn:feature_code":"PPL",
    "gn:name":"Gwanda",
    "gn:population":0,
    "gn:timezone":"Africa/Ouagadougou",
    "iso:country":"BF",
    "name:afr_x_preferred":[
        "Gwanda"
    ],
    "name:bar_x_preferred":[
        "Gwanda"
    ],
    "name:ceb_x_preferred":[
        "Gwanda"
    ],
    "name:deu_x_preferred":[
        "Gwanda"
    ],
    "name:eus_x_preferred":[
        "Gwanda"
    ],
    "name:fra_x_preferred":[
        "Gwanda"
    ],
    "name:frr_x_preferred":[
        "Gwanda"
    ],
    "name:hrv_x_preferred":[
        "Gwanda"
    ],
    "name:ita_x_preferred":[
        "Gwanda"
    ],
    "name:lit_x_preferred":[
        "Gvanda"
    ],
    "name:mrj_x_preferred":[
        "\u0413\u0432\u0430\u043d\u0434\u0430"
    ],
    "name:nld_x_preferred":[
        "Gwanda"
    ],
    "name:pol_x_preferred":[
        "Gwanda"
    ],
    "name:por_x_preferred":[
        "Gwanda"
    ],
    "name:ron_x_preferred":[
        "Gwanda"
    ],
    "name:rus_x_preferred":[
        "\u0413\u0432\u0430\u043d\u0434\u0430"
    ],
    "name:srp_x_preferred":[
        "\u0413\u0432\u0430\u043d\u0434\u0430"
    ],
    "name:ukr_x_preferred":[
        "\u0413\u0432\u0430\u043d\u0434\u0430"
    ],
    "name:urd_x_preferred":[
        "\u06af\u0648\u0627\u0646\u0688\u0627"
    ],
    "wof:name":"Gwanda",
    "wof:placetype":"locality"
},
  "geometry": {"coordinates":[-0.08159,13.51866],"type":"Point"}
}