{
  "type": "Feature",
  "properties": {
    "gn:admin1_code":"12",
    "gn:admin2_code":"40",
    "gn:asciiname":"Aladiou",
    "gn:country_code":"BF",
    "gn:dem":303,
    "gn:feature_class":"P",
    "gn:feature_code":"PPL",
    "gn:name":"Aladiou",
    "gn:population":0,
    "gn:timezone":"Africa/Ouagadougou",
    "iso:country":"BF",
    "wof:name":"Aladiou",
    "wof:placetype":"locality"
},
  "geometry": {"coordinates":[-0.93072,14.0417],"type":"Point"}
}