{
  "type": "Feature",
  "properties": {
    "gn:admin1_code":"01",
    "gn:asciiname":"Nassema",
    "gn:country_code":"BF",
    "gn:dem":281,
    "gn:feature_class":"P",
    "gn:feature_code":"PPL",
    "gn:name":"Nass\u00e9ma",
    "gn:population":0,
    "gn:timezone":"Africa/Ouagadougou",
    "iso:country":"BF",
    "name:und_x_variant":[
        "Nassim\u00e9",
        "Nass\u00e9ma"
    ],
    "wof:name":"Nassema",
    "wof:placetype":"locality"
},
  "geometry": {"coordinates":[-2.58333,11.41667],"type":"Point"}
}