{
  "type": "Feature",
  "properties": {
    "gn:admin1_code":"12",
    "gn:admin2_code":"71",
    "gn:asciiname":"Tiekaliedji",
    "gn:country_code":"BF",
    "gn:dem":297,
    "gn:feature_class":"P",
    "gn:feature_code":"PPL",
    "gn:name":"Ti\u00e9kali\u00e9dji",
    "gn:population":0,
    "gn:timezone":"Africa/Ouagadougou",
    "iso:country":"BF",
    "wof:name":"Tiekaliedji",
    "wof:placetype":"locality"
},
  "geometry": {"coordinates":[-0.50802,13.90408],"type":"Point"}
}