{
  "type": "Feature",
  "properties": {
    "gn:admin1_code":"03",
    "gn:admin2_code":"53",
    "gn:asciiname":"Sale",
    "gn:country_code":"BF",
    "gn:dem":328,
    "gn:feature_class":"P",
    "gn:feature_code":"PPL",
    "gn:name":"Sal\u00e9",
    "gn:population":0,
    "gn:timezone":"Africa/Ouagadougou",
    "iso:country":"BF",
    "name:und_x_variant":[
        "Sall\u00e9",
        "Sal\u00e9"
    ],
    "wof:name":"Sale",
    "wof:placetype":"locality"
},
  "geometry": {"coordinates":[-1.66639,12.59194],"type":"Point"}
}