{
  "type": "Feature",
  "properties": {
    "gn:admin1_code":"03",
    "gn:admin2_code":"53",
    "gn:asciiname":"Sale",
    "gn:country_code":"BF",
    "gn:dem":328,
    "gn:feature_class":"P",
    "gn:feature_code":"PPL",
    "gn:name":"Sal\u00e9",
    "gn:population":0,
    "gn:timezone":"Africa/Ouagadougou",
    "iso:country":"BF",
    "name:bul_x_preferred":[
        "\u0421\u0430\u043b\u0435"
    ],
    "name:cat_x_preferred":[
        "Sale"
    ],
    "name:ceb_x_preferred":[
        "Sale"
    ],
    "name:ces_x_preferred":[
        "Sale"
    ],
    "name:cym_x_preferred":[
        "Sale"
    ],
    "name:deu_x_preferred":[
        "Sale"
    ],
    "name:fin_x_preferred":[
        "Sale"
    ],
    "name:fra_x_preferred":[
        "Sale"
    ],
    "name:hye_x_preferred":[
        "\u054d\u0561\u056c\u0565"
    ],
    "name:ita_x_preferred":[
        "Sale"
    ],
    "name:jpn_x_preferred":[
        "\u30bb\u30fc\u30eb"
    ],
    "name:lmo_x_preferred":[
        "S\u00e0le"
    ],
    "name:nld_x_preferred":[
        "Sale"
    ],
    "name:pol_x_preferred":[
        "Sale"
    ],
    "name:por_x_preferred":[
        "Sale"
    ],
    "name:rus_x_preferred":[
        "\u0421\u0430\u043b\u0435"
    ],
    "name:srp_x_preferred":[
        "Sale"
    ],
    "name:swe_x_preferred":[
        "Sale"
    ],
    "name:ukr_x_preferred":[
        "\u0421\u0430\u043b\u0435"
    ],
    "name:und_x_variant":[
        "Sall\u00e9",
        "Sal\u00e9"
    ],
    "name:uzb_x_preferred":[
        "Sale"
    ],
    "wof:name":"Sale",
    "wof:placetype":"locality"
},
  "geometry": {"coordinates":[-1.66639,12.59194],"type":"Point"}
}