{
  "type": "Feature",
  "properties": {
    "gn:admin1_code":"13",
    "gn:asciiname":"Dalinpouo",
    "gn:country_code":"BF",
    "gn:dem":269,
    "gn:feature_class":"P",
    "gn:feature_code":"PPL",
    "gn:name":"Dalinpouo",
    "gn:population":0,
    "gn:timezone":"Africa/Ouagadougou",
    "iso:country":"BF",
    "wof:name":"Dalinpouo",
    "wof:placetype":"locality"
},
  "geometry": {"coordinates":[-2.81667,10.25],"type":"Point"}
}