{
  "type": "Feature",
  "properties": {
    "gn:admin1_code":"05",
    "gn:asciiname":"Tanpelga",
    "gn:country_code":"BF",
    "gn:dem":281,
    "gn:feature_class":"P",
    "gn:feature_code":"PPL",
    "gn:name":"Tanp\u00e8lga",
    "gn:population":0,
    "gn:timezone":"Africa/Ouagadougou",
    "iso:country":"BF",
    "name:und_x_variant":[
        "Tantogo",
        "Tanp\u00e8lga",
        "Tamp\u00e8lga"
    ],
    "wof:name":"Tanpelga",
    "wof:placetype":"locality"
},
  "geometry": {"coordinates":[-1.21667,12.91667],"type":"Point"}
}