{
  "type": "Feature",
  "properties": {
    "gn:admin1_code":"06",
    "gn:asciiname":"Lenon",
    "gn:country_code":"BF",
    "gn:dem":343,
    "gn:feature_class":"P",
    "gn:feature_code":"PPL",
    "gn:name":"L\u00e9non",
    "gn:population":0,
    "gn:timezone":"Africa/Ouagadougou",
    "iso:country":"BF",
    "wof:name":"Lenon",
    "wof:placetype":"locality"
},
  "geometry": {"coordinates":[-1.93333,11.65],"type":"Point"}
}