{
  "type": "Feature",
  "properties": {
    "gn:admin1_code":"05",
    "gn:admin2_code":"15",
    "gn:asciiname":"Boubou",
    "gn:country_code":"BF",
    "gn:dem":341,
    "gn:feature_class":"P",
    "gn:feature_code":"PPL",
    "gn:name":"Boubou",
    "gn:population":0,
    "gn:timezone":"Africa/Ouagadougou",
    "iso:country":"BF",
    "name:azb_x_preferred":[
        "\u0628\u0648\u0628\u0648"
    ],
    "name:fas_x_preferred":[
        "\u0628\u0648\u0628\u0648"
    ],
    "wof:name":"Boubou",
    "wof:placetype":"locality"
},
  "geometry": {"coordinates":[-1.80403,13.36696],"type":"Point"}
}