{
  "type": "Feature",
  "properties": {
    "gn:admin1_code":"08",
    "gn:admin2_code":"21",
    "gn:asciiname":"Botou",
    "gn:cc2":"BF",
    "gn:country_code":"BF",
    "gn:dem":292,
    "gn:feature_class":"P",
    "gn:feature_code":"PPL",
    "gn:name":"Botou",
    "gn:population":0,
    "gn:timezone":"Africa/Ouagadougou",
    "iso:country":"BF",
    "name:und_x_variant":[
        "Bodu",
        "Bodou",
        "Botou"
    ],
    "wof:name":"Botou",
    "wof:placetype":"locality"
},
  "geometry": {"coordinates":[0.15361,12.41778],"type":"Point"}
}