{
  "type": "Feature",
  "properties": {
    "gn:admin1_code":"05",
    "gn:admin2_code":"15",
    "gn:asciiname":"Basse",
    "gn:country_code":"BF",
    "gn:dem":328,
    "gn:feature_class":"P",
    "gn:feature_code":"PPL",
    "gn:name":"Bass\u00e9",
    "gn:population":0,
    "gn:timezone":"Africa/Ouagadougou",
    "iso:country":"BF",
    "name:und_x_variant":[
        "Bass\u00e9"
    ],
    "wof:name":"Basse",
    "wof:placetype":"locality"
},
  "geometry": {"coordinates":[-1.64985,13.70578],"type":"Point"}
}