{
  "type": "Feature",
  "properties": {
    "gn:admin1_code":"10",
    "gn:admin2_code":"76",
    "gn:asciiname":"Rapougouma",
    "gn:country_code":"BF",
    "gn:dem":329,
    "gn:feature_class":"P",
    "gn:feature_code":"PPL",
    "gn:name":"Rapougouma",
    "gn:population":0,
    "gn:timezone":"Africa/Ouagadougou",
    "iso:country":"BF",
    "wof:name":"Rapougouma",
    "wof:placetype":"locality"
},
  "geometry": {"coordinates":[-2.34651,13.64563],"type":"Point"}
}