{
  "type": "Feature",
  "properties": {
    "gn:admin1_code":"13",
    "gn:asciiname":"Soukera",
    "gn:country_code":"BF",
    "gn:dem":361,
    "gn:feature_class":"P",
    "gn:feature_code":"PPL",
    "gn:name":"Souk\u00e9ra",
    "gn:population":0,
    "gn:timezone":"Africa/Ouagadougou",
    "iso:country":"BF",
    "wof:name":"Soukera",
    "wof:placetype":"locality"
},
  "geometry": {"coordinates":[-3.6157,10.2585],"type":"Point"}
}