{
  "type": "Feature",
  "properties": {
    "gn:admin1_code":"03",
    "gn:admin2_code":"53",
    "gn:asciiname":"Sahongo",
    "gn:country_code":"BF",
    "gn:dem":345,
    "gn:feature_class":"P",
    "gn:feature_code":"PPL",
    "gn:name":"Sahongo",
    "gn:population":0,
    "gn:timezone":"Africa/Ouagadougou",
    "iso:country":"BF",
    "wof:name":"Sahongo",
    "wof:placetype":"locality"
},
  "geometry": {"coordinates":[-1.73417,12.36778],"type":"Point"}
}