{
  "type": "Feature",
  "properties": {
    "gn:admin1_code":"12",
    "gn:admin2_code":"40",
    "gn:asciiname":"Oudoundayire",
    "gn:country_code":"BF",
    "gn:dem":349,
    "gn:feature_class":"P",
    "gn:feature_code":"PPL",
    "gn:name":"Oudoundayir\u00e9",
    "gn:population":0,
    "gn:timezone":"Africa/Ouagadougou",
    "iso:country":"BF",
    "wof:name":"Oudoundayire",
    "wof:placetype":"locality"
},
  "geometry": {"coordinates":[-1.45963,13.89689],"type":"Point"}
}