{
  "type": "Feature",
  "properties": {
    "gn:admin1_code":"08",
    "gn:admin2_code":"42",
    "gn:asciiname":"Kirta",
    "gn:country_code":"BF",
    "gn:dem":231,
    "gn:feature_class":"P",
    "gn:feature_code":"PPL",
    "gn:name":"Kirta",
    "gn:population":0,
    "gn:timezone":"Africa/Ouagadougou",
    "iso:country":"BF",
    "name:amh_x_preferred":[
        "\u12aa\u122d\u1273"
    ],
    "name:ast_x_preferred":[
        "Kirta"
    ],
    "name:cat_x_preferred":[
        "Kirta"
    ],
    "name:eus_x_preferred":[
        "Kirta"
    ],
    "name:fra_x_preferred":[
        "Kirta"
    ],
    "name:glg_x_preferred":[
        "Kirta"
    ],
    "name:hun_x_preferred":[
        "Kirta"
    ],
    "name:ind_x_preferred":[
        "Kirta"
    ],
    "name:ita_x_preferred":[
        "Kirta"
    ],
    "name:kor_x_preferred":[
        "\ud0a4\ub974\ud0c0"
    ],
    "name:nld_x_preferred":[
        "Kirta"
    ],
    "name:pan_x_preferred":[
        "\u0a15\u0a3f\u0a30\u0a24\u0a3e"
    ],
    "name:pol_x_preferred":[
        "Kirta"
    ],
    "name:rus_x_preferred":[
        "\u041a\u0438\u0440\u0442\u0430"
    ],
    "name:slv_x_preferred":[
        "Kirta"
    ],
    "name:spa_x_preferred":[
        "Kirta"
    ],
    "name:ukr_x_preferred":[
        "\u041a\u0456\u0440\u0442\u0430"
    ],
    "name:zho_x_preferred":[
        "\u57fa\u5c14\u5854"
    ],
    "wof:name":"Kirta",
    "wof:placetype":"locality"
},
  "geometry": {"coordinates":[1.76798,12.42718],"type":"Point"}
}