{
  "type": "Feature",
  "properties": {
    "gn:admin1_code":"11",
    "gn:admin2_code":"68",
    "gn:asciiname":"Ourougou",
    "gn:country_code":"BF",
    "gn:dem":307,
    "gn:feature_class":"P",
    "gn:feature_code":"PPL",
    "gn:name":"Ourougou",
    "gn:population":0,
    "gn:timezone":"Africa/Ouagadougou",
    "iso:country":"BF",
    "name:und_x_variant":[
        "Ourgou",
        "Ourougou",
        "Ourgou-Man\u00e9ga",
        "Man\u00e9ra",
        "Man\u00e9ga"
    ],
    "wof:name":"Ourougou",
    "wof:placetype":"locality"
},
  "geometry": {"coordinates":[-1.525,12.77611],"type":"Point"}
}