{
  "type": "Feature",
  "properties": {
    "gn:admin1_code":"10",
    "gn:admin2_code":"76",
    "gn:asciiname":"Napango",
    "gn:country_code":"BF",
    "gn:dem":296,
    "gn:feature_class":"P",
    "gn:feature_code":"PPL",
    "gn:name":"Napango",
    "gn:population":0,
    "gn:timezone":"Africa/Ouagadougou",
    "iso:country":"BF",
    "wof:name":"Napango",
    "wof:placetype":"locality"
},
  "geometry": {"coordinates":[-2.67897,13.63485],"type":"Point"}
}