{
  "type": "Feature",
  "properties": {
    "gn:admin1_code":"01",
    "gn:asciiname":"Lei",
    "gn:country_code":"BF",
    "gn:dem":256,
    "gn:feature_class":"P",
    "gn:feature_code":"PPL",
    "gn:name":"L\u00e9\u00ef",
    "gn:population":0,
    "gn:timezone":"Africa/Ouagadougou",
    "iso:country":"BF",
    "wof:name":"Lei",
    "wof:placetype":"locality"
},
  "geometry": {"coordinates":[-3.65,12.96667],"type":"Point"}
}