{
  "type": "Feature",
  "properties": {
    "gn:admin1_code":"06",
    "gn:asciiname":"Byiri",
    "gn:country_code":"BF",
    "gn:dem":270,
    "gn:feature_class":"P",
    "gn:feature_code":"PPL",
    "gn:name":"Byiri",
    "gn:population":0,
    "gn:timezone":"Africa/Ouagadougou",
    "iso:country":"BF",
    "wof:name":"Byiri",
    "wof:placetype":"locality"
},
  "geometry": {"coordinates":[-2.56667,12.05],"type":"Point"}
}