{
  "type": "Feature",
  "properties": {
    "gn:admin1_code":"10",
    "gn:admin2_code":"76",
    "gn:asciiname":"Bangassomba",
    "gn:country_code":"BF",
    "gn:dem":310,
    "gn:feature_class":"P",
    "gn:feature_code":"PPL",
    "gn:name":"Bangassomba",
    "gn:population":0,
    "gn:timezone":"Africa/Ouagadougou",
    "iso:country":"BF",
    "name:und_x_variant":[
        "Banguessommba",
        "Bangassomba"
    ],
    "wof:name":"Bangassomba",
    "wof:placetype":"locality"
},
  "geometry": {"coordinates":[-2.19273,13.13988],"type":"Point"}
}