{
  "type": "Feature",
  "properties": {
    "gn:admin1_code":"07",
    "gn:asciiname":"Nakola",
    "gn:country_code":"BF",
    "gn:dem":344,
    "gn:feature_class":"P",
    "gn:feature_code":"PPL",
    "gn:name":"Nakola",
    "gn:population":0,
    "gn:timezone":"Africa/Ouagadougou",
    "iso:country":"BF",
    "wof:name":"Nakola",
    "wof:placetype":"locality"
},
  "geometry": {"coordinates":[-1.46667,11.38333],"type":"Point"}
}