{
  "type": "Feature",
  "properties": {
    "gn:admin1_code":"16",
    "gn:asciiname":"Pitioko",
    "gn:cc2":"BF",
    "gn:country_code":"BF",
    "gn:dem":258,
    "gn:feature_class":"P",
    "gn:feature_code":"PPLL",
    "gn:name":"Pitioko",
    "gn:population":0,
    "gn:timezone":"Africa/Ouagadougou",
    "iso:country":"BF",
    "name:und_x_variant":[
        "Pikieko",
        "Pitioko"
    ],
    "wof:name":"Pitioko",
    "wof:placetype":"locality"
},
  "geometry": {"coordinates":[-1.10028,12.23333],"type":"Point"}
}