{
  "type": "Feature",
  "properties": {
    "gn:admin1_code":"06",
    "gn:asciiname":"Nadion",
    "gn:country_code":"BF",
    "gn:dem":338,
    "gn:feature_class":"P",
    "gn:feature_code":"PPL",
    "gn:name":"Nadion",
    "gn:population":0,
    "gn:timezone":"Africa/Ouagadougou",
    "iso:country":"BF",
    "name:und_x_variant":[
        "Nadian",
        "Nadion"
    ],
    "wof:name":"Nadion",
    "wof:placetype":"locality"
},
  "geometry": {"coordinates":[-2.20882,11.12843],"type":"Point"}
}