{
  "type": "Feature",
  "properties": {
    "gn:admin1_code":"04",
    "gn:asciiname":"Koutiana",
    "gn:country_code":"BF",
    "gn:dem":278,
    "gn:feature_class":"P",
    "gn:feature_code":"PPL",
    "gn:name":"Koutiana",
    "gn:population":0,
    "gn:timezone":"Africa/Ouagadougou",
    "iso:country":"BF",
    "name:und_x_variant":[
        "Koutiama",
        "Koutiana"
    ],
    "wof:name":"Koutiana",
    "wof:placetype":"locality"
},
  "geometry": {"coordinates":[-0.15,11.83333],"type":"Point"}
}