{
  "type": "Feature",
  "properties": {
    "gn:admin1_code":"12",
    "gn:admin2_code":"71",
    "gn:asciiname":"Oulsalta",
    "gn:country_code":"BF",
    "gn:dem":278,
    "gn:feature_class":"P",
    "gn:feature_code":"PPL",
    "gn:name":"Oulsalta",
    "gn:population":0,
    "gn:timezone":"Africa/Ouagadougou",
    "iso:country":"BF",
    "wof:name":"Oulsalta",
    "wof:placetype":"locality"
},
  "geometry": {"coordinates":[0.46299,13.90162],"type":"Point"}
}