{
  "type": "Feature",
  "properties": {
    "gn:admin1_code":"08",
    "gn:admin2_code":"42",
    "gn:asciiname":"Kantchari",
    "gn:country_code":"BF",
    "gn:dem":275,
    "gn:feature_class":"P",
    "gn:feature_code":"PPL",
    "gn:name":"Kantchari",
    "gn:population":0,
    "gn:timezone":"Africa/Ouagadougou",
    "iso:country":"BF",
    "name:und_x_variant":[
        "Kanchari",
        "Kantchari"
    ],
    "name:urd_x_preferred":[
        "\u06a9\u0627\u0646\u062a\u0634\u0627\u0631\u06cc"
    ],
    "wof:name":"Kantchari",
    "wof:placetype":"locality"
},
  "geometry": {"coordinates":[1.51162,12.47558],"type":"Point"}
}