{
  "type": "Feature",
  "properties": {
    "gn:admin1_code":"07",
    "gn:asciiname":"Voko",
    "gn:country_code":"BF",
    "gn:dem":308,
    "gn:feature_class":"P",
    "gn:feature_code":"PPL",
    "gn:name":"Voko",
    "gn:population":0,
    "gn:timezone":"Africa/Ouagadougou",
    "iso:country":"BF",
    "wof:name":"Voko",
    "wof:placetype":"locality"
},
  "geometry": {"coordinates":[-1.26667,11.63333],"type":"Point"}
}