{
  "type": "Feature",
  "properties": {
    "gn:admin1_code":"13",
    "gn:asciiname":"Sebera",
    "gn:country_code":"BF",
    "gn:dem":312,
    "gn:feature_class":"P",
    "gn:feature_code":"PPL",
    "gn:name":"S\u00e9b\u00e9ra",
    "gn:population":0,
    "gn:timezone":"Africa/Ouagadougou",
    "iso:country":"BF",
    "wof:name":"Sebera",
    "wof:placetype":"locality"
},
  "geometry": {"coordinates":[-3.28333,10.51667],"type":"Point"}
}