{
  "type": "Feature",
  "properties": {
    "gn:admin1_code":"01",
    "gn:admin2_code":"73",
    "gn:asciiname":"Moara",
    "gn:country_code":"BF",
    "gn:dem":265,
    "gn:feature_class":"P",
    "gn:feature_code":"PPL",
    "gn:name":"Moara",
    "gn:population":0,
    "gn:timezone":"Africa/Ouagadougou",
    "iso:country":"BF",
    "name:deu_x_preferred":[
        "Moara"
    ],
    "name:fra_x_preferred":[
        "Moara"
    ],
    "name:ita_x_preferred":[
        "Moara"
    ],
    "name:ron_x_preferred":[
        "Moara"
    ],
    "name:vie_x_preferred":[
        "Moara"
    ],
    "wof:name":"Moara",
    "wof:placetype":"locality"
},
  "geometry": {"coordinates":[-3.2173,13.0704],"type":"Point"}
}