{
  "type": "Feature",
  "properties": {
    "gn:admin1_code":"06",
    "gn:asciiname":"Pou",
    "gn:country_code":"BF",
    "gn:dem":287,
    "gn:feature_class":"P",
    "gn:feature_code":"PPL",
    "gn:name":"Pou",
    "gn:population":0,
    "gn:timezone":"Africa/Ouagadougou",
    "iso:country":"BF",
    "wof:name":"Pou",
    "wof:placetype":"locality"
},
  "geometry": {"coordinates":[-2.53333,12.26667],"type":"Point"}
}