{
  "type": "Feature",
  "properties": {
    "gn:admin1_code":"06",
    "gn:asciiname":"Nopo",
    "gn:country_code":"BF",
    "gn:dem":328,
    "gn:feature_class":"P",
    "gn:feature_code":"PPL",
    "gn:name":"Nopo",
    "gn:population":0,
    "gn:timezone":"Africa/Ouagadougou",
    "iso:country":"BF",
    "wof:name":"Nopo",
    "wof:placetype":"locality"
},
  "geometry": {"coordinates":[-2.18333,11.58333],"type":"Point"}
}