{
  "type": "Feature",
  "properties": {
    "gn:admin1_code":"12",
    "gn:admin2_code":"40",
    "gn:asciiname":"Goroy",
    "gn:country_code":"BF",
    "gn:dem":321,
    "gn:feature_class":"P",
    "gn:feature_code":"PPL",
    "gn:name":"Goroy",
    "gn:population":0,
    "gn:timezone":"Africa/Ouagadougou",
    "iso:country":"BF",
    "wof:name":"Goroy",
    "wof:placetype":"locality"
},
  "geometry": {"coordinates":[-0.72723,14.34344],"type":"Point"}
}