{
  "type": "Feature",
  "properties": {
    "gn:admin1_code":"12",
    "gn:admin2_code":"75",
    "gn:asciiname":"Guisendyori",
    "gn:country_code":"BF",
    "gn:dem":268,
    "gn:feature_class":"P",
    "gn:feature_code":"PPL",
    "gn:name":"Guisendyori",
    "gn:population":0,
    "gn:timezone":"Africa/Ouagadougou",
    "iso:country":"BF",
    "wof:name":"Guisendyori",
    "wof:placetype":"locality"
},
  "geometry": {"coordinates":[0.56448,13.46264],"type":"Point"}
}