{
  "type": "Feature",
  "properties": {
    "gn:admin1_code":"10",
    "gn:admin2_code":"76",
    "gn:asciiname":"Zongo",
    "gn:country_code":"BF",
    "gn:dem":340,
    "gn:feature_class":"P",
    "gn:feature_code":"PPL",
    "gn:name":"Zongo",
    "gn:population":0,
    "gn:timezone":"Africa/Ouagadougou",
    "iso:country":"BF",
    "name:ceb_x_preferred":[
        "Zongo"
    ],
    "name:deu_x_preferred":[
        "Zongo"
    ],
    "name:fra_x_preferred":[
        "Zongo"
    ],
    "name:ita_x_preferred":[
        "Zongo"
    ],
    "name:rus_x_preferred":[
        "\u0417\u043e\u043d\u0433\u043e"
    ],
    "name:spa_x_preferred":[
        "Zongo"
    ],
    "name:swe_x_preferred":[
        "Zongo"
    ],
    "wof:name":"Zongo",
    "wof:placetype":"locality"
},
  "geometry": {"coordinates":[-2.37596,13.22745],"type":"Point"}
}