{
  "type": "Feature",
  "properties": {
    "gn:admin1_code":"07",
    "gn:asciiname":"Kalsagado",
    "gn:country_code":"BF",
    "gn:dem":328,
    "gn:feature_class":"P",
    "gn:feature_code":"PPL",
    "gn:name":"Kalsagado",
    "gn:population":0,
    "gn:timezone":"Africa/Ouagadougou",
    "iso:country":"BF",
    "wof:name":"Kalsagado",
    "wof:placetype":"locality"
},
  "geometry": {"coordinates":[-1.33333,11.96667],"type":"Point"}
}