{
  "type": "Feature",
  "properties": {
    "gn:admin1_code":"04",
    "gn:asciiname":"Dogotenga",
    "gn:country_code":"BF",
    "gn:dem":273,
    "gn:feature_class":"P",
    "gn:feature_code":"PPL",
    "gn:name":"Dogotenga",
    "gn:population":0,
    "gn:timezone":"Africa/Ouagadougou",
    "iso:country":"BF",
    "wof:name":"Dogotenga",
    "wof:placetype":"locality"
},
  "geometry": {"coordinates":[0.18287,11.67603],"type":"Point"}
}