{
  "type": "Feature",
  "properties": {
    "gn:admin1_code":"01",
    "gn:admin2_code":"58",
    "gn:asciiname":"Sadiniakono",
    "gn:country_code":"BF",
    "gn:dem":462,
    "gn:feature_class":"P",
    "gn:feature_code":"PPL",
    "gn:name":"Sadiniakono",
    "gn:population":0,
    "gn:timezone":"Africa/Ouagadougou",
    "iso:country":"BF",
    "wof:name":"Sadiniakono",
    "wof:placetype":"locality"
},
  "geometry": {"coordinates":[-4.0718,13.3064],"type":"Point"}
}