{
  "type": "Feature",
  "properties": {
    "gn:admin1_code":"10",
    "gn:admin2_code":"76",
    "gn:asciiname":"Nabaziniguima",
    "gn:country_code":"BF",
    "gn:dem":317,
    "gn:feature_class":"P",
    "gn:feature_code":"PPL",
    "gn:name":"Nabaziniguima",
    "gn:population":0,
    "gn:timezone":"Africa/Ouagadougou",
    "iso:country":"BF",
    "name:und_x_variant":[
        "Nabassiniguima",
        "Nabaziniguima"
    ],
    "wof:name":"Nabaziniguima",
    "wof:placetype":"locality"
},
  "geometry": {"coordinates":[-2.55565,13.58823],"type":"Point"}
}