{
  "type": "Feature",
  "properties": {
    "gn:admin1_code":"05",
    "gn:admin2_code":"15",
    "gn:asciiname":"Zandkom",
    "gn:country_code":"BF",
    "gn:dem":326,
    "gn:feature_class":"P",
    "gn:feature_code":"PPL",
    "gn:name":"Zandkom",
    "gn:population":0,
    "gn:timezone":"Africa/Ouagadougou",
    "iso:country":"BF",
    "wof:name":"Zandkom",
    "wof:placetype":"locality"
},
  "geometry": {"coordinates":[-1.5526,13.14071],"type":"Point"}
}