{
  "type": "Feature",
  "properties": {
    "gn:admin1_code":"10",
    "gn:admin2_code":"76",
    "gn:asciiname":"Ipala",
    "gn:country_code":"BF",
    "gn:dem":355,
    "gn:feature_class":"P",
    "gn:feature_code":"PPL",
    "gn:name":"Ipala",
    "gn:population":0,
    "gn:timezone":"Africa/Ouagadougou",
    "iso:country":"BF",
    "name:ceb_x_preferred":[
        "Ipala"
    ],
    "name:fra_x_preferred":[
        "Ipala"
    ],
    "name:hun_x_preferred":[
        "Ipala"
    ],
    "name:ita_x_preferred":[
        "Ipala"
    ],
    "name:nld_x_preferred":[
        "Ipala"
    ],
    "name:swe_x_preferred":[
        "Ipala"
    ],
    "wof:name":"Ipala",
    "wof:placetype":"locality"
},
  "geometry": {"coordinates":[-2.35798,13.75942],"type":"Point"}
}