{
  "type": "Feature",
  "properties": {
    "gn:admin1_code":"08",
    "gn:admin2_code":"42",
    "gn:asciiname":"Partiaga",
    "gn:country_code":"BF",
    "gn:dem":219,
    "gn:feature_class":"P",
    "gn:feature_code":"PPL",
    "gn:name":"Partiaga",
    "gn:population":0,
    "gn:timezone":"Africa/Ouagadougou",
    "iso:country":"BF",
    "name:und_x_variant":[
        "Partyaga",
        "Partiaga"
    ],
    "wof:name":"Partiaga",
    "wof:placetype":"locality"
},
  "geometry": {"coordinates":[2.01186,12.61083],"type":"Point"}
}