{
  "type": "Feature",
  "properties": {
    "gn:admin1_code":"10",
    "gn:admin2_code":"76",
    "gn:asciiname":"Tangaye",
    "gn:country_code":"BF",
    "gn:dem":327,
    "gn:feature_class":"P",
    "gn:feature_code":"PPL",
    "gn:name":"Tangaye",
    "gn:population":0,
    "gn:timezone":"Africa/Ouagadougou",
    "iso:country":"BF",
    "name:azb_x_preferred":[
        "\u062a\u0627\u0646\u0642\u0627\u06cc\u0647"
    ],
    "name:deu_x_preferred":[
        "Tangaye"
    ],
    "name:fas_x_preferred":[
        "\u062a\u0627\u0646\u06af\u0627\u06cc\u0647"
    ],
    "name:ita_x_preferred":[
        "Tangaye"
    ],
    "name:und_x_variant":[
        "Tangay"
    ],
    "wof:name":"Tangaye",
    "wof:placetype":"locality"
},
  "geometry": {"coordinates":[-2.54689,13.54009],"type":"Point"}
}