{
  "type": "Feature",
  "properties": {
    "gn:admin1_code":"10",
    "gn:admin2_code":"76",
    "gn:asciiname":"Tangaye",
    "gn:country_code":"BF",
    "gn:dem":327,
    "gn:feature_class":"P",
    "gn:feature_code":"PPL",
    "gn:name":"Tangaye",
    "gn:population":0,
    "gn:timezone":"Africa/Ouagadougou",
    "iso:country":"BF",
    "name:und_x_variant":[
        "Tangay",
        "Tangaye"
    ],
    "wof:name":"Tangaye",
    "wof:placetype":"locality"
},
  "geometry": {"coordinates":[-2.54689,13.54009],"type":"Point"}
}