{
  "type": "Feature",
  "properties": {
    "gn:admin1_code":"03",
    "gn:asciiname":"Wavoure",
    "gn:country_code":"BF",
    "gn:dem":306,
    "gn:feature_class":"P",
    "gn:feature_code":"PPL",
    "gn:name":"Wavour\u00e9",
    "gn:population":0,
    "gn:timezone":"Africa/Ouagadougou",
    "iso:country":"BF",
    "name:und_x_variant":[
        "Wavougu\u00e9",
        "Wavour\u00e9",
        "Ouavougu\u00e9"
    ],
    "wof:name":"Wavoure",
    "wof:placetype":"locality"
},
  "geometry": {"coordinates":[-1.63333,12.55],"type":"Point"}
}