{
  "type": "Feature",
  "properties": {
    "gn:admin1_code":"05",
    "gn:admin2_code":"70",
    "gn:asciiname":"Zontibe",
    "gn:country_code":"BF",
    "gn:dem":365,
    "gn:feature_class":"P",
    "gn:feature_code":"PPL",
    "gn:name":"Zontib\u00e9",
    "gn:population":0,
    "gn:timezone":"Africa/Ouagadougou",
    "iso:country":"BF",
    "wof:name":"Zontibe",
    "wof:placetype":"locality"
},
  "geometry": {"coordinates":[-1.25175,13.41516],"type":"Point"}
}