{
  "type": "Feature",
  "properties": {
    "gn:admin1_code":"09",
    "gn:admin2_code":"51",
    "gn:asciiname":"Fina",
    "gn:country_code":"BF",
    "gn:dem":306,
    "gn:feature_class":"P",
    "gn:feature_code":"PPL",
    "gn:name":"Fina",
    "gn:population":0,
    "gn:timezone":"Africa/Ouagadougou",
    "iso:country":"BF",
    "name:ceb_x_preferred":[
        "Fina"
    ],
    "name:deu_x_preferred":[
        "Fina"
    ],
    "name:fra_x_preferred":[
        "Fina"
    ],
    "name:jpn_x_preferred":[
        "\u30d5\u30a3\u30fc\u30ca"
    ],
    "name:nld_x_preferred":[
        "Fina"
    ],
    "name:spa_x_preferred":[
        "Fina"
    ],
    "name:swe_x_preferred":[
        "Fina"
    ],
    "name:und_x_variant":[
        "Dougoudialama",
        "Fina"
    ],
    "wof:name":"Fina",
    "wof:placetype":"locality"
},
  "geometry": {"coordinates":[-4.04443,11.56344],"type":"Point"}
}