{
  "type": "Feature",
  "properties": {
    "gn:admin1_code":"06",
    "gn:asciiname":"Koutiele",
    "gn:country_code":"BF",
    "gn:dem":321,
    "gn:feature_class":"P",
    "gn:feature_code":"PPL",
    "gn:name":"Kouti\u00e9l\u00e9",
    "gn:population":0,
    "gn:timezone":"Africa/Ouagadougou",
    "iso:country":"BF",
    "wof:name":"Koutiele",
    "wof:placetype":"locality"
},
  "geometry": {"coordinates":[-1.86667,11.75],"type":"Point"}
}