{
  "type": "Feature",
  "properties": {
    "gn:admin1_code":"13",
    "gn:asciiname":"Tanpe",
    "gn:country_code":"BF",
    "gn:dem":307,
    "gn:feature_class":"P",
    "gn:feature_code":"PPL",
    "gn:name":"Tanp\u00e9",
    "gn:population":0,
    "gn:timezone":"Africa/Ouagadougou",
    "iso:country":"BF",
    "wof:name":"Tanpe",
    "wof:placetype":"locality"
},
  "geometry": {"coordinates":[-3.35,10.96667],"type":"Point"}
}