{
  "type": "Feature",
  "properties": {
    "gn:admin1_code":"12",
    "gn:admin2_code":"75",
    "gn:asciiname":"Dar Salam",
    "gn:country_code":"BF",
    "gn:dem":248,
    "gn:feature_class":"P",
    "gn:feature_code":"PPL",
    "gn:name":"Dar Salam",
    "gn:population":0,
    "gn:timezone":"Africa/Ouagadougou",
    "iso:country":"BF",
    "wof:name":"Dar Salam",
    "wof:placetype":"locality"
},
  "geometry": {"coordinates":[0.92302,13.46695],"type":"Point"}
}