{
  "type": "Feature",
  "properties": {
    "gn:admin1_code":"09",
    "gn:admin2_code":"51",
    "gn:asciiname":"Tounouma",
    "gn:country_code":"BF",
    "gn:dem":431,
    "gn:feature_class":"P",
    "gn:feature_code":"PPL",
    "gn:name":"Tounouma",
    "gn:population":0,
    "gn:timezone":"Africa/Ouagadougou",
    "iso:country":"BF",
    "wof:name":"Tounouma",
    "wof:placetype":"locality"
},
  "geometry": {"coordinates":[-4.28156,11.17857],"type":"Point"}
}