{
  "type": "Feature",
  "properties": {
    "gn:admin1_code":"01",
    "gn:admin2_code":"73",
    "gn:asciiname":"Bassan",
    "gn:country_code":"BF",
    "gn:dem":267,
    "gn:feature_class":"P",
    "gn:feature_code":"PPL",
    "gn:name":"Bassan",
    "gn:population":0,
    "gn:timezone":"Africa/Ouagadougou",
    "iso:country":"BF",
    "wof:name":"Bassan",
    "wof:placetype":"locality"
},
  "geometry": {"coordinates":[-3.1726,13.0837],"type":"Point"}
}