{
  "type": "Feature",
  "properties": {
    "gn:admin1_code":"01",
    "gn:admin2_code":"73",
    "gn:asciiname":"Bassan",
    "gn:country_code":"BF",
    "gn:dem":267,
    "gn:feature_class":"P",
    "gn:feature_code":"PPL",
    "gn:name":"Bassan",
    "gn:population":0,
    "gn:timezone":"Africa/Ouagadougou",
    "iso:country":"BF",
    "name:cat_x_preferred":[
        "Ba\u00e7an"
    ],
    "name:ceb_x_preferred":[
        "Bassan"
    ],
    "name:deu_x_preferred":[
        "Bassan"
    ],
    "name:eus_x_preferred":[
        "Ba\u00e7an"
    ],
    "name:fra_x_preferred":[
        "Bassan"
    ],
    "name:hun_x_preferred":[
        "Bassan"
    ],
    "name:ita_x_preferred":[
        "Bassan"
    ],
    "name:kaz_x_preferred":[
        "\u0411\u0430\u0441\u0441\u0430\u043d"
    ],
    "name:lat_x_preferred":[
        "Bassan"
    ],
    "name:msa_x_preferred":[
        "Bassan"
    ],
    "name:nld_x_preferred":[
        "Bassan"
    ],
    "name:oci_x_preferred":[
        "Ba\u00e7an"
    ],
    "name:pms_x_preferred":[
        "Bassan"
    ],
    "name:pol_x_preferred":[
        "Bassan"
    ],
    "name:por_x_preferred":[
        "Bassan"
    ],
    "name:ron_x_preferred":[
        "Bassan"
    ],
    "name:slk_x_preferred":[
        "Bassan"
    ],
    "name:spa_x_preferred":[
        "Bassan"
    ],
    "name:sqi_x_preferred":[
        "Bassan"
    ],
    "name:srp_x_preferred":[
        "\u0411\u0430\u0441\u0430\u043d"
    ],
    "name:swe_x_preferred":[
        "Bassan"
    ],
    "name:ukr_x_preferred":[
        "\u0411\u0430\u0441\u0441\u0430\u043d"
    ],
    "name:vie_x_preferred":[
        "Bassan"
    ],
    "name:vol_x_preferred":[
        "Bassan"
    ],
    "name:war_x_preferred":[
        "Bassan"
    ],
    "name:zho_x_preferred":[
        "\u5df4\u6851"
    ],
    "wof:name":"Bassan",
    "wof:placetype":"locality"
},
  "geometry": {"coordinates":[-3.1726,13.0837],"type":"Point"}
}