{
  "type": "Feature",
  "properties": {
    "gn:admin1_code":"12",
    "gn:admin2_code":"71",
    "gn:asciiname":"Ouro Boki",
    "gn:country_code":"BF",
    "gn:dem":306,
    "gn:feature_class":"P",
    "gn:feature_code":"PPL",
    "gn:name":"Ouro Boki",
    "gn:population":0,
    "gn:timezone":"Africa/Ouagadougou",
    "iso:country":"BF",
    "wof:name":"Ouro Boki",
    "wof:placetype":"locality"
},
  "geometry": {"coordinates":[0.19364,13.97592],"type":"Point"}
}