{
  "type": "Feature",
  "properties": {
    "gn:admin1_code":"05",
    "gn:asciiname":"Ledere",
    "gn:country_code":"BF",
    "gn:dem":322,
    "gn:feature_class":"P",
    "gn:feature_code":"PPL",
    "gn:name":"L\u00e9d\u00e9r\u00e9",
    "gn:population":0,
    "gn:timezone":"Africa/Ouagadougou",
    "iso:country":"BF",
    "wof:name":"Ledere",
    "wof:placetype":"locality"
},
  "geometry": {"coordinates":[-0.76667,12.95],"type":"Point"}
}