{
  "type": "Feature",
  "properties": {
    "gn:admin1_code":"10",
    "gn:admin2_code":"76",
    "gn:asciiname":"Koundoula",
    "gn:country_code":"BF",
    "gn:dem":315,
    "gn:feature_class":"P",
    "gn:feature_code":"PPL",
    "gn:name":"Koundoula",
    "gn:population":0,
    "gn:timezone":"Africa/Ouagadougou",
    "iso:country":"BF",
    "name:azb_x_preferred":[
        "\u06a9\u0648\u0646\u062f\u0648\u0644\u0627"
    ],
    "name:fas_x_preferred":[
        "\u06a9\u0648\u0646\u062f\u0648\u0644\u0627"
    ],
    "name:fra_x_preferred":[
        "Koundoula"
    ],
    "wof:name":"Koundoula",
    "wof:placetype":"locality"
},
  "geometry": {"coordinates":[-1.88259,13.18481],"type":"Point"}
}