{
  "type": "Feature",
  "properties": {
    "gn:admin1_code":"12",
    "gn:admin2_code":"75",
    "gn:asciiname":"Binguel",
    "gn:country_code":"BF",
    "gn:dem":271,
    "gn:feature_class":"P",
    "gn:feature_code":"PPL",
    "gn:name":"B\u00efngu\u00e8l",
    "gn:population":0,
    "gn:timezone":"Africa/Ouagadougou",
    "iso:country":"BF",
    "wof:name":"Binguel",
    "wof:placetype":"locality"
},
  "geometry": {"coordinates":[0.4548,13.64506],"type":"Point"}
}