{
  "type": "Feature",
  "properties": {
    "gn:admin1_code":"09",
    "gn:asciiname":"Bouhahoun",
    "gn:country_code":"BF",
    "gn:dem":322,
    "gn:feature_class":"P",
    "gn:feature_code":"PPL",
    "gn:name":"Bouhahoun",
    "gn:population":0,
    "gn:timezone":"Africa/Ouagadougou",
    "iso:country":"BF",
    "name:und_x_variant":[
        "Bahon",
        "Bouhahoun",
        "Bahoun",
        "Bouhaoun",
        "Bonohoun"
    ],
    "wof:name":"Bouhahoun",
    "wof:placetype":"locality"
},
  "geometry": {"coordinates":[-3.76667,11.48333],"type":"Point"}
}