{
  "type": "Feature",
  "properties": {
    "gn:admin1_code":"10",
    "gn:admin2_code":"76",
    "gn:asciiname":"Kouni",
    "gn:country_code":"BF",
    "gn:dem":332,
    "gn:feature_class":"P",
    "gn:feature_code":"PPL",
    "gn:name":"Kouni",
    "gn:population":0,
    "gn:timezone":"Africa/Ouagadougou",
    "iso:country":"BF",
    "name:ceb_x_preferred":[
        "Kouni"
    ],
    "name:fra_x_preferred":[
        "Kouni"
    ],
    "wof:name":"Kouni",
    "wof:placetype":"locality"
},
  "geometry": {"coordinates":[-2.18207,13.03511],"type":"Point"}
}