{
  "type": "Feature",
  "properties": {
    "gn:admin1_code":"01",
    "gn:asciiname":"Oula",
    "gn:country_code":"BF",
    "gn:dem":299,
    "gn:feature_class":"P",
    "gn:feature_code":"PPL",
    "gn:name":"Oula",
    "gn:population":0,
    "gn:timezone":"Africa/Ouagadougou",
    "iso:country":"BF",
    "wof:name":"Oula",
    "wof:placetype":"locality"
},
  "geometry": {"coordinates":[-3.13333,12.36667],"type":"Point"}
}