{
  "type": "Feature",
  "properties": {
    "gn:admin1_code":"09",
    "gn:admin2_code":"51",
    "gn:asciiname":"Bonvale",
    "gn:country_code":"BF",
    "gn:dem":286,
    "gn:feature_class":"P",
    "gn:feature_code":"PPL",
    "gn:name":"Bonval\u00e9",
    "gn:population":0,
    "gn:timezone":"Africa/Ouagadougou",
    "iso:country":"BF",
    "name:und_x_variant":[
        "Banoual\u00e9",
        "Bonval\u00e9"
    ],
    "wof:name":"Bonvale",
    "wof:placetype":"locality"
},
  "geometry": {"coordinates":[-4.19346,11.76118],"type":"Point"}
}