{
  "type": "Feature",
  "properties": {
    "gn:admin1_code":"13",
    "gn:asciiname":"Tinkiro",
    "gn:country_code":"BF",
    "gn:dem":351,
    "gn:feature_class":"P",
    "gn:feature_code":"PPL",
    "gn:name":"Tinkiro",
    "gn:population":0,
    "gn:timezone":"Africa/Ouagadougou",
    "iso:country":"BF",
    "wof:name":"Tinkiro",
    "wof:placetype":"locality"
},
  "geometry": {"coordinates":[-3.41667,10.11667],"type":"Point"}
}