{
  "type": "Feature",
  "properties": {
    "gn:admin1_code":"10",
    "gn:admin2_code":"76",
    "gn:asciiname":"Oufre",
    "gn:country_code":"BF",
    "gn:dem":340,
    "gn:feature_class":"P",
    "gn:feature_code":"PPL",
    "gn:name":"Oufr\u00e9",
    "gn:population":0,
    "gn:timezone":"Africa/Ouagadougou",
    "iso:country":"BF",
    "wof:name":"Oufre",
    "wof:placetype":"locality"
},
  "geometry": {"coordinates":[-2.42126,13.54909],"type":"Point"}
}