{
  "type": "Feature",
  "properties": {
    "gn:admin1_code":"08",
    "gn:admin2_code":"21",
    "gn:asciiname":"Dyagourou",
    "gn:country_code":"BF",
    "gn:dem":274,
    "gn:feature_class":"P",
    "gn:feature_code":"PPL",
    "gn:name":"Dyagourou",
    "gn:population":0,
    "gn:timezone":"Africa/Ouagadougou",
    "iso:country":"BF",
    "wof:name":"Dyagourou",
    "wof:placetype":"locality"
},
  "geometry": {"coordinates":[0.0976,13.43538],"type":"Point"}
}