{
  "type": "Feature",
  "properties": {
    "gn:admin1_code":"12",
    "gn:admin2_code":"75",
    "gn:asciiname":"Gongorgol",
    "gn:country_code":"BF",
    "gn:dem":250,
    "gn:feature_class":"P",
    "gn:feature_code":"PPL",
    "gn:name":"Gongorgol",
    "gn:population":0,
    "gn:timezone":"Africa/Ouagadougou",
    "iso:country":"BF",
    "name:und_x_variant":[
        "Gongorol",
        "Gongorgol"
    ],
    "wof:name":"Gongorgol",
    "wof:placetype":"locality"
},
  "geometry": {"coordinates":[0.49647,13.31264],"type":"Point"}
}