{
  "type": "Feature",
  "properties": {
    "gn:admin1_code":"06",
    "gn:asciiname":"Sabou",
    "gn:country_code":"BF",
    "gn:dem":296,
    "gn:feature_class":"P",
    "gn:feature_code":"PPL",
    "gn:name":"Sabou",
    "gn:population":0,
    "gn:timezone":"Africa/Ouagadougou",
    "iso:country":"BF",
    "name:azb_x_preferred":[
        "\u0633\u0627\u0628\u0648"
    ],
    "name:fas_x_preferred":[
        "\u0633\u0627\u0628\u0648"
    ],
    "name:fra_x_preferred":[
        "Sabou"
    ],
    "name:und_x_variant":[
        "Sabu",
        "Sabou"
    ],
    "name:urd_x_preferred":[
        "\u0633\u0628\u0648"
    ],
    "wof:name":"Sabou",
    "wof:placetype":"locality"
},
  "geometry": {"coordinates":[-2.23333,12.06667],"type":"Point"}
}