{
  "type": "Feature",
  "properties": {
    "gn:admin1_code":"05",
    "gn:admin2_code":"64",
    "gn:asciiname":"Nabmassa",
    "gn:country_code":"BF",
    "gn:dem":277,
    "gn:feature_class":"P",
    "gn:feature_code":"PPL",
    "gn:name":"Nabmassa",
    "gn:population":0,
    "gn:timezone":"Africa/Ouagadougou",
    "iso:country":"BF",
    "name:azb_x_preferred":[
        "\u0646\u0627\u0628\u0645\u0627\u0633\u0627"
    ],
    "name:fas_x_preferred":[
        "\u0646\u0627\u0628\u0645\u0627\u0633\u0627"
    ],
    "wof:name":"Nabmassa",
    "wof:placetype":"locality"
},
  "geometry": {"coordinates":[-0.41665,13.22985],"type":"Point"}
}