{
  "type": "Feature",
  "properties": {
    "gn:admin1_code":"05",
    "gn:admin2_code":"70",
    "gn:asciiname":"Nebouli",
    "gn:country_code":"BF",
    "gn:dem":296,
    "gn:feature_class":"P",
    "gn:feature_code":"PPL",
    "gn:name":"N\u00e9bouli",
    "gn:population":0,
    "gn:timezone":"Africa/Ouagadougou",
    "iso:country":"BF",
    "wof:name":"Nebouli",
    "wof:placetype":"locality"
},
  "geometry": {"coordinates":[-0.88862,13.33809],"type":"Point"}
}