{
  "type": "Feature",
  "properties": {
    "gn:admin1_code":"05",
    "gn:admin2_code":"15",
    "gn:asciiname":"Felenga",
    "gn:country_code":"BF",
    "gn:dem":341,
    "gn:feature_class":"P",
    "gn:feature_code":"PPL",
    "gn:name":"F\u00e9l\u00e8nga",
    "gn:population":0,
    "gn:timezone":"Africa/Ouagadougou",
    "iso:country":"BF",
    "name:azb_x_preferred":[
        "\u0641\u0644\u0646\u0642\u0627"
    ],
    "name:ceb_x_preferred":[
        "F\u00e9l\u00e8nga"
    ],
    "name:fas_x_preferred":[
        "\u0641\u0644\u0646\u06af\u0627"
    ],
    "name:fra_x_preferred":[
        "F\u00e9lenga"
    ],
    "name:swe_x_preferred":[
        "F\u00e9l\u00e8nga"
    ],
    "wof:name":"Felenga",
    "wof:placetype":"locality"
},
  "geometry": {"coordinates":[-1.66156,13.79077],"type":"Point"}
}