{
  "type": "Feature",
  "properties": {
    "gn:admin1_code":"08",
    "gn:asciiname":"Ougarou",
    "gn:country_code":"BF",
    "gn:dem":293,
    "gn:feature_class":"P",
    "gn:feature_code":"PPL",
    "gn:name":"Ougarou",
    "gn:population":0,
    "gn:timezone":"Africa/Ouagadougou",
    "iso:country":"BF",
    "name:ceb_x_preferred":[
        "Ougarou"
    ],
    "name:fra_x_preferred":[
        "Ougarou"
    ],
    "name:swe_x_preferred":[
        "Ougarou"
    ],
    "wof:name":"Ougarou",
    "wof:placetype":"locality"
},
  "geometry": {"coordinates":[0.16667,12.43333],"type":"Point"}
}