{
  "type": "Feature",
  "properties": {
    "gn:admin1_code":"01",
    "gn:asciiname":"Silaro",
    "gn:country_code":"BF",
    "gn:dem":331,
    "gn:feature_class":"P",
    "gn:feature_code":"PPL",
    "gn:name":"Silaro",
    "gn:population":0,
    "gn:timezone":"Africa/Ouagadougou",
    "iso:country":"BF",
    "wof:name":"Silaro",
    "wof:placetype":"locality"
},
  "geometry": {"coordinates":[-3.31667,12.06667],"type":"Point"}
}