{
  "type": "Feature",
  "properties": {
    "gn:admin1_code":"12",
    "gn:admin2_code":"71",
    "gn:asciiname":"Gassel",
    "gn:country_code":"BF",
    "gn:dem":305,
    "gn:feature_class":"P",
    "gn:feature_code":"PPL",
    "gn:name":"Gass\u00e8l",
    "gn:population":0,
    "gn:timezone":"Africa/Ouagadougou",
    "iso:country":"BF",
    "name:ceb_x_preferred":[
        "Gassel"
    ],
    "name:fra_x_preferred":[
        "Gassel"
    ],
    "name:nld_x_preferred":[
        "Gassel"
    ],
    "wof:name":"Gassel",
    "wof:placetype":"locality"
},
  "geometry": {"coordinates":[0.2411,13.78602],"type":"Point"}
}