{
  "type": "Feature",
  "properties": {
    "gn:admin1_code":"09",
    "gn:admin2_code":"51",
    "gn:asciiname":"Kona",
    "gn:country_code":"BF",
    "gn:dem":332,
    "gn:feature_class":"P",
    "gn:feature_code":"PPL",
    "gn:name":"Kona",
    "gn:population":0,
    "gn:timezone":"Africa/Ouagadougou",
    "iso:country":"BF",
    "name:cat_x_preferred":[
        "Kona"
    ],
    "name:ceb_x_preferred":[
        "Kona"
    ],
    "name:dan_x_preferred":[
        "Kona"
    ],
    "name:deu_x_preferred":[
        "Kona"
    ],
    "name:fin_x_preferred":[
        "Kona"
    ],
    "name:fra_x_preferred":[
        "Kona"
    ],
    "name:nno_x_preferred":[
        "Kona"
    ],
    "name:spa_x_preferred":[
        "Kona"
    ],
    "name:swe_x_preferred":[
        "Kona"
    ],
    "name:und_x_variant":[
        "Moussobadougou",
        "Kona"
    ],
    "wof:name":"Kona",
    "wof:placetype":"locality"
},
  "geometry": {"coordinates":[-4.12119,11.26263],"type":"Point"}
}