{
  "type": "Feature",
  "properties": {
    "gn:admin1_code":"13",
    "gn:asciiname":"Simou",
    "gn:country_code":"BF",
    "gn:dem":266,
    "gn:feature_class":"P",
    "gn:feature_code":"PPL",
    "gn:name":"Simou",
    "gn:population":0,
    "gn:timezone":"Africa/Ouagadougou",
    "iso:country":"BF",
    "wof:name":"Simou",
    "wof:placetype":"locality"
},
  "geometry": {"coordinates":[-2.75,11.06667],"type":"Point"}
}