{
  "type": "Feature",
  "properties": {
    "gn:admin1_code":"13",
    "gn:asciiname":"Simou",
    "gn:country_code":"BF",
    "gn:dem":266,
    "gn:feature_class":"P",
    "gn:feature_code":"PPL",
    "gn:name":"Simou",
    "gn:population":0,
    "gn:timezone":"Africa/Ouagadougou",
    "iso:country":"BF",
    "name:bul_x_preferred":[
        "\u0421\u0438\u043c\u0443"
    ],
    "name:ceb_x_preferred":[
        "S\u00edmou"
    ],
    "name:ell_x_preferred":[
        "\u03a3\u03af\u03bc\u03bf\u03c5"
    ],
    "name:hye_x_preferred":[
        "\u054d\u056b\u0574\u0578\u0582"
    ],
    "name:pol_x_preferred":[
        "Simu"
    ],
    "name:swe_x_preferred":[
        "S\u00edmou"
    ],
    "name:urd_x_preferred":[
        "\u0633\u06cc\u0645\u0648"
    ],
    "wof:name":"Simou",
    "wof:placetype":"locality"
},
  "geometry": {"coordinates":[-2.75,11.06667],"type":"Point"}
}