{
  "type": "Feature",
  "properties": {
    "gn:admin1_code":"08",
    "gn:admin2_code":"21",
    "gn:asciiname":"Tann-Fwogou",
    "gn:country_code":"BF",
    "gn:dem":257,
    "gn:feature_class":"P",
    "gn:feature_code":"PPL",
    "gn:name":"Tann-Fwogou",
    "gn:population":0,
    "gn:timezone":"Africa/Ouagadougou",
    "iso:country":"BF",
    "wof:name":"Tann-Fwogou",
    "wof:placetype":"locality"
},
  "geometry": {"coordinates":[0.56723,13.02542],"type":"Point"}
}