{
  "type": "Feature",
  "properties": {
    "gn:admin1_code":"07",
    "gn:admin2_code":"47",
    "gn:asciiname":"Rounde",
    "gn:country_code":"BF",
    "gn:dem":335,
    "gn:feature_class":"P",
    "gn:feature_code":"PPL",
    "gn:name":"Round\u00e9",
    "gn:population":0,
    "gn:timezone":"Africa/Ouagadougou",
    "iso:country":"BF",
    "wof:name":"Rounde",
    "wof:placetype":"locality"
},
  "geometry": {"coordinates":[-1.47194,12.03417],"type":"Point"}
}