{
  "type": "Feature",
  "properties": {
    "gn:admin1_code":"13",
    "gn:asciiname":"Founfouna",
    "gn:country_code":"BF",
    "gn:dem":262,
    "gn:feature_class":"P",
    "gn:feature_code":"PPL",
    "gn:name":"Founfouna",
    "gn:population":0,
    "gn:timezone":"Africa/Ouagadougou",
    "iso:country":"BF",
    "wof:name":"Founfouna",
    "wof:placetype":"locality"
},
  "geometry": {"coordinates":[-3.08333,10.08333],"type":"Point"}
}