{
  "type": "Feature",
  "properties": {
    "gn:admin1_code":"05",
    "gn:admin2_code":"70",
    "gn:asciiname":"Guienbile",
    "gn:country_code":"BF",
    "gn:dem":291,
    "gn:feature_class":"P",
    "gn:feature_code":"PPL",
    "gn:name":"Guienbil\u00e9",
    "gn:population":0,
    "gn:timezone":"Africa/Ouagadougou",
    "iso:country":"BF",
    "name:und_x_variant":[
        "Gienbil\u00e9",
        "Guienbil\u00e9"
    ],
    "wof:name":"Guienbile",
    "wof:placetype":"locality"
},
  "geometry": {"coordinates":[-0.95842,13.69971],"type":"Point"}
}