{
  "type": "Feature",
  "properties": {
    "gn:admin1_code":"12",
    "gn:admin2_code":"71",
    "gn:asciiname":"Peteguerse",
    "gn:country_code":"BF",
    "gn:dem":283,
    "gn:feature_class":"P",
    "gn:feature_code":"PPL",
    "gn:name":"P\u00e9t\u00e9guers\u00e9",
    "gn:population":0,
    "gn:timezone":"Africa/Ouagadougou",
    "iso:country":"BF",
    "wof:name":"Peteguerse",
    "wof:placetype":"locality"
},
  "geometry": {"coordinates":[-0.36824,14.03565],"type":"Point"}
}