{
  "type": "Feature",
  "properties": {
    "gn:admin1_code":"04",
    "gn:asciiname":"Ibobo",
    "gn:country_code":"BF",
    "gn:dem":245,
    "gn:feature_class":"P",
    "gn:feature_code":"PPL",
    "gn:name":"Ibobo",
    "gn:population":0,
    "gn:timezone":"Africa/Ouagadougou",
    "iso:country":"BF",
    "wof:name":"Ibobo",
    "wof:placetype":"locality"
},
  "geometry": {"coordinates":[-0.71667,11.71667],"type":"Point"}
}