{
  "type": "Feature",
  "properties": {
    "gn:admin1_code":"01",
    "gn:asciiname":"Mana",
    "gn:country_code":"BF",
    "gn:dem":317,
    "gn:feature_class":"P",
    "gn:feature_code":"PPL",
    "gn:name":"Mana",
    "gn:population":0,
    "gn:timezone":"Africa/Ouagadougou",
    "iso:country":"BF",
    "name:azb_x_preferred":[
        "\u0645\u0627\u0646\u0627"
    ],
    "name:ceb_x_preferred":[
        "Mana"
    ],
    "name:fas_x_preferred":[
        "\u0645\u0627\u0646\u0627"
    ],
    "name:fra_x_preferred":[
        "Mana"
    ],
    "name:swe_x_preferred":[
        "Mana"
    ],
    "wof:name":"Mana",
    "wof:placetype":"locality"
},
  "geometry": {"coordinates":[-3.36667,11.86667],"type":"Point"}
}