{
  "type": "Feature",
  "properties": {
    "gn:admin1_code":"01",
    "gn:asciiname":"Mana",
    "gn:country_code":"BF",
    "gn:dem":317,
    "gn:feature_class":"P",
    "gn:feature_code":"PPL",
    "gn:name":"Mana",
    "gn:population":0,
    "gn:timezone":"Africa/Ouagadougou",
    "iso:country":"BF",
    "name:ara_x_preferred":[
        "\u0645\u0627\u0646\u0627"
    ],
    "name:azb_x_preferred":[
        "\u0645\u0627\u0646\u0627"
    ],
    "name:ben_x_preferred":[
        "\u09ae\u09be\u09a8\u09be"
    ],
    "name:ceb_x_preferred":[
        "Mana"
    ],
    "name:ell_x_preferred":[
        "\u039c\u03ac\u03bd\u03b1"
    ],
    "name:fas_x_preferred":[
        "\u0645\u0627\u0646\u0627"
    ],
    "name:fra_x_preferred":[
        "Mana"
    ],
    "name:heb_x_preferred":[
        "\u05de\u05e0\u05e4\u05d5\u05d5\u05d4"
    ],
    "name:hin_x_preferred":[
        "\u092e\u093e\u0928\u093e"
    ],
    "name:ind_x_preferred":[
        "Mana"
    ],
    "name:kor_x_preferred":[
        "\ub9c8\ub098"
    ],
    "name:por_x_preferred":[
        "Mana"
    ],
    "name:spa_x_preferred":[
        "Mana"
    ],
    "name:swe_x_preferred":[
        "Mana"
    ],
    "name:tur_x_preferred":[
        "Mana"
    ],
    "name:ukr_x_preferred":[
        "\u041c\u0430\u043d\u0430"
    ],
    "name:urd_x_preferred":[
        "\u0645\u0627\u0646\u0627"
    ],
    "name:vie_x_preferred":[
        "S\u00f4ng Mana"
    ],
    "wof:name":"Mana",
    "wof:placetype":"locality"
},
  "geometry": {"coordinates":[-3.36667,11.86667],"type":"Point"}
}