{
  "type": "Feature",
  "properties": {
    "gn:admin1_code":"12",
    "gn:admin2_code":"71",
    "gn:asciiname":"Boulmanga",
    "gn:country_code":"BF",
    "gn:dem":272,
    "gn:feature_class":"P",
    "gn:feature_code":"PPL",
    "gn:name":"Boulmanga",
    "gn:population":0,
    "gn:timezone":"Africa/Ouagadougou",
    "iso:country":"BF",
    "wof:name":"Boulmanga",
    "wof:placetype":"locality"
},
  "geometry": {"coordinates":[-0.34599,13.61904],"type":"Point"}
}