{
  "type": "Feature",
  "properties": {
    "gn:admin1_code":"00",
    "gn:asciiname":"Wantenga",
    "gn:country_code":"BF",
    "gn:dem":304,
    "gn:feature_class":"P",
    "gn:feature_code":"PPL",
    "gn:name":"Wantenga",
    "gn:population":0,
    "gn:timezone":"Africa/Ouagadougou",
    "iso:country":"BF",
    "wof:name":"Wantenga",
    "wof:placetype":"locality"
},
  "geometry": {"coordinates":[-0.65,12.66667],"type":"Point"}
}