{
  "type": "Feature",
  "properties": {
    "gn:admin1_code":"13",
    "gn:asciiname":"Banhie",
    "gn:country_code":"BF",
    "gn:dem":266,
    "gn:feature_class":"P",
    "gn:feature_code":"PPL",
    "gn:name":"Banhi\u00e9",
    "gn:population":0,
    "gn:timezone":"Africa/Ouagadougou",
    "iso:country":"BF",
    "wof:name":"Banhie",
    "wof:placetype":"locality"
},
  "geometry": {"coordinates":[-2.88333,10.26667],"type":"Point"}
}