{
  "type": "Feature",
  "properties": {
    "gn:admin1_code":"13",
    "gn:asciiname":"Baboura",
    "gn:country_code":"BF",
    "gn:dem":362,
    "gn:feature_class":"P",
    "gn:feature_code":"PPL",
    "gn:name":"Baboura",
    "gn:population":0,
    "gn:timezone":"Africa/Ouagadougou",
    "iso:country":"BF",
    "wof:name":"Baboura",
    "wof:placetype":"locality"
},
  "geometry": {"coordinates":[-3.85,10.06667],"type":"Point"}
}