{
  "type": "Feature",
  "properties": {
    "gn:admin1_code":"12",
    "gn:admin2_code":"71",
    "gn:asciiname":"Missikilo",
    "gn:country_code":"BF",
    "gn:dem":289,
    "gn:feature_class":"P",
    "gn:feature_code":"PPL",
    "gn:name":"Missikilo",
    "gn:population":0,
    "gn:timezone":"Africa/Ouagadougou",
    "iso:country":"BF",
    "wof:name":"Missikilo",
    "wof:placetype":"locality"
},
  "geometry": {"coordinates":[-0.07332,13.61443],"type":"Point"}
}