{
  "type": "Feature",
  "properties": {
    "gn:admin1_code":"02",
    "gn:asciiname":"Bini",
    "gn:country_code":"BF",
    "gn:dem":348,
    "gn:feature_class":"P",
    "gn:feature_code":"PPL",
    "gn:name":"Bini",
    "gn:population":0,
    "gn:timezone":"Africa/Ouagadougou",
    "iso:country":"BF",
    "name:fra_x_preferred":[
        "Bini"
    ],
    "wof:name":"Bini",
    "wof:placetype":"locality"
},
  "geometry": {"coordinates":[-3.73333,10.55],"type":"Point"}
}