{
  "type": "Feature",
  "properties": {
    "gn:admin1_code":"06",
    "gn:asciiname":"Pina",
    "gn:country_code":"BF",
    "gn:dem":257,
    "gn:feature_class":"P",
    "gn:feature_code":"PPL",
    "gn:name":"Pina",
    "gn:population":0,
    "gn:timezone":"Africa/Ouagadougou",
    "iso:country":"BF",
    "name:arg_x_preferred":[
        "Pina"
    ],
    "name:bre_x_preferred":[
        "Pina"
    ],
    "name:cat_x_preferred":[
        "Pina"
    ],
    "name:ceb_x_preferred":[
        "Pina"
    ],
    "name:ces_x_preferred":[
        "Pina"
    ],
    "name:deu_x_preferred":[
        "Pina"
    ],
    "name:fas_x_preferred":[
        "\u067e\u06cc\u0646\u0627"
    ],
    "name:fra_x_preferred":[
        "Pina"
    ],
    "name:hun_x_preferred":[
        "Pina"
    ],
    "name:pol_x_preferred":[
        "Pina"
    ],
    "name:por_x_preferred":[
        "Pina"
    ],
    "name:spa_x_preferred":[
        "Pina"
    ],
    "name:swe_x_preferred":[
        "Pina"
    ],
    "wof:name":"Pina",
    "wof:placetype":"locality"
},
  "geometry": {"coordinates":[-2.63333,11.15],"type":"Point"}
}