{
  "type": "Feature",
  "properties": {
    "gn:admin1_code":"06",
    "gn:asciiname":"Pina",
    "gn:country_code":"BF",
    "gn:dem":257,
    "gn:feature_class":"P",
    "gn:feature_code":"PPL",
    "gn:name":"Pina",
    "gn:population":0,
    "gn:timezone":"Africa/Ouagadougou",
    "iso:country":"BF",
    "wof:name":"Pina",
    "wof:placetype":"locality"
},
  "geometry": {"coordinates":[-2.63333,11.15],"type":"Point"}
}