{
  "type": "Feature",
  "properties": {
    "gn:admin1_code":"05",
    "gn:asciiname":"Loanga",
    "gn:country_code":"BF",
    "gn:dem":291,
    "gn:feature_class":"P",
    "gn:feature_code":"PPL",
    "gn:name":"Loanga",
    "gn:population":0,
    "gn:timezone":"Africa/Ouagadougou",
    "iso:country":"BF",
    "wof:name":"Loanga",
    "wof:placetype":"locality"
},
  "geometry": {"coordinates":[-0.36667,12.56667],"type":"Point"}
}