{
  "type": "Feature",
  "properties": {
    "gn:admin1_code":"04",
    "gn:asciiname":"Loko",
    "gn:country_code":"BF",
    "gn:dem":245,
    "gn:feature_class":"P",
    "gn:feature_code":"PPL",
    "gn:name":"Loko",
    "gn:population":0,
    "gn:timezone":"Africa/Ouagadougou",
    "iso:country":"BF",
    "name:ceb_x_preferred":[
        "Loko"
    ],
    "name:deu_x_preferred":[
        "Loko"
    ],
    "name:fra_x_preferred":[
        "Loko"
    ],
    "name:kaz_x_preferred":[
        "\u041b\u043e\u043a\u043e"
    ],
    "name:por_x_preferred":[
        "Loko"
    ],
    "name:ron_x_preferred":[
        "Loko"
    ],
    "name:rus_x_preferred":[
        "\u041b\u043e\u043a\u043e"
    ],
    "name:swe_x_preferred":[
        "Loko"
    ],
    "wof:name":"Loko",
    "wof:placetype":"locality"
},
  "geometry": {"coordinates":[-0.08333,11.25],"type":"Point"}
}