{
  "type": "Feature",
  "properties": {
    "gn:admin1_code":"13",
    "gn:asciiname":"Galgouli",
    "gn:country_code":"BF",
    "gn:dem":335,
    "gn:feature_class":"P",
    "gn:feature_code":"PPL",
    "gn:name":"Galgouli",
    "gn:population":0,
    "gn:timezone":"Africa/Ouagadougou",
    "iso:country":"BF",
    "name:und_x_variant":[
        "Gagouli",
        "Gaguli",
        "Galgouli"
    ],
    "wof:name":"Galgouli",
    "wof:placetype":"locality"
},
  "geometry": {"coordinates":[-3.45,9.96667],"type":"Point"}
}