{
  "type": "Feature",
  "properties": {
    "gn:admin1_code":"08",
    "gn:asciiname":"Kondouagou",
    "gn:country_code":"BF",
    "gn:dem":330,
    "gn:feature_class":"P",
    "gn:feature_code":"PPL",
    "gn:name":"Kondouagou",
    "gn:population":0,
    "gn:timezone":"Africa/Ouagadougou",
    "iso:country":"BF",
    "wof:name":"Kondouagou",
    "wof:placetype":"locality"
},
  "geometry": {"coordinates":[0.26667,12.23333],"type":"Point"}
}