{
  "type": "Feature",
  "properties": {
    "gn:admin1_code":"07",
    "gn:admin2_code":"44",
    "gn:asciiname":"Bere",
    "gn:country_code":"BF",
    "gn:dem":291,
    "gn:feature_class":"P",
    "gn:feature_code":"PPL",
    "gn:name":"B\u00e9r\u00e9",
    "gn:population":0,
    "gn:timezone":"Africa/Ouagadougou",
    "iso:country":"BF",
    "name:und_x_variant":[
        "B\u00e9r\u00e9"
    ],
    "wof:name":"Bere",
    "wof:placetype":"locality"
},
  "geometry": {"coordinates":[-1.15,11.83333],"type":"Point"}
}