{
  "type": "Feature",
  "properties": {
    "gn:admin1_code":"08",
    "gn:admin2_code":"42",
    "gn:asciiname":"Tansarga",
    "gn:country_code":"BF",
    "gn:dem":297,
    "gn:feature_class":"P",
    "gn:feature_code":"PPL",
    "gn:name":"Tansarga",
    "gn:population":0,
    "gn:timezone":"Africa/Ouagadougou",
    "iso:country":"BF",
    "name:deu_x_preferred":[
        "Tansarga"
    ],
    "name:fra_x_preferred":[
        "Tansarga"
    ],
    "name:ita_x_preferred":[
        "Tansarga"
    ],
    "name:spa_x_preferred":[
        "Tansarga"
    ],
    "name:vie_x_preferred":[
        "Tansarga"
    ],
    "wof:name":"Tansarga",
    "wof:placetype":"locality"
},
  "geometry": {"coordinates":[1.86694,11.87528],"type":"Point"}
}