{
  "type": "Feature",
  "properties": {
    "gn:admin1_code":"07",
    "gn:asciiname":"Naialague",
    "gn:country_code":"BF",
    "gn:dem":305,
    "gn:feature_class":"P",
    "gn:feature_code":"PPL",
    "gn:name":"Na\u00efalagu\u00e9",
    "gn:population":0,
    "gn:timezone":"Africa/Ouagadougou",
    "iso:country":"BF",
    "wof:name":"Naialague",
    "wof:placetype":"locality"
},
  "geometry": {"coordinates":[-1.23333,11.93333],"type":"Point"}
}