{
  "type": "Feature",
  "properties": {
    "gn:admin1_code":"05",
    "gn:admin2_code":"70",
    "gn:asciiname":"Rounougou",
    "gn:country_code":"BF",
    "gn:dem":290,
    "gn:feature_class":"P",
    "gn:feature_code":"PPL",
    "gn:name":"Rounougou",
    "gn:population":0,
    "gn:timezone":"Africa/Ouagadougou",
    "iso:country":"BF",
    "wof:name":"Rounougou",
    "wof:placetype":"locality"
},
  "geometry": {"coordinates":[-0.77778,13.31175],"type":"Point"}
}