{
  "type": "Feature",
  "properties": {
    "gn:admin1_code":"00",
    "gn:asciiname":"Natougou",
    "gn:country_code":"BF",
    "gn:dem":280,
    "gn:feature_class":"P",
    "gn:feature_code":"PPL",
    "gn:name":"Natougou",
    "gn:population":0,
    "gn:timezone":"Africa/Ouagadougou",
    "iso:country":"BF",
    "wof:name":"Natougou",
    "wof:placetype":"locality"
},
  "geometry": {"coordinates":[1.68333,12.61667],"type":"Point"}
}