{
  "type": "Feature",
  "properties": {
    "gn:admin1_code":"01",
    "gn:admin2_code":"58",
    "gn:asciiname":"Diallo",
    "gn:country_code":"BF",
    "gn:dem":285,
    "gn:feature_class":"P",
    "gn:feature_code":"PPL",
    "gn:name":"Diallo",
    "gn:population":0,
    "gn:timezone":"Africa/Ouagadougou",
    "iso:country":"BF",
    "wof:name":"Diallo",
    "wof:placetype":"locality"
},
  "geometry": {"coordinates":[-3.9298,13.1753],"type":"Point"}
}