{
  "type": "Feature",
  "properties": {
    "gn:admin1_code":"07",
    "gn:asciiname":"Daiassemnore",
    "gn:country_code":"BF",
    "gn:dem":300,
    "gn:feature_class":"P",
    "gn:feature_code":"PPL",
    "gn:name":"Da\u00efassemnor\u00e9",
    "gn:population":0,
    "gn:timezone":"Africa/Ouagadougou",
    "iso:country":"BF",
    "wof:name":"Daiassemnore",
    "wof:placetype":"locality"
},
  "geometry": {"coordinates":[-1.35,11.76667],"type":"Point"}
}