{
  "type": "Feature",
  "properties": {
    "gn:admin1_code":"01",
    "gn:asciiname":"Poundou",
    "gn:country_code":"BF",
    "gn:dem":303,
    "gn:feature_class":"P",
    "gn:feature_code":"PPL",
    "gn:name":"Poundou",
    "gn:population":0,
    "gn:timezone":"Africa/Ouagadougou",
    "iso:country":"BF",
    "name:und_x_variant":[
        "Pondou",
        "Poundou"
    ],
    "wof:name":"Poundou",
    "wof:placetype":"locality"
},
  "geometry": {"coordinates":[-3.58235,12.19013],"type":"Point"}
}