{
  "type": "Feature",
  "properties": {
    "gn:admin1_code":"07",
    "gn:asciiname":"Badabiessan",
    "gn:country_code":"BF",
    "gn:dem":258,
    "gn:feature_class":"P",
    "gn:feature_code":"PPL",
    "gn:name":"Badabiessan",
    "gn:population":0,
    "gn:timezone":"Africa/Ouagadougou",
    "iso:country":"BF",
    "wof:name":"Badabiessan",
    "wof:placetype":"locality"
},
  "geometry": {"coordinates":[-0.93333,11.05],"type":"Point"}
}