{
  "type": "Feature",
  "properties": {
    "gn:admin1_code":"03",
    "gn:admin2_code":"53",
    "gn:asciiname":"Koubri",
    "gn:country_code":"BF",
    "gn:dem":289,
    "gn:feature_class":"P",
    "gn:feature_code":"PPL",
    "gn:name":"Koubri",
    "gn:population":0,
    "gn:timezone":"Africa/Ouagadougou",
    "iso:country":"BF",
    "name:und_x_variant":[
        "Koubry",
        "Koubri"
    ],
    "wof:name":"Koubri",
    "wof:placetype":"locality"
},
  "geometry": {"coordinates":[-1.38694,12.16361],"type":"Point"}
}