{
  "type": "Feature",
  "properties": {
    "gn:admin1_code":"11",
    "gn:asciiname":"Goantenga",
    "gn:country_code":"BF",
    "gn:dem":300,
    "gn:feature_class":"P",
    "gn:feature_code":"PPL",
    "gn:name":"Goantenga",
    "gn:population":0,
    "gn:timezone":"Africa/Ouagadougou",
    "iso:country":"BF",
    "wof:name":"Goantenga",
    "wof:placetype":"locality"
},
  "geometry": {"coordinates":[-0.61667,12.18333],"type":"Point"}
}