{
  "type": "Feature",
  "properties": {
    "gn:admin1_code":"13",
    "gn:asciiname":"Kpera",
    "gn:country_code":"BF",
    "gn:dem":355,
    "gn:feature_class":"P",
    "gn:feature_code":"PPL",
    "gn:name":"Kp\u00e9ra",
    "gn:population":0,
    "gn:timezone":"Africa/Ouagadougou",
    "iso:country":"BF",
    "name:und_x_variant":[
        "Pa\u00efra",
        "Kp\u00e9ra"
    ],
    "wof:name":"Kpera",
    "wof:placetype":"locality"
},
  "geometry": {"coordinates":[-3.45,10.45],"type":"Point"}
}