{
  "type": "Feature",
  "properties": {
    "gn:admin1_code":"08",
    "gn:admin2_code":"42",
    "gn:asciiname":"Bouandyaga",
    "gn:country_code":"BF",
    "gn:dem":243,
    "gn:feature_class":"P",
    "gn:feature_code":"PPL",
    "gn:name":"Bouandyaga",
    "gn:population":0,
    "gn:timezone":"Africa/Ouagadougou",
    "iso:country":"BF",
    "wof:name":"Bouandyaga",
    "wof:placetype":"locality"
},
  "geometry": {"coordinates":[1.56778,12.28253],"type":"Point"}
}