{
  "type": "Feature",
  "properties": {
    "gn:admin1_code":"05",
    "gn:admin2_code":"70",
    "gn:asciiname":"Zoungo",
    "gn:country_code":"BF",
    "gn:dem":315,
    "gn:feature_class":"P",
    "gn:feature_code":"PPL",
    "gn:name":"Zoungo",
    "gn:population":0,
    "gn:timezone":"Africa/Ouagadougou",
    "iso:country":"BF",
    "wof:name":"Zoungo",
    "wof:placetype":"locality"
},
  "geometry": {"coordinates":[-1.14636,13.28675],"type":"Point"}
}