{
  "type": "Feature",
  "properties": {
    "gn:admin1_code":"x21",
    "gn:asciiname":"Coalla",
    "gn:country_code":"BF",
    "gn:dem":260,
    "gn:feature_class":"P",
    "gn:feature_code":"PPL",
    "gn:name":"Coalla",
    "gn:population":0,
    "gn:timezone":"Africa/Ouagadougou",
    "iso:country":"BF",
    "name:fra_x_preferred":[
        "Coalla"
    ],
    "wof:name":"Coalla",
    "wof:placetype":"locality"
},
  "geometry": {"coordinates":[-0.13694,13.41056],"type":"Point"}
}