{
  "type": "Feature",
  "properties": {
    "gn:admin1_code":"02",
    "gn:asciiname":"Boussara",
    "gn:country_code":"BF",
    "gn:dem":283,
    "gn:feature_class":"P",
    "gn:feature_code":"PPL",
    "gn:name":"Boussara",
    "gn:population":0,
    "gn:timezone":"Africa/Ouagadougou",
    "iso:country":"BF",
    "wof:name":"Boussara",
    "wof:placetype":"locality"
},
  "geometry": {"coordinates":[-4.56667,10.51667],"type":"Point"}
}