{
  "type": "Feature",
  "properties": {
    "gn:admin1_code":"08",
    "gn:admin2_code":"50",
    "gn:asciiname":"Kikideni",
    "gn:country_code":"BF",
    "gn:dem":308,
    "gn:feature_class":"P",
    "gn:feature_code":"PPL",
    "gn:name":"Kikid\u00e9ni",
    "gn:population":0,
    "gn:timezone":"Africa/Ouagadougou",
    "iso:country":"BF",
    "name:und_x_variant":[
        "Penti\u00e9ri",
        "Kikid\u00e9ni"
    ],
    "wof:name":"Kikideni",
    "wof:placetype":"locality"
},
  "geometry": {"coordinates":[0.39833,11.93667],"type":"Point"}
}