{
  "type": "Feature",
  "properties": {
    "gn:admin1_code":"03",
    "gn:admin2_code":"53",
    "gn:asciiname":"Polesgo",
    "gn:country_code":"BF",
    "gn:dem":305,
    "gn:feature_class":"P",
    "gn:feature_code":"PPL",
    "gn:name":"Polesgo",
    "gn:population":0,
    "gn:timezone":"Africa/Ouagadougou",
    "iso:country":"BF",
    "name:und_x_variant":[
        "Pal\u00e8sgo",
        "Polesgo"
    ],
    "wof:name":"Polesgo",
    "wof:placetype":"locality"
},
  "geometry": {"coordinates":[-1.49639,12.4375],"type":"Point"}
}