{
  "type": "Feature",
  "properties": {
    "gn:admin1_code":"10",
    "gn:admin2_code":"76",
    "gn:asciiname":"Kougousoulo",
    "gn:country_code":"BF",
    "gn:dem":343,
    "gn:feature_class":"P",
    "gn:feature_code":"PPL",
    "gn:name":"Kougousoul\u00f4",
    "gn:population":0,
    "gn:timezone":"Africa/Ouagadougou",
    "iso:country":"BF",
    "wof:name":"Kougousoulo",
    "wof:placetype":"locality"
},
  "geometry": {"coordinates":[-1.91997,13.5984],"type":"Point"}
}