{
  "type": "Feature",
  "properties": {
    "gn:admin1_code":"08",
    "gn:admin2_code":"42",
    "gn:asciiname":"Tantiri",
    "gn:country_code":"BF",
    "gn:dem":270,
    "gn:feature_class":"P",
    "gn:feature_code":"PPL",
    "gn:name":"Tantiri",
    "gn:population":0,
    "gn:timezone":"Africa/Ouagadougou",
    "iso:country":"BF",
    "name:und_x_variant":[
        "Tantili",
        "Tantiri"
    ],
    "wof:name":"Tantiri",
    "wof:placetype":"locality"
},
  "geometry": {"coordinates":[1.38717,12.59869],"type":"Point"}
}