{
  "type": "Feature",
  "properties": {
    "gn:admin1_code":"08",
    "gn:asciiname":"Goueli",
    "gn:country_code":"BF",
    "gn:dem":274,
    "gn:feature_class":"P",
    "gn:feature_code":"PPL",
    "gn:name":"Gou\u00e9li",
    "gn:population":0,
    "gn:timezone":"Africa/Ouagadougou",
    "iso:country":"BF",
    "wof:name":"Goueli",
    "wof:placetype":"locality"
},
  "geometry": {"coordinates":[0.01667,12.73333],"type":"Point"}
}