{
  "type": "Feature",
  "properties": {
    "gn:admin1_code":"03",
    "gn:admin2_code":"53",
    "gn:asciiname":"Dassasgo",
    "gn:country_code":"BF",
    "gn:dem":305,
    "gn:feature_class":"P",
    "gn:feature_code":"PPL",
    "gn:name":"Dassasgo",
    "gn:population":0,
    "gn:timezone":"Africa/Ouagadougou",
    "iso:country":"BF",
    "wof:name":"Dassasgo",
    "wof:placetype":"locality"
},
  "geometry": {"coordinates":[-1.63806,12.39631],"type":"Point"}
}