{
  "type": "Feature",
  "properties": {
    "gn:admin1_code":"01",
    "gn:asciiname":"Ziasso",
    "gn:country_code":"BF",
    "gn:dem":290,
    "gn:feature_class":"P",
    "gn:feature_code":"PPL",
    "gn:name":"Ziasso",
    "gn:population":0,
    "gn:timezone":"Africa/Ouagadougou",
    "iso:country":"BF",
    "wof:name":"Ziasso",
    "wof:placetype":"locality"
},
  "geometry": {"coordinates":[-3.33333,12.15],"type":"Point"}
}