{
  "type": "Feature",
  "properties": {
    "gn:admin1_code":"12",
    "gn:admin2_code":"33",
    "gn:asciiname":"Oudyoumoudi",
    "gn:country_code":"BF",
    "gn:dem":280,
    "gn:feature_class":"P",
    "gn:feature_code":"PPL",
    "gn:name":"Oudyoumoudi",
    "gn:population":0,
    "gn:timezone":"Africa/Ouagadougou",
    "iso:country":"BF",
    "name:und_x_variant":[
        "Boulounidi",
        "Boulougnidi",
        "Bulugnidi",
        "Oudyoumoudi"
    ],
    "wof:name":"Oudyoumoudi",
    "wof:placetype":"locality"
},
  "geometry": {"coordinates":[-0.43163,14.07427],"type":"Point"}
}