{
  "type": "Feature",
  "properties": {
    "gn:admin1_code":"10",
    "gn:admin2_code":"76",
    "gn:asciiname":"Sologomnore",
    "gn:country_code":"BF",
    "gn:dem":331,
    "gn:feature_class":"P",
    "gn:feature_code":"PPL",
    "gn:name":"Sologomnor\u00e9",
    "gn:population":0,
    "gn:timezone":"Africa/Ouagadougou",
    "iso:country":"BF",
    "wof:name":"Sologomnore",
    "wof:placetype":"locality"
},
  "geometry": {"coordinates":[-2.33172,13.27002],"type":"Point"}
}