{
  "type": "Feature",
  "properties": {
    "gn:admin1_code":"03",
    "gn:admin2_code":"53",
    "gn:asciiname":"Nagren",
    "gn:country_code":"BF",
    "gn:dem":294,
    "gn:feature_class":"P",
    "gn:feature_code":"PPL",
    "gn:name":"Nagren",
    "gn:population":0,
    "gn:timezone":"Africa/Ouagadougou",
    "iso:country":"BF",
    "wof:name":"Nagren",
    "wof:placetype":"locality"
},
  "geometry": {"coordinates":[-1.36472,12.33139],"type":"Point"}
}