{
  "type": "Feature",
  "properties": {
    "gn:admin1_code":"x22",
    "gn:asciiname":"Tengsoba",
    "gn:country_code":"BF",
    "gn:dem":210,
    "gn:feature_class":"P",
    "gn:feature_code":"PPL",
    "gn:name":"Tengsoba",
    "gn:population":0,
    "gn:timezone":"Africa/Ouagadougou",
    "iso:country":"BF",
    "wof:name":"Tengsoba",
    "wof:placetype":"locality"
},
  "geometry": {"coordinates":[0.43321,11.45528],"type":"Point"}
}