{
  "type": "Feature",
  "properties": {
    "gn:admin1_code":"11",
    "gn:asciiname":"Basbyedo",
    "gn:country_code":"BF",
    "gn:dem":287,
    "gn:feature_class":"P",
    "gn:feature_code":"PPL",
    "gn:name":"Basby\u00e9do",
    "gn:population":0,
    "gn:timezone":"Africa/Ouagadougou",
    "iso:country":"BF",
    "name:und_x_variant":[
        "Basb\u00e9do",
        "Basby\u00e9do"
    ],
    "wof:name":"Basbyedo",
    "wof:placetype":"locality"
},
  "geometry": {"coordinates":[-1.15,12.61667],"type":"Point"}
}