{
  "type": "Feature",
  "properties": {
    "gn:admin1_code":"06",
    "gn:asciiname":"Tonton",
    "gn:country_code":"BF",
    "gn:dem":292,
    "gn:feature_class":"P",
    "gn:feature_code":"PPL",
    "gn:name":"Tonton",
    "gn:population":0,
    "gn:timezone":"Africa/Ouagadougou",
    "iso:country":"BF",
    "name:ceb_x_preferred":[
        "Tonton"
    ],
    "name:fra_x_preferred":[
        "Tonton"
    ],
    "name:swe_x_preferred":[
        "Tonton"
    ],
    "wof:name":"Tonton",
    "wof:placetype":"locality"
},
  "geometry": {"coordinates":[-2.65,12.58333],"type":"Point"}
}