{
  "type": "Feature",
  "properties": {
    "gn:admin1_code":"10",
    "gn:admin2_code":"76",
    "gn:asciiname":"Koudma",
    "gn:country_code":"BF",
    "gn:dem":325,
    "gn:feature_class":"P",
    "gn:feature_code":"PPL",
    "gn:name":"Koudma",
    "gn:population":0,
    "gn:timezone":"Africa/Ouagadougou",
    "iso:country":"BF",
    "wof:name":"Koudma",
    "wof:placetype":"locality"
},
  "geometry": {"coordinates":[-2.10727,13.35451],"type":"Point"}
}