{
  "type": "Feature",
  "properties": {
    "gn:admin1_code":"08",
    "gn:admin2_code":"42",
    "gn:asciiname":"Moumougou",
    "gn:country_code":"BF",
    "gn:dem":261,
    "gn:feature_class":"P",
    "gn:feature_code":"PPL",
    "gn:name":"Moumougou",
    "gn:population":0,
    "gn:timezone":"Africa/Ouagadougou",
    "iso:country":"BF",
    "wof:name":"Moumougou",
    "wof:placetype":"locality"
},
  "geometry": {"coordinates":[1.30293,12.33182],"type":"Point"}
}