{
  "type": "Feature",
  "properties": {
    "gn:admin1_code":"12",
    "gn:admin2_code":"33",
    "gn:asciiname":"Touka Ouropila",
    "gn:country_code":"BF",
    "gn:dem":280,
    "gn:feature_class":"P",
    "gn:feature_code":"PPL",
    "gn:name":"Touka Ouropila",
    "gn:population":0,
    "gn:timezone":"Africa/Ouagadougou",
    "iso:country":"BF",
    "wof:name":"Touka Ouropila",
    "wof:placetype":"locality"
},
  "geometry": {"coordinates":[-0.24908,14.19879],"type":"Point"}
}