{
  "type": "Feature",
  "properties": {
    "gn:admin1_code":"09",
    "gn:admin2_code":"51",
    "gn:asciiname":"Bare",
    "gn:country_code":"BF",
    "gn:dem":321,
    "gn:feature_class":"P",
    "gn:feature_code":"PPL",
    "gn:name":"Bar\u00e9",
    "gn:population":0,
    "gn:timezone":"Africa/Ouagadougou",
    "iso:country":"BF",
    "name:bos_x_preferred":[
        "Bare"
    ],
    "name:ceb_x_preferred":[
        "Bare"
    ],
    "name:deu_x_preferred":[
        "Bare"
    ],
    "name:eus_x_preferred":[
        "Bare"
    ],
    "name:fra_x_preferred":[
        "Bare"
    ],
    "name:hrv_x_preferred":[
        "Bare"
    ],
    "name:hun_x_preferred":[
        "Bare"
    ],
    "name:ita_x_preferred":[
        "Bare"
    ],
    "name:nld_x_preferred":[
        "Bare"
    ],
    "name:por_x_preferred":[
        "Bare"
    ],
    "name:slv_x_preferred":[
        "Bare"
    ],
    "name:swe_x_preferred":[
        "Bare"
    ],
    "name:und_x_variant":[
        "Bari",
        "Bar\u00e9"
    ],
    "wof:name":"Bare",
    "wof:placetype":"locality"
},
  "geometry": {"coordinates":[-4.10735,11.08091],"type":"Point"}
}