{
  "type": "Feature",
  "properties": {
    "gn:admin1_code":"09",
    "gn:admin2_code":"51",
    "gn:asciiname":"Diefourma",
    "gn:country_code":"BF",
    "gn:dem":311,
    "gn:feature_class":"P",
    "gn:feature_code":"PPL",
    "gn:name":"Diefourma",
    "gn:population":0,
    "gn:timezone":"Africa/Ouagadougou",
    "iso:country":"BF",
    "name:und_x_variant":[
        "Di\u00e9bourma",
        "Di\u00e9fourouma",
        "Diefourma"
    ],
    "wof:name":"Diefourma",
    "wof:placetype":"locality"
},
  "geometry": {"coordinates":[-4.627,11.39903],"type":"Point"}
}