{
  "type": "Feature",
  "properties": {
    "gn:admin1_code":"06",
    "gn:asciiname":"Koulgoren",
    "gn:country_code":"BF",
    "gn:dem":314,
    "gn:feature_class":"P",
    "gn:feature_code":"PPL",
    "gn:name":"Koulgoren",
    "gn:population":0,
    "gn:timezone":"Africa/Ouagadougou",
    "iso:country":"BF",
    "wof:name":"Koulgoren",
    "wof:placetype":"locality"
},
  "geometry": {"coordinates":[-2.01667,12.28333],"type":"Point"}
}