{
  "type": "Feature",
  "properties": {
    "gn:admin1_code":"08",
    "gn:admin2_code":"42",
    "gn:asciiname":"Namounou",
    "gn:cc2":"BF",
    "gn:country_code":"BF",
    "gn:dem":269,
    "gn:feature_class":"P",
    "gn:feature_code":"PPL",
    "gn:name":"Namounou",
    "gn:population":0,
    "gn:timezone":"Africa/Ouagadougou",
    "iso:country":"BF",
    "name:deu_x_preferred":[
        "Namounou"
    ],
    "name:fra_x_preferred":[
        "Namounou"
    ],
    "name:ita_x_preferred":[
        "Namounou"
    ],
    "name:spa_x_preferred":[
        "Namounou"
    ],
    "name:und_x_variant":[
        "Niamounou",
        "Namounou"
    ],
    "name:vie_x_preferred":[
        "Namounou"
    ],
    "wof:name":"Namounou",
    "wof:placetype":"locality"
},
  "geometry": {"coordinates":[1.69917,11.86056],"type":"Point"}
}