{
  "type": "Feature",
  "properties": {
    "gn:admin1_code":"01",
    "gn:admin2_code":"73",
    "gn:asciiname":"Toare",
    "gn:country_code":"BF",
    "gn:dem":295,
    "gn:feature_class":"P",
    "gn:feature_code":"PPL",
    "gn:name":"Toar\u00e9",
    "gn:population":0,
    "gn:timezone":"Africa/Ouagadougou",
    "iso:country":"BF",
    "name:und_x_variant":[
        "To\u00efr\u00e9",
        "To\u00e9r\u00e9",
        "Toar\u00e9"
    ],
    "wof:name":"Toare",
    "wof:placetype":"locality"
},
  "geometry": {"coordinates":[-2.75708,13.05692],"type":"Point"}
}