{
  "type": "Feature",
  "properties": {
    "gn:admin1_code":"10",
    "gn:asciiname":"Nyonnyogo",
    "gn:country_code":"BF",
    "gn:dem":293,
    "gn:feature_class":"P",
    "gn:feature_code":"PPL",
    "gn:name":"Nyonnyogo",
    "gn:population":0,
    "gn:timezone":"Africa/Ouagadougou",
    "iso:country":"BF",
    "wof:name":"Nyonnyogo",
    "wof:placetype":"locality"
},
  "geometry": {"coordinates":[-2.61667,12.88333],"type":"Point"}
}