{
  "type": "Feature",
  "properties": {
    "gn:admin1_code":"13",
    "gn:asciiname":"Defitara",
    "gn:country_code":"BF",
    "gn:dem":379,
    "gn:feature_class":"P",
    "gn:feature_code":"PPL",
    "gn:name":"D\u00e9fitara",
    "gn:population":0,
    "gn:timezone":"Africa/Ouagadougou",
    "iso:country":"BF",
    "wof:name":"Defitara",
    "wof:placetype":"locality"
},
  "geometry": {"coordinates":[-3.43333,10.06667],"type":"Point"}
}