{
  "type": "Feature",
  "properties": {
    "gn:admin1_code":"05",
    "gn:admin2_code":"64",
    "gn:asciiname":"Logobili",
    "gn:country_code":"BF",
    "gn:dem":303,
    "gn:feature_class":"P",
    "gn:feature_code":"PPL",
    "gn:name":"Logobili",
    "gn:population":0,
    "gn:timezone":"Africa/Ouagadougou",
    "iso:country":"BF",
    "name:und_x_variant":[
        "L\u00e9nobila",
        "Lorobili",
        "Logobili"
    ],
    "wof:name":"Logobili",
    "wof:placetype":"locality"
},
  "geometry": {"coordinates":[-0.52856,13.01434],"type":"Point"}
}