{
  "type": "Feature",
  "properties": {
    "iso:country":"BF",
    "name:bul_x_preferred":[
        "\u0421\u0438\u043d\u0434\u043e\u0443"
    ],
    "name:ceb_x_preferred":[
        "Sindou"
    ],
    "name:deu_x_preferred":[
        "Sindou"
    ],
    "name:ell_x_preferred":[
        "\u03a3\u03b9\u03bd\u03c4\u03bf\u03cd"
    ],
    "name:eng_x_preferred":[
        "Sindou"
    ],
    "name:fra_x_preferred":[
        "Sindou"
    ],
    "name:ita_x_preferred":[
        "Sindou"
    ],
    "name:jpn_x_preferred":[
        "\u30b7\u30f3\u30c9\u30a5"
    ],
    "name:nld_x_preferred":[
        "Sindou"
    ],
    "name:nob_x_preferred":[
        "Sindou"
    ],
    "name:pol_x_preferred":[
        "Sindou"
    ],
    "name:por_x_preferred":[
        "Sindou"
    ],
    "name:ron_x_preferred":[
        "Sindou"
    ],
    "name:rus_x_preferred":[
        "\u0421\u0438\u043d\u0434\u0443"
    ],
    "name:swe_x_preferred":[
        "Sindou"
    ],
    "name:ukr_x_preferred":[
        "\u0421\u0438\u043d\u0434\u0443"
    ],
    "name:unk_x_variant":[
        "Sindu"
    ],
    "name:urd_x_preferred":[
        "\u0633\u0646\u062f\u0624"
    ],
    "name:war_x_preferred":[
        "Sindou"
    ],
    "qs:gn_country":"BF",
    "qs:gn_fcode":"PPLA2",
    "qs:gn_pop":3917,
    "qs:name":"Sindou",
    "qs:name_adm0":"Burkina Faso",
    "qs:name_adm1":"L\u00e9raba",
    "qs:photos":50,
    "qs:photos_1k":10,
    "qs:photos_9k":1,
    "qs:photos_9r":2,
    "qs:photos_all":50,
    "qs:photos_sr":2,
    "qs:placetype":"Town",
    "qs:pop_sr":"4",
    "qs:woe_adm0":23424978,
    "wd:wordcount":249,
    "wof:name":"Sindou",
    "wof:placetype":"locality",
    "wof:population":3917
},
  "geometry": {"coordinates":[-5.16667,10.66667],"type":"Point"}
}