{
  "type": "Feature",
  "properties": {
    "gn:admin1_code":"01",
    "gn:admin2_code":"58",
    "gn:asciiname":"Nabasso",
    "gn:country_code":"BF",
    "gn:dem":298,
    "gn:feature_class":"P",
    "gn:feature_code":"PPL",
    "gn:name":"Nabasso",
    "gn:population":0,
    "gn:timezone":"Africa/Ouagadougou",
    "iso:country":"BF",
    "name:und_x_variant":[
        "Nibasso",
        "Nabasso"
    ],
    "wof:name":"Nabasso",
    "wof:placetype":"locality"
},
  "geometry": {"coordinates":[-3.9573,13.2261],"type":"Point"}
}