{
  "type": "Feature",
  "properties": {
    "gn:admin1_code":"10",
    "gn:admin2_code":"76",
    "gn:asciiname":"Didiel",
    "gn:country_code":"BF",
    "gn:dem":301,
    "gn:feature_class":"P",
    "gn:feature_code":"PPL",
    "gn:name":"Didi\u00e8l",
    "gn:population":0,
    "gn:timezone":"Africa/Ouagadougou",
    "iso:country":"BF",
    "wof:name":"Didiel",
    "wof:placetype":"locality"
},
  "geometry": {"coordinates":[-2.32769,14.11529],"type":"Point"}
}