{
  "type": "Feature",
  "properties": {
    "gn:admin1_code":"05",
    "gn:admin2_code":"15",
    "gn:asciiname":"Sasse",
    "gn:country_code":"BF",
    "gn:dem":340,
    "gn:feature_class":"P",
    "gn:feature_code":"PPL",
    "gn:name":"Sass\u00e9",
    "gn:population":0,
    "gn:timezone":"Africa/Ouagadougou",
    "iso:country":"BF",
    "name:ceb_x_preferred":[
        "Sasse"
    ],
    "name:deu_x_preferred":[
        "Sasse"
    ],
    "name:swe_x_preferred":[
        "Sasse"
    ],
    "wof:name":"Sasse",
    "wof:placetype":"locality"
},
  "geometry": {"coordinates":[-1.85005,13.44432],"type":"Point"}
}