{
  "type": "Feature",
  "properties": {
    "gn:admin1_code":"06",
    "gn:asciiname":"Zado",
    "gn:country_code":"BF",
    "gn:dem":287,
    "gn:feature_class":"P",
    "gn:feature_code":"PPL",
    "gn:name":"Zado",
    "gn:population":0,
    "gn:timezone":"Africa/Ouagadougou",
    "iso:country":"BF",
    "wof:name":"Zado",
    "wof:placetype":"locality"
},
  "geometry": {"coordinates":[-2.66667,12.13333],"type":"Point"}
}