{
  "type": "Feature",
  "properties": {
    "gn:admin1_code":"05",
    "gn:admin2_code":"15",
    "gn:asciiname":"Sanoui",
    "gn:country_code":"BF",
    "gn:dem":312,
    "gn:feature_class":"P",
    "gn:feature_code":"PPL",
    "gn:name":"Sanoui",
    "gn:population":0,
    "gn:timezone":"Africa/Ouagadougou",
    "iso:country":"BF",
    "name:azb_x_preferred":[
        "\u0633\u0627\u0646\u0647\u0648\u0626\u06cc"
    ],
    "name:ceb_x_preferred":[
        "Sanoui"
    ],
    "name:fas_x_preferred":[
        "\u0633\u0627\u0646\u0647\u0648\u0626\u06cc"
    ],
    "name:fra_x_preferred":[
        "Sanhoui"
    ],
    "name:swe_x_preferred":[
        "Sanoui"
    ],
    "name:und_x_variant":[
        "Sanhoui",
        "Sanoui"
    ],
    "wof:name":"Sanoui",
    "wof:placetype":"locality"
},
  "geometry": {"coordinates":[-1.39163,13.18367],"type":"Point"}
}