{
  "type": "Feature",
  "properties": {
    "gn:admin1_code":"12",
    "gn:admin2_code":"75",
    "gn:asciiname":"Bandiosi",
    "gn:country_code":"BF",
    "gn:dem":253,
    "gn:feature_class":"P",
    "gn:feature_code":"PPL",
    "gn:name":"Bandiosi",
    "gn:population":0,
    "gn:timezone":"Africa/Ouagadougou",
    "iso:country":"BF",
    "wof:name":"Bandiosi",
    "wof:placetype":"locality"
},
  "geometry": {"coordinates":[0.71186,13.32055],"type":"Point"}
}