{
  "type": "Feature",
  "properties": {
    "gn:admin1_code":"06",
    "gn:asciiname":"Nago",
    "gn:country_code":"BF",
    "gn:dem":318,
    "gn:feature_class":"P",
    "gn:feature_code":"PPL",
    "gn:name":"Nago",
    "gn:population":0,
    "gn:timezone":"Africa/Ouagadougou",
    "iso:country":"BF",
    "name:ara_x_preferred":[
        "\u0646\u0627\u063a\u0648"
    ],
    "name:cat_x_preferred":[
        "Nago"
    ],
    "name:ceb_x_preferred":[
        "Nago Shi"
    ],
    "name:deu_x_preferred":[
        "Nago"
    ],
    "name:fas_x_preferred":[
        "\u0646\u0627\u06af\u0648"
    ],
    "name:fra_x_preferred":[
        "Nago"
    ],
    "name:glg_x_preferred":[
        "Nago"
    ],
    "name:heb_x_preferred":[
        "\u05e0\u05d0\u05d2\u05d5"
    ],
    "name:ita_x_preferred":[
        "Nago"
    ],
    "name:jpn_x_preferred":[
        "\u540d\u8b77\u5e02"
    ],
    "name:kor_x_preferred":[
        "\ub098\uace0\uc2dc"
    ],
    "name:lit_x_preferred":[
        "Nago"
    ],
    "name:mlg_x_preferred":[
        "Nago"
    ],
    "name:mzn_x_preferred":[
        "\u0646\u0627\u06af\u0648"
    ],
    "name:nld_x_preferred":[
        "Nago"
    ],
    "name:pol_x_preferred":[
        "Nago"
    ],
    "name:por_x_preferred":[
        "Nago"
    ],
    "name:ron_x_preferred":[
        "Nago"
    ],
    "name:rus_x_preferred":[
        "\u041d\u0430\u0433\u043e"
    ],
    "name:spa_x_preferred":[
        "Nago"
    ],
    "name:swe_x_preferred":[
        "Nago"
    ],
    "name:tgk_x_preferred":[
        "\u041d\u0430\u0433\u043e"
    ],
    "name:tgl_x_preferred":[
        "Nago"
    ],
    "name:tum_x_preferred":[
        "Nago"
    ],
    "name:tur_x_preferred":[
        "Nago"
    ],
    "name:ukr_x_preferred":[
        "\u041d\u0430\u0491\u043e"
    ],
    "name:vie_x_preferred":[
        "Nago"
    ],
    "name:war_x_preferred":[
        "Nago"
    ],
    "name:zho_x_preferred":[
        "\u540d\u8b77\u5e02"
    ],
    "wof:name":"Nago",
    "wof:placetype":"locality"
},
  "geometry": {"coordinates":[-2.35,11.85],"type":"Point"}
}