{
  "type": "Feature",
  "properties": {
    "gn:admin1_code":"07",
    "gn:admin2_code":"47",
    "gn:asciiname":"Gana",
    "gn:country_code":"BF",
    "gn:dem":323,
    "gn:feature_class":"P",
    "gn:feature_code":"PPL",
    "gn:name":"Gana",
    "gn:population":0,
    "gn:timezone":"Africa/Ouagadougou",
    "iso:country":"BF",
    "name:deu_x_preferred":[
        "Gana"
    ],
    "name:lit_x_preferred":[
        "Gana"
    ],
    "name:pol_x_preferred":[
        "Ganowie"
    ],
    "name:rus_x_preferred":[
        "\u0413\u0430\u043d\u0430"
    ],
    "name:spa_x_preferred":[
        "Gana"
    ],
    "name:swe_x_preferred":[
        "Gana"
    ],
    "name:tam_x_preferred":[
        "\u0b95\u0ba3\u0b99\u0bcd\u0b95\u0bb3\u0bcd"
    ],
    "name:tat_x_preferred":[
        "\u0413\u0430\u043d\u0430\u043b\u0430\u0440"
    ],
    "wof:name":"Gana",
    "wof:placetype":"locality"
},
  "geometry": {"coordinates":[-1.40028,12.05722],"type":"Point"}
}