{
  "type": "Feature",
  "properties": {
    "gn:admin1_code":"07",
    "gn:admin2_code":"47",
    "gn:asciiname":"Gana",
    "gn:country_code":"BF",
    "gn:dem":323,
    "gn:feature_class":"P",
    "gn:feature_code":"PPL",
    "gn:name":"Gana",
    "gn:population":0,
    "gn:timezone":"Africa/Ouagadougou",
    "iso:country":"BF",
    "wof:name":"Gana",
    "wof:placetype":"locality"
},
  "geometry": {"coordinates":[-1.40028,12.05722],"type":"Point"}
}