{
  "type": "Feature",
  "properties": {
    "gn:admin1_code":"11",
    "gn:asciiname":"Ibele",
    "gn:country_code":"BF",
    "gn:dem":308,
    "gn:feature_class":"P",
    "gn:feature_code":"PPL",
    "gn:name":"Ib\u00e9l\u00e9",
    "gn:population":0,
    "gn:timezone":"Africa/Ouagadougou",
    "iso:country":"BF",
    "name:und_x_variant":[
        "Yib\u00e8l\u00e9",
        "Ib\u00e9l\u00e9"
    ],
    "wof:name":"Ibele",
    "wof:placetype":"locality"
},
  "geometry": {"coordinates":[-1.75,12.71667],"type":"Point"}
}