{
  "type": "Feature",
  "properties": {
    "gn:admin1_code":"10",
    "gn:admin2_code":"76",
    "gn:asciiname":"Guibou",
    "gn:country_code":"BF",
    "gn:dem":316,
    "gn:feature_class":"P",
    "gn:feature_code":"PPL",
    "gn:name":"Guibou",
    "gn:population":0,
    "gn:timezone":"Africa/Ouagadougou",
    "iso:country":"BF",
    "wof:name":"Guibou",
    "wof:placetype":"locality"
},
  "geometry": {"coordinates":[-1.98771,13.41502],"type":"Point"}
}