{
  "type": "Feature",
  "properties": {
    "gn:admin1_code":"11",
    "gn:admin2_code":"68",
    "gn:asciiname":"Loumbila",
    "gn:country_code":"BF",
    "gn:dem":298,
    "gn:feature_class":"P",
    "gn:feature_code":"PPL",
    "gn:name":"Loumbila",
    "gn:population":0,
    "gn:timezone":"Africa/Ouagadougou",
    "iso:country":"BF",
    "name:deu_x_preferred":[
        "Loumbila"
    ],
    "name:fra_x_preferred":[
        "Loumbila"
    ],
    "name:ita_x_preferred":[
        "Loumbila"
    ],
    "name:spa_x_preferred":[
        "Loumbila"
    ],
    "name:und_x_variant":[
        "Lambila-Poko",
        "Lumbila",
        "Lombila"
    ],
    "name:vie_x_preferred":[
        "Loumbila"
    ],
    "wof:name":"Loumbila",
    "wof:placetype":"locality"
},
  "geometry": {"coordinates":[-1.37056,12.51917],"type":"Point"}
}