{
  "type": "Feature",
  "properties": {
    "gn:admin1_code":"12",
    "gn:admin2_code":"33",
    "gn:asciiname":"Laesseno",
    "gn:country_code":"BF",
    "gn:dem":296,
    "gn:feature_class":"P",
    "gn:feature_code":"PPL",
    "gn:name":"La\u00e9ss\u00e9no",
    "gn:population":0,
    "gn:timezone":"Africa/Ouagadougou",
    "iso:country":"BF",
    "wof:name":"Laesseno",
    "wof:placetype":"locality"
},
  "geometry": {"coordinates":[-0.4613,14.3827],"type":"Point"}
}