{
  "type": "Feature",
  "properties": {
    "gn:admin1_code":"07",
    "gn:asciiname":"Songo",
    "gn:country_code":"BF",
    "gn:dem":207,
    "gn:feature_class":"P",
    "gn:feature_code":"PPL",
    "gn:name":"Songo",
    "gn:population":0,
    "gn:timezone":"Africa/Ouagadougou",
    "iso:country":"BF",
    "name:ceb_x_preferred":[
        "Songo"
    ],
    "name:deu_x_preferred":[
        "Songo"
    ],
    "name:fra_x_preferred":[
        "Songo"
    ],
    "name:por_x_preferred":[
        "Songo"
    ],
    "name:swe_x_preferred":[
        "Songo"
    ],
    "wof:name":"Songo",
    "wof:placetype":"locality"
},
  "geometry": {"coordinates":[-0.88333,10.98333],"type":"Point"}
}