{
  "type": "Feature",
  "properties": {
    "gn:admin1_code":"02",
    "gn:asciiname":"Kongohouro",
    "gn:country_code":"BF",
    "gn:dem":406,
    "gn:feature_class":"P",
    "gn:feature_code":"PPL",
    "gn:name":"Kongohouro",
    "gn:population":0,
    "gn:timezone":"Africa/Ouagadougou",
    "iso:country":"BF",
    "wof:name":"Kongohouro",
    "wof:placetype":"locality"
},
  "geometry": {"coordinates":[-3.85,10.18333],"type":"Point"}
}