{
  "type": "Feature",
  "properties": {
    "gn:admin1_code":"10",
    "gn:asciiname":"Yoroga",
    "gn:country_code":"BF",
    "gn:dem":305,
    "gn:feature_class":"P",
    "gn:feature_code":"PPL",
    "gn:name":"Yoroga",
    "gn:population":0,
    "gn:timezone":"Africa/Ouagadougou",
    "iso:country":"BF",
    "wof:name":"Yoroga",
    "wof:placetype":"locality"
},
  "geometry": {"coordinates":[-2.08333,12.71667],"type":"Point"}
}