{
  "type": "Feature",
  "properties": {
    "gn:admin1_code":"13",
    "gn:asciiname":"Gouale",
    "gn:country_code":"BF",
    "gn:dem":344,
    "gn:feature_class":"P",
    "gn:feature_code":"PPL",
    "gn:name":"Goual\u00e9",
    "gn:population":0,
    "gn:timezone":"Africa/Ouagadougou",
    "iso:country":"BF",
    "wof:name":"Gouale",
    "wof:placetype":"locality"
},
  "geometry": {"coordinates":[-3.48333,10.16667],"type":"Point"}
}