{
  "type": "Feature",
  "properties": {
    "gn:admin1_code":"04",
    "gn:admin2_code":"28",
    "gn:asciiname":"Dialgaye",
    "gn:cc2":"BF",
    "gn:country_code":"BF",
    "gn:dem":278,
    "gn:feature_class":"P",
    "gn:feature_code":"PPL",
    "gn:name":"Dialgaye",
    "gn:population":0,
    "gn:timezone":"Africa/Ouagadougou",
    "iso:country":"BF",
    "name:ceb_x_preferred":[
        "Dialgaye Department"
    ],
    "name:deu_x_preferred":[
        "Dialgaye"
    ],
    "name:fra_x_preferred":[
        "Dialgaye"
    ],
    "name:ita_x_preferred":[
        "Dialgaye"
    ],
    "name:spa_x_preferred":[
        "Dialgaye"
    ],
    "name:swe_x_preferred":[
        "Dialgaye Department"
    ],
    "name:und_x_variant":[
        "Dialgay",
        "Dialgaye"
    ],
    "name:vie_x_preferred":[
        "Dialgaye"
    ],
    "wof:name":"Dialgaye",
    "wof:placetype":"locality"
},
  "geometry": {"coordinates":[-0.37611,11.96444],"type":"Point"}
}