{
  "type": "Feature",
  "properties": {
    "gn:admin1_code":"04",
    "gn:admin2_code":"59",
    "gn:asciiname":"Yargatenga",
    "gn:country_code":"BF",
    "gn:dem":267,
    "gn:feature_class":"P",
    "gn:feature_code":"PPL",
    "gn:name":"Yargatenga",
    "gn:population":0,
    "gn:timezone":"Africa/Ouagadougou",
    "iso:country":"BF",
    "name:deu_x_preferred":[
        "Yargatenga"
    ],
    "name:fra_x_preferred":[
        "Yargatenga"
    ],
    "name:ita_x_preferred":[
        "Yargatenga"
    ],
    "name:spa_x_preferred":[
        "Yargatenga"
    ],
    "name:und_x_variant":[
        "Kargatenga"
    ],
    "name:urd_x_preferred":[
        "\u06cc\u0627\u0631\u06af\u0679\u0646\u06af\u0627 \u0688\u06cc\u067e\u0627\u0631\u0679\u0645\u0646\u0679"
    ],
    "name:vie_x_preferred":[
        "Yargatenga"
    ],
    "wof:name":"Yargatenga",
    "wof:placetype":"locality"
},
  "geometry": {"coordinates":[0.00528,11.2125],"type":"Point"}
}