{
  "type": "Feature",
  "properties": {
    "gn:admin1_code":"04",
    "gn:admin2_code":"59",
    "gn:asciiname":"Yargatenga",
    "gn:country_code":"BF",
    "gn:dem":267,
    "gn:feature_class":"P",
    "gn:feature_code":"PPL",
    "gn:name":"Yargatenga",
    "gn:population":0,
    "gn:timezone":"Africa/Ouagadougou",
    "iso:country":"BF",
    "name:und_x_variant":[
        "Kargatenga",
        "Yargatenga"
    ],
    "wof:name":"Yargatenga",
    "wof:placetype":"locality"
},
  "geometry": {"coordinates":[0.00528,11.2125],"type":"Point"}
}