{
  "type": "Feature",
  "properties": {
    "gn:admin1_code":"07",
    "gn:asciiname":"Titintabe",
    "gn:country_code":"BF",
    "gn:dem":297,
    "gn:feature_class":"P",
    "gn:feature_code":"PPL",
    "gn:name":"Titintab\u00e9",
    "gn:population":0,
    "gn:timezone":"Africa/Ouagadougou",
    "iso:country":"BF",
    "wof:name":"Titintabe",
    "wof:placetype":"locality"
},
  "geometry": {"coordinates":[-1.28333,11.73333],"type":"Point"}
}