{
  "type": "Feature",
  "properties": {
    "gn:admin1_code":"12",
    "gn:admin2_code":"71",
    "gn:asciiname":"Kargouzi",
    "gn:country_code":"BF",
    "gn:dem":281,
    "gn:feature_class":"P",
    "gn:feature_code":"PPL",
    "gn:name":"Kargouzi",
    "gn:population":0,
    "gn:timezone":"Africa/Ouagadougou",
    "iso:country":"BF",
    "wof:name":"Kargouzi",
    "wof:placetype":"locality"
},
  "geometry": {"coordinates":[0.0517,13.76158],"type":"Point"}
}