{
  "type": "Feature",
  "properties": {
    "gn:admin1_code":"01",
    "gn:asciiname":"Besetenga",
    "gn:country_code":"BF",
    "gn:dem":287,
    "gn:feature_class":"P",
    "gn:feature_code":"PPL",
    "gn:name":"B\u00e9setenga",
    "gn:population":0,
    "gn:timezone":"Africa/Ouagadougou",
    "iso:country":"BF",
    "wof:name":"Besetenga",
    "wof:placetype":"locality"
},
  "geometry": {"coordinates":[-2.73333,12.73333],"type":"Point"}
}