{
  "type": "Feature",
  "properties": {
    "gn:admin1_code":"01",
    "gn:asciiname":"Laro",
    "gn:country_code":"BF",
    "gn:dem":261,
    "gn:feature_class":"P",
    "gn:feature_code":"PPL",
    "gn:name":"Laro",
    "gn:population":0,
    "gn:timezone":"Africa/Ouagadougou",
    "iso:country":"BF",
    "name:ceb_x_preferred":[
        "Laro"
    ],
    "name:fas_x_preferred":[
        "\u0644\u0627\u0631\u0648"
    ],
    "name:swe_x_preferred":[
        "Laro"
    ],
    "wof:name":"Laro",
    "wof:placetype":"locality"
},
  "geometry": {"coordinates":[-2.83333,11.28333],"type":"Point"}
}