{
  "type": "Feature",
  "properties": {
    "gn:admin1_code":"02",
    "gn:asciiname":"Irikourounko",
    "gn:country_code":"BF",
    "gn:dem":299,
    "gn:feature_class":"P",
    "gn:feature_code":"PPL",
    "gn:name":"Irikourounko",
    "gn:population":0,
    "gn:timezone":"Africa/Ouagadougou",
    "iso:country":"BF",
    "wof:name":"Irikourounko",
    "wof:placetype":"locality"
},
  "geometry": {"coordinates":[-4.01667,10.71667],"type":"Point"}
}