{
  "type": "Feature",
  "properties": {
    "gn:admin1_code":"05",
    "gn:admin2_code":"64",
    "gn:asciiname":"Kilema",
    "gn:country_code":"BF",
    "gn:dem":288,
    "gn:feature_class":"P",
    "gn:feature_code":"PPL",
    "gn:name":"Kil\u00e9ma",
    "gn:population":0,
    "gn:timezone":"Africa/Ouagadougou",
    "iso:country":"BF",
    "wof:name":"Kilema",
    "wof:placetype":"locality"
},
  "geometry": {"coordinates":[-0.7393,13.55393],"type":"Point"}
}