{
  "type": "Feature",
  "properties": {
    "gn:admin1_code":"05",
    "gn:admin2_code":"70",
    "gn:asciiname":"Sabouli",
    "gn:country_code":"BF",
    "gn:dem":302,
    "gn:feature_class":"P",
    "gn:feature_code":"PPL",
    "gn:name":"Sabouli",
    "gn:population":0,
    "gn:timezone":"Africa/Ouagadougou",
    "iso:country":"BF",
    "wof:name":"Sabouli",
    "wof:placetype":"locality"
},
  "geometry": {"coordinates":[-1.33814,13.13188],"type":"Point"}
}