{
  "type": "Feature",
  "properties": {
    "gn:admin1_code":"13",
    "gn:asciiname":"Gongonka",
    "gn:country_code":"BF",
    "gn:dem":318,
    "gn:feature_class":"P",
    "gn:feature_code":"PPL",
    "gn:name":"Gongonka",
    "gn:population":0,
    "gn:timezone":"Africa/Ouagadougou",
    "iso:country":"BF",
    "wof:name":"Gongonka",
    "wof:placetype":"locality"
},
  "geometry": {"coordinates":[-2.98333,9.75],"type":"Point"}
}