{
  "type": "Feature",
  "properties": {
    "gn:admin1_code":"11",
    "gn:asciiname":"Tangsera",
    "gn:country_code":"BF",
    "gn:dem":353,
    "gn:feature_class":"P",
    "gn:feature_code":"PPL",
    "gn:name":"Tangs\u00e9ra",
    "gn:population":0,
    "gn:timezone":"Africa/Ouagadougou",
    "iso:country":"BF",
    "name:und_x_variant":[
        "Tangs\u00e9ga",
        "Tangs\u00e9ra"
    ],
    "wof:name":"Tangsera",
    "wof:placetype":"locality"
},
  "geometry": {"coordinates":[-1.35,12.73333],"type":"Point"}
}