{
  "type": "Feature",
  "properties": {
    "gn:admin1_code":"11",
    "gn:asciiname":"Katanga",
    "gn:country_code":"BF",
    "gn:dem":320,
    "gn:feature_class":"P",
    "gn:feature_code":"PPL",
    "gn:name":"Katanga",
    "gn:population":0,
    "gn:timezone":"Africa/Ouagadougou",
    "iso:country":"BF",
    "wof:name":"Katanga",
    "wof:placetype":"locality"
},
  "geometry": {"coordinates":[-1.71667,12.65],"type":"Point"}
}