{
  "type": "Feature",
  "properties": {
    "gn:admin1_code":"06",
    "gn:asciiname":"Poune",
    "gn:country_code":"BF",
    "gn:dem":338,
    "gn:feature_class":"P",
    "gn:feature_code":"PPL",
    "gn:name":"Poune",
    "gn:population":0,
    "gn:timezone":"Africa/Ouagadougou",
    "iso:country":"BF",
    "name:und_x_variant":[
        "Pou",
        "Pu",
        "Poune"
    ],
    "wof:name":"Poune",
    "wof:placetype":"locality"
},
  "geometry": {"coordinates":[-1.58333,11.51667],"type":"Point"}
}