{
  "type": "Feature",
  "properties": {
    "gn:admin1_code":"02",
    "gn:asciiname":"Bonpe",
    "gn:country_code":"BF",
    "gn:dem":280,
    "gn:feature_class":"P",
    "gn:feature_code":"PPL",
    "gn:name":"Bonp\u00e9",
    "gn:population":0,
    "gn:timezone":"Africa/Ouagadougou",
    "iso:country":"BF",
    "name:und_x_variant":[
        "Bomp\u00e9",
        "Bonp\u00e9"
    ],
    "wof:name":"Bonpe",
    "wof:placetype":"locality"
},
  "geometry": {"coordinates":[-4.78333,10.46667],"type":"Point"}
}