{
  "type": "Feature",
  "properties": {
    "gn:admin1_code":"09",
    "gn:asciiname":"Tienena",
    "gn:country_code":"BF",
    "gn:dem":541,
    "gn:feature_class":"P",
    "gn:feature_code":"PPL",
    "gn:name":"Ti\u00e9n\u00e9na",
    "gn:population":0,
    "gn:timezone":"Africa/Ouagadougou",
    "iso:country":"BF",
    "wof:name":"Tienena",
    "wof:placetype":"locality"
},
  "geometry": {"coordinates":[-5.26667,10.91667],"type":"Point"}
}