{
  "type": "Feature",
  "properties": {
    "gn:admin1_code":"08",
    "gn:asciiname":"Haba",
    "gn:country_code":"BF",
    "gn:dem":253,
    "gn:feature_class":"P",
    "gn:feature_code":"PPL",
    "gn:name":"Haba",
    "gn:population":0,
    "gn:timezone":"Africa/Ouagadougou",
    "iso:country":"BF",
    "name:ceb_x_preferred":[
        "Haba"
    ],
    "name:deu_x_preferred":[
        "Haba"
    ],
    "name:spa_x_preferred":[
        "Haba"
    ],
    "name:swe_x_preferred":[
        "Haba"
    ],
    "wof:name":"Haba",
    "wof:placetype":"locality"
},
  "geometry": {"coordinates":[0.73333,12.91667],"type":"Point"}
}