{
  "type": "Feature",
  "properties": {
    "gn:admin1_code":"08",
    "gn:admin2_code":"21",
    "gn:asciiname":"Piyou",
    "gn:country_code":"BF",
    "gn:dem":282,
    "gn:feature_class":"P",
    "gn:feature_code":"PPL",
    "gn:name":"Piyou",
    "gn:population":0,
    "gn:timezone":"Africa/Ouagadougou",
    "iso:country":"BF",
    "wof:name":"Piyou",
    "wof:placetype":"locality"
},
  "geometry": {"coordinates":[-0.06337,13.22814],"type":"Point"}
}