{
  "type": "Feature",
  "properties": {
    "gn:admin1_code":"13",
    "gn:asciiname":"Sangolo",
    "gn:country_code":"BF",
    "gn:dem":313,
    "gn:feature_class":"P",
    "gn:feature_code":"PPL",
    "gn:name":"Sangolo",
    "gn:population":0,
    "gn:timezone":"Africa/Ouagadougou",
    "iso:country":"BF",
    "name:ceb_x_preferred":[
        "Sangolo"
    ],
    "name:swe_x_preferred":[
        "Sangolo"
    ],
    "wof:name":"Sangolo",
    "wof:placetype":"locality"
},
  "geometry": {"coordinates":[-3.46667,10.76667],"type":"Point"}
}