{
  "type": "Feature",
  "properties": {
    "gn:admin1_code":"07",
    "gn:admin2_code":"47",
    "gn:asciiname":"Poussouwaka",
    "gn:country_code":"BF",
    "gn:dem":323,
    "gn:feature_class":"P",
    "gn:feature_code":"PPL",
    "gn:name":"Poussouwaka",
    "gn:population":0,
    "gn:timezone":"Africa/Ouagadougou",
    "iso:country":"BF",
    "name:und_x_variant":[
        "Watinga",
        "Poussouwaka"
    ],
    "wof:name":"Poussouwaka",
    "wof:placetype":"locality"
},
  "geometry": {"coordinates":[-1.62,12.08167],"type":"Point"}
}