{
  "type": "Feature",
  "properties": {
    "gn:admin1_code":"11",
    "gn:asciiname":"Nabitenga",
    "gn:country_code":"BF",
    "gn:dem":311,
    "gn:feature_class":"P",
    "gn:feature_code":"PPL",
    "gn:name":"Nabitenga",
    "gn:population":0,
    "gn:timezone":"Africa/Ouagadougou",
    "iso:country":"BF",
    "name:ceb_x_preferred":[
        "Nabitenga"
    ],
    "name:swe_x_preferred":[
        "Nabitenga"
    ],
    "wof:name":"Nabitenga",
    "wof:placetype":"locality"
},
  "geometry": {"coordinates":[-0.58333,12.31667],"type":"Point"}
}