{
  "type": "Feature",
  "properties": {
    "gn:admin1_code":"11",
    "gn:admin2_code":"68",
    "gn:asciiname":"Yanga",
    "gn:country_code":"BF",
    "gn:dem":326,
    "gn:feature_class":"P",
    "gn:feature_code":"PPL",
    "gn:name":"Yanga",
    "gn:population":0,
    "gn:timezone":"Africa/Ouagadougou",
    "iso:country":"BF",
    "name:ceb_x_preferred":[
        "Yanga"
    ],
    "name:deu_x_preferred":[
        "Yanga"
    ],
    "name:fra_x_preferred":[
        "Yanga"
    ],
    "name:rus_x_preferred":[
        "\u042f\u043d\u0433\u0430"
    ],
    "name:swe_x_preferred":[
        "Yanga"
    ],
    "wof:name":"Yanga",
    "wof:placetype":"locality"
},
  "geometry": {"coordinates":[-1.31639,12.73333],"type":"Point"}
}