{
  "type": "Feature",
  "properties": {
    "gn:admin1_code":"01",
    "gn:admin2_code":"73",
    "gn:asciiname":"Korome",
    "gn:country_code":"BF",
    "gn:dem":260,
    "gn:feature_class":"P",
    "gn:feature_code":"PPL",
    "gn:name":"Korom\u00e9",
    "gn:population":0,
    "gn:timezone":"Africa/Ouagadougou",
    "iso:country":"BF",
    "wof:name":"Korome",
    "wof:placetype":"locality"
},
  "geometry": {"coordinates":[-3.3701,13.1305],"type":"Point"}
}