{
  "type": "Feature",
  "properties": {
    "gn:admin1_code":"05",
    "gn:asciiname":"Sini",
    "gn:country_code":"BF",
    "gn:dem":306,
    "gn:feature_class":"P",
    "gn:feature_code":"PPL",
    "gn:name":"Sini",
    "gn:population":0,
    "gn:timezone":"Africa/Ouagadougou",
    "iso:country":"BF",
    "name:bel_x_preferred":[
        "\u0421\u0456\u043d\u0456"
    ],
    "name:bpy_x_preferred":[
        "\u09b8\u09bf\u09a8\u09bf"
    ],
    "name:cat_x_preferred":[
        "Sini"
    ],
    "name:ceb_x_preferred":[
        "Sini"
    ],
    "name:deu_x_preferred":[
        "Sini"
    ],
    "name:fin_x_preferred":[
        "Sini"
    ],
    "name:fra_x_preferred":[
        "Sini"
    ],
    "name:ita_x_preferred":[
        "Sini"
    ],
    "name:nld_x_preferred":[
        "Sini"
    ],
    "name:swe_x_preferred":[
        "Sini"
    ],
    "wof:name":"Sini",
    "wof:placetype":"locality"
},
  "geometry": {"coordinates":[-0.46009,12.60778],"type":"Point"}
}