{
  "type": "Feature",
  "properties": {
    "gn:admin1_code":"05",
    "gn:asciiname":"Sini",
    "gn:country_code":"BF",
    "gn:dem":306,
    "gn:feature_class":"P",
    "gn:feature_code":"PPL",
    "gn:name":"Sini",
    "gn:population":0,
    "gn:timezone":"Africa/Ouagadougou",
    "iso:country":"BF",
    "wof:name":"Sini",
    "wof:placetype":"locality"
},
  "geometry": {"coordinates":[-0.46009,12.60778],"type":"Point"}
}