{
  "type": "Feature",
  "properties": {
    "gn:admin1_code":"04",
    "gn:asciiname":"Kouapkouka",
    "gn:country_code":"BF",
    "gn:dem":291,
    "gn:feature_class":"P",
    "gn:feature_code":"PPL",
    "gn:name":"Kouapkouka",
    "gn:population":0,
    "gn:timezone":"Africa/Ouagadougou",
    "iso:country":"BF",
    "wof:name":"Kouapkouka",
    "wof:placetype":"locality"
},
  "geometry": {"coordinates":[-0.33333,12.43333],"type":"Point"}
}