{
  "type": "Feature",
  "properties": {
    "gn:admin1_code":"08",
    "gn:asciiname":"Bouban",
    "gn:country_code":"BF",
    "gn:dem":269,
    "gn:feature_class":"P",
    "gn:feature_code":"PPL",
    "gn:name":"Bouban",
    "gn:population":0,
    "gn:timezone":"Africa/Ouagadougou",
    "iso:country":"BF",
    "wof:name":"Bouban",
    "wof:placetype":"locality"
},
  "geometry": {"coordinates":[0.78333,12.48333],"type":"Point"}
}