{
  "type": "Feature",
  "properties": {
    "gn:admin1_code":"03",
    "gn:asciiname":"Silmissin",
    "gn:country_code":"BF",
    "gn:dem":312,
    "gn:feature_class":"P",
    "gn:feature_code":"PPL",
    "gn:name":"Silmissin",
    "gn:population":0,
    "gn:timezone":"Africa/Ouagadougou",
    "iso:country":"BF",
    "name:azb_x_preferred":[
        "\u0633\u06cc\u0644\u0645\u06cc\u0633\u06cc\u0646"
    ],
    "name:fas_x_preferred":[
        "\u0633\u06cc\u0644\u0645\u06cc\u0633\u06cc\u0646"
    ],
    "name:fra_x_preferred":[
        "Silmissin"
    ],
    "wof:name":"Silmissin",
    "wof:placetype":"locality"
},
  "geometry": {"coordinates":[-1.39417,12.11917],"type":"Point"}
}