{
  "type": "Feature",
  "properties": {
    "gn:admin1_code":"05",
    "gn:admin2_code":"70",
    "gn:asciiname":"Gaoua",
    "gn:country_code":"BF",
    "gn:dem":347,
    "gn:feature_class":"P",
    "gn:feature_code":"PPL",
    "gn:name":"Gaoua",
    "gn:population":0,
    "gn:timezone":"Africa/Ouagadougou",
    "iso:country":"BF",
    "name:ben_x_preferred":[
        "\u0997\u09be\u0989\u09df\u09be"
    ],
    "name:ceb_x_preferred":[
        "Gaoua"
    ],
    "name:deu_x_preferred":[
        "Gaoua"
    ],
    "name:fas_x_preferred":[
        "\u06af\u0627\u0626\u0648\u0622"
    ],
    "name:fin_x_preferred":[
        "Gaoua"
    ],
    "name:fra_x_preferred":[
        "Gaoua"
    ],
    "name:frr_x_preferred":[
        "Gaoua"
    ],
    "name:heb_x_preferred":[
        "\u05d2\u05d5\u05d0\u05d4"
    ],
    "name:hin_x_preferred":[
        "\u0917\u093e\u0909\u0906"
    ],
    "name:hun_x_preferred":[
        "Gaoua"
    ],
    "name:ind_x_preferred":[
        "Gaoua"
    ],
    "name:ita_x_preferred":[
        "Gaoua"
    ],
    "name:kor_x_preferred":[
        "\uac00\uc6b0\uc544"
    ],
    "name:lit_x_preferred":[
        "Gaua"
    ],
    "name:nld_x_preferred":[
        "Gaoua"
    ],
    "name:pol_x_preferred":[
        "Gaoua"
    ],
    "name:por_x_preferred":[
        "Gaoua"
    ],
    "name:ron_x_preferred":[
        "Gaoua"
    ],
    "name:rus_x_preferred":[
        "\u0413\u0430\u0432\u0430"
    ],
    "name:spa_x_preferred":[
        "Gaoua"
    ],
    "name:swe_x_preferred":[
        "Gaoua"
    ],
    "name:tur_x_preferred":[
        "Gaoua"
    ],
    "name:ukr_x_preferred":[
        "\u0413\u0430\u0432\u0430"
    ],
    "name:urd_x_preferred":[
        "\u06af\u0627\u0624\u0627"
    ],
    "name:vie_x_preferred":[
        "Gaoua"
    ],
    "name:war_x_preferred":[
        "Gaoua"
    ],
    "wof:name":"Gaoua",
    "wof:placetype":"locality"
},
  "geometry": {"coordinates":[-1.10228,13.11803],"type":"Point"}
}