{
  "type": "Feature",
  "properties": {
    "gn:admin1_code":"10",
    "gn:admin2_code":"76",
    "gn:asciiname":"Songotaba",
    "gn:country_code":"BF",
    "gn:dem":321,
    "gn:feature_class":"P",
    "gn:feature_code":"PPL",
    "gn:name":"Songotaba",
    "gn:population":0,
    "gn:timezone":"Africa/Ouagadougou",
    "iso:country":"BF",
    "wof:name":"Songotaba",
    "wof:placetype":"locality"
},
  "geometry": {"coordinates":[-1.97149,13.84746],"type":"Point"}
}