{
  "type": "Feature",
  "properties": {
    "gn:admin1_code":"10",
    "gn:admin2_code":"76",
    "gn:asciiname":"Keneko",
    "gn:country_code":"BF",
    "gn:dem":340,
    "gn:feature_class":"P",
    "gn:feature_code":"PPL",
    "gn:name":"K\u00e9n\u00e9ko",
    "gn:population":0,
    "gn:timezone":"Africa/Ouagadougou",
    "iso:country":"BF",
    "wof:name":"Keneko",
    "wof:placetype":"locality"
},
  "geometry": {"coordinates":[-2.26021,13.28659],"type":"Point"}
}