{
  "type": "Feature",
  "properties": {
    "gn:admin1_code":"13",
    "gn:asciiname":"Tiankoura",
    "gn:country_code":"BF",
    "gn:dem":271,
    "gn:feature_class":"P",
    "gn:feature_code":"PPL",
    "gn:name":"Tiankoura",
    "gn:population":0,
    "gn:timezone":"Africa/Ouagadougou",
    "iso:country":"BF",
    "name:ceb_x_preferred":[
        "Tiankoura"
    ],
    "name:swe_x_preferred":[
        "Tiankoura"
    ],
    "name:und_x_variant":[
        "Tiankura",
        "Tionkoura"
    ],
    "wof:name":"Tiankoura",
    "wof:placetype":"locality"
},
  "geometry": {"coordinates":[-3.25588,10.76634],"type":"Point"}
}