{
  "type": "Feature",
  "properties": {
    "gn:admin1_code":"01",
    "gn:asciiname":"Siena",
    "gn:country_code":"BF",
    "gn:dem":309,
    "gn:feature_class":"P",
    "gn:feature_code":"PPL",
    "gn:name":"Si\u00e9na",
    "gn:population":0,
    "gn:timezone":"Africa/Ouagadougou",
    "iso:country":"BF",
    "name:und_x_variant":[
        "Bi\u00e9na",
        "Si\u00e9na"
    ],
    "wof:name":"Siena",
    "wof:placetype":"locality"
},
  "geometry": {"coordinates":[-2.96667,12.85],"type":"Point"}
}