{
  "type": "Feature",
  "properties": {
    "gn:admin1_code":"11",
    "gn:asciiname":"Digre",
    "gn:country_code":"BF",
    "gn:dem":319,
    "gn:feature_class":"P",
    "gn:feature_code":"PPL",
    "gn:name":"Digr\u00e9",
    "gn:population":0,
    "gn:timezone":"Africa/Ouagadougou",
    "iso:country":"BF",
    "name:und_x_variant":[
        "Digr\u00e9"
    ],
    "wof:name":"Digre",
    "wof:placetype":"locality"
},
  "geometry": {"coordinates":[-0.56667,12.28333],"type":"Point"}
}