{
  "type": "Feature",
  "properties": {
    "gn:admin1_code":"08",
    "gn:asciiname":"Tyebadi",
    "gn:country_code":"BF",
    "gn:dem":259,
    "gn:feature_class":"P",
    "gn:feature_code":"PPL",
    "gn:name":"Ty\u00e9badi",
    "gn:population":0,
    "gn:timezone":"Africa/Ouagadougou",
    "iso:country":"BF",
    "wof:name":"Tyebadi",
    "wof:placetype":"locality"
},
  "geometry": {"coordinates":[0.95,12.13333],"type":"Point"}
}