{
  "type": "Feature",
  "properties": {
    "gn:admin1_code":"09",
    "gn:admin2_code":"51",
    "gn:asciiname":"Bossora",
    "gn:country_code":"BF",
    "gn:dem":283,
    "gn:feature_class":"P",
    "gn:feature_code":"PPL",
    "gn:name":"Bossora",
    "gn:population":0,
    "gn:timezone":"Africa/Ouagadougou",
    "iso:country":"BF",
    "name:und_x_variant":[
        "Basora",
        "Bossora"
    ],
    "wof:name":"Bossora",
    "wof:placetype":"locality"
},
  "geometry": {"coordinates":[-4.09133,11.7111],"type":"Point"}
}