{
  "type": "Feature",
  "properties": {
    "gn:admin1_code":"05",
    "gn:asciiname":"Koulpele",
    "gn:country_code":"BF",
    "gn:dem":325,
    "gn:feature_class":"P",
    "gn:feature_code":"PPL",
    "gn:name":"Koulp\u00e9l\u00e9",
    "gn:population":0,
    "gn:timezone":"Africa/Ouagadougou",
    "iso:country":"BF",
    "wof:name":"Koulpele",
    "wof:placetype":"locality"
},
  "geometry": {"coordinates":[-0.65,12.81667],"type":"Point"}
}