{
  "type": "Feature",
  "properties": {
    "gn:admin1_code":"08",
    "gn:admin2_code":"42",
    "gn:asciiname":"Boguel",
    "gn:country_code":"BF",
    "gn:dem":261,
    "gn:feature_class":"P",
    "gn:feature_code":"PPL",
    "gn:name":"Bogu\u00e8l",
    "gn:population":0,
    "gn:timezone":"Africa/Ouagadougou",
    "iso:country":"BF",
    "name:und_x_variant":[
        "Bog\u00e8l",
        "Bogu\u00e8l"
    ],
    "wof:name":"Boguel",
    "wof:placetype":"locality"
},
  "geometry": {"coordinates":[2.01283,12.47468],"type":"Point"}
}