{
  "type": "Feature",
  "properties": {
    "gn:admin1_code":"12",
    "gn:admin2_code":"71",
    "gn:asciiname":"Sampelga",
    "gn:country_code":"BF",
    "gn:dem":286,
    "gn:feature_class":"P",
    "gn:feature_code":"PPL",
    "gn:name":"Samp\u00e8lga",
    "gn:population":0,
    "gn:timezone":"Africa/Ouagadougou",
    "iso:country":"BF",
    "name:und_x_variant":[
        "Sempelga",
        "Samp\u00e8lga"
    ],
    "wof:name":"Sampelga",
    "wof:placetype":"locality"
},
  "geometry": {"coordinates":[0.21985,13.75028],"type":"Point"}
}