{
  "type": "Feature",
  "properties": {
    "gn:admin1_code":"12",
    "gn:admin2_code":"75",
    "gn:asciiname":"Takatami",
    "gn:country_code":"BF",
    "gn:dem":236,
    "gn:feature_class":"P",
    "gn:feature_code":"PPL",
    "gn:name":"Takatami",
    "gn:population":0,
    "gn:timezone":"Africa/Ouagadougou",
    "iso:country":"BF",
    "wof:name":"Takatami",
    "wof:placetype":"locality"
},
  "geometry": {"coordinates":[0.95085,13.24823],"type":"Point"}
}