{
  "type": "Feature",
  "properties": {
    "gn:admin1_code":"10",
    "gn:admin2_code":"76",
    "gn:asciiname":"Bouga",
    "gn:country_code":"BF",
    "gn:dem":335,
    "gn:feature_class":"P",
    "gn:feature_code":"PPL",
    "gn:name":"Bouga",
    "gn:population":0,
    "gn:timezone":"Africa/Ouagadougou",
    "iso:country":"BF",
    "name:und_x_variant":[
        "Bougo",
        "Bouga"
    ],
    "wof:name":"Bouga",
    "wof:placetype":"locality"
},
  "geometry": {"coordinates":[-1.86628,13.24135],"type":"Point"}
}