{
  "type": "Feature",
  "properties": {
    "gn:admin1_code":"11",
    "gn:asciiname":"Nidrihida",
    "gn:country_code":"BF",
    "gn:dem":310,
    "gn:feature_class":"P",
    "gn:feature_code":"PPL",
    "gn:name":"Nidrihida",
    "gn:population":0,
    "gn:timezone":"Africa/Ouagadougou",
    "iso:country":"BF",
    "name:und_x_variant":[
        "Yoriyada",
        "Nidrihida"
    ],
    "wof:name":"Nidrihida",
    "wof:placetype":"locality"
},
  "geometry": {"coordinates":[-1.63333,12.76667],"type":"Point"}
}