{
  "type": "Feature",
  "properties": {
    "gn:admin1_code":"12",
    "gn:admin2_code":"75",
    "gn:asciiname":"Karmanma",
    "gn:country_code":"BF",
    "gn:dem":249,
    "gn:feature_class":"P",
    "gn:feature_code":"PPL",
    "gn:name":"Karmanma",
    "gn:population":0,
    "gn:timezone":"Africa/Ouagadougou",
    "iso:country":"BF",
    "wof:name":"Karmanma",
    "wof:placetype":"locality"
},
  "geometry": {"coordinates":[0.91321,13.45191],"type":"Point"}
}