{
  "type": "Feature",
  "properties": {
    "gn:admin1_code":"13",
    "gn:asciiname":"Pouloupoulou",
    "gn:country_code":"BF",
    "gn:dem":247,
    "gn:feature_class":"P",
    "gn:feature_code":"PPL",
    "gn:name":"Pouloupoulou",
    "gn:population":0,
    "gn:timezone":"Africa/Ouagadougou",
    "iso:country":"BF",
    "name:und_x_variant":[
        "Idietou",
        "Pouloupoulou"
    ],
    "wof:name":"Pouloupoulou",
    "wof:placetype":"locality"
},
  "geometry": {"coordinates":[-2.96667,9.96667],"type":"Point"}
}