{
  "type": "Feature",
  "properties": {
    "gn:admin1_code":"09",
    "gn:admin2_code":"51",
    "gn:asciiname":"Koulima",
    "gn:country_code":"BF",
    "gn:dem":476,
    "gn:feature_class":"P",
    "gn:feature_code":"PPL",
    "gn:name":"Koulima",
    "gn:population":0,
    "gn:timezone":"Africa/Ouagadougou",
    "iso:country":"BF",
    "wof:name":"Koulima",
    "wof:placetype":"locality"
},
  "geometry": {"coordinates":[-4.28737,11.15662],"type":"Point"}
}