{
  "type": "Feature",
  "properties": {
    "gn:admin1_code":"04",
    "gn:asciiname":"Bado",
    "gn:country_code":"BF",
    "gn:dem":256,
    "gn:feature_class":"P",
    "gn:feature_code":"PPL",
    "gn:name":"Bado",
    "gn:population":0,
    "gn:timezone":"Africa/Ouagadougou",
    "iso:country":"BF",
    "name:ceb_x_preferred":[
        "Bado"
    ],
    "name:deu_x_preferred":[
        "Bado"
    ],
    "name:swe_x_preferred":[
        "Bado"
    ],
    "name:und_x_variant":[
        "Dabo",
        "Bado"
    ],
    "wof:name":"Bado",
    "wof:placetype":"locality"
},
  "geometry": {"coordinates":[-0.45,11.63333],"type":"Point"}
}