{
  "type": "Feature",
  "properties": {
    "gn:admin1_code":"12",
    "gn:admin2_code":"75",
    "gn:asciiname":"Pontityaga",
    "gn:country_code":"BF",
    "gn:dem":259,
    "gn:feature_class":"P",
    "gn:feature_code":"PPL",
    "gn:name":"Pontityaga",
    "gn:population":0,
    "gn:timezone":"Africa/Ouagadougou",
    "iso:country":"BF",
    "wof:name":"Pontityaga",
    "wof:placetype":"locality"
},
  "geometry": {"coordinates":[0.60099,13.21886],"type":"Point"}
}