{
  "type": "Feature",
  "properties": {
    "gn:admin1_code":"13",
    "gn:asciiname":"Boussoulbi",
    "gn:country_code":"BF",
    "gn:dem":266,
    "gn:feature_class":"P",
    "gn:feature_code":"PPL",
    "gn:name":"Boussoulbi",
    "gn:population":0,
    "gn:timezone":"Africa/Ouagadougou",
    "iso:country":"BF",
    "wof:name":"Boussoulbi",
    "wof:placetype":"locality"
},
  "geometry": {"coordinates":[-3.06667,9.96667],"type":"Point"}
}