{
  "type": "Feature",
  "properties": {
    "gn:admin1_code":"11",
    "gn:asciiname":"Boilguen",
    "gn:country_code":"BF",
    "gn:dem":342,
    "gn:feature_class":"P",
    "gn:feature_code":"PPL",
    "gn:name":"Boilguen",
    "gn:population":0,
    "gn:timezone":"Africa/Ouagadougou",
    "iso:country":"BF",
    "wof:name":"Boilguen",
    "wof:placetype":"locality"
},
  "geometry": {"coordinates":[-0.81667,12.56667],"type":"Point"}
}