{
  "type": "Feature",
  "properties": {
    "gn:admin1_code":"03",
    "gn:admin2_code":"53",
    "gn:asciiname":"Bissighin",
    "gn:country_code":"BF",
    "gn:dem":309,
    "gn:feature_class":"P",
    "gn:feature_code":"PPL",
    "gn:name":"Bissighin",
    "gn:population":0,
    "gn:timezone":"Africa/Ouagadougou",
    "iso:country":"BF",
    "name:und_x_variant":[
        "Bissiguen"
    ],
    "wof:name":"Bissighin",
    "wof:placetype":"locality"
},
  "geometry": {"coordinates":[-1.60484,12.39354],"type":"Point"}
}