{
  "type": "Feature",
  "properties": {
    "gn:admin1_code":"09",
    "gn:asciiname":"Indibi",
    "gn:country_code":"BF",
    "gn:dem":265,
    "gn:feature_class":"P",
    "gn:feature_code":"PPL",
    "gn:name":"Indibi",
    "gn:population":0,
    "gn:timezone":"Africa/Ouagadougou",
    "iso:country":"BF",
    "wof:name":"Indibi",
    "wof:placetype":"locality"
},
  "geometry": {"coordinates":[-2.93333,11.43333],"type":"Point"}
}