{
  "type": "Feature",
  "properties": {
    "gn:admin1_code":"02",
    "gn:asciiname":"Chion",
    "gn:country_code":"BF",
    "gn:dem":450,
    "gn:feature_class":"P",
    "gn:feature_code":"PPL",
    "gn:name":"Chion",
    "gn:population":0,
    "gn:timezone":"Africa/Ouagadougou",
    "iso:country":"BF",
    "wof:name":"Chion",
    "wof:placetype":"locality"
},
  "geometry": {"coordinates":[-5.31667,10.66667],"type":"Point"}
}