{
  "type": "Feature",
  "properties": {
    "gn:admin1_code":"11",
    "gn:asciiname":"Koaken",
    "gn:country_code":"BF",
    "gn:dem":294,
    "gn:feature_class":"P",
    "gn:feature_code":"PPL",
    "gn:name":"Koaken",
    "gn:population":0,
    "gn:timezone":"Africa/Ouagadougou",
    "iso:country":"BF",
    "name:und_x_variant":[
        "Koakin",
        "Koaken"
    ],
    "wof:name":"Koaken",
    "wof:placetype":"locality"
},
  "geometry": {"coordinates":[-1.51667,12.58333],"type":"Point"}
}