{
  "type": "Feature",
  "properties": {
    "gn:admin1_code":"13",
    "gn:asciiname":"Kientara",
    "gn:country_code":"BF",
    "gn:dem":294,
    "gn:feature_class":"P",
    "gn:feature_code":"PPL",
    "gn:name":"Kientara",
    "gn:population":0,
    "gn:timezone":"Africa/Ouagadougou",
    "iso:country":"BF",
    "wof:name":"Kientara",
    "wof:placetype":"locality"
},
  "geometry": {"coordinates":[-3.03333,9.75],"type":"Point"}
}