{
  "type": "Feature",
  "properties": {
    "gn:admin1_code":"10",
    "gn:admin2_code":"76",
    "gn:asciiname":"Boule",
    "gn:country_code":"BF",
    "gn:dem":316,
    "gn:feature_class":"P",
    "gn:feature_code":"PPL",
    "gn:name":"Boul\u00e9",
    "gn:population":0,
    "gn:timezone":"Africa/Ouagadougou",
    "iso:country":"BF",
    "name:ceb_x_preferred":[
        "Boule"
    ],
    "name:deu_x_preferred":[
        "Boule"
    ],
    "name:fra_x_preferred":[
        "Boule"
    ],
    "name:ita_x_preferred":[
        "Boule"
    ],
    "name:nld_x_preferred":[
        "Boule"
    ],
    "name:rus_x_preferred":[
        "\u0411\u0443\u043b\u0435"
    ],
    "name:spa_x_preferred":[
        "Boule"
    ],
    "name:swe_x_preferred":[
        "Boule"
    ],
    "wof:name":"Boule",
    "wof:placetype":"locality"
},
  "geometry": {"coordinates":[-2.00899,13.13343],"type":"Point"}
}