{
  "type": "Feature",
  "properties": {
    "gn:admin1_code":"02",
    "gn:asciiname":"Outila",
    "gn:country_code":"BF",
    "gn:dem":520,
    "gn:feature_class":"P",
    "gn:feature_code":"PPL",
    "gn:name":"Outila",
    "gn:population":0,
    "gn:timezone":"Africa/Ouagadougou",
    "iso:country":"BF",
    "name:und_x_variant":[
        "Outiela",
        "Outila"
    ],
    "wof:name":"Outila",
    "wof:placetype":"locality"
},
  "geometry": {"coordinates":[-5.43333,10.98333],"type":"Point"}
}