{
  "type": "Feature",
  "properties": {
    "gn:admin1_code":"02",
    "gn:asciiname":"Tionouna",
    "gn:country_code":"BF",
    "gn:dem":284,
    "gn:feature_class":"P",
    "gn:feature_code":"PPL",
    "gn:name":"Tionouna",
    "gn:population":0,
    "gn:timezone":"Africa/Ouagadougou",
    "iso:country":"BF",
    "name:ceb_x_preferred":[
        "Tionouna"
    ],
    "name:fra_x_preferred":[
        "Tionouna"
    ],
    "name:swe_x_preferred":[
        "Tionouna"
    ],
    "wof:name":"Tionouna",
    "wof:placetype":"locality"
},
  "geometry": {"coordinates":[-4.81667,10.51667],"type":"Point"}
}