{
  "type": "Feature",
  "properties": {
    "gn:admin1_code":"08",
    "gn:admin2_code":"21",
    "gn:asciiname":"Louroudye",
    "gn:country_code":"BF",
    "gn:dem":272,
    "gn:feature_class":"P",
    "gn:feature_code":"PPL",
    "gn:name":"Louroudy\u00e8",
    "gn:population":0,
    "gn:timezone":"Africa/Ouagadougou",
    "iso:country":"BF",
    "wof:name":"Louroudye",
    "wof:placetype":"locality"
},
  "geometry": {"coordinates":[0.49181,13.08743],"type":"Point"}
}