{
  "type": "Feature",
  "properties": {
    "gn:admin1_code":"12",
    "gn:admin2_code":"75",
    "gn:asciiname":"Gountoure",
    "gn:country_code":"BF",
    "gn:dem":257,
    "gn:feature_class":"P",
    "gn:feature_code":"PPL",
    "gn:name":"Gountour\u00e9",
    "gn:population":0,
    "gn:timezone":"Africa/Ouagadougou",
    "iso:country":"BF",
    "wof:name":"Gountoure",
    "wof:placetype":"locality"
},
  "geometry": {"coordinates":[0.46808,13.38079],"type":"Point"}
}