{
  "type": "Feature",
  "properties": {
    "gn:admin1_code":"05",
    "gn:admin2_code":"70",
    "gn:asciiname":"Delga",
    "gn:country_code":"BF",
    "gn:dem":318,
    "gn:feature_class":"P",
    "gn:feature_code":"PPL",
    "gn:name":"Delga",
    "gn:population":0,
    "gn:timezone":"Africa/Ouagadougou",
    "iso:country":"BF",
    "wof:name":"Delga",
    "wof:placetype":"locality"
},
  "geometry": {"coordinates":[-1.14495,13.14898],"type":"Point"}
}