{
  "type": "Feature",
  "properties": {
    "gn:admin1_code":"10",
    "gn:admin2_code":"34",
    "gn:asciiname":"Bakoui",
    "gn:country_code":"BF",
    "gn:dem":299,
    "gn:feature_class":"P",
    "gn:feature_code":"PPL",
    "gn:name":"Bakoui",
    "gn:population":0,
    "gn:timezone":"Africa/Ouagadougou",
    "iso:country":"BF",
    "wof:name":"Bakoui",
    "wof:placetype":"locality"
},
  "geometry": {"coordinates":[-1.64082,13.01293],"type":"Point"}
}