{
  "type": "Feature",
  "properties": {
    "gn:admin1_code":"13",
    "gn:asciiname":"Bele",
    "gn:country_code":"BF",
    "gn:dem":290,
    "gn:feature_class":"P",
    "gn:feature_code":"PPL",
    "gn:name":"B\u00e9l\u00e9",
    "gn:population":0,
    "gn:timezone":"Africa/Ouagadougou",
    "iso:country":"BF",
    "name:ceb_x_preferred":[
        "Bele"
    ],
    "name:swe_x_preferred":[
        "Bele"
    ],
    "wof:name":"Bele",
    "wof:placetype":"locality"
},
  "geometry": {"coordinates":[-2.98333,10.65],"type":"Point"}
}