{
  "type": "Feature",
  "properties": {
    "gn:admin1_code":"02",
    "gn:asciiname":"Konka",
    "gn:country_code":"BF",
    "gn:dem":344,
    "gn:feature_class":"P",
    "gn:feature_code":"PPL",
    "gn:name":"Konka",
    "gn:population":0,
    "gn:timezone":"Africa/Ouagadougou",
    "iso:country":"BF",
    "name:ceb_x_preferred":[
        "Konka"
    ],
    "name:swe_x_preferred":[
        "Konka"
    ],
    "name:urd_x_preferred":[
        "\u06a9\u0631\u06cc\u06af \u062f\u0631\u06cc\u0627"
    ],
    "wof:name":"Konka",
    "wof:placetype":"locality"
},
  "geometry": {"coordinates":[-3.96667,10.45],"type":"Point"}
}