{
  "type": "Feature",
  "properties": {
    "gn:admin1_code":"05",
    "gn:admin2_code":"15",
    "gn:asciiname":"Santaba",
    "gn:country_code":"BF",
    "gn:dem":339,
    "gn:feature_class":"P",
    "gn:feature_code":"PPL",
    "gn:name":"Santaba",
    "gn:population":0,
    "gn:timezone":"Africa/Ouagadougou",
    "iso:country":"BF",
    "wof:name":"Santaba",
    "wof:placetype":"locality"
},
  "geometry": {"coordinates":[-1.81778,13.35961],"type":"Point"}
}