{
  "type": "Feature",
  "properties": {
    "gn:admin1_code":"11",
    "gn:admin2_code":"68",
    "gn:asciiname":"Sadaba",
    "gn:country_code":"BF",
    "gn:dem":319,
    "gn:feature_class":"P",
    "gn:feature_code":"PPL",
    "gn:name":"Sadaba",
    "gn:population":0,
    "gn:timezone":"Africa/Ouagadougou",
    "iso:country":"BF",
    "name:und_x_variant":[
        "Sataba",
        "Sadaba"
    ],
    "wof:name":"Sadaba",
    "wof:placetype":"locality"
},
  "geometry": {"coordinates":[-1.33833,12.80611],"type":"Point"}
}