{
  "type": "Feature",
  "properties": {
    "gn:admin1_code":"04",
    "gn:asciiname":"Guihire",
    "gn:country_code":"BF",
    "gn:dem":295,
    "gn:feature_class":"P",
    "gn:feature_code":"PPL",
    "gn:name":"Guihir\u00e9",
    "gn:population":0,
    "gn:timezone":"Africa/Ouagadougou",
    "iso:country":"BF",
    "wof:name":"Guihire",
    "wof:placetype":"locality"
},
  "geometry": {"coordinates":[-0.58333,11.83333],"type":"Point"}
}