{
  "type": "Feature",
  "properties": {
    "gn:admin1_code":"13",
    "gn:asciiname":"Djipologo",
    "gn:country_code":"BF",
    "gn:dem":287,
    "gn:feature_class":"P",
    "gn:feature_code":"PPL",
    "gn:name":"Djipologo",
    "gn:population":0,
    "gn:timezone":"Africa/Ouagadougou",
    "iso:country":"BF",
    "name:und_x_variant":[
        "Jipologo",
        "Djipologo"
    ],
    "wof:name":"Djipologo",
    "wof:placetype":"locality"
},
  "geometry": {"coordinates":[-3.11667,10.93333],"type":"Point"}
}