{
  "type": "Feature",
  "properties": {
    "gn:admin1_code":"12",
    "gn:admin2_code":"40",
    "gn:asciiname":"Bolle",
    "gn:country_code":"BF",
    "gn:dem":285,
    "gn:feature_class":"P",
    "gn:feature_code":"PPL",
    "gn:name":"Boll\u00e9",
    "gn:population":0,
    "gn:timezone":"Africa/Ouagadougou",
    "iso:country":"BF",
    "name:ukr_x_preferred":[
        "\u0411\u043e\u043b\u043b\u0435"
    ],
    "wof:name":"Bolle",
    "wof:placetype":"locality"
},
  "geometry": {"coordinates":[-0.86808,13.85788],"type":"Point"}
}