{
  "type": "Feature",
  "properties": {
    "gn:admin1_code":"08",
    "gn:admin2_code":"42",
    "gn:asciiname":"Boudieri",
    "gn:country_code":"BF",
    "gn:dem":238,
    "gn:feature_class":"P",
    "gn:feature_code":"PPL",
    "gn:name":"Boudi\u00e9ri",
    "gn:population":0,
    "gn:timezone":"Africa/Ouagadougou",
    "iso:country":"BF",
    "wof:name":"Boudieri",
    "wof:placetype":"locality"
},
  "geometry": {"coordinates":[1.65242,12.31647],"type":"Point"}
}