{
  "type": "Feature",
  "properties": {
    "gn:admin1_code":"01",
    "gn:admin2_code":"58",
    "gn:asciiname":"Massalo",
    "gn:country_code":"BF",
    "gn:dem":356,
    "gn:feature_class":"P",
    "gn:feature_code":"PPL",
    "gn:name":"Massalo",
    "gn:population":0,
    "gn:timezone":"Africa/Ouagadougou",
    "iso:country":"BF",
    "wof:name":"Massalo",
    "wof:placetype":"locality"
},
  "geometry": {"coordinates":[-4.1611,12.8088],"type":"Point"}
}