{
  "type": "Feature",
  "properties": {
    "gn:admin1_code":"11",
    "gn:asciiname":"Tanlili",
    "gn:country_code":"BF",
    "gn:dem":328,
    "gn:feature_class":"P",
    "gn:feature_code":"PPL",
    "gn:name":"Tanlili",
    "gn:population":0,
    "gn:timezone":"Africa/Ouagadougou",
    "iso:country":"BF",
    "name:und_x_variant":[
        "Tanlilli",
        "Tanlili"
    ],
    "wof:name":"Tanlili",
    "wof:placetype":"locality"
},
  "geometry": {"coordinates":[-1.28333,12.76667],"type":"Point"}
}