{
  "type": "Feature",
  "properties": {
    "gn:admin1_code":"05",
    "gn:asciiname":"Tamse",
    "gn:country_code":"BF",
    "gn:dem":307,
    "gn:feature_class":"P",
    "gn:feature_code":"PPL",
    "gn:name":"Tams\u00e9",
    "gn:population":0,
    "gn:timezone":"Africa/Ouagadougou",
    "iso:country":"BF",
    "name:und_x_variant":[
        "Tamsen",
        "Tams\u00e9"
    ],
    "wof:name":"Tamse",
    "wof:placetype":"locality"
},
  "geometry": {"coordinates":[-1.01667,12.75],"type":"Point"}
}