{
  "type": "Feature",
  "properties": {
    "gn:admin1_code":"13",
    "gn:asciiname":"Diemoukourou",
    "gn:country_code":"BF",
    "gn:dem":257,
    "gn:feature_class":"P",
    "gn:feature_code":"PPL",
    "gn:name":"Di\u00e9moukourou",
    "gn:population":0,
    "gn:timezone":"Africa/Ouagadougou",
    "iso:country":"BF",
    "wof:name":"Diemoukourou",
    "wof:placetype":"locality"
},
  "geometry": {"coordinates":[-3.23333,10.76667],"type":"Point"}
}