{
  "type": "Feature",
  "properties": {
    "gn:admin1_code":"06",
    "gn:asciiname":"Mariou",
    "gn:country_code":"BF",
    "gn:dem":326,
    "gn:feature_class":"P",
    "gn:feature_code":"PPL",
    "gn:name":"Mariou",
    "gn:population":0,
    "gn:timezone":"Africa/Ouagadougou",
    "iso:country":"BF",
    "name:azb_x_preferred":[
        "\u0646\u0627\u0631\u06cc\u0648"
    ],
    "name:ceb_x_preferred":[
        "Mariou"
    ],
    "name:fas_x_preferred":[
        "\u0646\u0627\u0631\u06cc\u0648"
    ],
    "name:fra_x_preferred":[
        "Nariou"
    ],
    "name:und_x_variant":[
        "Nariou",
        "Mariou"
    ],
    "wof:name":"Mariou",
    "wof:placetype":"locality"
},
  "geometry": {"coordinates":[-2.15,12.08333],"type":"Point"}
}