{
  "type": "Feature",
  "properties": {
    "gn:admin1_code":"13",
    "gn:asciiname":"Diasara",
    "gn:country_code":"BF",
    "gn:dem":307,
    "gn:feature_class":"P",
    "gn:feature_code":"PPL",
    "gn:name":"Diasara",
    "gn:population":0,
    "gn:timezone":"Africa/Ouagadougou",
    "iso:country":"BF",
    "name:und_x_variant":[
        "Diassara",
        "Diasara"
    ],
    "wof:name":"Diasara",
    "wof:placetype":"locality"
},
  "geometry": {"coordinates":[-3.56667,10.68333],"type":"Point"}
}