{
  "type": "Feature",
  "properties": {
    "gn:admin1_code":"10",
    "gn:admin2_code":"76",
    "gn:asciiname":"Rassouli",
    "gn:country_code":"BF",
    "gn:dem":334,
    "gn:feature_class":"P",
    "gn:feature_code":"PPL",
    "gn:name":"Rassouli",
    "gn:population":0,
    "gn:timezone":"Africa/Ouagadougou",
    "iso:country":"BF",
    "name:und_x_variant":[
        "Dassouri",
        "Rassouli"
    ],
    "wof:name":"Rassouli",
    "wof:placetype":"locality"
},
  "geometry": {"coordinates":[-2.51516,13.29833],"type":"Point"}
}