{
  "type": "Feature",
  "properties": {
    "gn:admin1_code":"12",
    "gn:admin2_code":"71",
    "gn:asciiname":"Sakatemba",
    "gn:country_code":"BF",
    "gn:dem":273,
    "gn:feature_class":"P",
    "gn:feature_code":"PPL",
    "gn:name":"Sakat\u00e8mba",
    "gn:population":0,
    "gn:timezone":"Africa/Ouagadougou",
    "iso:country":"BF",
    "wof:name":"Sakatemba",
    "wof:placetype":"locality"
},
  "geometry": {"coordinates":[0.19647,13.69089],"type":"Point"}
}