{
  "type": "Feature",
  "properties": {
    "gn:admin1_code":"09",
    "gn:admin2_code":"51",
    "gn:asciiname":"Saouleni",
    "gn:country_code":"BF",
    "gn:dem":361,
    "gn:feature_class":"P",
    "gn:feature_code":"PPL",
    "gn:name":"Saoul\u00e9ni",
    "gn:population":0,
    "gn:timezone":"Africa/Ouagadougou",
    "iso:country":"BF",
    "wof:name":"Saouleni",
    "wof:placetype":"locality"
},
  "geometry": {"coordinates":[-4.30363,11.29322],"type":"Point"}
}