{
  "type": "Feature",
  "properties": {
    "gn:admin1_code":"02",
    "gn:asciiname":"Nafona",
    "gn:country_code":"BF",
    "gn:dem":312,
    "gn:feature_class":"P",
    "gn:feature_code":"PPL",
    "gn:name":"Nafona",
    "gn:population":0,
    "gn:timezone":"Africa/Ouagadougou",
    "iso:country":"BF",
    "name:ceb_x_preferred":[
        "Nafona"
    ],
    "name:fra_x_preferred":[
        "Nafona"
    ],
    "name:swe_x_preferred":[
        "Nafona"
    ],
    "wof:name":"Nafona",
    "wof:placetype":"locality"
},
  "geometry": {"coordinates":[-5.01667,10.25],"type":"Point"}
}