{
  "type": "Feature",
  "properties": {
    "gn:admin1_code":"05",
    "gn:admin2_code":"70",
    "gn:asciiname":"Koumnoro",
    "gn:country_code":"BF",
    "gn:dem":333,
    "gn:feature_class":"P",
    "gn:feature_code":"PPL",
    "gn:name":"Koumnoro",
    "gn:population":0,
    "gn:timezone":"Africa/Ouagadougou",
    "iso:country":"BF",
    "wof:name":"Koumnoro",
    "wof:placetype":"locality"
},
  "geometry": {"coordinates":[-1.23047,13.25914],"type":"Point"}
}