{
  "type": "Feature",
  "properties": {
    "gn:admin1_code":"01",
    "gn:admin2_code":"73",
    "gn:asciiname":"Bompela",
    "gn:country_code":"BF",
    "gn:dem":315,
    "gn:feature_class":"P",
    "gn:feature_code":"PPL",
    "gn:name":"Bomp\u00e9la",
    "gn:population":0,
    "gn:timezone":"Africa/Ouagadougou",
    "iso:country":"BF",
    "name:und_x_variant":[
        "Bonp\u00e9la",
        "Bomp\u00e9la"
    ],
    "wof:name":"Bompela",
    "wof:placetype":"locality"
},
  "geometry": {"coordinates":[-2.72473,13.12247],"type":"Point"}
}