{
  "type": "Feature",
  "properties": {
    "gn:admin1_code":"08",
    "gn:admin2_code":"50",
    "gn:asciiname":"Diabo",
    "gn:country_code":"BF",
    "gn:dem":314,
    "gn:feature_class":"P",
    "gn:feature_code":"PPL",
    "gn:name":"Diabo",
    "gn:population":0,
    "gn:timezone":"Africa/Ouagadougou",
    "iso:country":"BF",
    "name:deu_x_preferred":[
        "Diabo"
    ],
    "name:fra_x_preferred":[
        "Diabo"
    ],
    "name:ita_x_preferred":[
        "Diabo"
    ],
    "name:por_x_preferred":[
        "Diabo"
    ],
    "name:spa_x_preferred":[
        "Diabo"
    ],
    "name:vie_x_preferred":[
        "Diabo"
    ],
    "wof:name":"Diabo",
    "wof:placetype":"locality"
},
  "geometry": {"coordinates":[-0.03333,12.01667],"type":"Point"}
}