{
  "type": "Feature",
  "properties": {
    "gn:admin1_code":"12",
    "gn:admin2_code":"40",
    "gn:asciiname":"Dane Zao",
    "gn:country_code":"BF",
    "gn:dem":324,
    "gn:feature_class":"P",
    "gn:feature_code":"PPL",
    "gn:name":"Dan\u00e9 Zao",
    "gn:population":0,
    "gn:timezone":"Africa/Ouagadougou",
    "iso:country":"BF",
    "wof:name":"Dane Zao",
    "wof:placetype":"locality"
},
  "geometry": {"coordinates":[-0.90901,14.29617],"type":"Point"}
}