{
  "type": "Feature",
  "properties": {
    "gn:admin1_code":"01",
    "gn:asciiname":"Bourasso",
    "gn:country_code":"BF",
    "gn:dem":262,
    "gn:feature_class":"P",
    "gn:feature_code":"PPL",
    "gn:name":"Bourasso",
    "gn:population":0,
    "gn:timezone":"Africa/Ouagadougou",
    "iso:country":"BF",
    "name:deu_x_preferred":[
        "Bourasso"
    ],
    "name:fra_x_preferred":[
        "Bourasso"
    ],
    "name:ita_x_preferred":[
        "Bourasso"
    ],
    "name:spa_x_preferred":[
        "Bourasso"
    ],
    "name:und_x_variant":[
        "Burasso",
        "Bourasso"
    ],
    "name:vie_x_preferred":[
        "Bourasso"
    ],
    "name:zho_x_preferred":[
        "\u5e03\u62c9\u7d22\u7e23"
    ],
    "wof:name":"Bourasso",
    "wof:placetype":"locality"
},
  "geometry": {"coordinates":[-3.71667,12.63333],"type":"Point"}
}