{
  "type": "Feature",
  "properties": {
    "gn:admin1_code":"02",
    "gn:asciiname":"Naveninso",
    "gn:country_code":"BF",
    "gn:dem":330,
    "gn:feature_class":"P",
    "gn:feature_code":"PPL",
    "gn:name":"Nav\u00e9ninso",
    "gn:population":0,
    "gn:timezone":"Africa/Ouagadougou",
    "iso:country":"BF",
    "wof:name":"Naveninso",
    "wof:placetype":"locality"
},
  "geometry": {"coordinates":[-5.41667,10.53333],"type":"Point"}
}