{
  "type": "Feature",
  "properties": {
    "gn:admin1_code":"05",
    "gn:admin2_code":"70",
    "gn:asciiname":"Tamassogo",
    "gn:country_code":"BF",
    "gn:dem":308,
    "gn:feature_class":"P",
    "gn:feature_code":"PPL",
    "gn:name":"Tamassogo",
    "gn:population":0,
    "gn:timezone":"Africa/Ouagadougou",
    "iso:country":"BF",
    "wof:name":"Tamassogo",
    "wof:placetype":"locality"
},
  "geometry": {"coordinates":[-1.08571,13.27265],"type":"Point"}
}