{
  "type": "Feature",
  "properties": {
    "gn:admin1_code":"09",
    "gn:admin2_code":"54",
    "gn:asciiname":"Lanviera",
    "gn:country_code":"BF",
    "gn:dem":350,
    "gn:feature_class":"P",
    "gn:feature_code":"PPL",
    "gn:name":"Lanvi\u00e9ra",
    "gn:population":0,
    "gn:timezone":"Africa/Ouagadougou",
    "iso:country":"BF",
    "wof:name":"Lanviera",
    "wof:placetype":"locality"
},
  "geometry": {"coordinates":[-4.92466,11.27865],"type":"Point"}
}