{
  "type": "Feature",
  "properties": {
    "gn:admin1_code":"03",
    "gn:admin2_code":"53",
    "gn:asciiname":"Samben",
    "gn:country_code":"BF",
    "gn:dem":334,
    "gn:feature_class":"P",
    "gn:feature_code":"PPL",
    "gn:name":"Samben",
    "gn:population":0,
    "gn:timezone":"Africa/Ouagadougou",
    "iso:country":"BF",
    "name:und_x_variant":[
        "Sambin",
        "Samben"
    ],
    "wof:name":"Samben",
    "wof:placetype":"locality"
},
  "geometry": {"coordinates":[-1.73861,12.19528],"type":"Point"}
}