{
  "type": "Feature",
  "properties": {
    "gn:admin1_code":"09",
    "gn:asciiname":"Moussobadougou",
    "gn:country_code":"BF",
    "gn:dem":361,
    "gn:feature_class":"P",
    "gn:feature_code":"PPL",
    "gn:name":"Moussobadougou",
    "gn:population":0,
    "gn:timezone":"Africa/Ouagadougou",
    "iso:country":"BF",
    "wof:name":"Moussobadougou",
    "wof:placetype":"locality"
},
  "geometry": {"coordinates":[-4.33333,10.83333],"type":"Point"}
}