{
  "type": "Feature",
  "properties": {
    "gn:admin1_code":"10",
    "gn:asciiname":"Koulou",
    "gn:country_code":"BF",
    "gn:dem":298,
    "gn:feature_class":"P",
    "gn:feature_code":"PPL",
    "gn:name":"Koulou",
    "gn:population":0,
    "gn:timezone":"Africa/Ouagadougou",
    "iso:country":"BF",
    "name:fin_x_preferred":[
        "Koulou"
    ],
    "name:fra_x_preferred":[
        "Koulou"
    ],
    "name:ita_x_preferred":[
        "Koulou"
    ],
    "name:nld_x_preferred":[
        "Koulou"
    ],
    "name:spa_x_preferred":[
        "Koulou"
    ],
    "name:und_x_variant":[
        "Kulu",
        "Koulou"
    ],
    "wof:name":"Koulou",
    "wof:placetype":"locality"
},
  "geometry": {"coordinates":[-1.58333,12.96667],"type":"Point"}
}