{
  "type": "Feature",
  "properties": {
    "gn:admin1_code":"07",
    "gn:admin2_code":"47",
    "gn:asciiname":"Yelou",
    "gn:country_code":"BF",
    "gn:dem":312,
    "gn:feature_class":"P",
    "gn:feature_code":"PPL",
    "gn:name":"Y\u00e9lou",
    "gn:population":0,
    "gn:timezone":"Africa/Ouagadougou",
    "iso:country":"BF",
    "name:ceb_x_preferred":[
        "Y\u00e9lou"
    ],
    "name:deu_x_preferred":[
        "Y\u00e9lou"
    ],
    "name:ita_x_preferred":[
        "Yelou"
    ],
    "name:msa_x_preferred":[
        "Yelou"
    ],
    "name:ron_x_preferred":[
        "Yelou"
    ],
    "name:spa_x_preferred":[
        "Y\u00e9lou"
    ],
    "wof:name":"Yelou",
    "wof:placetype":"locality"
},
  "geometry": {"coordinates":[-1.72694,12.06528],"type":"Point"}
}