{
  "type": "Feature",
  "properties": {
    "gn:admin1_code":"01",
    "gn:admin2_code":"73",
    "gn:asciiname":"Toeni",
    "gn:country_code":"BF",
    "gn:dem":263,
    "gn:feature_class":"P",
    "gn:feature_code":"PPL",
    "gn:name":"To\u00e9ni",
    "gn:population":0,
    "gn:timezone":"Africa/Ouagadougou",
    "iso:country":"BF",
    "name:deu_x_preferred":[
        "To\u00e9ni"
    ],
    "name:fra_x_preferred":[
        "To\u00e9ni"
    ],
    "name:ita_x_preferred":[
        "To\u00e9ni"
    ],
    "name:spa_x_preferred":[
        "To\u00e9ni"
    ],
    "name:und_x_variant":[
        "T\u00e9n\u00e9",
        "To\u00e9ni"
    ],
    "name:vie_x_preferred":[
        "To\u00e9ni"
    ],
    "wof:name":"Toeni",
    "wof:placetype":"locality"
},
  "geometry": {"coordinates":[-3.2008,13.37993],"type":"Point"}
}