{
  "type": "Feature",
  "properties": {
    "gn:admin1_code":"13",
    "gn:asciiname":"Soroumboura",
    "gn:country_code":"BF",
    "gn:dem":345,
    "gn:feature_class":"P",
    "gn:feature_code":"PPL",
    "gn:name":"Soroumboura",
    "gn:population":0,
    "gn:timezone":"Africa/Ouagadougou",
    "iso:country":"BF",
    "wof:name":"Soroumboura",
    "wof:placetype":"locality"
},
  "geometry": {"coordinates":[-3.41667,10.15],"type":"Point"}
}