{
  "type": "Feature",
  "properties": {
    "gn:admin1_code":"01",
    "gn:admin2_code":"73",
    "gn:asciiname":"Gomboro",
    "gn:country_code":"BF",
    "gn:dem":309,
    "gn:feature_class":"P",
    "gn:feature_code":"PPL",
    "gn:name":"Gomboro",
    "gn:population":0,
    "gn:timezone":"Africa/Ouagadougou",
    "iso:country":"BF",
    "name:deu_x_preferred":[
        "Gomboro"
    ],
    "name:fra_x_preferred":[
        "Gomboro"
    ],
    "name:ita_x_preferred":[
        "Gomboro"
    ],
    "name:spa_x_preferred":[
        "Gomboro"
    ],
    "name:und_x_variant":[
        "Gondoro",
        "Gomdoro",
        "Gomboro"
    ],
    "name:vie_x_preferred":[
        "Gomboro"
    ],
    "wof:name":"Gomboro",
    "wof:placetype":"locality"
},
  "geometry": {"coordinates":[-2.77637,13.48457],"type":"Point"}
}