{
  "type": "Feature",
  "properties": {
    "gn:admin1_code":"01",
    "gn:asciiname":"Saran",
    "gn:country_code":"BF",
    "gn:dem":307,
    "gn:feature_class":"P",
    "gn:feature_code":"PPL",
    "gn:name":"Saran",
    "gn:population":0,
    "gn:timezone":"Africa/Ouagadougou",
    "iso:country":"BF",
    "name:ara_x_preferred":[
        "\u0633\u0627\u0631\u0627\u0646"
    ],
    "name:cat_x_preferred":[
        "Saran"
    ],
    "name:ceb_x_preferred":[
        "Saran"
    ],
    "name:deu_x_preferred":[
        "Saran"
    ],
    "name:fra_x_preferred":[
        "Saran"
    ],
    "name:ita_x_preferred":[
        "Saran"
    ],
    "name:jpn_x_preferred":[
        "\u30b5\u30e9\u30f3"
    ],
    "name:nld_x_preferred":[
        "Saran"
    ],
    "name:pol_x_preferred":[
        "Saran"
    ],
    "name:por_x_preferred":[
        "Saran"
    ],
    "name:spa_x_preferred":[
        "Saran"
    ],
    "name:swe_x_preferred":[
        "Saran"
    ],
    "name:und_x_variant":[
        "Sara"
    ],
    "wof:name":"Saran",
    "wof:placetype":"locality"
},
  "geometry": {"coordinates":[-2.96667,12.91667],"type":"Point"}
}