{
  "type": "Feature",
  "properties": {
    "gn:admin1_code":"10",
    "gn:admin2_code":"76",
    "gn:asciiname":"Boundoukamba",
    "gn:country_code":"BF",
    "gn:dem":304,
    "gn:feature_class":"P",
    "gn:feature_code":"PPL",
    "gn:name":"Boundoukamba",
    "gn:population":0,
    "gn:timezone":"Africa/Ouagadougou",
    "iso:country":"BF",
    "name:und_x_variant":[
        "Boundoukanba",
        "Boundoukamba"
    ],
    "wof:name":"Boundoukamba",
    "wof:placetype":"locality"
},
  "geometry": {"coordinates":[-2.62215,13.53836],"type":"Point"}
}