{
  "type": "Feature",
  "properties": {
    "gn:admin1_code":"12",
    "gn:admin2_code":"33",
    "gn:asciiname":"Deou",
    "gn:country_code":"BF",
    "gn:dem":327,
    "gn:feature_class":"P",
    "gn:feature_code":"PPLA3",
    "gn:name":"D\u00e9ou",
    "gn:population":0,
    "gn:timezone":"Africa/Ouagadougou",
    "iso:country":"BF",
    "name:und_x_variant":[
        "D\u00e9ou"
    ],
    "wof:name":"Deou",
    "wof:placetype":"locality"
},
  "geometry": {"coordinates":[-0.71901,14.60084],"type":"Point"}
}