{
  "type": "Feature",
  "properties": {
    "gn:admin1_code":"13",
    "gn:asciiname":"Gonbon",
    "gn:country_code":"BF",
    "gn:dem":311,
    "gn:feature_class":"P",
    "gn:feature_code":"PPL",
    "gn:name":"Gonbon",
    "gn:population":0,
    "gn:timezone":"Africa/Ouagadougou",
    "iso:country":"BF",
    "wof:name":"Gonbon",
    "wof:placetype":"locality"
},
  "geometry": {"coordinates":[-2.98333,10.26667],"type":"Point"}
}