{
  "type": "Feature",
  "properties": {
    "gn:admin1_code":"01",
    "gn:asciiname":"Goumbio",
    "gn:country_code":"BF",
    "gn:dem":262,
    "gn:feature_class":"P",
    "gn:feature_code":"PPL",
    "gn:name":"Goumbio",
    "gn:population":0,
    "gn:timezone":"Africa/Ouagadougou",
    "iso:country":"BF",
    "wof:name":"Goumbio",
    "wof:placetype":"locality"
},
  "geometry": {"coordinates":[-3.73333,12.46667],"type":"Point"}
}