{
  "type": "Feature",
  "properties": {
    "gn:admin1_code":"08",
    "gn:admin2_code":"42",
    "gn:asciiname":"Tongogoden",
    "gn:country_code":"BF",
    "gn:dem":227,
    "gn:feature_class":"P",
    "gn:feature_code":"PPL",
    "gn:name":"Tongogod\u00e8n",
    "gn:population":0,
    "gn:timezone":"Africa/Ouagadougou",
    "iso:country":"BF",
    "wof:name":"Tongogoden",
    "wof:placetype":"locality"
},
  "geometry": {"coordinates":[2.01736,12.63829],"type":"Point"}
}