{
  "type": "Feature",
  "properties": {
    "gn:admin1_code":"13",
    "gn:asciiname":"Koulinkouna",
    "gn:country_code":"BF",
    "gn:dem":289,
    "gn:feature_class":"P",
    "gn:feature_code":"PPL",
    "gn:name":"Koulinkouna",
    "gn:population":0,
    "gn:timezone":"Africa/Ouagadougou",
    "iso:country":"BF",
    "wof:name":"Koulinkouna",
    "wof:placetype":"locality"
},
  "geometry": {"coordinates":[-3.31667,10.41667],"type":"Point"}
}