{
  "type": "Feature",
  "properties": {
    "gn:admin1_code":"01",
    "gn:asciiname":"Sakala",
    "gn:country_code":"BF",
    "gn:dem":281,
    "gn:feature_class":"P",
    "gn:feature_code":"PPL",
    "gn:name":"Sakala",
    "gn:population":0,
    "gn:timezone":"Africa/Ouagadougou",
    "iso:country":"BF",
    "name:ceb_x_preferred":[
        "Sakala"
    ],
    "name:deu_x_preferred":[
        "Sakala"
    ],
    "name:est_x_preferred":[
        "Sakala"
    ],
    "name:glg_x_preferred":[
        "Sakala"
    ],
    "name:new_x_preferred":[
        "\u0938\u0915\u0932\u093e"
    ],
    "name:swe_x_preferred":[
        "Sakala"
    ],
    "name:und_x_variant":[
        "Sagala",
        "S\u00e9gala"
    ],
    "wof:name":"Sakala",
    "wof:placetype":"locality"
},
  "geometry": {"coordinates":[-3.53333,12.38333],"type":"Point"}
}