{
  "type": "Feature",
  "properties": {
    "gn:admin1_code":"02",
    "gn:asciiname":"Dapri",
    "gn:country_code":"BF",
    "gn:dem":360,
    "gn:feature_class":"P",
    "gn:feature_code":"PPL",
    "gn:name":"Dapri",
    "gn:population":0,
    "gn:timezone":"Africa/Ouagadougou",
    "iso:country":"BF",
    "wof:name":"Dapri",
    "wof:placetype":"locality"
},
  "geometry": {"coordinates":[-4.75,10.76667],"type":"Point"}
}