{
  "type": "Feature",
  "properties": {
    "gn:admin1_code":"11",
    "gn:asciiname":"Sodrotenga",
    "gn:country_code":"BF",
    "gn:dem":323,
    "gn:feature_class":"P",
    "gn:feature_code":"PPL",
    "gn:name":"Sodrotenga",
    "gn:population":0,
    "gn:timezone":"Africa/Ouagadougou",
    "iso:country":"BF",
    "wof:name":"Sodrotenga",
    "wof:placetype":"locality"
},
  "geometry": {"coordinates":[-1.81667,12.83333],"type":"Point"}
}