{
  "type": "Feature",
  "properties": {
    "gn:admin1_code":"09",
    "gn:admin2_code":"54",
    "gn:asciiname":"Ndana",
    "gn:country_code":"BF",
    "gn:dem":337,
    "gn:feature_class":"P",
    "gn:feature_code":"PPL",
    "gn:name":"Ndana",
    "gn:population":0,
    "gn:timezone":"Africa/Ouagadougou",
    "iso:country":"BF",
    "name:ceb_x_preferred":[
        "Ndana"
    ],
    "name:deu_x_preferred":[
        "Ndana"
    ],
    "name:swe_x_preferred":[
        "Ndana"
    ],
    "wof:name":"Ndana",
    "wof:placetype":"locality"
},
  "geometry": {"coordinates":[-4.70202,11.77784],"type":"Point"}
}