{
  "type": "Feature",
  "properties": {
    "gn:admin1_code":"10",
    "gn:admin2_code":"76",
    "gn:asciiname":"Rassomde",
    "gn:country_code":"BF",
    "gn:dem":312,
    "gn:feature_class":"P",
    "gn:feature_code":"PPL",
    "gn:name":"Rassomd\u00e9",
    "gn:population":0,
    "gn:timezone":"Africa/Ouagadougou",
    "iso:country":"BF",
    "name:und_x_variant":[
        "Rassomb\u00e9",
        "Rassomd\u00e9"
    ],
    "wof:name":"Rassomde",
    "wof:placetype":"locality"
},
  "geometry": {"coordinates":[-2.12836,13.17517],"type":"Point"}
}