{
  "type": "Feature",
  "properties": {
    "gn:admin1_code":"07",
    "gn:admin2_code":"47",
    "gn:asciiname":"Sokomtenga",
    "gn:country_code":"BF",
    "gn:dem":332,
    "gn:feature_class":"P",
    "gn:feature_code":"PPL",
    "gn:name":"Sokomtenga",
    "gn:population":0,
    "gn:timezone":"Africa/Ouagadougou",
    "iso:country":"BF",
    "wof:name":"Sokomtenga",
    "wof:placetype":"locality"
},
  "geometry": {"coordinates":[-1.38611,12.04389],"type":"Point"}
}