{
  "type": "Feature",
  "properties": {
    "gn:admin1_code":"09",
    "gn:asciiname":"Maro",
    "gn:country_code":"BF",
    "gn:dem":318,
    "gn:feature_class":"P",
    "gn:feature_code":"PPL",
    "gn:name":"Maro",
    "gn:population":0,
    "gn:timezone":"Africa/Ouagadougou",
    "iso:country":"BF",
    "name:ceb_x_preferred":[
        "Maro"
    ],
    "name:deu_x_preferred":[
        "Maro"
    ],
    "name:fra_x_preferred":[
        "Maro"
    ],
    "name:ita_x_preferred":[
        "Maro"
    ],
    "name:nld_x_preferred":[
        "Maro"
    ],
    "name:spa_x_preferred":[
        "Maro"
    ],
    "name:swe_x_preferred":[
        "Maro"
    ],
    "name:tgl_x_preferred":[
        "Maro"
    ],
    "wof:name":"Maro",
    "wof:placetype":"locality"
},
  "geometry": {"coordinates":[-3.81667,11.53333],"type":"Point"}
}