{
  "type": "Feature",
  "properties": {
    "iso:country":"BF",
    "name:deu_x_preferred":[
        "Bani"
    ],
    "name:eng_x_preferred":[
        "Bani"
    ],
    "name:fra_x_preferred":[
        "Dori"
    ],
    "name:ita_x_preferred":[
        "Bani"
    ],
    "name:nan_x_preferred":[
        "Bani"
    ],
    "name:nld_x_preferred":[
        "Bani"
    ],
    "name:unk_x_variant":[
        "Dani"
    ],
    "name:vie_x_preferred":[
        "Bani"
    ],
    "qs:gn_country":"BF",
    "qs:gn_fcode":"PPL",
    "qs:gn_pop":0,
    "qs:name":"Bani",
    "qs:name_adm0":"Burkina Faso",
    "qs:name_adm1":"Seno",
    "qs:photos":44,
    "qs:photos_1k":9,
    "qs:photos_9k":1,
    "qs:photos_9r":2,
    "qs:photos_all":44,
    "qs:photos_sr":2,
    "qs:placetype":"Town",
    "qs:pop_sr":"4",
    "qs:woe_adm0":23424978,
    "wof:name":"Bani",
    "wof:placetype":"locality"
},
  "geometry": {"coordinates":[-0.17222,13.72139],"type":"Point"}
}