{
  "type": "Feature",
  "properties": {
    "gn:admin1_code":"05",
    "gn:admin2_code":"70",
    "gn:asciiname":"Tebre",
    "gn:country_code":"BF",
    "gn:dem":310,
    "gn:feature_class":"P",
    "gn:feature_code":"PPL",
    "gn:name":"T\u00e9br\u00e9",
    "gn:population":0,
    "gn:timezone":"Africa/Ouagadougou",
    "iso:country":"BF",
    "name:und_x_variant":[
        "T\u00e9r\u00e9",
        "T\u00e9b\u00e9r\u00e9",
        "T\u00e9br\u00e9"
    ],
    "wof:name":"Tebre",
    "wof:placetype":"locality"
},
  "geometry": {"coordinates":[-0.71808,13.04145],"type":"Point"}
}