{
  "type": "Feature",
  "properties": {
    "gn:admin1_code":"10",
    "gn:asciiname":"Mia",
    "gn:country_code":"BF",
    "gn:dem":335,
    "gn:feature_class":"P",
    "gn:feature_code":"PPL",
    "gn:name":"Mia",
    "gn:population":0,
    "gn:timezone":"Africa/Ouagadougou",
    "iso:country":"BF",
    "name:ceb_x_preferred":[
        "Mia"
    ],
    "name:deu_x_preferred":[
        "Mia"
    ],
    "name:nld_x_preferred":[
        "Mia"
    ],
    "name:nor_x_preferred":[
        "Mia"
    ],
    "name:por_x_preferred":[
        "Mia"
    ],
    "name:tur_x_preferred":[
        "MIA"
    ],
    "wof:name":"Mia",
    "wof:placetype":"locality"
},
  "geometry": {"coordinates":[-2.05,12.85],"type":"Point"}
}