{
  "type": "Feature",
  "properties": {
    "gn:admin1_code":"05",
    "gn:admin2_code":"15",
    "gn:asciiname":"Roalaga",
    "gn:country_code":"BF",
    "gn:dem":309,
    "gn:feature_class":"P",
    "gn:feature_code":"PPL",
    "gn:name":"Roalaga",
    "gn:population":0,
    "gn:timezone":"Africa/Ouagadougou",
    "iso:country":"BF",
    "wof:name":"Roalaga",
    "wof:placetype":"locality"
},
  "geometry": {"coordinates":[-1.52561,13.52144],"type":"Point"}
}