{
  "type": "Feature",
  "properties": {
    "gn:admin1_code":"10",
    "gn:asciiname":"Toesse",
    "gn:country_code":"BF",
    "gn:dem":350,
    "gn:feature_class":"P",
    "gn:feature_code":"PPL",
    "gn:name":"To\u00e8ss\u00e9",
    "gn:population":0,
    "gn:timezone":"Africa/Ouagadougou",
    "iso:country":"BF",
    "wof:name":"Toesse",
    "wof:placetype":"locality"
},
  "geometry": {"coordinates":[-2.31667,12.93333],"type":"Point"}
}