{
  "type": "Feature",
  "properties": {
    "gn:admin1_code":"10",
    "gn:admin2_code":"76",
    "gn:asciiname":"Podebokou",
    "gn:country_code":"BF",
    "gn:dem":323,
    "gn:feature_class":"P",
    "gn:feature_code":"PPL",
    "gn:name":"Pod\u00e9bokou",
    "gn:population":0,
    "gn:timezone":"Africa/Ouagadougou",
    "iso:country":"BF",
    "wof:name":"Podebokou",
    "wof:placetype":"locality"
},
  "geometry": {"coordinates":[-2.08178,13.90579],"type":"Point"}
}