{
  "type": "Feature",
  "properties": {
    "gn:admin1_code":"08",
    "gn:admin2_code":"42",
    "gn:asciiname":"Pendyaga",
    "gn:country_code":"BF",
    "gn:dem":228,
    "gn:feature_class":"P",
    "gn:feature_code":"PPL",
    "gn:name":"Pendyaga",
    "gn:population":0,
    "gn:timezone":"Africa/Ouagadougou",
    "iso:country":"BF",
    "name:und_x_variant":[
        "P\u00e8ndiaga",
        "Pendyaga"
    ],
    "wof:name":"Pendyaga",
    "wof:placetype":"locality"
},
  "geometry": {"coordinates":[2.01234,12.56811],"type":"Point"}
}