{
  "type": "Feature",
  "properties": {
    "gn:admin1_code":"12",
    "gn:admin2_code":"75",
    "gn:asciiname":"Bosongri",
    "gn:country_code":"BF",
    "gn:dem":247,
    "gn:feature_class":"P",
    "gn:feature_code":"PPL",
    "gn:name":"Bosongri",
    "gn:population":0,
    "gn:timezone":"Africa/Ouagadougou",
    "iso:country":"BF",
    "wof:name":"Bosongri",
    "wof:placetype":"locality"
},
  "geometry": {"coordinates":[0.44823,13.31095],"type":"Point"}
}