{
  "type": "Feature",
  "properties": {
    "gn:admin1_code":"10",
    "gn:asciiname":"Tanse",
    "gn:country_code":"BF",
    "gn:dem":331,
    "gn:feature_class":"P",
    "gn:feature_code":"PPL",
    "gn:name":"Tans\u00e9",
    "gn:population":0,
    "gn:timezone":"Africa/Ouagadougou",
    "iso:country":"BF",
    "name:und_x_variant":[
        "Tansabelgo",
        "Tans\u00e9"
    ],
    "wof:name":"Tanse",
    "wof:placetype":"locality"
},
  "geometry": {"coordinates":[-1.81667,12.96667],"type":"Point"}
}