{
  "type": "Feature",
  "properties": {
    "gn:admin1_code":"12",
    "gn:admin2_code":"75",
    "gn:asciiname":"Tambondi",
    "gn:country_code":"BF",
    "gn:dem":255,
    "gn:feature_class":"P",
    "gn:feature_code":"PPL",
    "gn:name":"Tambondi",
    "gn:population":0,
    "gn:timezone":"Africa/Ouagadougou",
    "iso:country":"BF",
    "wof:name":"Tambondi",
    "wof:placetype":"locality"
},
  "geometry": {"coordinates":[0.569,13.40918],"type":"Point"}
}