{
  "type": "Feature",
  "properties": {
    "gn:admin1_code":"11",
    "gn:asciiname":"Gourango",
    "gn:country_code":"BF",
    "gn:dem":323,
    "gn:feature_class":"P",
    "gn:feature_code":"PPL",
    "gn:name":"Gourango",
    "gn:population":0,
    "gn:timezone":"Africa/Ouagadougou",
    "iso:country":"BF",
    "wof:name":"Gourango",
    "wof:placetype":"locality"
},
  "geometry": {"coordinates":[-2.05,12.31667],"type":"Point"}
}