{
  "type": "Feature",
  "properties": {
    "gn:admin1_code":"04",
    "gn:asciiname":"Liguidi Malgam",
    "gn:country_code":"BF",
    "gn:dem":277,
    "gn:feature_class":"P",
    "gn:feature_code":"PPL",
    "gn:name":"Liguidi Malgam",
    "gn:population":0,
    "gn:timezone":"Africa/Ouagadougou",
    "iso:country":"BF",
    "name:und_x_variant":[
        "Liguid Malgam",
        "Liguidi Malgam"
    ],
    "wof:name":"Liguidi Malgam",
    "wof:placetype":"locality"
},
  "geometry": {"coordinates":[-0.36667,12.06667],"type":"Point"}
}