{
  "type": "Feature",
  "properties": {
    "gn:admin1_code":"06",
    "gn:asciiname":"Niou",
    "gn:country_code":"BF",
    "gn:dem":303,
    "gn:feature_class":"P",
    "gn:feature_code":"PPL",
    "gn:name":"Niou",
    "gn:population":0,
    "gn:timezone":"Africa/Ouagadougou",
    "iso:country":"BF",
    "wof:name":"Niou",
    "wof:placetype":"locality"
},
  "geometry": {"coordinates":[-2.23333,11.75],"type":"Point"}
}