{
  "type": "Feature",
  "properties": {
    "gn:admin1_code":"10",
    "gn:asciiname":"Pousyanga",
    "gn:country_code":"BF",
    "gn:dem":323,
    "gn:feature_class":"P",
    "gn:feature_code":"PPL",
    "gn:name":"Pousyanga",
    "gn:population":0,
    "gn:timezone":"Africa/Ouagadougou",
    "iso:country":"BF",
    "name:und_x_variant":[
        "Pousgnangden",
        "Pousyanga",
        "Poussyanga"
    ],
    "wof:name":"Pousyanga",
    "wof:placetype":"locality"
},
  "geometry": {"coordinates":[-1.96667,12.81667],"type":"Point"}
}