{
  "type": "Feature",
  "properties": {
    "gn:admin1_code":"09",
    "gn:admin2_code":"51",
    "gn:asciiname":"Dande",
    "gn:country_code":"BF",
    "gn:dem":322,
    "gn:feature_class":"P",
    "gn:feature_code":"PPL",
    "gn:name":"Dand\u00e9",
    "gn:population":0,
    "gn:timezone":"Africa/Ouagadougou",
    "iso:country":"BF",
    "name:cat_x_preferred":[
        "Dande"
    ],
    "name:deu_x_preferred":[
        "Dande"
    ],
    "name:frr_x_preferred":[
        "Dande"
    ],
    "name:ita_x_preferred":[
        "Dande"
    ],
    "name:por_x_preferred":[
        "Dande"
    ],
    "wof:name":"Dande",
    "wof:placetype":"locality"
},
  "geometry": {"coordinates":[-4.5611,11.58479],"type":"Point"}
}