{
  "type": "Feature",
  "properties": {
    "gn:admin1_code":"04",
    "gn:admin2_code":"59",
    "gn:asciiname":"Yonde",
    "gn:country_code":"BF",
    "gn:dem":298,
    "gn:feature_class":"P",
    "gn:feature_code":"PPL",
    "gn:name":"Yond\u00e9",
    "gn:population":0,
    "gn:timezone":"Africa/Ouagadougou",
    "iso:country":"BF",
    "name:deu_x_preferred":[
        "Yond\u00e9"
    ],
    "name:fra_x_preferred":[
        "Yond\u00e9"
    ],
    "name:ita_x_preferred":[
        "Yond\u00e9"
    ],
    "name:spa_x_preferred":[
        "Yond\u00e9"
    ],
    "name:und_x_variant":[
        "Yond\u00e9"
    ],
    "name:urd_x_preferred":[
        "\u06cc\u0648\u0646\u062f\u06d2 \u0688\u06cc\u067e\u0627\u0631\u0679\u0645\u0646\u0679"
    ],
    "name:vie_x_preferred":[
        "Yond\u00e9"
    ],
    "wof:name":"Yonde",
    "wof:placetype":"locality"
},
  "geometry": {"coordinates":[0.14667,11.49472],"type":"Point"}
}