{
  "type": "Feature",
  "properties": {
    "gn:admin1_code":"13",
    "gn:asciiname":"Tessepe",
    "gn:country_code":"BF",
    "gn:dem":290,
    "gn:feature_class":"P",
    "gn:feature_code":"PPL",
    "gn:name":"Tess\u00e9pe",
    "gn:population":0,
    "gn:timezone":"Africa/Ouagadougou",
    "iso:country":"BF",
    "wof:name":"Tessepe",
    "wof:placetype":"locality"
},
  "geometry": {"coordinates":[-2.98333,10.48333],"type":"Point"}
}