{
  "type": "Feature",
  "properties": {
    "gn:admin1_code":"09",
    "gn:admin2_code":"51",
    "gn:asciiname":"Sangoulema",
    "gn:country_code":"BF",
    "gn:dem":304,
    "gn:feature_class":"P",
    "gn:feature_code":"PPL",
    "gn:name":"Sangoul\u00e9ma",
    "gn:population":0,
    "gn:timezone":"Africa/Ouagadougou",
    "iso:country":"BF",
    "name:und_x_variant":[
        "Bougoul\u00e9ma",
        "Sougoul\u00e9ma",
        "Sangou\u00e9lema",
        "Sangoul\u00e9ma"
    ],
    "wof:name":"Sangoulema",
    "wof:placetype":"locality"
},
  "geometry": {"coordinates":[-4.50008,11.38866],"type":"Point"}
}