{
  "type": "Feature",
  "properties": {
    "gn:admin1_code":"09",
    "gn:asciiname":"Zabo",
    "gn:country_code":"BF",
    "gn:dem":313,
    "gn:feature_class":"P",
    "gn:feature_code":"PPL",
    "gn:name":"Zabo",
    "gn:population":0,
    "gn:timezone":"Africa/Ouagadougou",
    "iso:country":"BF",
    "wof:name":"Zabo",
    "wof:placetype":"locality"
},
  "geometry": {"coordinates":[-3.85,11.36667],"type":"Point"}
}