{
  "type": "Feature",
  "properties": {
    "gn:admin1_code":"12",
    "gn:admin2_code":"40",
    "gn:asciiname":"Gassiliki",
    "gn:country_code":"BF",
    "gn:dem":301,
    "gn:feature_class":"P",
    "gn:feature_code":"PPL",
    "gn:name":"Gassiliki",
    "gn:population":0,
    "gn:timezone":"Africa/Ouagadougou",
    "iso:country":"BF",
    "wof:name":"Gassiliki",
    "wof:placetype":"locality"
},
  "geometry": {"coordinates":[-0.95813,14.00508],"type":"Point"}
}