{
  "type": "Feature",
  "properties": {
    "gn:admin1_code":"13",
    "gn:asciiname":"Nibetion",
    "gn:country_code":"BF",
    "gn:dem":241,
    "gn:feature_class":"P",
    "gn:feature_code":"PPL",
    "gn:name":"Nib\u00e9tion",
    "gn:population":0,
    "gn:timezone":"Africa/Ouagadougou",
    "iso:country":"BF",
    "wof:name":"Nibetion",
    "wof:placetype":"locality"
},
  "geometry": {"coordinates":[-2.81667,10.11667],"type":"Point"}
}