{
  "type": "Feature",
  "properties": {
    "gn:admin1_code":"12",
    "gn:admin2_code":"71",
    "gn:asciiname":"Nobwel",
    "gn:country_code":"BF",
    "gn:dem":276,
    "gn:feature_class":"P",
    "gn:feature_code":"PPL",
    "gn:name":"Nobw\u00e8l",
    "gn:population":0,
    "gn:timezone":"Africa/Ouagadougou",
    "iso:country":"BF",
    "name:und_x_variant":[
        "Nobieul",
        "Nobw\u00e8l"
    ],
    "wof:name":"Nobwel",
    "wof:placetype":"locality"
},
  "geometry": {"coordinates":[-0.31227,14.02096],"type":"Point"}
}