{
  "type": "Feature",
  "properties": {
    "gn:admin1_code":"01",
    "gn:admin2_code":"73",
    "gn:asciiname":"Boule",
    "gn:country_code":"BF",
    "gn:dem":317,
    "gn:feature_class":"P",
    "gn:feature_code":"PPL",
    "gn:name":"Boul\u00e9",
    "gn:population":0,
    "gn:timezone":"Africa/Ouagadougou",
    "iso:country":"BF",
    "wof:name":"Boule",
    "wof:placetype":"locality"
},
  "geometry": {"coordinates":[-2.87243,13.39078],"type":"Point"}
}