{
  "type": "Feature",
  "properties": {
    "gn:admin1_code":"09",
    "gn:asciiname":"Sianikoui",
    "gn:country_code":"BF",
    "gn:dem":343,
    "gn:feature_class":"P",
    "gn:feature_code":"PPL",
    "gn:name":"Sianikoui",
    "gn:population":0,
    "gn:timezone":"Africa/Ouagadougou",
    "iso:country":"BF",
    "wof:name":"Sianikoui",
    "wof:placetype":"locality"
},
  "geometry": {"coordinates":[-3.55,11.53333],"type":"Point"}
}