{
  "type": "Feature",
  "properties": {
    "gn:admin1_code":"12",
    "gn:admin2_code":"40",
    "gn:asciiname":"Gamtiki",
    "gn:country_code":"BF",
    "gn:dem":319,
    "gn:feature_class":"P",
    "gn:feature_code":"PPL",
    "gn:name":"Gamtiki",
    "gn:population":0,
    "gn:timezone":"Africa/Ouagadougou",
    "iso:country":"BF",
    "wof:name":"Gamtiki",
    "wof:placetype":"locality"
},
  "geometry": {"coordinates":[-1.13805,14.28279],"type":"Point"}
}