{
  "type": "Feature",
  "properties": {
    "gn:admin1_code":"01",
    "gn:admin2_code":"58",
    "gn:asciiname":"Touma",
    "gn:country_code":"BF",
    "gn:dem":438,
    "gn:feature_class":"P",
    "gn:feature_code":"PPL",
    "gn:name":"Touma",
    "gn:population":0,
    "gn:timezone":"Africa/Ouagadougou",
    "iso:country":"BF",
    "name:und_x_variant":[
        "Toma",
        "Touma"
    ],
    "wof:name":"Touma",
    "wof:placetype":"locality"
},
  "geometry": {"coordinates":[-4.4015,12.6415],"type":"Point"}
}