{
  "type": "Feature",
  "properties": {
    "gn:admin1_code":"03",
    "gn:admin2_code":"53",
    "gn:asciiname":"Peodogo",
    "gn:country_code":"BF",
    "gn:dem":301,
    "gn:feature_class":"P",
    "gn:feature_code":"PPL",
    "gn:name":"P\u00e9odogo",
    "gn:population":0,
    "gn:timezone":"Africa/Ouagadougou",
    "iso:country":"BF",
    "wof:name":"Peodogo",
    "wof:placetype":"locality"
},
  "geometry": {"coordinates":[-1.3525,12.29833],"type":"Point"}
}