{
  "type": "Feature",
  "properties": {
    "gn:admin1_code":"12",
    "gn:admin2_code":"40",
    "gn:asciiname":"Diguel",
    "gn:country_code":"BF",
    "gn:dem":298,
    "gn:feature_class":"P",
    "gn:feature_code":"PPL",
    "gn:name":"Digu\u00e9l",
    "gn:population":0,
    "gn:timezone":"Africa/Ouagadougou",
    "iso:country":"BF",
    "name:und_x_variant":[
        "Digguiel",
        "Digu\u00e9l"
    ],
    "wof:name":"Diguel",
    "wof:placetype":"locality"
},
  "geometry": {"coordinates":[-1.51309,14.0371],"type":"Point"}
}