{
  "type": "Feature",
  "properties": {
    "gn:admin1_code":"03",
    "gn:asciiname":"Bangre",
    "gn:country_code":"BF",
    "gn:dem":304,
    "gn:feature_class":"P",
    "gn:feature_code":"PPL",
    "gn:name":"Bangr\u00e9",
    "gn:population":0,
    "gn:timezone":"Africa/Ouagadougou",
    "iso:country":"BF",
    "name:ara_x_preferred":[
        "\u0628\u0627\u0646\u063a\u0631\u064a"
    ],
    "name:ceb_x_preferred":[
        "Bangre"
    ],
    "name:fra_x_preferred":[
        "Bangre"
    ],
    "name:msa_x_preferred":[
        "Bangre"
    ],
    "name:nep_x_preferred":[
        "\u092c\u093e\u0901\u0917\u094d\u0930\u0947"
    ],
    "name:new_x_preferred":[
        "\u092c\u093e\u0902\u0917\u094d\u0930\u0947"
    ],
    "name:pol_x_preferred":[
        "Bangre"
    ],
    "name:und_x_variant":[
        "Baran\u00e9",
        "Bangr\u00e9"
    ],
    "wof:name":"Bangre",
    "wof:placetype":"locality"
},
  "geometry": {"coordinates":[-1.32833,12.15389],"type":"Point"}
}