{
  "type": "Feature",
  "properties": {
    "gn:admin1_code":"03",
    "gn:asciiname":"Bangre",
    "gn:country_code":"BF",
    "gn:dem":304,
    "gn:feature_class":"P",
    "gn:feature_code":"PPL",
    "gn:name":"Bangr\u00e9",
    "gn:population":0,
    "gn:timezone":"Africa/Ouagadougou",
    "iso:country":"BF",
    "name:und_x_variant":[
        "Baran\u00e9",
        "Bangr\u00e9"
    ],
    "wof:name":"Bangre",
    "wof:placetype":"locality"
},
  "geometry": {"coordinates":[-1.32833,12.15389],"type":"Point"}
}