{
  "type": "Feature",
  "properties": {
    "gn:admin1_code":"11",
    "gn:asciiname":"Silmyougou",
    "gn:country_code":"BF",
    "gn:dem":292,
    "gn:feature_class":"P",
    "gn:feature_code":"PPL",
    "gn:name":"Silmyougou",
    "gn:population":0,
    "gn:timezone":"Africa/Ouagadougou",
    "iso:country":"BF",
    "name:und_x_variant":[
        "Silmiougou",
        "Silmyougou"
    ],
    "wof:name":"Silmyougou",
    "wof:placetype":"locality"
},
  "geometry": {"coordinates":[-1.46667,12.63333],"type":"Point"}
}