{
  "type": "Feature",
  "properties": {
    "gn:admin1_code":"12",
    "gn:admin2_code":"75",
    "gn:asciiname":"Marsila",
    "gn:country_code":"BF",
    "gn:dem":253,
    "gn:feature_class":"P",
    "gn:feature_code":"PPL",
    "gn:name":"Marsila",
    "gn:population":0,
    "gn:timezone":"Africa/Ouagadougou",
    "iso:country":"BF",
    "name:und_x_variant":[
        "Mansila",
        "Marsila"
    ],
    "wof:name":"Marsila",
    "wof:placetype":"locality"
},
  "geometry": {"coordinates":[0.63743,13.15996],"type":"Point"}
}