{
  "type": "Feature",
  "properties": {
    "gn:admin1_code":"04",
    "gn:asciiname":"Koulouoko",
    "gn:country_code":"BF",
    "gn:dem":279,
    "gn:feature_class":"P",
    "gn:feature_code":"PPL",
    "gn:name":"Koulouoko",
    "gn:population":0,
    "gn:timezone":"Africa/Ouagadougou",
    "iso:country":"BF",
    "wof:name":"Koulouoko",
    "wof:placetype":"locality"
},
  "geometry": {"coordinates":[-0.35,12.01667],"type":"Point"}
}