{
  "type": "Feature",
  "properties": {
    "gn:admin1_code":"01",
    "gn:asciiname":"Zouma",
    "gn:country_code":"BF",
    "gn:dem":276,
    "gn:feature_class":"P",
    "gn:feature_code":"PPL",
    "gn:name":"Zouma",
    "gn:population":0,
    "gn:timezone":"Africa/Ouagadougou",
    "iso:country":"BF",
    "name:ceb_x_preferred":[
        "Zouma"
    ],
    "name:deu_x_preferred":[
        "Zouma"
    ],
    "name:fra_x_preferred":[
        "Zouma"
    ],
    "name:swe_x_preferred":[
        "Zouma"
    ],
    "wof:name":"Zouma",
    "wof:placetype":"locality"
},
  "geometry": {"coordinates":[-2.91667,12.66667],"type":"Point"}
}