{
  "type": "Feature",
  "properties": {
    "gn:admin1_code":"04",
    "gn:asciiname":"Tankwense",
    "gn:country_code":"BF",
    "gn:dem":296,
    "gn:feature_class":"P",
    "gn:feature_code":"PPL",
    "gn:name":"Tankwens\u00e9",
    "gn:population":0,
    "gn:timezone":"Africa/Ouagadougou",
    "iso:country":"BF",
    "wof:name":"Tankwense",
    "wof:placetype":"locality"
},
  "geometry": {"coordinates":[-0.48333,12.41667],"type":"Point"}
}