{
  "type": "Feature",
  "properties": {
    "gn:admin1_code":"01",
    "gn:asciiname":"Da",
    "gn:country_code":"BF",
    "gn:dem":300,
    "gn:feature_class":"P",
    "gn:feature_code":"PPL",
    "gn:name":"Da",
    "gn:population":0,
    "gn:timezone":"Africa/Ouagadougou",
    "iso:country":"BF",
    "wof:name":"Da",
    "wof:placetype":"locality"
},
  "geometry": {"coordinates":[-3.15,12.03333],"type":"Point"}
}