{
  "type": "Feature",
  "properties": {
    "gn:admin1_code":"08",
    "gn:asciiname":"Daboura",
    "gn:country_code":"BF",
    "gn:dem":281,
    "gn:feature_class":"P",
    "gn:feature_code":"PPL",
    "gn:name":"Daboura",
    "gn:population":0,
    "gn:timezone":"Africa/Ouagadougou",
    "iso:country":"BF",
    "wof:name":"Daboura",
    "wof:placetype":"locality"
},
  "geometry": {"coordinates":[0.76667,12.61667],"type":"Point"}
}