{
  "type": "Feature",
  "properties": {
    "gn:admin1_code":"03",
    "gn:admin2_code":"53",
    "gn:asciiname":"Kounda",
    "gn:country_code":"BF",
    "gn:dem":284,
    "gn:feature_class":"P",
    "gn:feature_code":"PPL",
    "gn:name":"Kounda",
    "gn:population":0,
    "gn:timezone":"Africa/Ouagadougou",
    "iso:country":"BF",
    "name:azb_x_preferred":[
        "\u06a9\u0648\u0646\u062f\u0627"
    ],
    "name:ceb_x_preferred":[
        "Kounda"
    ],
    "name:fas_x_preferred":[
        "\u06a9\u0648\u0646\u062f\u0627"
    ],
    "name:swe_x_preferred":[
        "Kounda"
    ],
    "name:und_x_variant":[
        "Koanda",
        "Kounda"
    ],
    "wof:name":"Kounda",
    "wof:placetype":"locality"
},
  "geometry": {"coordinates":[-1.39222,12.43139],"type":"Point"}
}