{
  "type": "Feature",
  "properties": {
    "gn:admin1_code":"02",
    "gn:asciiname":"Moussoumourou",
    "gn:country_code":"BF",
    "gn:dem":304,
    "gn:feature_class":"P",
    "gn:feature_code":"PPL",
    "gn:name":"Moussoumourou",
    "gn:population":0,
    "gn:timezone":"Africa/Ouagadougou",
    "iso:country":"BF",
    "name:ceb_x_preferred":[
        "Moussoumourou"
    ],
    "name:fra_x_preferred":[
        "Moussoumourou"
    ],
    "name:por_x_preferred":[
        "Moussoumourou"
    ],
    "name:swe_x_preferred":[
        "Moussoumourou"
    ],
    "name:und_x_variant":[
        "Mousoumourou",
        "Moussoumourou"
    ],
    "wof:name":"Moussoumourou",
    "wof:placetype":"locality"
},
  "geometry": {"coordinates":[-4.43717,10.59998],"type":"Point"}
}