{
  "type": "Feature",
  "properties": {
    "gn:admin1_code":"07",
    "gn:asciiname":"Goulouga",
    "gn:country_code":"BF",
    "gn:dem":282,
    "gn:feature_class":"P",
    "gn:feature_code":"PPL",
    "gn:name":"Goulouga",
    "gn:population":0,
    "gn:timezone":"Africa/Ouagadougou",
    "iso:country":"BF",
    "wof:name":"Goulouga",
    "wof:placetype":"locality"
},
  "geometry": {"coordinates":[-0.76667,11.36667],"type":"Point"}
}