{
  "type": "Feature",
  "properties": {
    "gn:admin1_code":"11",
    "gn:admin2_code":"60",
    "gn:asciiname":"Tyenpalogo",
    "gn:country_code":"BF",
    "gn:dem":311,
    "gn:feature_class":"P",
    "gn:feature_code":"PPL",
    "gn:name":"Tyenpalogo",
    "gn:population":0,
    "gn:timezone":"Africa/Ouagadougou",
    "iso:country":"BF",
    "name:und_x_variant":[
        "Tiendpalgo",
        "Tyenpalogo",
        "Tiempalogo"
    ],
    "wof:name":"Tyenpalogo",
    "wof:placetype":"locality"
},
  "geometry": {"coordinates":[-1.73083,12.65556],"type":"Point"}
}