{
  "type": "Feature",
  "properties": {
    "gn:admin1_code":"01",
    "gn:admin2_code":"58",
    "gn:asciiname":"Bin",
    "gn:country_code":"BF",
    "gn:dem":313,
    "gn:feature_class":"P",
    "gn:feature_code":"PPL",
    "gn:name":"Bin",
    "gn:population":0,
    "gn:timezone":"Africa/Ouagadougou",
    "iso:country":"BF",
    "wof:name":"Bin",
    "wof:placetype":"locality"
},
  "geometry": {"coordinates":[-4.13333,12.03333],"type":"Point"}
}