{
  "type": "Feature",
  "properties": {
    "gn:admin1_code":"08",
    "gn:asciiname":"Diaboandi",
    "gn:country_code":"BF",
    "gn:dem":201,
    "gn:feature_class":"P",
    "gn:feature_code":"PPL",
    "gn:name":"Diaboandi",
    "gn:population":0,
    "gn:timezone":"Africa/Ouagadougou",
    "iso:country":"BF",
    "wof:name":"Diaboandi",
    "wof:placetype":"locality"
},
  "geometry": {"coordinates":[1.51667,11.58333],"type":"Point"}
}