{
  "type": "Feature",
  "properties": {
    "gn:admin1_code":"07",
    "gn:asciiname":"Yorogo",
    "gn:country_code":"BF",
    "gn:dem":330,
    "gn:feature_class":"P",
    "gn:feature_code":"PPL",
    "gn:name":"Yorogo",
    "gn:population":0,
    "gn:timezone":"Africa/Ouagadougou",
    "iso:country":"BF",
    "wof:name":"Yorogo",
    "wof:placetype":"locality"
},
  "geometry": {"coordinates":[-1.31667,11.95],"type":"Point"}
}