{
  "type": "Feature",
  "properties": {
    "gn:admin1_code":"02",
    "gn:asciiname":"Yetolo",
    "gn:country_code":"BF",
    "gn:dem":314,
    "gn:feature_class":"P",
    "gn:feature_code":"PPL",
    "gn:name":"Y\u00e9tolo",
    "gn:population":0,
    "gn:timezone":"Africa/Ouagadougou",
    "iso:country":"BF",
    "wof:name":"Yetolo",
    "wof:placetype":"locality"
},
  "geometry": {"coordinates":[-5.38333,10.55],"type":"Point"}
}