{
  "type": "Feature",
  "properties": {
    "gn:admin1_code":"11",
    "gn:asciiname":"Saberen",
    "gn:country_code":"BF",
    "gn:dem":325,
    "gn:feature_class":"P",
    "gn:feature_code":"PPL",
    "gn:name":"Sab\u00e9ren",
    "gn:population":0,
    "gn:timezone":"Africa/Ouagadougou",
    "iso:country":"BF",
    "name:und_x_variant":[
        "Sab\u00e9ren",
        "Sab\u00e9rin"
    ],
    "wof:name":"Saberen",
    "wof:placetype":"locality"
},
  "geometry": {"coordinates":[-1.78333,12.75],"type":"Point"}
}