{
  "type": "Feature",
  "properties": {
    "gn:admin1_code":"05",
    "gn:admin2_code":"15",
    "gn:asciiname":"Rouko Foulbes",
    "gn:country_code":"BF",
    "gn:dem":321,
    "gn:feature_class":"P",
    "gn:feature_code":"PPL",
    "gn:name":"Rouko Foulb\u00e9s",
    "gn:population":0,
    "gn:timezone":"Africa/Ouagadougou",
    "iso:country":"BF",
    "wof:name":"Rouko Foulbes",
    "wof:placetype":"locality"
},
  "geometry": {"coordinates":[-1.68455,13.20621],"type":"Point"}
}