{
  "type": "Feature",
  "properties": {
    "gn:admin1_code":"09",
    "gn:admin2_code":"54",
    "gn:asciiname":"Ngorolaba",
    "gn:country_code":"BF",
    "gn:dem":327,
    "gn:feature_class":"P",
    "gn:feature_code":"PPL",
    "gn:name":"Ngorolaba",
    "gn:population":0,
    "gn:timezone":"Africa/Ouagadougou",
    "iso:country":"BF",
    "name:deu_x_preferred":[
        "Morolaba"
    ],
    "name:fra_x_preferred":[
        "Morolaba"
    ],
    "name:ita_x_preferred":[
        "Morolaba"
    ],
    "name:spa_x_preferred":[
        "Morolaba"
    ],
    "name:und_x_variant":[
        "Morotaba",
        "Ngorolaba"
    ],
    "name:vie_x_preferred":[
        "Morolaba"
    ],
    "wof:name":"Ngorolaba",
    "wof:placetype":"locality"
},
  "geometry": {"coordinates":[-5.01919,11.90111],"type":"Point"}
}