{
  "type": "Feature",
  "properties": {
    "gn:admin1_code":"01",
    "gn:asciiname":"Bissa",
    "gn:country_code":"BF",
    "gn:dem":351,
    "gn:feature_class":"P",
    "gn:feature_code":"PPL",
    "gn:name":"Bissa",
    "gn:population":0,
    "gn:timezone":"Africa/Ouagadougou",
    "iso:country":"BF",
    "wof:name":"Bissa",
    "wof:placetype":"locality"
},
  "geometry": {"coordinates":[-3.45,11.91667],"type":"Point"}
}