{
  "type": "Feature",
  "properties": {
    "gn:admin1_code":"01",
    "gn:asciiname":"Bissa",
    "gn:country_code":"BF",
    "gn:dem":351,
    "gn:feature_class":"P",
    "gn:feature_code":"PPL",
    "gn:name":"Bissa",
    "gn:population":0,
    "gn:timezone":"Africa/Ouagadougou",
    "iso:country":"BF",
    "name:azb_x_preferred":[
        "\u0628\u06cc\u0633\u0627"
    ],
    "name:ceb_x_preferred":[
        "Bissa"
    ],
    "name:fas_x_preferred":[
        "\u0628\u06cc\u0633\u0627"
    ],
    "name:fra_x_preferred":[
        "Bissa"
    ],
    "name:swe_x_preferred":[
        "Bissa"
    ],
    "wof:name":"Bissa",
    "wof:placetype":"locality"
},
  "geometry": {"coordinates":[-3.45,11.91667],"type":"Point"}
}