{
  "type": "Feature",
  "properties": {
    "gn:admin1_code":"05",
    "gn:asciiname":"Leba",
    "gn:country_code":"BF",
    "gn:dem":310,
    "gn:feature_class":"P",
    "gn:feature_code":"PPL",
    "gn:name":"L\u00e9ba",
    "gn:population":0,
    "gn:timezone":"Africa/Ouagadougou",
    "iso:country":"BF",
    "name:ceb_x_preferred":[
        "Leba"
    ],
    "name:deu_x_preferred":[
        "Leba"
    ],
    "name:ita_x_preferred":[
        "Leba"
    ],
    "name:srp_x_preferred":[
        "\u041b\u0435\u0431\u0430"
    ],
    "name:swe_x_preferred":[
        "Leba"
    ],
    "wof:name":"Leba",
    "wof:placetype":"locality"
},
  "geometry": {"coordinates":[-0.86667,12.65],"type":"Point"}
}