{
  "type": "Feature",
  "properties": {
    "gn:admin1_code":"08",
    "gn:admin2_code":"42",
    "gn:asciiname":"Kinyanga",
    "gn:country_code":"BF",
    "gn:dem":254,
    "gn:feature_class":"P",
    "gn:feature_code":"PPL",
    "gn:name":"Kinyanga",
    "gn:population":0,
    "gn:timezone":"Africa/Ouagadougou",
    "iso:country":"BF",
    "wof:name":"Kinyanga",
    "wof:placetype":"locality"
},
  "geometry": {"coordinates":[2.01553,12.43132],"type":"Point"}
}