{
  "type": "Feature",
  "properties": {
    "gn:admin1_code":"03",
    "gn:admin2_code":"53",
    "gn:asciiname":"Lilboure",
    "gn:country_code":"BF",
    "gn:dem":305,
    "gn:feature_class":"P",
    "gn:feature_code":"PPL",
    "gn:name":"Lilbour\u00e9",
    "gn:population":0,
    "gn:timezone":"Africa/Ouagadougou",
    "iso:country":"BF",
    "wof:name":"Lilboure",
    "wof:placetype":"locality"
},
  "geometry": {"coordinates":[-1.47111,12.24667],"type":"Point"}
}