{
  "type": "Feature",
  "properties": {
    "gn:admin1_code":"10",
    "gn:asciiname":"La",
    "gn:country_code":"BF",
    "gn:dem":300,
    "gn:feature_class":"P",
    "gn:feature_code":"PPL",
    "gn:name":"La",
    "gn:population":0,
    "gn:timezone":"Africa/Ouagadougou",
    "iso:country":"BF",
    "name:fas_x_preferred":[
        "\u0644\u0627"
    ],
    "name:glg_x_preferred":[
        "La"
    ],
    "wof:name":"La",
    "wof:placetype":"locality"
},
  "geometry": {"coordinates":[-2.45,12.88333],"type":"Point"}
}