{
  "type": "Feature",
  "properties": {
    "gn:admin1_code":"10",
    "gn:admin2_code":"76",
    "gn:asciiname":"Wagara",
    "gn:country_code":"BF",
    "gn:dem":330,
    "gn:feature_class":"P",
    "gn:feature_code":"PPL",
    "gn:name":"Wagara",
    "gn:population":0,
    "gn:timezone":"Africa/Ouagadougou",
    "iso:country":"BF",
    "wof:name":"Wagara",
    "wof:placetype":"locality"
},
  "geometry": {"coordinates":[-2.57548,13.89051],"type":"Point"}
}