{
  "type": "Feature",
  "properties": {
    "gn:admin1_code":"10",
    "gn:admin2_code":"76",
    "gn:asciiname":"Yeribou",
    "gn:country_code":"BF",
    "gn:dem":308,
    "gn:feature_class":"P",
    "gn:feature_code":"PPL",
    "gn:name":"Y\u00e9ribou",
    "gn:population":0,
    "gn:timezone":"Africa/Ouagadougou",
    "iso:country":"BF",
    "name:und_x_variant":[
        "Yiribou",
        "Y\u00e9ribou"
    ],
    "wof:name":"Yeribou",
    "wof:placetype":"locality"
},
  "geometry": {"coordinates":[-2.15078,13.51921],"type":"Point"}
}