{
  "type": "Feature",
  "properties": {
    "gn:admin1_code":"05",
    "gn:admin2_code":"70",
    "gn:asciiname":"Tanguiligui",
    "gn:country_code":"BF",
    "gn:dem":325,
    "gn:feature_class":"P",
    "gn:feature_code":"PPL",
    "gn:name":"Tanguiligui",
    "gn:population":0,
    "gn:timezone":"Africa/Ouagadougou",
    "iso:country":"BF",
    "wof:name":"Tanguiligui",
    "wof:placetype":"locality"
},
  "geometry": {"coordinates":[-1.24505,13.39019],"type":"Point"}
}