{
  "type": "Feature",
  "properties": {
    "gn:admin1_code":"01",
    "gn:asciiname":"Bogo",
    "gn:country_code":"BF",
    "gn:dem":279,
    "gn:feature_class":"P",
    "gn:feature_code":"PPL",
    "gn:name":"Bogo",
    "gn:population":0,
    "gn:timezone":"Africa/Ouagadougou",
    "iso:country":"BF",
    "name:ceb_x_preferred":[
        "Bogo"
    ],
    "name:dan_x_preferred":[
        "Bog\u00f8"
    ],
    "name:deu_x_preferred":[
        "Bogo"
    ],
    "name:fra_x_preferred":[
        "Bogo"
    ],
    "name:ind_x_preferred":[
        "Bogo"
    ],
    "name:nld_x_preferred":[
        "Bogo"
    ],
    "name:pol_x_preferred":[
        "Bogo"
    ],
    "name:swe_x_preferred":[
        "Bogo"
    ],
    "wof:name":"Bogo",
    "wof:placetype":"locality"
},
  "geometry": {"coordinates":[-3.95,12.95],"type":"Point"}
}