{
  "type": "Feature",
  "properties": {
    "gn:admin1_code":"11",
    "gn:admin2_code":"68",
    "gn:asciiname":"Nyoro",
    "gn:country_code":"BF",
    "gn:dem":314,
    "gn:feature_class":"P",
    "gn:feature_code":"PPL",
    "gn:name":"Nyoro",
    "gn:population":0,
    "gn:timezone":"Africa/Ouagadougou",
    "iso:country":"BF",
    "name:und_x_variant":[
        "Nioniogo",
        "Nyoro",
        "Nionogo"
    ],
    "wof:name":"Nyoro",
    "wof:placetype":"locality"
},
  "geometry": {"coordinates":[-1.56111,12.59472],"type":"Point"}
}