{
  "type": "Feature",
  "properties": {
    "gn:admin1_code":"05",
    "gn:admin2_code":"70",
    "gn:asciiname":"Samsaka",
    "gn:country_code":"BF",
    "gn:dem":318,
    "gn:feature_class":"P",
    "gn:feature_code":"PPL",
    "gn:name":"Samsaka",
    "gn:population":0,
    "gn:timezone":"Africa/Ouagadougou",
    "iso:country":"BF",
    "wof:name":"Samsaka",
    "wof:placetype":"locality"
},
  "geometry": {"coordinates":[-1.25621,13.7073],"type":"Point"}
}