{
  "type": "Feature",
  "properties": {
    "gn:admin1_code":"10",
    "gn:admin2_code":"76",
    "gn:asciiname":"Bouli",
    "gn:country_code":"BF",
    "gn:dem":288,
    "gn:feature_class":"P",
    "gn:feature_code":"PPL",
    "gn:name":"Bouli",
    "gn:population":0,
    "gn:timezone":"Africa/Ouagadougou",
    "iso:country":"BF",
    "name:dan_x_preferred":[
        "Bouli"
    ],
    "name:fra_x_preferred":[
        "Bouli"
    ],
    "name:pol_x_preferred":[
        "Bouli"
    ],
    "name:wuu_x_preferred":[
        "\u96ea\u4eba\u6ce2\u5229"
    ],
    "name:zho_x_preferred":[
        "\u96ea\u4eba\u6ce2\u5229"
    ],
    "wof:name":"Bouli",
    "wof:placetype":"locality"
},
  "geometry": {"coordinates":[-2.72189,13.65441],"type":"Point"}
}