{
  "type": "Feature",
  "properties": {
    "gn:admin1_code":"07",
    "gn:asciiname":"Pori",
    "gn:country_code":"BF",
    "gn:dem":295,
    "gn:feature_class":"P",
    "gn:feature_code":"PPL",
    "gn:name":"Pori",
    "gn:population":0,
    "gn:timezone":"Africa/Ouagadougou",
    "iso:country":"BF",
    "wof:name":"Pori",
    "wof:placetype":"locality"
},
  "geometry": {"coordinates":[-1.56667,11.36667],"type":"Point"}
}