{
  "type": "Feature",
  "properties": {
    "gn:admin1_code":"07",
    "gn:asciiname":"Pori",
    "gn:country_code":"BF",
    "gn:dem":295,
    "gn:feature_class":"P",
    "gn:feature_code":"PPL",
    "gn:name":"Pori",
    "gn:population":0,
    "gn:timezone":"Africa/Ouagadougou",
    "iso:country":"BF",
    "name:ara_x_preferred":[
        "\u0628\u0648\u0631\u064a"
    ],
    "name:bel_x_preferred":[
        "\u041f\u043e\u0440\u044b"
    ],
    "name:bul_x_preferred":[
        "\u041f\u043e\u0440\u0438"
    ],
    "name:cat_x_preferred":[
        "Pori"
    ],
    "name:ceb_x_preferred":[
        "Pori"
    ],
    "name:ces_x_preferred":[
        "Pori"
    ],
    "name:cor_x_preferred":[
        "Pori"
    ],
    "name:dan_x_preferred":[
        "Pori"
    ],
    "name:deu_x_preferred":[
        "Pori"
    ],
    "name:ell_x_preferred":[
        "\u03a0\u03cc\u03c1\u03b9"
    ],
    "name:epo_x_preferred":[
        "Pori"
    ],
    "name:est_x_preferred":[
        "Pori"
    ],
    "name:eus_x_preferred":[
        "Pori"
    ],
    "name:fas_x_preferred":[
        "\u067e\u0631\u06cc"
    ],
    "name:fin_x_preferred":[
        "Pori"
    ],
    "name:fra_x_preferred":[
        "Pori"
    ],
    "name:gle_x_preferred":[
        "Pori"
    ],
    "name:glg_x_preferred":[
        "Pori"
    ],
    "name:heb_x_preferred":[
        "\u05e4\u05d5\u05e8\u05d9"
    ],
    "name:hrv_x_preferred":[
        "Pori"
    ],
    "name:hun_x_preferred":[
        "Pori"
    ],
    "name:ind_x_preferred":[
        "Pori"
    ],
    "name:ita_x_preferred":[
        "Pori"
    ],
    "name:jpn_x_preferred":[
        "\u30dd\u30ea"
    ],
    "name:kal_x_preferred":[
        "Pori"
    ],
    "name:koi_x_preferred":[
        "\u041f\u043e\u0440\u0438"
    ],
    "name:kor_x_preferred":[
        "\ud3ec\ub9ac"
    ],
    "name:lat_x_preferred":[
        "Arctopolis"
    ],
    "name:lav_x_preferred":[
        "Pori"
    ],
    "name:lit_x_preferred":[
        "Poris"
    ],
    "name:mkd_x_preferred":[
        "\u041f\u043e\u0440\u0438"
    ],
    "name:mri_x_preferred":[
        "Pori"
    ],
    "name:mrj_x_preferred":[
        "\u041f\u043e\u0440\u0438"
    ],
    "name:nld_x_preferred":[
        "Pori"
    ],
    "name:nno_x_preferred":[
        "Bj\u00f6rneborg"
    ],
    "name:nor_x_preferred":[
        "Bj\u00f6rneborg"
    ],
    "name:pnb_x_preferred":[
        "\u067e\u0648\u0631\u06cc"
    ],
    "name:pol_x_preferred":[
        "Pori"
    ],
    "name:por_x_preferred":[
        "Pori"
    ],
    "name:ron_x_preferred":[
        "Pori"
    ],
    "name:rus_x_preferred":[
        "\u041f\u043e\u0440\u0438"
    ],
    "name:sco_x_preferred":[
        "Pori"
    ],
    "name:slk_x_preferred":[
        "Pori"
    ],
    "name:sme_x_preferred":[
        "Pori"
    ],
    "name:spa_x_preferred":[
        "Pori"
    ],
    "name:sqi_x_preferred":[
        "Pori"
    ],
    "name:srp_x_preferred":[
        "\u041f\u043e\u0440\u0438"
    ],
    "name:swe_x_preferred":[
        "Bj\u00f6rneborg"
    ],
    "name:tat_x_preferred":[
        "\u041f\u043e\u0440\u0438"
    ],
    "name:tur_x_preferred":[
        "Pori"
    ],
    "name:ukr_x_preferred":[
        "\u041f\u043e\u0440\u0456"
    ],
    "name:urd_x_preferred":[
        "\u067e\u0648\u0631\u06cc"
    ],
    "name:vep_x_preferred":[
        "Pori"
    ],
    "name:vol_x_preferred":[
        "Pori"
    ],
    "name:war_x_preferred":[
        "Pori"
    ],
    "wof:name":"Pori",
    "wof:placetype":"locality"
},
  "geometry": {"coordinates":[-1.56667,11.36667],"type":"Point"}
}