{
  "type": "Feature",
  "properties": {
    "gn:admin1_code":"05",
    "gn:admin2_code":"15",
    "gn:asciiname":"Kagare",
    "gn:country_code":"BF",
    "gn:dem":336,
    "gn:feature_class":"P",
    "gn:feature_code":"PPL",
    "gn:name":"Kagar\u00e9",
    "gn:population":0,
    "gn:timezone":"Africa/Ouagadougou",
    "iso:country":"BF",
    "wof:name":"Kagare",
    "wof:placetype":"locality"
},
  "geometry": {"coordinates":[-1.85884,13.59747],"type":"Point"}
}