{
  "type": "Feature",
  "properties": {
    "gn:admin1_code":"01",
    "gn:admin2_code":"58",
    "gn:asciiname":"Yaraye",
    "gn:country_code":"BF",
    "gn:dem":418,
    "gn:feature_class":"P",
    "gn:feature_code":"PPL",
    "gn:name":"Yaray\u00e9",
    "gn:population":0,
    "gn:timezone":"Africa/Ouagadougou",
    "iso:country":"BF",
    "name:und_x_variant":[
        "S\u00e9noulo",
        "Yaray\u00e9"
    ],
    "wof:name":"Yaraye",
    "wof:placetype":"locality"
},
  "geometry": {"coordinates":[-4.2199,13.2123],"type":"Point"}
}