{
  "type": "Feature",
  "properties": {
    "gn:admin1_code":"08",
    "gn:asciiname":"Pouarogoudi",
    "gn:country_code":"BF",
    "gn:dem":280,
    "gn:feature_class":"P",
    "gn:feature_code":"PPL",
    "gn:name":"Pouarogoudi",
    "gn:population":0,
    "gn:timezone":"Africa/Ouagadougou",
    "iso:country":"BF",
    "wof:name":"Pouarogoudi",
    "wof:placetype":"locality"
},
  "geometry": {"coordinates":[0.05,12.33333],"type":"Point"}
}