{
  "type": "Feature",
  "properties": {
    "gn:admin1_code":"01",
    "gn:asciiname":"Kwon",
    "gn:country_code":"BF",
    "gn:dem":284,
    "gn:feature_class":"P",
    "gn:feature_code":"PPL",
    "gn:name":"Kwon",
    "gn:population":0,
    "gn:timezone":"Africa/Ouagadougou",
    "iso:country":"BF",
    "name:ast_x_preferred":[
        "Kwon"
    ],
    "name:kor_x_preferred":[
        "\uad8c"
    ],
    "name:por_x_preferred":[
        "Kwon"
    ],
    "name:spa_x_preferred":[
        "Kwon"
    ],
    "name:und_x_variant":[
        "Kon"
    ],
    "name:vie_x_preferred":[
        "Kwon"
    ],
    "wof:name":"Kwon",
    "wof:placetype":"locality"
},
  "geometry": {"coordinates":[-2.75,12.53333],"type":"Point"}
}