{
  "type": "Feature",
  "properties": {
    "gn:admin1_code":"10",
    "gn:admin2_code":"76",
    "gn:asciiname":"Bassinam",
    "gn:country_code":"BF",
    "gn:dem":328,
    "gn:feature_class":"P",
    "gn:feature_code":"PPL",
    "gn:name":"Bassinam",
    "gn:population":0,
    "gn:timezone":"Africa/Ouagadougou",
    "iso:country":"BF",
    "name:und_x_variant":[
        "Bassinan",
        "Bassinam"
    ],
    "wof:name":"Bassinam",
    "wof:placetype":"locality"
},
  "geometry": {"coordinates":[-2.36194,13.19374],"type":"Point"}
}