{
  "type": "Feature",
  "properties": {
    "gn:admin1_code":"07",
    "gn:admin2_code":"47",
    "gn:asciiname":"Doundouni",
    "gn:country_code":"BF",
    "gn:dem":311,
    "gn:feature_class":"P",
    "gn:feature_code":"PPL",
    "gn:name":"Doundouni",
    "gn:population":0,
    "gn:timezone":"Africa/Ouagadougou",
    "iso:country":"BF",
    "name:azb_x_preferred":[
        "\u062f\u0648\u0646\u062f\u0648\u0646\u06cc"
    ],
    "name:ceb_x_preferred":[
        "Doundouni"
    ],
    "name:fas_x_preferred":[
        "\u062f\u0648\u0646\u062f\u0648\u0646\u06cc"
    ],
    "name:swe_x_preferred":[
        "Doundouni"
    ],
    "wof:name":"Doundouni",
    "wof:placetype":"locality"
},
  "geometry": {"coordinates":[-1.92483,12.08659],"type":"Point"}
}