{
  "type": "Feature",
  "properties": {
    "gn:admin1_code":"11",
    "gn:admin2_code":"68",
    "gn:asciiname":"Tampwi",
    "gn:country_code":"BF",
    "gn:dem":294,
    "gn:feature_class":"P",
    "gn:feature_code":"PPL",
    "gn:name":"Tampwi",
    "gn:population":0,
    "gn:timezone":"Africa/Ouagadougou",
    "iso:country":"BF",
    "name:und_x_variant":[
        "Tampoui",
        "Tampwi"
    ],
    "wof:name":"Tampwi",
    "wof:placetype":"locality"
},
  "geometry": {"coordinates":[-1.25556,12.72389],"type":"Point"}
}