{
  "type": "Feature",
  "properties": {
    "gn:admin1_code":"07",
    "gn:admin2_code":"47",
    "gn:asciiname":"Pissi",
    "gn:country_code":"BF",
    "gn:dem":302,
    "gn:feature_class":"P",
    "gn:feature_code":"PPL",
    "gn:name":"Pissi",
    "gn:population":0,
    "gn:timezone":"Africa/Ouagadougou",
    "iso:country":"BF",
    "name:cym_x_preferred":[
        "Pissi"
    ],
    "name:fas_x_preferred":[
        "\u067e\u06cc\u0633\u06cc"
    ],
    "name:fra_x_preferred":[
        "Pissi"
    ],
    "wof:name":"Pissi",
    "wof:placetype":"locality"
},
  "geometry": {"coordinates":[-1.29944,12.05861],"type":"Point"}
}