{
  "type": "Feature",
  "properties": {
    "gn:admin1_code":"05",
    "gn:admin2_code":"70",
    "gn:asciiname":"Galouenga",
    "gn:country_code":"BF",
    "gn:dem":331,
    "gn:feature_class":"P",
    "gn:feature_code":"PPL",
    "gn:name":"Galouenga",
    "gn:population":0,
    "gn:timezone":"Africa/Ouagadougou",
    "iso:country":"BF",
    "wof:name":"Galouenga",
    "wof:placetype":"locality"
},
  "geometry": {"coordinates":[-1.33649,13.4637],"type":"Point"}
}