{
  "type": "Feature",
  "properties": {
    "gn:admin1_code":"03",
    "gn:asciiname":"Doundoulma",
    "gn:country_code":"BF",
    "gn:dem":346,
    "gn:feature_class":"P",
    "gn:feature_code":"PPL",
    "gn:name":"Doundoulma",
    "gn:population":0,
    "gn:timezone":"Africa/Ouagadougou",
    "iso:country":"BF",
    "name:und_x_variant":[
        "Dondoulma",
        "Doundoulma"
    ],
    "wof:name":"Doundoulma",
    "wof:placetype":"locality"
},
  "geometry": {"coordinates":[-1.72528,12.40417],"type":"Point"}
}