{
  "type": "Feature",
  "properties": {
    "gn:admin1_code":"13",
    "gn:asciiname":"Londjonpo",
    "gn:country_code":"BF",
    "gn:dem":288,
    "gn:feature_class":"P",
    "gn:feature_code":"PPL",
    "gn:name":"Londjonpo",
    "gn:population":0,
    "gn:timezone":"Africa/Ouagadougou",
    "iso:country":"BF",
    "wof:name":"Londjonpo",
    "wof:placetype":"locality"
},
  "geometry": {"coordinates":[-3.18333,10.56667],"type":"Point"}
}