{
  "type": "Feature",
  "properties": {
    "gn:admin1_code":"05",
    "gn:admin2_code":"64",
    "gn:asciiname":"Narbingou",
    "gn:country_code":"BF",
    "gn:dem":272,
    "gn:feature_class":"P",
    "gn:feature_code":"PPL",
    "gn:name":"Narbingou",
    "gn:population":0,
    "gn:timezone":"Africa/Ouagadougou",
    "iso:country":"BF",
    "wof:name":"Narbingou",
    "wof:placetype":"locality"
},
  "geometry": {"coordinates":[-0.4672,13.55214],"type":"Point"}
}