{
  "type": "Feature",
  "properties": {
    "gn:admin1_code":"13",
    "gn:asciiname":"Bolanbar",
    "gn:country_code":"BF",
    "gn:dem":311,
    "gn:feature_class":"P",
    "gn:feature_code":"PPL",
    "gn:name":"Bolanbar",
    "gn:population":0,
    "gn:timezone":"Africa/Ouagadougou",
    "iso:country":"BF",
    "name:und_x_variant":[
        "Kobar\u00e9",
        "Kobar",
        "Bolanbar"
    ],
    "wof:name":"Bolanbar",
    "wof:placetype":"locality"
},
  "geometry": {"coordinates":[-3.03333,11.05],"type":"Point"}
}