{
  "type": "Feature",
  "properties": {
    "gn:admin1_code":"12",
    "gn:admin2_code":"33",
    "gn:asciiname":"Fourkoussou",
    "gn:country_code":"BF",
    "gn:dem":284,
    "gn:feature_class":"P",
    "gn:feature_code":"PPL",
    "gn:name":"Fourkoussou",
    "gn:population":0,
    "gn:timezone":"Africa/Ouagadougou",
    "iso:country":"BF",
    "wof:name":"Fourkoussou",
    "wof:placetype":"locality"
},
  "geometry": {"coordinates":[-0.46351,14.33146],"type":"Point"}
}