{
  "type": "Feature",
  "properties": {
    "gn:admin1_code":"07",
    "gn:admin2_code":"47",
    "gn:asciiname":"Koaken",
    "gn:country_code":"BF",
    "gn:dem":316,
    "gn:feature_class":"P",
    "gn:feature_code":"PPL",
    "gn:name":"Koaken",
    "gn:population":0,
    "gn:timezone":"Africa/Ouagadougou",
    "iso:country":"BF",
    "wof:name":"Koaken",
    "wof:placetype":"locality"
},
  "geometry": {"coordinates":[-1.44139,12.06222],"type":"Point"}
}