{
  "type": "Feature",
  "properties": {
    "gn:admin1_code":"08",
    "gn:asciiname":"Nabougou",
    "gn:country_code":"BF",
    "gn:dem":305,
    "gn:feature_class":"P",
    "gn:feature_code":"PPL",
    "gn:name":"Nabougou",
    "gn:population":0,
    "gn:timezone":"Africa/Ouagadougou",
    "iso:country":"BF",
    "wof:name":"Nabougou",
    "wof:placetype":"locality"
},
  "geometry": {"coordinates":[0.15,12.33333],"type":"Point"}
}