{
  "type": "Feature",
  "properties": {
    "gn:admin1_code":"06",
    "gn:admin2_code":"77",
    "gn:asciiname":"Luin",
    "gn:country_code":"BF",
    "gn:dem":335,
    "gn:feature_class":"P",
    "gn:feature_code":"PPL",
    "gn:name":"Luin",
    "gn:population":0,
    "gn:timezone":"Africa/Ouagadougou",
    "iso:country":"BF",
    "name:ukr_x_preferred":[
        "\u041b\u0443\u0457\u043d"
    ],
    "name:und_x_variant":[
        "Lou\u00e9",
        "Lu",
        "Luin"
    ],
    "wof:name":"Luin",
    "wof:placetype":"locality"
},
  "geometry": {"coordinates":[-1.84444,11.58361],"type":"Point"}
}