{
  "type": "Feature",
  "properties": {
    "gn:admin1_code":"08",
    "gn:asciiname":"Nanissonga",
    "gn:country_code":"BF",
    "gn:dem":219,
    "gn:feature_class":"P",
    "gn:feature_code":"PPL",
    "gn:name":"Nanissonga",
    "gn:population":0,
    "gn:timezone":"Africa/Ouagadougou",
    "iso:country":"BF",
    "wof:name":"Nanissonga",
    "wof:placetype":"locality"
},
  "geometry": {"coordinates":[0.53333,10.98333],"type":"Point"}
}