{
  "type": "Feature",
  "properties": {
    "gn:admin1_code":"12",
    "gn:admin2_code":"40",
    "gn:asciiname":"Binguel Dafedji",
    "gn:country_code":"BF",
    "gn:dem":285,
    "gn:feature_class":"P",
    "gn:feature_code":"PPL",
    "gn:name":"Bingu\u00e8l Daf\u00e9dji",
    "gn:population":0,
    "gn:timezone":"Africa/Ouagadougou",
    "iso:country":"BF",
    "wof:name":"Binguel Dafedji",
    "wof:placetype":"locality"
},
  "geometry": {"coordinates":[-0.9308,14.6026],"type":"Point"}
}