{
  "type": "Feature",
  "properties": {
    "gn:admin1_code":"12",
    "gn:admin2_code":"71",
    "gn:asciiname":"Touka Korno",
    "gn:country_code":"BF",
    "gn:dem":279,
    "gn:feature_class":"P",
    "gn:feature_code":"PPL",
    "gn:name":"Touka Korno",
    "gn:population":0,
    "gn:timezone":"Africa/Ouagadougou",
    "iso:country":"BF",
    "wof:name":"Touka Korno",
    "wof:placetype":"locality"
},
  "geometry": {"coordinates":[-0.21372,14.18381],"type":"Point"}
}