{
  "type": "Feature",
  "properties": {
    "gn:admin1_code":"11",
    "gn:admin2_code":"68",
    "gn:asciiname":"Koalla",
    "gn:country_code":"BF",
    "gn:dem":282,
    "gn:feature_class":"P",
    "gn:feature_code":"PPLL",
    "gn:name":"Koalla",
    "gn:population":0,
    "gn:timezone":"Africa/Ouagadougou",
    "iso:country":"BF",
    "name:und_x_variant":[
        "Tangadamen",
        "Koalla"
    ],
    "wof:name":"Koalla",
    "wof:placetype":"locality"
},
  "geometry": {"coordinates":[-1.24778,12.37361],"type":"Point"}
}