{
  "type": "Feature",
  "properties": {
    "gn:admin1_code":"04",
    "gn:admin2_code":"49",
    "gn:asciiname":"Komtoega",
    "gn:country_code":"BF",
    "gn:dem":277,
    "gn:feature_class":"P",
    "gn:feature_code":"PPL",
    "gn:name":"Komto\u00e9ga",
    "gn:population":0,
    "gn:timezone":"Africa/Ouagadougou",
    "iso:country":"BF",
    "name:deu_x_preferred":[
        "Komto\u00e8ga"
    ],
    "name:fra_x_preferred":[
        "Komto\u00e8ga"
    ],
    "name:ita_x_preferred":[
        "Komto\u00e8ga"
    ],
    "name:por_x_preferred":[
        "Komto\u00e8ga"
    ],
    "name:spa_x_preferred":[
        "Komto\u00e8ga"
    ],
    "name:und_x_variant":[
        "Kombo\u00e9ga",
        "Komto\u00e9ga"
    ],
    "name:vie_x_preferred":[
        "Komto\u00e8ga"
    ],
    "wof:name":"Komtoega",
    "wof:placetype":"locality"
},
  "geometry": {"coordinates":[-0.67944,11.82556],"type":"Point"}
}