{
  "type": "Feature",
  "properties": {
    "gn:admin1_code":"13",
    "gn:asciiname":"Bondoumena",
    "gn:country_code":"BF",
    "gn:dem":292,
    "gn:feature_class":"P",
    "gn:feature_code":"PPL",
    "gn:name":"Bondoum\u00e9na",
    "gn:population":0,
    "gn:timezone":"Africa/Ouagadougou",
    "iso:country":"BF",
    "wof:name":"Bondoumena",
    "wof:placetype":"locality"
},
  "geometry": {"coordinates":[-3.35,10.21667],"type":"Point"}
}