{
  "type": "Feature",
  "properties": {
    "gn:admin1_code":"01",
    "gn:admin2_code":"58",
    "gn:asciiname":"Kouka",
    "gn:country_code":"BF",
    "gn:dem":318,
    "gn:feature_class":"P",
    "gn:feature_code":"PPL",
    "gn:name":"Kouka",
    "gn:population":0,
    "gn:timezone":"Africa/Ouagadougou",
    "iso:country":"BF",
    "name:ceb_x_preferred":[
        "Kouka"
    ],
    "name:fra_x_preferred":[
        "Kouka"
    ],
    "name:swe_x_preferred":[
        "Kouka"
    ],
    "name:und_x_variant":[
        "Kuko",
        "Kouba",
        "Kouko",
        "Kouka"
    ],
    "wof:name":"Kouka",
    "wof:placetype":"locality"
},
  "geometry": {"coordinates":[-4.33785,11.89822],"type":"Point"}
}