{
  "type": "Feature",
  "properties": {
    "gn:admin1_code":"08",
    "gn:asciiname":"Tanebya",
    "gn:country_code":"BF",
    "gn:dem":264,
    "gn:feature_class":"P",
    "gn:feature_code":"PPL",
    "gn:name":"Tanebya",
    "gn:population":0,
    "gn:timezone":"Africa/Ouagadougou",
    "iso:country":"BF",
    "wof:name":"Tanebya",
    "wof:placetype":"locality"
},
  "geometry": {"coordinates":[0.21667,12.71667],"type":"Point"}
}