{
  "type": "Feature",
  "properties": {
    "gn:admin1_code":"11",
    "gn:asciiname":"Ravigi",
    "gn:country_code":"BF",
    "gn:dem":315,
    "gn:feature_class":"P",
    "gn:feature_code":"PPL",
    "gn:name":"Ravigi",
    "gn:population":0,
    "gn:timezone":"Africa/Ouagadougou",
    "iso:country":"BF",
    "name:und_x_variant":[
        "Ravigui",
        "Ravigi"
    ],
    "wof:name":"Ravigi",
    "wof:placetype":"locality"
},
  "geometry": {"coordinates":[-1.33333,12.68333],"type":"Point"}
}