{
  "type": "Feature",
  "properties": {
    "gn:admin1_code":"08",
    "gn:admin2_code":"21",
    "gn:asciiname":"Tomannga",
    "gn:country_code":"BF",
    "gn:dem":254,
    "gn:feature_class":"P",
    "gn:feature_code":"PPL",
    "gn:name":"Tomannga",
    "gn:population":0,
    "gn:timezone":"Africa/Ouagadougou",
    "iso:country":"BF",
    "wof:name":"Tomannga",
    "wof:placetype":"locality"
},
  "geometry": {"coordinates":[0.16095,13.23072],"type":"Point"}
}