{
  "type": "Feature",
  "properties": {
    "gn:admin1_code":"13",
    "gn:asciiname":"Nonkiero",
    "gn:country_code":"BF",
    "gn:dem":279,
    "gn:feature_class":"P",
    "gn:feature_code":"PPL",
    "gn:name":"Nonkiero",
    "gn:population":0,
    "gn:timezone":"Africa/Ouagadougou",
    "iso:country":"BF",
    "wof:name":"Nonkiero",
    "wof:placetype":"locality"
},
  "geometry": {"coordinates":[-3.21667,10.65],"type":"Point"}
}