{
  "type": "Feature",
  "properties": {
    "gn:admin1_code":"01",
    "gn:admin2_code":"73",
    "gn:asciiname":"Ouile",
    "gn:country_code":"BF",
    "gn:dem":315,
    "gn:feature_class":"P",
    "gn:feature_code":"PPL",
    "gn:name":"Ouil\u00e9",
    "gn:population":0,
    "gn:timezone":"Africa/Ouagadougou",
    "iso:country":"BF",
    "name:und_x_variant":[
        "Wile",
        "Ouil\u00e9"
    ],
    "wof:name":"Ouile",
    "wof:placetype":"locality"
},
  "geometry": {"coordinates":[-2.6988,13.36958],"type":"Point"}
}