{
  "type": "Feature",
  "properties": {
    "gn:admin1_code":"08",
    "gn:admin2_code":"42",
    "gn:asciiname":"Kankwari",
    "gn:country_code":"BF",
    "gn:dem":238,
    "gn:feature_class":"P",
    "gn:feature_code":"PPL",
    "gn:name":"Kankwari",
    "gn:population":0,
    "gn:timezone":"Africa/Ouagadougou",
    "iso:country":"BF",
    "wof:name":"Kankwari",
    "wof:placetype":"locality"
},
  "geometry": {"coordinates":[2.05404,12.34853],"type":"Point"}
}