{
  "type": "Feature",
  "properties": {
    "gn:admin1_code":"13",
    "gn:asciiname":"Niego",
    "gn:country_code":"BF",
    "gn:dem":250,
    "gn:feature_class":"P",
    "gn:feature_code":"PPL",
    "gn:name":"Ni\u00e9go",
    "gn:population":0,
    "gn:timezone":"Africa/Ouagadougou",
    "iso:country":"BF",
    "name:und_x_variant":[
        "Niebo",
        "Ni\u00e9go"
    ],
    "wof:name":"Niego",
    "wof:placetype":"locality"
},
  "geometry": {"coordinates":[-2.69869,11.11471],"type":"Point"}
}