{
  "type": "Feature",
  "properties": {
    "gn:admin1_code":"08",
    "gn:admin2_code":"42",
    "gn:asciiname":"Garbogoum",
    "gn:country_code":"BF",
    "gn:dem":244,
    "gn:feature_class":"P",
    "gn:feature_code":"PPL",
    "gn:name":"Garbogoum",
    "gn:population":0,
    "gn:timezone":"Africa/Ouagadougou",
    "iso:country":"BF",
    "name:und_x_variant":[
        "Guerbogou",
        "Guerbogoum",
        "Guerbagoum",
        "Garbogoum"
    ],
    "wof:name":"Garbogoum",
    "wof:placetype":"locality"
},
  "geometry": {"coordinates":[1.61152,12.39949],"type":"Point"}
}