{
  "type": "Feature",
  "properties": {
    "gn:admin1_code":"10",
    "gn:admin2_code":"76",
    "gn:asciiname":"Seguenega",
    "gn:country_code":"BF",
    "gn:dem":324,
    "gn:feature_class":"P",
    "gn:feature_code":"PPL",
    "gn:name":"S\u00e9gu\u00e9n\u00e9ga",
    "gn:population":0,
    "gn:timezone":"Africa/Ouagadougou",
    "iso:country":"BF",
    "name:deu_x_preferred":[
        "S\u00e9gu\u00e9n\u00e9ga"
    ],
    "name:fra_x_preferred":[
        "S\u00e9gu\u00e9n\u00e9ga"
    ],
    "name:ita_x_preferred":[
        "S\u00e9gu\u00e9n\u00e9ga"
    ],
    "name:pol_x_preferred":[
        "Seguenega"
    ],
    "name:spa_x_preferred":[
        "S\u00e9gu\u00e9n\u00e9ga"
    ],
    "name:und_x_variant":[
        "S\u00e9gu\u00e9n\u00e9ga"
    ],
    "name:vie_x_preferred":[
        "S\u00e9gu\u00e9n\u00e9ga"
    ],
    "wof:name":"Seguenega",
    "wof:placetype":"locality"
},
  "geometry": {"coordinates":[-1.96694,13.44167],"type":"Point"}
}