{
  "type": "Feature",
  "properties": {
    "gn:admin1_code":"09",
    "gn:admin2_code":"54",
    "gn:asciiname":"Sintasso",
    "gn:country_code":"BF",
    "gn:dem":508,
    "gn:feature_class":"P",
    "gn:feature_code":"PPL",
    "gn:name":"Sintasso",
    "gn:population":0,
    "gn:timezone":"Africa/Ouagadougou",
    "iso:country":"BF",
    "wof:name":"Sintasso",
    "wof:placetype":"locality"
},
  "geometry": {"coordinates":[-5.30011,11.16903],"type":"Point"}
}