{
  "type": "Feature",
  "properties": {
    "gn:admin1_code":"01",
    "gn:admin2_code":"73",
    "gn:asciiname":"Bangassi",
    "gn:country_code":"BF",
    "gn:dem":268,
    "gn:feature_class":"P",
    "gn:feature_code":"PPL",
    "gn:name":"Bangassi",
    "gn:population":0,
    "gn:timezone":"Africa/Ouagadougou",
    "iso:country":"BF",
    "name:fin_x_preferred":[
        "Bangassi"
    ],
    "name:fra_x_preferred":[
        "Bangassi"
    ],
    "name:ita_x_preferred":[
        "Bangassi"
    ],
    "name:nld_x_preferred":[
        "Bangassi"
    ],
    "name:spa_x_preferred":[
        "Bangassi"
    ],
    "name:und_x_variant":[
        "Banhassi"
    ],
    "wof:name":"Bangassi",
    "wof:placetype":"locality"
},
  "geometry": {"coordinates":[-3.2782,13.1577],"type":"Point"}
}