{
  "type": "Feature",
  "properties": {
    "gn:admin1_code":"12",
    "gn:admin2_code":"71",
    "gn:asciiname":"Bwolonga",
    "gn:country_code":"BF",
    "gn:dem":288,
    "gn:feature_class":"P",
    "gn:feature_code":"PPL",
    "gn:name":"Bwolonga",
    "gn:population":0,
    "gn:timezone":"Africa/Ouagadougou",
    "iso:country":"BF",
    "wof:name":"Bwolonga",
    "wof:placetype":"locality"
},
  "geometry": {"coordinates":[0.06208,13.6738],"type":"Point"}
}