{
  "type": "Feature",
  "properties": {
    "gn:admin1_code":"01",
    "gn:admin2_code":"58",
    "gn:asciiname":"Dokui",
    "gn:country_code":"BF",
    "gn:dem":332,
    "gn:feature_class":"P",
    "gn:feature_code":"PPL",
    "gn:name":"Dokui",
    "gn:population":0,
    "gn:timezone":"Africa/Ouagadougou",
    "iso:country":"BF",
    "name:deu_x_preferred":[
        "Dokuy"
    ],
    "name:fra_x_preferred":[
        "Dokuy"
    ],
    "name:ita_x_preferred":[
        "Dokuy"
    ],
    "name:por_x_preferred":[
        "Dokuy"
    ],
    "name:spa_x_preferred":[
        "Dokuy"
    ],
    "name:und_x_variant":[
        "Dokoui",
        "Dokui"
    ],
    "name:vie_x_preferred":[
        "Dokuy"
    ],
    "wof:name":"Dokui",
    "wof:placetype":"locality"
},
  "geometry": {"coordinates":[-4.107,12.55034],"type":"Point"}
}