{
  "type": "Feature",
  "properties": {
    "gn:admin1_code":"00",
    "gn:asciiname":"Sogoden",
    "gn:country_code":"BF",
    "gn:dem":276,
    "gn:feature_class":"P",
    "gn:feature_code":"PPL",
    "gn:name":"Sogoden",
    "gn:population":0,
    "gn:timezone":"Africa/Ouagadougou",
    "iso:country":"BF",
    "name:und_x_variant":[
        "Sogodin"
    ],
    "wof:name":"Sogoden",
    "wof:placetype":"locality"
},
  "geometry": {"coordinates":[-1.06667,12.68333],"type":"Point"}
}