{
  "type": "Feature",
  "properties": {
    "gn:admin1_code":"10",
    "gn:asciiname":"Somyaleguem",
    "gn:country_code":"BF",
    "gn:dem":298,
    "gn:feature_class":"P",
    "gn:feature_code":"PPL",
    "gn:name":"Somyal\u00e9gu\u00e8m",
    "gn:population":0,
    "gn:timezone":"Africa/Ouagadougou",
    "iso:country":"BF",
    "wof:name":"Somyaleguem",
    "wof:placetype":"locality"
},
  "geometry": {"coordinates":[-2.35,12.66667],"type":"Point"}
}