{
  "type": "Feature",
  "properties": {
    "gn:admin1_code":"07",
    "gn:admin2_code":"47",
    "gn:asciiname":"Gonse",
    "gn:country_code":"BF",
    "gn:dem":294,
    "gn:feature_class":"P",
    "gn:feature_code":"PPL",
    "gn:name":"Gons\u00e9",
    "gn:population":0,
    "gn:timezone":"Africa/Ouagadougou",
    "iso:country":"BF",
    "name:fra_x_preferred":[
        "Gons\u00e9"
    ],
    "wof:name":"Gonse",
    "wof:placetype":"locality"
},
  "geometry": {"coordinates":[-1.28917,12.03194],"type":"Point"}
}