{
  "type": "Feature",
  "properties": {
    "gn:admin1_code":"12",
    "gn:admin2_code":"75",
    "gn:asciiname":"Guitanga",
    "gn:country_code":"BF",
    "gn:dem":264,
    "gn:feature_class":"P",
    "gn:feature_code":"PPL",
    "gn:name":"Guitanga",
    "gn:population":0,
    "gn:timezone":"Africa/Ouagadougou",
    "iso:country":"BF",
    "name:ceb_x_preferred":[
        "Guitanga"
    ],
    "name:fra_x_preferred":[
        "Guitanga"
    ],
    "wof:name":"Guitanga",
    "wof:placetype":"locality"
},
  "geometry": {"coordinates":[0.81857,13.06024],"type":"Point"}
}