{
  "type": "Feature",
  "properties": {
    "gn:admin1_code":"01",
    "gn:admin2_code":"73",
    "gn:asciiname":"Toumbila",
    "gn:country_code":"BF",
    "gn:dem":273,
    "gn:feature_class":"P",
    "gn:feature_code":"PPL",
    "gn:name":"Toumbila",
    "gn:population":0,
    "gn:timezone":"Africa/Ouagadougou",
    "iso:country":"BF",
    "wof:name":"Toumbila",
    "wof:placetype":"locality"
},
  "geometry": {"coordinates":[-3.3393,13.0033],"type":"Point"}
}