{
  "type": "Feature",
  "properties": {
    "gn:admin1_code":"05",
    "gn:asciiname":"Bisigui Yolgo",
    "gn:country_code":"BF",
    "gn:dem":344,
    "gn:feature_class":"P",
    "gn:feature_code":"PPL",
    "gn:name":"Bisigui Yolgo",
    "gn:population":0,
    "gn:timezone":"Africa/Ouagadougou",
    "iso:country":"BF",
    "name:und_x_variant":[
        "Bissigui Yologo",
        "Bisigui Yolgo",
        "Bissigui Yolgo"
    ],
    "wof:name":"Bisigui Yolgo",
    "wof:placetype":"locality"
},
  "geometry": {"coordinates":[-1.15,12.98333],"type":"Point"}
}