{
  "type": "Feature",
  "properties": {
    "gn:admin1_code":"10",
    "gn:admin2_code":"76",
    "gn:asciiname":"Siguinoguin",
    "gn:country_code":"BF",
    "gn:dem":298,
    "gn:feature_class":"P",
    "gn:feature_code":"PPL",
    "gn:name":"Siguinoguin",
    "gn:population":0,
    "gn:timezone":"Africa/Ouagadougou",
    "iso:country":"BF",
    "name:azb_x_preferred":[
        "\u0633\u06cc\u0642\u0648\u06cc\u0646\u0648\u0642\u0648\u06cc\u0646"
    ],
    "name:ceb_x_preferred":[
        "Siguinoguin"
    ],
    "name:fas_x_preferred":[
        "\u0633\u06cc\u06af\u0648\u06cc\u0646\u0648\u06af\u0648\u06cc\u0646"
    ],
    "name:fra_x_preferred":[
        "Siguinoguin"
    ],
    "name:swe_x_preferred":[
        "Siguinoguin"
    ],
    "wof:name":"Siguinoguin",
    "wof:placetype":"locality"
},
  "geometry": {"coordinates":[-2.65622,13.63082],"type":"Point"}
}