{
  "type": "Feature",
  "properties": {
    "gn:admin1_code":"12",
    "gn:admin2_code":"75",
    "gn:asciiname":"Karsandi",
    "gn:country_code":"BF",
    "gn:dem":262,
    "gn:feature_class":"P",
    "gn:feature_code":"PPL",
    "gn:name":"Karsandi",
    "gn:population":0,
    "gn:timezone":"Africa/Ouagadougou",
    "iso:country":"BF",
    "wof:name":"Karsandi",
    "wof:placetype":"locality"
},
  "geometry": {"coordinates":[0.35989,13.36525],"type":"Point"}
}