{
  "type": "Feature",
  "properties": {
    "gn:admin1_code":"07",
    "gn:asciiname":"Koakin",
    "gn:country_code":"BF",
    "gn:dem":316,
    "gn:feature_class":"P",
    "gn:feature_code":"PPL",
    "gn:name":"Koakin",
    "gn:population":0,
    "gn:timezone":"Africa/Ouagadougou",
    "iso:country":"BF",
    "wof:name":"Koakin",
    "wof:placetype":"locality"
},
  "geometry": {"coordinates":[-1.13333,11.68333],"type":"Point"}
}