{
  "type": "Feature",
  "properties": {
    "gn:admin1_code":"08",
    "gn:admin2_code":"42",
    "gn:asciiname":"Dangou",
    "gn:country_code":"BF",
    "gn:dem":254,
    "gn:feature_class":"P",
    "gn:feature_code":"PPL",
    "gn:name":"Dangou",
    "gn:population":0,
    "gn:timezone":"Africa/Ouagadougou",
    "iso:country":"BF",
    "wof:name":"Dangou",
    "wof:placetype":"locality"
},
  "geometry": {"coordinates":[1.6094,12.10404],"type":"Point"}
}