{
  "type": "Feature",
  "properties": {
    "gn:admin1_code":"00",
    "gn:asciiname":"Bontou",
    "gn:country_code":"BF",
    "gn:dem":371,
    "gn:feature_class":"P",
    "gn:feature_code":"PPL",
    "gn:name":"Bontou",
    "gn:population":0,
    "gn:timezone":"Africa/Ouagadougou",
    "iso:country":"BF",
    "wof:name":"Bontou",
    "wof:placetype":"locality"
},
  "geometry": {"coordinates":[-3.75,10.23333],"type":"Point"}
}