{
  "type": "Feature",
  "properties": {
    "gn:admin1_code":"03",
    "gn:admin2_code":"53",
    "gn:asciiname":"Garguen",
    "gn:country_code":"BF",
    "gn:dem":306,
    "gn:feature_class":"P",
    "gn:feature_code":"PPL",
    "gn:name":"Garguen",
    "gn:population":0,
    "gn:timezone":"Africa/Ouagadougou",
    "iso:country":"BF",
    "name:und_x_variant":[
        "Gagen",
        "Garguen",
        "Garghin",
        "Gaguin"
    ],
    "wof:name":"Garguen",
    "wof:placetype":"locality"
},
  "geometry": {"coordinates":[-1.52139,12.25472],"type":"Point"}
}