{
  "type": "Feature",
  "properties": {
    "gn:admin1_code":"11",
    "gn:asciiname":"Kisligoeme",
    "gn:country_code":"BF",
    "gn:dem":303,
    "gn:feature_class":"P",
    "gn:feature_code":"PPL",
    "gn:name":"Kisligo\u00e9m\u00e9",
    "gn:population":0,
    "gn:timezone":"Africa/Ouagadougou",
    "iso:country":"BF",
    "name:und_x_variant":[
        "Kissirigou\u00e8m",
        "Kisligo\u00e9m\u00e9"
    ],
    "wof:name":"Kisligoeme",
    "wof:placetype":"locality"
},
  "geometry": {"coordinates":[-1.38333,12.81667],"type":"Point"}
}