{
  "type": "Feature",
  "properties": {
    "gn:admin1_code":"10",
    "gn:asciiname":"Teksarabo",
    "gn:country_code":"BF",
    "gn:dem":303,
    "gn:feature_class":"P",
    "gn:feature_code":"PPL",
    "gn:name":"Teksarabo",
    "gn:population":0,
    "gn:timezone":"Africa/Ouagadougou",
    "iso:country":"BF",
    "name:und_x_variant":[
        "Teksagabo",
        "Teksarabo"
    ],
    "wof:name":"Teksarabo",
    "wof:placetype":"locality"
},
  "geometry": {"coordinates":[-1.56667,12.91667],"type":"Point"}
}