{
  "type": "Feature",
  "properties": {
    "gn:admin1_code":"11",
    "gn:asciiname":"Gwapega",
    "gn:country_code":"BF",
    "gn:dem":324,
    "gn:feature_class":"P",
    "gn:feature_code":"PPL",
    "gn:name":"Gwap\u00e9ga",
    "gn:population":0,
    "gn:timezone":"Africa/Ouagadougou",
    "iso:country":"BF",
    "wof:name":"Gwapega",
    "wof:placetype":"locality"
},
  "geometry": {"coordinates":[-1.95,12.71667],"type":"Point"}
}