{
  "type": "Feature",
  "properties": {
    "gn:admin1_code":"07",
    "gn:asciiname":"Kazanga",
    "gn:country_code":"BF",
    "gn:dem":278,
    "gn:feature_class":"P",
    "gn:feature_code":"PPL",
    "gn:name":"Kazanga",
    "gn:population":0,
    "gn:timezone":"Africa/Ouagadougou",
    "iso:country":"BF",
    "wof:name":"Kazanga",
    "wof:placetype":"locality"
},
  "geometry": {"coordinates":[-1.05,11.73333],"type":"Point"}
}