{
  "type": "Feature",
  "properties": {
    "gn:admin1_code":"13",
    "gn:asciiname":"Tanbili",
    "gn:country_code":"BF",
    "gn:dem":271,
    "gn:feature_class":"P",
    "gn:feature_code":"PPL",
    "gn:name":"Tanbili",
    "gn:population":0,
    "gn:timezone":"Africa/Ouagadougou",
    "iso:country":"BF",
    "wof:name":"Tanbili",
    "wof:placetype":"locality"
},
  "geometry": {"coordinates":[-3.01667,10.71667],"type":"Point"}
}