{
  "type": "Feature",
  "properties": {
    "gn:admin1_code":"01",
    "gn:asciiname":"Sammpopo",
    "gn:country_code":"BF",
    "gn:dem":256,
    "gn:feature_class":"P",
    "gn:feature_code":"PPL",
    "gn:name":"Sammpopo",
    "gn:population":0,
    "gn:timezone":"Africa/Ouagadougou",
    "iso:country":"BF",
    "wof:name":"Sammpopo",
    "wof:placetype":"locality"
},
  "geometry": {"coordinates":[-3.55,12.85],"type":"Point"}
}