{
  "type": "Feature",
  "properties": {
    "gn:admin1_code":"05",
    "gn:admin2_code":"70",
    "gn:asciiname":"Bebere",
    "gn:country_code":"BF",
    "gn:dem":320,
    "gn:feature_class":"P",
    "gn:feature_code":"PPL",
    "gn:name":"B\u00e9b\u00e9r\u00e9",
    "gn:population":0,
    "gn:timezone":"Africa/Ouagadougou",
    "iso:country":"BF",
    "wof:name":"Bebere",
    "wof:placetype":"locality"
},
  "geometry": {"coordinates":[-1.09529,13.42284],"type":"Point"}
}