{
  "type": "Feature",
  "properties": {
    "gn:admin1_code":"04",
    "gn:asciiname":"Niegue",
    "gn:country_code":"BF",
    "gn:dem":278,
    "gn:feature_class":"P",
    "gn:feature_code":"PPL",
    "gn:name":"Ni\u00e9gu\u00e9",
    "gn:population":0,
    "gn:timezone":"Africa/Ouagadougou",
    "iso:country":"BF",
    "wof:name":"Niegue",
    "wof:placetype":"locality"
},
  "geometry": {"coordinates":[-0.01667,11.66667],"type":"Point"}
}