{
  "type": "Feature",
  "properties": {
    "gn:admin1_code":"13",
    "gn:asciiname":"Setado",
    "gn:country_code":"BF",
    "gn:dem":320,
    "gn:feature_class":"P",
    "gn:feature_code":"PPL",
    "gn:name":"S\u00e9tado",
    "gn:population":0,
    "gn:timezone":"Africa/Ouagadougou",
    "iso:country":"BF",
    "wof:name":"Setado",
    "wof:placetype":"locality"
},
  "geometry": {"coordinates":[-3.15,9.85],"type":"Point"}
}