{
  "type": "Feature",
  "properties": {
    "gn:admin1_code":"09",
    "gn:admin2_code":"51",
    "gn:asciiname":"Banankeledara",
    "gn:country_code":"BF",
    "gn:dem":333,
    "gn:feature_class":"P",
    "gn:feature_code":"PPL",
    "gn:name":"Banank\u00e9l\u00e9dara",
    "gn:population":0,
    "gn:timezone":"Africa/Ouagadougou",
    "iso:country":"BF",
    "wof:name":"Banankeledara",
    "wof:placetype":"locality"
},
  "geometry": {"coordinates":[-4.32849,11.3178],"type":"Point"}
}