{
  "type": "Feature",
  "properties": {
    "gn:admin1_code":"x19",
    "gn:asciiname":"Koutougou",
    "gn:country_code":"BF",
    "gn:dem":298,
    "gn:feature_class":"P",
    "gn:feature_code":"PPL",
    "gn:name":"Koutougou",
    "gn:population":0,
    "gn:timezone":"Africa/Ouagadougou",
    "iso:country":"BF",
    "wof:name":"Koutougou",
    "wof:placetype":"locality"
},
  "geometry": {"coordinates":[-2.36667,12.25],"type":"Point"}
}