{
  "type": "Feature",
  "properties": {
    "gn:admin1_code":"12",
    "gn:admin2_code":"71",
    "gn:asciiname":"Niagassi",
    "gn:country_code":"BF",
    "gn:dem":308,
    "gn:feature_class":"P",
    "gn:feature_code":"PPL",
    "gn:name":"Niagassi",
    "gn:population":0,
    "gn:timezone":"Africa/Ouagadougou",
    "iso:country":"BF",
    "name:und_x_variant":[
        "Uiengossi",
        "Ouhiangossi",
        "Niagassi"
    ],
    "wof:name":"Niagassi",
    "wof:placetype":"locality"
},
  "geometry": {"coordinates":[0.30261,13.78913],"type":"Point"}
}