{
  "type": "Feature",
  "properties": {
    "gn:admin1_code":"04",
    "gn:asciiname":"Kampoueyorgho",
    "gn:country_code":"BF",
    "gn:dem":310,
    "gn:feature_class":"P",
    "gn:feature_code":"PPL",
    "gn:name":"Kampou\u00e9yorgho",
    "gn:population":0,
    "gn:timezone":"Africa/Ouagadougou",
    "iso:country":"BF",
    "name:und_x_variant":[
        "Compo-Yorgo",
        "Kampou\u00e9yorgho"
    ],
    "wof:name":"Kampoueyorgho",
    "wof:placetype":"locality"
},
  "geometry": {"coordinates":[-0.38333,11.86667],"type":"Point"}
}