{
  "type": "Feature",
  "properties": {
    "gn:admin1_code":"03",
    "gn:admin2_code":"53",
    "gn:asciiname":"Koulogroure",
    "gn:country_code":"BF",
    "gn:dem":302,
    "gn:feature_class":"P",
    "gn:feature_code":"PPL",
    "gn:name":"Koulogrour\u00e9",
    "gn:population":0,
    "gn:timezone":"Africa/Ouagadougou",
    "iso:country":"BF",
    "wof:name":"Koulogroure",
    "wof:placetype":"locality"
},
  "geometry": {"coordinates":[-1.42207,12.35749],"type":"Point"}
}