{
  "type": "Feature",
  "properties": {
    "gn:admin1_code":"09",
    "gn:admin2_code":"54",
    "gn:asciiname":"Diossogou",
    "gn:country_code":"BF",
    "gn:dem":533,
    "gn:feature_class":"P",
    "gn:feature_code":"PPL",
    "gn:name":"Diossogou",
    "gn:population":0,
    "gn:timezone":"Africa/Ouagadougou",
    "iso:country":"BF",
    "name:und_x_variant":[
        "Diesoko",
        "Diossogou"
    ],
    "wof:name":"Diossogou",
    "wof:placetype":"locality"
},
  "geometry": {"coordinates":[-5.00467,11.03917],"type":"Point"}
}