{
  "type": "Feature",
  "properties": {
    "gn:admin1_code":"06",
    "gn:admin2_code":"72",
    "gn:asciiname":"Kounou",
    "gn:country_code":"BF",
    "gn:dem":310,
    "gn:feature_class":"P",
    "gn:feature_code":"PPL",
    "gn:name":"Kounou",
    "gn:population":0,
    "gn:timezone":"Africa/Ouagadougou",
    "iso:country":"BF",
    "wof:name":"Kounou",
    "wof:placetype":"locality"
},
  "geometry": {"coordinates":[-1.62806,11.03139],"type":"Point"}
}