{
  "type": "Feature",
  "properties": {
    "gn:admin1_code":"12",
    "gn:admin2_code":"40",
    "gn:asciiname":"Kouye",
    "gn:country_code":"BF",
    "gn:dem":301,
    "gn:feature_class":"P",
    "gn:feature_code":"PPL",
    "gn:name":"Kouy\u00e9",
    "gn:population":0,
    "gn:timezone":"Africa/Ouagadougou",
    "iso:country":"BF",
    "wof:name":"Kouye",
    "wof:placetype":"locality"
},
  "geometry": {"coordinates":[-1.8578,14.34304],"type":"Point"}
}