{
  "type": "Feature",
  "properties": {
    "gn:admin1_code":"13",
    "gn:asciiname":"Manoa",
    "gn:country_code":"BF",
    "gn:dem":255,
    "gn:feature_class":"P",
    "gn:feature_code":"PPL",
    "gn:name":"Manoa",
    "gn:population":0,
    "gn:timezone":"Africa/Ouagadougou",
    "iso:country":"BF",
    "name:fra_x_preferred":[
        "M\u0101noa"
    ],
    "name:haw_x_preferred":[
        "M\u0101noa"
    ],
    "name:ilo_x_preferred":[
        "Manoa"
    ],
    "name:jpn_x_preferred":[
        "\u30de\u30ce\u30a2"
    ],
    "name:nor_x_preferred":[
        "Manoa"
    ],
    "name:por_x_preferred":[
        "Manoa"
    ],
    "name:und_x_variant":[
        "Maroa",
        "Manoa"
    ],
    "wof:name":"Manoa",
    "wof:placetype":"locality"
},
  "geometry": {"coordinates":[-2.95,10.73333],"type":"Point"}
}