{
  "type": "Feature",
  "properties": {
    "gn:admin1_code":"08",
    "gn:admin2_code":"50",
    "gn:asciiname":"Bankatatougou",
    "gn:country_code":"BF",
    "gn:dem":289,
    "gn:feature_class":"P",
    "gn:feature_code":"PPL",
    "gn:name":"Bankatatougou",
    "gn:population":0,
    "gn:timezone":"Africa/Ouagadougou",
    "iso:country":"BF",
    "wof:name":"Bankatatougou",
    "wof:placetype":"locality"
},
  "geometry": {"coordinates":[1.05953,12.28969],"type":"Point"}
}