{
  "type": "Feature",
  "properties": {
    "gn:admin1_code":"12",
    "gn:admin2_code":"75",
    "gn:asciiname":"Sago",
    "gn:country_code":"BF",
    "gn:dem":251,
    "gn:feature_class":"P",
    "gn:feature_code":"PPL",
    "gn:name":"Sago",
    "gn:population":0,
    "gn:timezone":"Africa/Ouagadougou",
    "iso:country":"BF",
    "wof:name":"Sago",
    "wof:placetype":"locality"
},
  "geometry": {"coordinates":[0.50593,13.45],"type":"Point"}
}