{
  "type": "Feature",
  "properties": {
    "gn:admin1_code":"13",
    "gn:asciiname":"Loropeni",
    "gn:country_code":"BF",
    "gn:dem":334,
    "gn:feature_class":"P",
    "gn:feature_code":"PPL",
    "gn:name":"Lorop\u00e9ni",
    "gn:population":0,
    "gn:timezone":"Africa/Ouagadougou",
    "iso:country":"BF",
    "name:und_x_variant":[
        "Lorop\u00e9ni"
    ],
    "wof:name":"Loropeni",
    "wof:placetype":"locality"
},
  "geometry": {"coordinates":[-3.52974,10.29935],"type":"Point"}
}