{
  "type": "Feature",
  "properties": {
    "gn:admin1_code":"13",
    "gn:asciiname":"Loropeni",
    "gn:country_code":"BF",
    "gn:dem":334,
    "gn:feature_class":"P",
    "gn:feature_code":"PPL",
    "gn:name":"Lorop\u00e9ni",
    "gn:population":0,
    "gn:timezone":"Africa/Ouagadougou",
    "iso:country":"BF",
    "name:ara_x_preferred":[
        "\u0623\u0637\u0644\u0627\u0644 \u0644\u0648\u0631\u0648\u0628\u064a\u0646\u064a"
    ],
    "name:ast_x_preferred":[
        "Lorop\u00e9ni"
    ],
    "name:cat_x_preferred":[
        "Lorop\u00e9ni"
    ],
    "name:deu_x_preferred":[
        "Lorop\u00e9ni"
    ],
    "name:fas_x_preferred":[
        "\u0644\u0648\u0631\u0648\u067e\u06cc\u0646\u06cc"
    ],
    "name:fin_x_preferred":[
        "Lorop\u00e9ni"
    ],
    "name:fra_x_preferred":[
        "Lorop\u00e9ni"
    ],
    "name:hrv_x_preferred":[
        "Lorop\u00e9ni"
    ],
    "name:ita_x_preferred":[
        "Lorop\u00e9ni"
    ],
    "name:kat_x_preferred":[
        "\u10da\u10dd\u10e0\u10dd\u10de\u10d4\u10dc\u10d8"
    ],
    "name:nld_x_preferred":[
        "Lorop\u00e9ni"
    ],
    "name:pol_x_preferred":[
        "Lorop\u00e9ni"
    ],
    "name:por_x_preferred":[
        "Lorop\u00e9ni"
    ],
    "name:ron_x_preferred":[
        "Loropeni"
    ],
    "name:spa_x_preferred":[
        "Lorop\u00e9ni"
    ],
    "name:srp_x_preferred":[
        "\u041b\u043e\u0440\u043e\u043f\u0435\u043d\u0438"
    ],
    "name:swe_x_preferred":[
        "Lorop\u00e9ni"
    ],
    "name:tur_x_preferred":[
        "Lorop\u00e9ni"
    ],
    "name:urd_x_preferred":[
        "\u0644\u0648\u0631\u0648\u067e\u0626\u0646\u06cc"
    ],
    "name:vie_x_preferred":[
        "Lorop\u00e9ni"
    ],
    "name:zho_x_preferred":[
        "\u6d1b\u7f57\u6d3e\u5c3c"
    ],
    "wof:name":"Loropeni",
    "wof:placetype":"locality"
},
  "geometry": {"coordinates":[-3.52974,10.29935],"type":"Point"}
}