{
  "type": "Feature",
  "properties": {
    "gn:admin1_code":"10",
    "gn:asciiname":"Masyenwoune",
    "gn:country_code":"BF",
    "gn:dem":320,
    "gn:feature_class":"P",
    "gn:feature_code":"PPL",
    "gn:name":"Masy\u00e9nwoun\u00e9",
    "gn:population":0,
    "gn:timezone":"Africa/Ouagadougou",
    "iso:country":"BF",
    "name:und_x_variant":[
        "Massy\u00e8nwoun\u00e9",
        "Masy\u00e9nwoun\u00e9"
    ],
    "wof:name":"Masyenwoune",
    "wof:placetype":"locality"
},
  "geometry": {"coordinates":[-1.66667,12.96667],"type":"Point"}
}