{
  "type": "Feature",
  "properties": {
    "gn:admin1_code":"08",
    "gn:asciiname":"Komwana",
    "gn:country_code":"BF",
    "gn:dem":235,
    "gn:feature_class":"P",
    "gn:feature_code":"PPL",
    "gn:name":"Komwana",
    "gn:population":0,
    "gn:timezone":"Africa/Ouagadougou",
    "iso:country":"BF",
    "wof:name":"Komwana",
    "wof:placetype":"locality"
},
  "geometry": {"coordinates":[0.91667,12.06667],"type":"Point"}
}