{
  "type": "Feature",
  "properties": {
    "gn:admin1_code":"12",
    "gn:admin2_code":"75",
    "gn:asciiname":"Pougoumbel",
    "gn:country_code":"BF",
    "gn:dem":265,
    "gn:feature_class":"P",
    "gn:feature_code":"PPL",
    "gn:name":"Pougoumb\u00e8l",
    "gn:population":0,
    "gn:timezone":"Africa/Ouagadougou",
    "iso:country":"BF",
    "wof:name":"Pougoumbel",
    "wof:placetype":"locality"
},
  "geometry": {"coordinates":[0.22931,13.61822],"type":"Point"}
}