{
  "type": "Feature",
  "properties": {
    "gn:admin1_code":"11",
    "gn:asciiname":"Zoungou",
    "gn:country_code":"BF",
    "gn:dem":288,
    "gn:feature_class":"P",
    "gn:feature_code":"PPL",
    "gn:name":"Zoungou",
    "gn:population":0,
    "gn:timezone":"Africa/Ouagadougou",
    "iso:country":"BF",
    "name:fra_x_preferred":[
        "Zoungou"
    ],
    "name:und_x_variant":[
        "Noungou",
        "Zoungou"
    ],
    "wof:name":"Zoungou",
    "wof:placetype":"locality"
},
  "geometry": {"coordinates":[-0.53169,12.14441],"type":"Point"}
}