{
  "type": "Feature",
  "properties": {
    "gn:admin1_code":"10",
    "gn:admin2_code":"76",
    "gn:asciiname":"Kourouba",
    "gn:country_code":"BF",
    "gn:dem":330,
    "gn:feature_class":"P",
    "gn:feature_code":"PPL",
    "gn:name":"Kourouba",
    "gn:population":0,
    "gn:timezone":"Africa/Ouagadougou",
    "iso:country":"BF",
    "name:fin_x_preferred":[
        "Kourouba"
    ],
    "name:fra_x_preferred":[
        "Kourouba"
    ],
    "name:ita_x_preferred":[
        "Kourouba"
    ],
    "name:nld_x_preferred":[
        "Kourouba"
    ],
    "name:spa_x_preferred":[
        "Kourouba"
    ],
    "name:zho_x_preferred":[
        "\u5eab\u9b6f\u5df4"
    ],
    "wof:name":"Kourouba",
    "wof:placetype":"locality"
},
  "geometry": {"coordinates":[-2.55923,13.10094],"type":"Point"}
}