{
  "type": "Feature",
  "properties": {
    "gn:admin1_code":"07",
    "gn:admin2_code":"47",
    "gn:asciiname":"Seguedin",
    "gn:country_code":"BF",
    "gn:dem":311,
    "gn:feature_class":"P",
    "gn:feature_code":"PPL",
    "gn:name":"S\u00e9gu\u00e9din",
    "gn:population":0,
    "gn:timezone":"Africa/Ouagadougou",
    "iso:country":"BF",
    "name:azb_x_preferred":[
        "\u0633\u06cc\u0646\u0642\u062f\u06cc\u0646"
    ],
    "name:ceb_x_preferred":[
        "S\u00e9gu\u00e9din"
    ],
    "name:fas_x_preferred":[
        "\u0633\u06cc\u0646\u06af\u062f\u06cc\u0646"
    ],
    "name:swe_x_preferred":[
        "S\u00e9gu\u00e9din"
    ],
    "name:und_x_variant":[
        "S\u00e9r\u00e9din",
        "Singdin",
        "S\u00e9g\u00e9den",
        "S\u00e9gu\u00e9din",
        "S\u00e9guedin",
        "S\u00e9gu\u00e9den"
    ],
    "wof:name":"Seguedin",
    "wof:placetype":"locality"
},
  "geometry": {"coordinates":[-1.97498,12.00779],"type":"Point"}
}