{
  "type": "Feature",
  "properties": {
    "gn:admin1_code":"12",
    "gn:admin2_code":"75",
    "gn:asciiname":"Kobougou",
    "gn:country_code":"BF",
    "gn:dem":249,
    "gn:feature_class":"P",
    "gn:feature_code":"PPL",
    "gn:name":"Kobougou",
    "gn:population":0,
    "gn:timezone":"Africa/Ouagadougou",
    "iso:country":"BF",
    "wof:name":"Kobougou",
    "wof:placetype":"locality"
},
  "geometry": {"coordinates":[0.46716,13.35141],"type":"Point"}
}