{
  "type": "Feature",
  "properties": {
    "gn:admin1_code":"07",
    "gn:asciiname":"Larga",
    "gn:country_code":"BF",
    "gn:dem":297,
    "gn:feature_class":"P",
    "gn:feature_code":"PPL",
    "gn:name":"Larga",
    "gn:population":0,
    "gn:timezone":"Africa/Ouagadougou",
    "iso:country":"BF",
    "name:ceb_x_preferred":[
        "Larga"
    ],
    "name:chv_x_preferred":[
        "\u041b\u0430\u0440\u0433\u0430"
    ],
    "name:deu_x_preferred":[
        "Larga"
    ],
    "name:epo_x_preferred":[
        "Larga"
    ],
    "name:fra_x_preferred":[
        "Larga"
    ],
    "name:ron_x_preferred":[
        "Larga"
    ],
    "name:rus_x_preferred":[
        "\u041b\u0430\u0440\u0433\u0430"
    ],
    "name:srp_x_preferred":[
        "\u041b\u0430\u0440\u0433\u0430"
    ],
    "name:swe_x_preferred":[
        "Larga"
    ],
    "name:ukr_x_preferred":[
        "\u041b\u0430\u0440\u0433\u0430"
    ],
    "wof:name":"Larga",
    "wof:placetype":"locality"
},
  "geometry": {"coordinates":[-1.11667,11.66667],"type":"Point"}
}