{
  "type": "Feature",
  "properties": {
    "gn:admin1_code":"07",
    "gn:asciiname":"Larga",
    "gn:country_code":"BF",
    "gn:dem":297,
    "gn:feature_class":"P",
    "gn:feature_code":"PPL",
    "gn:name":"Larga",
    "gn:population":0,
    "gn:timezone":"Africa/Ouagadougou",
    "iso:country":"BF",
    "wof:name":"Larga",
    "wof:placetype":"locality"
},
  "geometry": {"coordinates":[-1.11667,11.66667],"type":"Point"}
}