{
  "type": "Feature",
  "properties": {
    "gn:admin1_code":"13",
    "gn:asciiname":"Bou",
    "gn:country_code":"BF",
    "gn:dem":261,
    "gn:feature_class":"P",
    "gn:feature_code":"PPL",
    "gn:name":"Bou",
    "gn:population":0,
    "gn:timezone":"Africa/Ouagadougou",
    "iso:country":"BF",
    "name:cat_x_preferred":[
        "Bou"
    ],
    "name:ceb_x_preferred":[
        "Bou"
    ],
    "name:deu_x_preferred":[
        "Bou"
    ],
    "name:eus_x_preferred":[
        "Bou"
    ],
    "name:fas_x_preferred":[
        "\u0628\u0648"
    ],
    "name:fra_x_preferred":[
        "Bou"
    ],
    "name:hun_x_preferred":[
        "Bou"
    ],
    "name:ind_x_preferred":[
        "Bou"
    ],
    "name:ita_x_preferred":[
        "Bou"
    ],
    "name:lat_x_preferred":[
        "Bou"
    ],
    "name:msa_x_preferred":[
        "Bou"
    ],
    "name:nld_x_preferred":[
        "Bou"
    ],
    "name:oci_x_preferred":[
        "Bou"
    ],
    "name:pms_x_preferred":[
        "Bou"
    ],
    "name:pol_x_preferred":[
        "Bou"
    ],
    "name:por_x_preferred":[
        "Bou"
    ],
    "name:slk_x_preferred":[
        "Bou"
    ],
    "name:spa_x_preferred":[
        "Bou"
    ],
    "name:srp_x_preferred":[
        "\u0411\u0443"
    ],
    "name:swe_x_preferred":[
        "Bou"
    ],
    "name:ukr_x_preferred":[
        "\u0411\u0443"
    ],
    "name:uzb_x_preferred":[
        "Bou"
    ],
    "name:vie_x_preferred":[
        "Bou"
    ],
    "name:vol_x_preferred":[
        "Bou"
    ],
    "name:war_x_preferred":[
        "Bou"
    ],
    "name:zho_x_preferred":[
        "\u5e03"
    ],
    "wof:name":"Bou",
    "wof:placetype":"locality"
},
  "geometry": {"coordinates":[-2.95,10.51667],"type":"Point"}
}