{
  "type": "Feature",
  "properties": {
    "gn:admin1_code":"13",
    "gn:asciiname":"Noborodo",
    "gn:country_code":"BF",
    "gn:dem":273,
    "gn:feature_class":"P",
    "gn:feature_code":"PPL",
    "gn:name":"Noborodo",
    "gn:population":0,
    "gn:timezone":"Africa/Ouagadougou",
    "iso:country":"BF",
    "wof:name":"Noborodo",
    "wof:placetype":"locality"
},
  "geometry": {"coordinates":[-3.06667,9.75],"type":"Point"}
}