{
  "type": "Feature",
  "properties": {
    "gn:admin1_code":"01",
    "gn:asciiname":"Da",
    "gn:country_code":"BF",
    "gn:dem":267,
    "gn:feature_class":"P",
    "gn:feature_code":"PPL",
    "gn:name":"Da",
    "gn:population":0,
    "gn:timezone":"Africa/Ouagadougou",
    "iso:country":"BF",
    "name:ara_x_preferred":[
        "\u062f\u0627"
    ],
    "name:ben_x_preferred":[
        "\u09a1\u09be"
    ],
    "name:ell_x_preferred":[
        "\u039d\u03c4\u03b1"
    ],
    "name:fas_x_preferred":[
        "\u062f\u0627"
    ],
    "name:hin_x_preferred":[
        "\u0921\u093e"
    ],
    "name:hun_x_preferred":[
        "Da"
    ],
    "name:ind_x_preferred":[
        "Da"
    ],
    "name:por_x_preferred":[
        "S\u00f4ng \u0110\u00e0"
    ],
    "name:und_x_variant":[
        "La",
        "Da"
    ],
    "name:urd_x_preferred":[
        "\u0688\u0627"
    ],
    "wof:name":"Da",
    "wof:placetype":"locality"
},
  "geometry": {"coordinates":[-3.18333,12.43333],"type":"Point"}
}