{
  "type": "Feature",
  "properties": {
    "gn:admin1_code":"01",
    "gn:asciiname":"Da",
    "gn:country_code":"BF",
    "gn:dem":267,
    "gn:feature_class":"P",
    "gn:feature_code":"PPL",
    "gn:name":"Da",
    "gn:population":0,
    "gn:timezone":"Africa/Ouagadougou",
    "iso:country":"BF",
    "name:und_x_variant":[
        "La",
        "Da"
    ],
    "wof:name":"Da",
    "wof:placetype":"locality"
},
  "geometry": {"coordinates":[-3.18333,12.43333],"type":"Point"}
}