{
  "type": "Feature",
  "properties": {
    "gn:admin1_code":"11",
    "gn:asciiname":"Gouropila",
    "gn:country_code":"BF",
    "gn:dem":311,
    "gn:feature_class":"P",
    "gn:feature_code":"PPL",
    "gn:name":"Gouropila",
    "gn:population":0,
    "gn:timezone":"Africa/Ouagadougou",
    "iso:country":"BF",
    "name:und_x_variant":[
        "Gourpila",
        "Gouropila"
    ],
    "wof:name":"Gouropila",
    "wof:placetype":"locality"
},
  "geometry": {"coordinates":[-1.75,12.73333],"type":"Point"}
}