{
  "type": "Feature",
  "properties": {
    "gn:admin1_code":"02",
    "gn:asciiname":"Tiebata",
    "gn:country_code":"BF",
    "gn:dem":277,
    "gn:feature_class":"P",
    "gn:feature_code":"PPL",
    "gn:name":"Ti\u00e9bata",
    "gn:population":0,
    "gn:timezone":"Africa/Ouagadougou",
    "iso:country":"BF",
    "name:ceb_x_preferred":[
        "Ti\u00e9bata"
    ],
    "name:fra_x_preferred":[
        "Tiebata"
    ],
    "name:swe_x_preferred":[
        "Ti\u00e9bata"
    ],
    "name:und_x_variant":[
        "Ti\u00e9bata"
    ],
    "wof:name":"Tiebata",
    "wof:placetype":"locality"
},
  "geometry": {"coordinates":[-4.26667,9.85],"type":"Point"}
}