{
  "type": "Feature",
  "properties": {
    "gn:admin1_code":"03",
    "gn:admin2_code":"53",
    "gn:asciiname":"Namassa",
    "gn:country_code":"BF",
    "gn:dem":312,
    "gn:feature_class":"P",
    "gn:feature_code":"PPL",
    "gn:name":"Namassa",
    "gn:population":0,
    "gn:timezone":"Africa/Ouagadougou",
    "iso:country":"BF",
    "name:azb_x_preferred":[
        "\u0646\u0627\u0645\u0627\u0633\u0627"
    ],
    "name:fas_x_preferred":[
        "\u0646\u0627\u0645\u0627\u0633\u0627"
    ],
    "name:fra_x_preferred":[
        "Namassa"
    ],
    "wof:name":"Namassa",
    "wof:placetype":"locality"
},
  "geometry": {"coordinates":[-1.68472,12.12972],"type":"Point"}
}