{
  "type": "Feature",
  "properties": {
    "gn:admin1_code":"05",
    "gn:admin2_code":"15",
    "gn:asciiname":"Nongou",
    "gn:country_code":"BF",
    "gn:dem":351,
    "gn:feature_class":"P",
    "gn:feature_code":"PPL",
    "gn:name":"Nongou",
    "gn:population":0,
    "gn:timezone":"Africa/Ouagadougou",
    "iso:country":"BF",
    "wof:name":"Nongou",
    "wof:placetype":"locality"
},
  "geometry": {"coordinates":[-1.58265,13.32717],"type":"Point"}
}